Workbook
Name Slicer_TL: #N/A
Name Slicer_TL1: #N/A
Name Slicer_TL7: #N/A

Sheet Dashboard
B1: Retention Performance | P1: Feb
P2: Working Days | Q2: 31
B3: Retention Queue Performance | P3: Days Worked | Q3: 18
B4: KPI's | C4: Last week Performance | F4: Last Week Sans Monday | I4: MTD Performance Calls Ans | L4: Last Month Comparison
C5: Calls | D5: Service Level | E5: ABA% | F5: Calls | G5: Service Level | H5: ABA% | I5: Calls | J5: Service Level | K5: ABA% | L5: Calls | M5: Service Level | N5: ABA%
B6: Retention Queue Performance | C6: 1456 | D6: 0.95 | E6: 0 | F6: 1122 | G6: 0.95 | H6: 0 | I6: 6630 | J6: 0.83 | K6: 0.06 | L6: 6862 | M6: 0.77 | N6: 0.08
B7: Service | C7: 10 | D7: 0.8 | E7: 0 | F7: 10 | G7: 0.8 | H7: 0 | I7: 2041 | J7: 0.72 | K7: 0.1 | L7: 69 | M7: 0.8 | N7: 0.02 | P7: Power BI MTD
B8: Collections | C8: 7 | D8: 0.71 | E8: 0.02 | F8: 7 | G8: 0.71 | H8: 0.02 | I8: 28 | J8: 0.79 | K8: 0 | L8: 85 | M8: 0.81 | N8: 0.08 | P8: ACH - 30.8% | R8: Telreg Skilled Conv - 19.3%
C10: MOM Comparison | I10: LW Monday Performance | P10: QA MTD
C11: MTD | D11: EOM Estimate | E11: Last Month | F11: MOM Change | J11: Calls Answered | K11: Calls Handled | L11: Service Level | M11: ABA% | N11: Calls Abandoned | P11: AVG | Q11: # of Evals | S11: Crit
C12: Calls | D12: Calls | E12: Calls | F12: Calls | I12: Retention | J12: 334 | K12: 334 | L12: 0.87 | M12: 0.04 | N12: 27 | P12: 0.95142857 | Q12: 35 | S12: 0.98639457
B13: Retention Queue Performance | C13: 6630 | D13: 11418.333 | E13: 6862 | F13: 4556.3333 | I13: Telreg | J13: 0 | K13: 0 | L13: 0 | M13: 0 | N13: 0
B14: Service | C14: 2041 | D14: 3515.0556 | E14: 69 | F14: 3446.0556 | I14: Collections | J14: 0 | K14: 0 | L14: 0.86 | M14: 0 | N14: 0
B15: Collections | C15: 28 | D15: 48.222222 | E15: 85 | F15: -36.777778 | G15: % Difference | I15: Totals | J15: 334 | K15: 334 | L15: 0.57666667 | M15: 0.013333333 | N15: 27
B16: Combined | C16: 8699 | D16: 14981.611 | E16: 7016 | F16: 7965.6111 | G16: 2.1353494 | I16: % of TV | J16: 0.22674813
B20: KPI Retention | C20: Last Week | F20: Current Week | I20: MTD | L20: Previous Month
B21: Column1 | C21: Calls | D21: Sales | E21: Conversion | F21: Calls2 | G21: Sales3 | H21: Conversion4 | I21: Calls5 | J21: Sales6 | K21: Conversion7 | L21: Calls8 | M21: Sales9 | N21: Conversion2
B22: Service | C22: 11 | D22: 20 | E22: 1.8181818 | F22: 0 | G22: 3 | H22: #DIV/0! | I22: 2041 | J22: 198 | K22: 0.097011269 | L22: 69 | M22: 62 | N22: 0.89855072
B23: OOW | C23: 1467 | D23: 19 | E23: 0.012951602 | F23: 1238 | G23: 17 | H23: 0.013731826 | I23: 8671 | J23: 142 | K23: 0.016376427 | L23: 6931 | M23: 81 | N23: 0.011686625
B24: Retention | C24: 1456 | D24: 1155 | E24: 0.79326923 | F24: 1238 | G24: 1033 | H24: 0.83441034 | I24: 6630 | J24: 5088 | K24: 0.76742081 | L24: 6862 | M24: 5367 | N24: 0.78213349
K26: Month | P26: Prev | R26: Current
B27: Outliers Ret | C27: Prev Month | D27: MTD | E27: Cur Week | F27: Lst Week | G27: Action | H27: Goal | I27: Stage | K27: Agents | L27: Canc Rate | M27: Save % | N27: Serv Con | P27: Agent | Q27: ININ Wrap | R27: Agent | S27: ININ Wrap
B28: Douglas Barnes | C28: 0.67961165 | D28: 0.70445344 | E28: 0.87179487 | F28: 1.4285714 | K28: Khadijah Young | L28: 0.69950739 | M28: 1.1551724 | N28: 0.058524173 | P28: Douglas Barnes | Q28: 9 | R28: Chasady Parker | S28: 26
B29: Amy Smiley | C29: 0.64684015 | D29: 0.69 | E29: 0.65116279 | F29: 0.84615385 | K29: Regina Watson | L29: 0.62751678 | M29: 0.99328859 | N29: 0.30263158 | P29: Khadijah Young | Q29: 6 | R29: Angelica Gonzalez | S29: 7
C30: 0 | D30: 0 | E30: 0 | F30: 0 | K30: Angelica Gonzalez | L30: 0.69555035 | M30: 0.94964871 | N30: 0.15135135 | P30: Chasady Parker | Q30: 5 | R30: Mohamed Bayoumy | S30: 5
C31: 0 | D31: 0 | E31: 0 | F31: 0 | K31: Larry Moorehead | L31: 0.77469136 | M31: 0.73148148 | N31: 0.035598706 | P31: Chanetta Gant | Q31: 4 | R31: Regina Watson | S31: 5
C32: 0 | D32: 0 | E32: 0 | F32: 0 | K32: Mohamed Bayoumy | L32: 0.74178935 | M32: 0.73046433 | N32: 0.11428571 | P32: Angelica Gonzalez | Q32: 3 | R32: Douglas Barnes | S32: 3
K33: Margaret Reddy | L33: 0.95631068 | M33: 0.70873786 | N33: 0.070921986 | P33: Amy Smiley | Q33: 3 | R33: Perry Young III | S33: 3
B34: Outlier Cancellation | C34: Prev Month | D34: MTD | E34: Cur Week | F34: Lst Week | G34: Action | H34: Goal | I34: Stage | K34: Douglas Barnes | L34: 0.93927126 | M34: 0.70445344 | N34: 0.016393443 | P34: Mohamed Bayoumy | Q34: 3 | R34: Chanetta Gant | S34: 2
B35: Douglas Barnes | C35: 0.88673139 | D35: 0.93927126 | E35: 1.0512821 | F35: 0.71428571 | G35: pm | H35: 0.7 | K35: Amy Smiley | L35: 0.77666667 | M35: 0.69 | N35: 0 | P35: Larry Moorehead | Q35: 2 | R35: Matthew Livingstone | S35: 1
B36: Larry Moorehead | C36: 0.81849315 | D36: 0.77469136 | E36: 1.0181818 | F36: 0 | G36: pm | H36: 0.7 | K36: Chanetta Gant | L36: 0.78615071 | M36: 0.67617108 | N36: 0.51851852 | P36: Perry Young III | Q36: 1 | R36: Khadijah Young | S36: 0
B37: Perry Young | C37: 0.85487805 | D37: 1.003886 | E37: 1.2594937 | F37: 0.79435484 | G37: pm | H37: 0.7 | K37: Matthew Livingstone | L37: 0.88091603 | M37: 0.64427481 | N37: 0 | P37: Margaret Reddy | Q37: 1 | R37: Larry Moorehead | S37: 0
B38: Margaret Reddy | C38: 0.8562753 | D38: 0.95631068 | E38: 1.0309278 | F38: 0.82352941 | G38: pm | H38: 0.7 | K38: Perry Young | L38: 1.003886 | M38: 0.62953368 | N38: 0 | P38: Regina Watson | Q38: 0 | R38: Margaret Reddy | S38: 0
K39: Chasady Parker | L39: 0.38374718 | M39: 0.55756208 | N39: 0.057971014 | P39: Matthew Livingstone | Q39: 0 | R39: Amy Smiley | S39: 0
K40: Christina Johnson | L40: 0 | M40: 0 | N40: 0 | P40: Christina Johnson | Q40: 0 | R40: Christina Johnson | S40: 0
B41: Absenteeism | K41: Week
B42: Previous MTD | F42: MTD | K42: Agents | L42: Canc Rate | M42: Save % | N42: IW S2C
B43: Sales - Tel Reg | F43: Sales - Tel Reg | K43: Regina Watson | L43: 0.55833333 | M43: 1.225 | N43: 0
B44: Total Schedule Time | C44: 2319.15 | F44: Total Schedule Time | G44: 2194.1167 | K44: Angelica Gonzalez | L44: 0.7983871 | M44: 0.70967742 | N44: 0
B45: On Queue Time / Nesting | C45: 1690.65 | D45: 0.72899554 | F45: On Queue Time / Nesting | G45: 1411.0333 | H45: 0.64309859 | K45: Khadijah Young | L45: 0.63333333 | M45: 0.94444444 | N45: 0
B46: PTO | C46: 21 | D46: 0.0090550417 | F46: PTO | G46: 54.5 | H46: 0.024839153 | K46: Perry Young | L46: 1.2594937 | M46: 0.60126582 | N46: 0
B47: Break | C47: 115.51667 | D47: 0.049809916 | F47: Break | G47: 104.98333 | H47: 0.047847653 | K47: Margaret Reddy | L47: 1.0309278 | M47: 0.68041237 | N47: 0
B48: Lunch | C48: 116.21667 | D48: 0.050111751 | F48: Lunch | G48: 109.86667 | H48: 0.050073302 | K48: Larry Moorehead | L48: 1.0181818 | M48: 0.81818182 | N48: 0
B49: VTO / MATO | C49: 14.533333 | D49: 0.0062666638 | F49: VTO / MATO | G49: 0 | H49: 0 | K49: Amy Smiley | L49: 0.6744186 | M49: 0.65116279 | N49: 0
B50: Absenteeism | C50: 108.73333 | D50: 0.046884994 | F50: Absenteeism | G50: 117.93333 | H50: 0.053749801 | K50: Chasady Parker | L50: 0.34065934 | M50: 0.69230769 | N50: 0
B51: LOA / Bereavment | C51: 187 | D51: 0.080632991 | F51: LOA / Bereavment | G51: 170 | H51: 0.077479927 | K51: Douglas Barnes | L51: 1.0512821 | M51: 0.87179487 | N51: 0
B52: Scheduled OT | C52: 0 | D52: 0 | F52: Scheduled OT | G52: 0 | H52: 0 | K52: Chanetta Gant | L52: 0.75182482 | M52: 0.68613139 | N52: 0 | P52: Total | Q52: 37 | R52: Total | S52: 52
B53: Make Up Time | C53: 0 | D53: 0 | F53: Make Up Time | G53: 0 | H53: 0 | K53: Mohamed Bayoumy | L53: 0.70056497 | M53: 0.97740113 | N53: 0
B54: Coaching / Meeting / Team Huddle | C54: 37.166667 | D54: 0.016025987 | F54: Coaching / Meeting / Team Huddle | G54: 51.666667 | H54: 0.023547821 | K54: Matthew Livingstone | L54: 1.0093458 | M54: 1.0747664 | N54: 0
B55: SME / Peer Coaching | C55: 2.25 | D55: 0.00097018304 | F55: SME / Peer Coaching | G55: 0 | H55: 0 | K55: Christina Johnson | L55: 0 | M55: 0 | N55: 0
B56: Back Office / Off Queue | C56: 0 | D56: 0 | F56: Back Office / Off Queue | G56: 0 | H56: 0
B57: Training | C57: 0 | D57: 0 | F57: Training | G57: 155.35 | H57: 0.070802981
B58: Outbound Calls | C58: 1.4166667 | D58: 0.00061085599 | F58: Outbound Calls | G58: 1.4666667 | H58: 0.00066845428
B59: System Issues | C59: 15.683333 | D59: 0.0067625351 | F59: System Issues | G59: 6.45 | H59: 0.0029396796
B60: No Ticket Time | C60: 8.9833333 | D60: 0.0038735456 | F60: No Ticket Time | G60: 10.866667 | H60: 0.0049526385
B61: Flex Time / Unavailable | C61: 0 | D61: 0 | F61: Flex Time / Unavailable | G61: 0 | H61: 0
B62: Site Closure | C62: 0 | D62: 0 | F62: Site Closure | G62: 0 | H62: 0
B63: 0 | C63: 0 | D63: 0 | F63: 0 | G63: 0 | H63: 0
B64: Productive Time | C64: Unproductive Time | F64: Productive Time | G64: Unproductive Time
B65: 0.79641248 | C65: 0.20358752 | F65: 0.7859655 | G65: 0.2140345

Sheet Shrink
A1: Agent Name | B1: Activity Code Name | C1: Description | D1: Is Paid | E1: Length In Minutes | F1: Start (New_York) | G1: End (New_York)
A2: Amy Smiley | B2: Vacation | C2: Gary - ticket # 13495- PTO for March 30th, 31st , April 1st,2nd,3rd - wfm approved | D2: Yes | E2: 450 | F2: 46113.417 | G2: 46113.729 | J2: Total Schedule Time | K2: =SUM(K3:K36) -> 203694 | N2: Sales - Tel Reg
A3: Amy Smiley | B3: End of shift | D3: No | E3: 60 | F3: 46113.729 | G3: 46113.771 | J3: Vacation | K3: =SUMIF($B$2:$B$100000,"Vacation",$E$2:$E$100000) -> 4020 | N3: Total Schedule Time | O3: =K2/60 -> 3394.9
A4: Amy Smiley | B4: Vacation | C4: Gary - ticket # 13495- PTO for March 30th, 31st , April 1st,2nd,3rd - wfm approved | D4: Yes | E4: 450 | F4: 46114.417 | G4: 46114.729 | J4: On Queue | K4: =SUMIF($B$2:$B$100000,"On Queue",$E$2:$E$100000) -> 125088 | N4: On Queue Time / Nesting | O4: =(K4+K18)/60 -> 2084.8 | P4: =O4/$O$3 -> 0.61409762
A5: Amy Smiley | B5: End of shift | D5: No | E5: 60 | F5: 46114.729 | G5: 46114.771 | J5: VTO | K5: =SUMIF($B$2:$B$100000,"VTO",$E$2:$E$100000) -> 428 | N5: PTO | O5: =K3/60 -> 67 | P5: =O5/$O$3 -> 0.019735486
A6: Amy Smiley | B6: Vacation | C6: Gary - ticket # 13495- PTO for March 30th, 31st , April 1st,2nd,3rd - wfm approved | D6: Yes | E6: 330 | F6: 46115.375 | G6: 46115.604 | J6: MATO | K6: =SUMIF($B$2:$B$100000,"MATO",$E$2:$E$100000) -> 0 | N6: Break | O6: =K19/60 -> 160.45 | P6: =O6/$O$3 -> 0.04726207
A7: Amy Smiley | B7: End of shift | D7: No | E7: 60 | F7: 46115.604 | G7: 46115.646 | J7: Weather - Site Closure | K7: =SUMIF($B$2:$B$100000,"Weather - Site Closure",$E$2:$E$100000) -> 0 | N7: Lunch | O7: =K20/60 -> 165.31667 | P7: =O7/$O$3 -> 0.048695592
A8: Amy Smiley | B8: Absent | D8: No | E8: 330 | F8: 46118.375 | G8: 46118.604 | J8: NCNS | K8: =SUMIF($B$2:$B$100000,"NCNS",$E$2:$E$100000) -> 2184 | N8: VTO / MATO | O8: =(K5+K6)/60 -> 7.1333333 | P8: =O8/$O$3 -> 0.002101191
A9: Amy Smiley | B9: End of shift | D9: No | E9: 60 | F9: 46118.604 | G9: 46118.646 | J9: Absent | K9: =SUMIF($B$2:$B$100000,"Absent ",$E$2:$E$100000) -> 10680 | N9: Absenteeism | O9: =(K8+K9+K10+K11+K12+K13)/60 -> 376.78333 | P9: =O9/$O$3 -> 0.11098511
A10: Amy Smiley | B10: Absent | D10: No | E10: 330 | F10: 46119.375 | G10: 46119.604 | J10: Late | K10: =SUMIF($B$2:$B$100000,"Late",$E$2:$E$100000) -> 1400 | N10: LOA / Bereavment | O10: =(K16+K17)/60 -> 153 | P10: =O10/$O$3 -> 0.045067601
A11: Amy Smiley | B11: End of shift | D11: No | E11: 60 | F11: 46119.604 | G11: 46119.646 | J11: Left Early | K11: =SUMIF($B$2:$B$100000,"Left Early",$E$2:$E$100000) -> 2906 | N11: Scheduled OT | O11: =K14/60 -> 6 | P11: =O11/$O$3 -> 0.0017673569
A12: Amy Smiley | B12: On Queue | D12: Yes | E12: 120 | F12: 46120.417 | G12: 46120.5 | J12: Shift Abandoned | K12: =SUMIF($B$2:$B$100000,"Shift Abandoned",$E$2:$E$100000) -> 4417 | N12: Make Up Time | O12: =K15/60 -> 0 | P12: =O12/$O$3 -> 0
A13: Amy Smiley | B13: Break | D13: Yes | E13: 15 | F13: 46120.5 | G13: 46120.51 | J13: Termed | K13: =SUMIF($B$2:$B$100000,"Termed",$E$2:$E$100000) -> 1020 | N13: Coaching / Meeting / Team Huddle | O13: =(K21+K22+K23)/60 -> 54.666667 | P13: =O13/$O$3 -> 0.016102585
A14: Amy Smiley | B14: On Queue | D14: Yes | E14: 12 | F14: 46120.51 | G14: 46120.519 | J14: Scheduled OT | K14: =SUMIF($B$2:$B$100000,"Scheduled OT",$E$2:$E$100000) -> 360 | N14: SME / Peer Coaching | O14: =(K24+K25)/60 -> 2.5 | P14: =O14/$O$3 -> 0.00073639872
A15: Amy Smiley | B15: Coaching | C15: William Coad Ticket # 14609:Coaching 15 mins 1230pm | D15: Yes | E15: 15 | F15: 46120.519 | G15: 46120.529 | J15: Make Up Time | K15: =SUMIF($B$2:$B$100000,"MUT",$E$2:$E$100000) -> 0 | N15: Back Office / Off Queue | O15: =(K26+K27)/60 -> 0 | P15: =O15/$O$3 -> 0
A16: Amy Smiley | B16: No ticket | D16: Yes | E16: 6 | F16: 46120.529 | G16: 46120.533 | J16: LOA | K16: =SUMIF($B$2:$B$100000,"LOA",$E$2:$E$100000) -> 8670 | N16: Training | O16: =(K29+K30)/60 -> 252.85 | P16: =O16/$O$3 -> 0.074479366
A17: Amy Smiley | B17: On Queue | D17: Yes | E17: 87 | F17: 46120.533 | G17: 46120.594 | J17: Bereavement | K17: =SUMIF($B$2:$B$100000,"Bereavement",$E$2:$E$100000) -> 510 | N17: Outbound Calls | O17: =(K31+K32)/60 -> 5.2833333 | P17: =O17/$O$3 -> 0.001556256
A18: Amy Smiley | B18: Meal | D18: No | E18: 30 | F18: 46120.594 | G18: 46120.615 | J18: Nesting | K18: =SUMIF($B$2:$B$100000,"Nesting",$E$2:$E$100000) -> 0 | N18: System Issues | O18: =(K33+K34)/60 -> 37.383333 | P18: =O18/$O$3 -> 0.011011615
A19: Amy Smiley | B19: On Queue | D19: Yes | E19: 165 | F19: 46120.615 | G19: 46120.729 | J19: Break | K19: =SUMIF($B$2:$B$100000,"Break",$E$2:$E$100000) -> 9627 | N19: No Ticket Time | O19: =(K35+K36)/60 -> 21.733333 | P19: =O19/$O$3 -> 0.0064017595
A20: Amy Smiley | B20: End of shift | D20: No | E20: 60 | F20: 46120.729 | G20: 46120.771 | J20: Meal | K20: =SUMIF($B$2:$B$100000,"Meal",$E$2:$E$100000) -> 9919 | N20: Flex Time / Unavailable | O20: =K28/60 -> 0 | P20: =O20/$O$3 -> 0
A21: Amy Smiley | B21: No ticket | D21: Yes | E21: 6 | F21: 46121.412 | G21: 46121.417 | J21: Coaching | K21: =SUMIF($B$2:$B$100000,"Coaching ",$E$2:$E$100000) -> 554 | N21: Site Closure | O21: =K7/60 -> 0 | P21: =O21/$O$3 -> 0
A22: Amy Smiley | B22: On Queue | D22: Yes | E22: 45 | F22: 46121.417 | G22: 46121.448 | J22: Team Huddle | K22: =SUMIF($B$2:$B$100000,"Team Huddle",$E$2:$E$100000) -> 1363
A23: Amy Smiley | B23: Shift Abandoned | D23: No | E23: 6 | F23: 46121.448 | G23: 46121.452 | J23: Meeting | K23: =SUMIF($B$2:$B$100000,"Team Huddle",$E$2:$E$100000) -> 1363 | N23: Productive Time | O23: Unproductive Time
A24: Amy Smiley | B24: On Queue | D24: Yes | E24: 69 | F24: 46121.452 | G24: 46121.5 | J24: Peer Coaching | K24: =SUMIF($B$2:$B$100000,"Meeting",$E$2:$E$100000) -> 150 | N24: =P4+P6+P11+P12+P13+P14+P15+P16+P17 -> 0.75600165 | O24: =P5+P7+P8+P9+P10+P18+P19+P20+P21 -> 0.24399835
A25: Amy Smiley | B25: Break | D25: Yes | E25: 15 | F25: 46121.5 | G25: 46121.51 | J25: SME Support | K25: =SUMIF($B$2:$B$100000,"SME Support",$E$2:$E$100000) -> 0
A26: Amy Smiley | B26: On Queue | D26: Yes | E26: 105 | F26: 46121.51 | G26: 46121.583 | J26: Back Office | K26: =SUMIF($B$2:$B$100000,"Back Office",$E$2:$E$100000) -> 0
A27: Amy Smiley | B27: Meal | D27: No | E27: 30 | F27: 46121.583 | G27: 46121.604 | J27: Off Queue | K27: =SUMIF($B$2:$B$100000,"Off Queue",$E$2:$E$100000) -> 0
A28: Amy Smiley | B28: On Queue | D28: Yes | E28: 180 | F28: 46121.604 | G28: 46121.729 | J28: Unavailable | K28: =SUMIF($B$2:$B$100000,"Unavailable",$E$2:$E$100000) -> 0
A29: Amy Smiley | B29: End of shift | D29: No | E29: 60 | F29: 46121.729 | G29: 46121.771 | J29: Training | K29: =SUMIF($B$2:$B$100000,"Training",$E$2:$E$100000) -> 585
A30: Amy Smiley | B30: On Queue | D30: Yes | E30: 144 | F30: 46122.375 | G30: 46122.475 | J30: Client Training | K30: =SUMIF($B$2:$B$100000,"Client Training",$E$2:$E$100000) -> 14586
A31: Amy Smiley | B31: Shift Abandoned | D31: No | E31: 5 | F31: 46122.475 | G31: 46122.478 | J31: Outbound | K31: =SUMIF($B$2:$B$100000,"Outbound",$E$2:$E$100000) -> 0
A32: Amy Smiley | B32: On Queue | D32: Yes | E32: 16 | F32: 46122.478 | G32: 46122.49 | J32: Agent Customer Callback | K32: =SUMIF($B$2:$B$100000,"Agent Customer Callback",$E$2:$E$100000) -> 317
A33: Amy Smiley | B33: Meal | D33: No | E33: 30 | F33: 46122.49 | G33: 46122.51 | J33: D&G System Outage | K33: =SUMIF($B$2:$B$100000,"D&G System Outage",$E$2:$E$100000) -> 0
A34: Amy Smiley | B34: On Queue | D34: Yes | E34: 135 | F34: 46122.51 | G34: 46122.604 | J34: Agent System Issues | K34: =SUMIF($B$2:$B$100000,"Agent System Issues",$E$2:$E$100000) -> 2243
A35: Amy Smiley | B35: End of shift | D35: No | E35: 60 | F35: 46122.604 | G35: 46122.646 | J35: No ticket | K35: =SUMIF($B$2:$B$100000,"No Ticket",$E$2:$E$100000) -> 1018
A36: Amy Smiley | B36: On Queue | D36: Yes | E36: 110 | F36: 46125.375 | G36: 46125.451 | J36: Off Queue - No Ticket/Request | K36: =SUMIF($B$2:$B$100000,"Off Queue - No Ticket/Request",$E$2:$E$100000) -> 286
A37: Amy Smiley | B37: Left Early | D37: No | E37: 91 | F37: 46125.451 | G37: 46125.515
A38: Amy Smiley | B38: On Queue | D38: Yes | E38: 129 | F38: 46125.515 | G38: 46125.604
A39: Amy Smiley | B39: End of shift | D39: No | E39: 60 | F39: 46125.604 | G39: 46125.646
A40: Amy Smiley | B40: Absent | C40: called in as absent- claimed has PTO - no ticket submitted in advance . | D40: No | E40: 330 | F40: 46126.375 | G40: 46126.604
A41: Amy Smiley | B41: End of shift | D41: No | E41: 60 | F41: 46126.604 | G41: 46126.646
A42: Amy Smiley | B42: On Queue | D42: Yes | E42: 120 | F42: 46127.417 | G42: 46127.5
A43: Amy Smiley | B43: Break | D43: Yes | E43: 15 | F43: 46127.5 | G43: 46127.51
A44: Amy Smiley | B44: On Queue | D44: Yes | E44: 19 | F44: 46127.51 | G44: 46127.524
A45: Amy Smiley | B45: Shift Abandoned | C45: on queue and not responding for 9 mins | D45: No | E45: 9 | F45: 46127.524 | G45: 46127.53
A46: Amy Smiley | B46: On Queue | D46: Yes | E46: 77 | F46: 46127.53 | G46: 46127.583
A47: Amy Smiley | B47: Meal | D47: No | E47: 30 | F47: 46127.583 | G47: 46127.604
A48: Amy Smiley | B48: Shift Abandoned | C48: Long lunch | D48: No | E48: 6 | F48: 46127.604 | G48: 46127.608
A49: Amy Smiley | B49: On Queue | D49: Yes | E49: 174 | F49: 46127.608 | G49: 46127.729
A50: Amy Smiley | B50: End of shift | D50: No | E50: 60 | F50: 46127.729 | G50: 46127.771
A51: Amy Smiley | B51: On Queue | D51: Yes | E51: 120 | F51: 46128.417 | G51: 46128.5
A52: Amy Smiley | B52: Break | D52: Yes | E52: 15 | F52: 46128.5 | G52: 46128.51
A53: Amy Smiley | B53: On Queue | D53: Yes | E53: 120 | F53: 46128.51 | G53: 46128.594
A54: Amy Smiley | B54: Meal | D54: No | E54: 30 | F54: 46128.594 | G54: 46128.615
A55: Amy Smiley | B55: On Queue | D55: Yes | E55: 26 | F55: 46128.615 | G55: 46128.633
A56: Amy Smiley | B56: Agent System Issues | C56: Eddie Mendoza Ticket # 15232:System issues 2:44 pm. 21 minutes to restart SRW. | D56: No | E56: 15 | F56: 46128.633 | G56: 46128.643
A57: Amy Smiley | B57: On Queue | D57: Yes | E57: 124 | F57: 46128.643 | G57: 46128.729
A58: Amy Smiley | B58: End of shift | D58: No | E58: 60 | F58: 46128.729 | G58: 46128.771
A59: Amy Smiley | B59: On Queue | D59: Yes | E59: 65 | F59: 46129.375 | G59: 46129.42
A60: Amy Smiley | B60: Shift Abandoned | D60: No | E60: 7 | F60: 46129.42 | G60: 46129.425
A61: Amy Smiley | B61: On Queue | D61: Yes | E61: 93 | F61: 46129.425 | G61: 46129.49
A62: Amy Smiley | B62: Meal | D62: No | E62: 30 | F62: 46129.49 | G62: 46129.51
A63: Amy Smiley | B63: On Queue | D63: Yes | E63: 15 | F63: 46129.51 | G63: 46129.521
A64: Amy Smiley | B64: Team Huddle | C64: Presched Huddle -NO EXTENTION | D64: Yes | E64: 29 | F64: 46129.521 | G64: 46129.541
A65: Amy Smiley | B65: No ticket | D65: Yes | E65: 7 | F65: 46129.541 | G65: 46129.546
A66: Amy Smiley | B66: On Queue | D66: Yes | E66: 84 | F66: 46129.546 | G66: 46129.604
A67: Amy Smiley | B67: End of shift | D67: No | E67: 60 | F67: 46129.604 | G67: 46129.646
A68: Amy Smiley | B68: On Queue | D68: Yes | E68: 105 | F68: 46132.375 | G68: 46132.448
A69: Amy Smiley | B69: Break | D69: Yes | E69: 15 | F69: 46132.448 | G69: 46132.458
A70: Amy Smiley | B70: On Queue | D70: Yes | E70: 19 | F70: 46132.458 | G70: 46132.472
A71: Amy Smiley | B71: Agent Customer Callback | D71: Yes | E71: 5 | F71: 46132.472 | G71: 46132.475
A72: Amy Smiley | B72: On Queue | D72: Yes | E72: 141 | F72: 46132.475 | G72: 46132.573
A73: Amy Smiley | B73: Meal | D73: No | E73: 30 | F73: 46132.573 | G73: 46132.594
A74: Amy Smiley | B74: On Queue | D74: Yes | E74: 90 | F74: 46132.594 | G74: 46132.656
A75: Amy Smiley | B75: Break | D75: Yes | E75: 15 | F75: 46132.656 | G75: 46132.667
A76: Amy Smiley | B76: On Queue | D76: Yes | E76: 90 | F76: 46132.667 | G76: 46132.729
... A82: Amy Smiley | B82: On Queue | D82: Yes | E82: 16 | F82: 46133.51 | G82: 46133.522
A83: Amy Smiley | B83: Agent Customer Callback | C83: William Coad Ticket # 15530:Call Back request Amy Smiley 925-278-9525 1231pm | D83: Yes | E83: 5 | F83: 46133.522 | G83: 46133.525
A84: Amy Smiley | B84: On Queue | D84: Yes | E84: 9 | F84: 46133.525 | G84: 46133.531
A85: Amy Smiley | B85: Coaching | C85: William Coad Ticket # 15498:Coaching 15 mins 1145am - William asked for it to be moved | D85: Yes | E85: 15 | F85: 46133.531 | G85: 46133.542
A86: Amy Smiley | B86: On Queue | D86: Yes | E86: 34 | F86: 46133.542 | G86: 46133.565
A87: Amy Smiley | B87: Agent Customer Callback | C87: William Coad Ticket # 15538:Call Back request Amy Smiley (315) 219-9011 134pm | D87: Yes | E87: 5 | F87: 46133.565 | G87: 46133.569
A88: Amy Smiley | B88: On Queue | D88: Yes | E88: 51 | F88: 46133.569 | G88: 46133.604
A89: Amy Smiley | B89: End of shift | D89: No | E89: 60 | F89: 46133.604 | G89: 46133.646
A90: Amy Smiley | B90: Client Training | D90: Yes | E90: 120 | F90: 46134.417 | G90: 46134.5
A91: Amy Smiley | B91: Break | D91: Yes | E91: 15 | F91: 46134.5 | G91: 46134.51
A92: Amy Smiley | B92: Client Training | D92: Yes | E92: 105 | F92: 46134.51 | G92: 46134.583
A93: Amy Smiley | B93: Meal | D93: No | E93: 30 | F93: 46134.583 | G93: 46134.604
A94: Amy Smiley | B94: Client Training | D94: Yes | E94: 90 | F94: 46134.604 | G94: 46134.667
A95: Amy Smiley | B95: Break | D95: Yes | E95: 15 | F95: 46134.667 | G95: 46134.677
A96: Amy Smiley | B96: Client Training | D96: Yes | E96: 105 | F96: 46134.677 | G96: 46134.75
A97: Amy Smiley | B97: End of shift | D97: No | E97: 60 | F97: 46134.75 | G97: 46134.792
A98: Amy Smiley | B98: Late | D98: No | E98: 10 | F98: 46135.417 | G98: 46135.424
A99: Amy Smiley | B99: Client Training | D99: Yes | E99: 110 | F99: 46135.424 | G99: 46135.5
... A109: Amy Smiley | B109: On Queue | D109: Yes | E109: 15 | F109: 46136.51 | G109: 46136.521
A110: Amy Smiley | B110: Team Huddle | C110: Presched Huddle -NO EXTENTION | D110: Yes | E110: 30 | F110: 46136.521 | G110: 46136.542
A111: Amy Smiley | B111: On Queue | D111: Yes | E111: 90 | F111: 46136.542 | G111: 46136.604
A112: Amy Smiley | B112: End of shift | D112: No | E112: 60 | F112: 46136.604 | G112: 46136.646
A113: Amy Smiley | B113: On Queue | D113: Yes | E113: 105 | F113: 46139.375 | G113: 46139.448
A114: Amy Smiley | B114: Break | D114: Yes | E114: 15 | F114: 46139.448 | G114: 46139.458
...

Sheet Eval
P1: Agent Name | Q1: Agent Email | R1: Evaluations | S1: Average Score | T1: Average Critical Score
B2: TL | C2: Associate | D2: Evaluations | E2: Average Score | F2: Average Critical Score | P2: Aaliyah Kemp | Q2: Aaliyah.Kemp@corp.spdatallc.com | R2: 2 | S2: 0.89 | T2: 0
B3: Will | C3: Amy Smiley | D3: =_xlfn.XLOOKUP(C3,P:P,R:R,0) -> 0 | E3: =_xlfn.XLOOKUP(C3,P:P,S:S,0) -> 0 | F3: =_xlfn.XLOOKUP(C3,P:P,T:T,0) -> 0 | P3: Aana Taufiq | Q3: Aana.Taufiq@corp.spdatallc.com
B4: Will | C4: Angelica Gonzalez | D4: =_xlfn.XLOOKUP(C4,P:P,R:R,0) -> 0 | E4: =_xlfn.XLOOKUP(C4,P:P,S:S,0) -> 0 | F4: =_xlfn.XLOOKUP(C4,P:P,T:T,0) -> 0 | P4: Aaron Alfaro02 | Q4: Aaron.alfaro02@movate.com
B5: Will | C5: Chanetta Gant | D5: =_xlfn.XLOOKUP(C5,P:P,R:R,0) -> 0 | E5: =_xlfn.XLOOKUP(C5,P:P,S:S,0) -> 0 | F5: =_xlfn.XLOOKUP(C5,P:P,T:T,0) -> 0 | P5: Aaron Royal | Q5: Aaron.Royal@corp.spdatallc.com
B6: Will | C6: Chasady Parker | D6: =_xlfn.XLOOKUP(C6,P:P,R:R,0) -> 0 | E6: =_xlfn.XLOOKUP(C6,P:P,S:S,0) -> 0 | F6: =_xlfn.XLOOKUP(C6,P:P,T:T,0) -> 0 | P6: Abdifitah Ahmed | Q6: Abdifitah.Ahmed@corp.spdatallc.com | R6: 2 | S6: 0.89 | T6: 0
B7: Will | C7: Christina Johnson | D7: =_xlfn.XLOOKUP(C7,P:P,R:R,0) -> 0 | E7: =_xlfn.XLOOKUP(C7,P:P,S:S,0) -> 0 | F7: =_xlfn.XLOOKUP(C7,P:P,T:T,0) -> 0 | P7: Abhiuday Pundir | Q7: Abhiuday.Pundir@corp.spdatallc.com | R7: 2 | S7: 0.91 | T7: 0
B8: Will | C8: Douglas Barnes | D8: =_xlfn.XLOOKUP(C8,P:P,R:R,0) -> 9 | E8: =_xlfn.XLOOKUP(C8,P:P,S:S,0) -> 0.9 | F8: =_xlfn.XLOOKUP(C8,P:P,T:T,0) -> 1 | P8: Abigail Ruiz | Q8: Abigail.Ruiz@movate.com
B9: Will | C9: Khadijah Young | D9: =_xlfn.XLOOKUP(C9,P:P,R:R,0) -> 5 | E9: =_xlfn.XLOOKUP(C9,P:P,S:S,0) -> 0.87 | F9: =_xlfn.XLOOKUP(C9,P:P,T:T,0) -> 1 | P9: Abinash Sritharan | Q9: Abinash.Sritharan@corp.spdatallc.com | R9: 2 | S9: 0.98 | T9: 0
B10: Will | C10: Larry Moorehead | D10: =_xlfn.XLOOKUP(C10,P:P,R:R,0) -> 5 | E10: =_xlfn.XLOOKUP(C10,P:P,S:S,0) -> 1 | F10: =_xlfn.XLOOKUP(C10,P:P,T:T,0) -> 1 | P10: Abraham.Martinez | Q10: Abraham.Martinez@movate.com | R10: 4 | S10: 1 | T10: 0
B11: Will | C11: Margaret Reddy | D11: =_xlfn.XLOOKUP(C11,P:P,R:R,0) -> 5 | E11: =_xlfn.XLOOKUP(C11,P:P,S:S,0) -> 0.9 | F11: =_xlfn.XLOOKUP(C11,P:P,T:T,0) -> 1 | P11: Adam Wilkes | Q11: Adam.Wilkes@domesticandgeneral.com
B12: Will | C12: Matthew Livingstone | D12: =_xlfn.XLOOKUP(C12,P:P,R:R,0) -> 5 | E12: =_xlfn.XLOOKUP(C12,P:P,S:S,0) -> 0.92 | F12: =_xlfn.XLOOKUP(C12,P:P,T:T,0) -> 1 | P12: Aditya Karnawat | Q12: Aditya.Karnawat@corp.spdatallc.com
B13: Will | C13: Mohamed Bayoumy | D13: =_xlfn.XLOOKUP(C13,P:P,R:R,0) -> 5 | E13: =_xlfn.XLOOKUP(C13,P:P,S:S,0) -> 0.98 | F13: =_xlfn.XLOOKUP(C13,P:P,T:T,0) -> 0.90476196 | P13: Adnan Malik | Q13: Adnan.Malik@corp.spdatallc.com
B14: Will | C14: Perry Young III | D14: =_xlfn.XLOOKUP(C14,P:P,R:R,0) -> 5 | E14: =_xlfn.XLOOKUP(C14,P:P,S:S,0) -> 0.99 | F14: =_xlfn.XLOOKUP(C14,P:P,T:T,0) -> 1 | P14: Adonis Rosalle | Q14: Adonis.Rosalle@corp.spdatallc.com
B15: Will | C15: Regina Watson | D15: =_xlfn.XLOOKUP(C15,P:P,R:R,0) -> 5 | E15: =_xlfn.XLOOKUP(C15,P:P,S:S,0) -> 1 | F15: =_xlfn.XLOOKUP(C15,P:P,T:T,0) -> 1 | P15: Adrian Marin | Q15: Adrian.Marin@movate.com
B16: Nick | C16: Carla Grant | D16: =_xlfn.XLOOKUP(C16,P:P,R:R,0) -> 0 | E16: =_xlfn.XLOOKUP(C16,P:P,S:S,0) -> 0 | F16: =_xlfn.XLOOKUP(C16,P:P,T:T,0) -> 0 | P16: Adrian Rapadas | Q16: Adrian.Rapadas@corp.spdatallc.com
B17: Nick | C17: Cassiddy Jordan | D17: =_xlfn.XLOOKUP(C17,P:P,R:R,0) -> 0 | E17: =_xlfn.XLOOKUP(C17,P:P,S:S,0) -> 0 | F17: =_xlfn.XLOOKUP(C17,P:P,T:T,0) -> 0 | P17: Adrian Underwood | Q17: Adrian.Underwood@corp.spdatallc.com
B18: Nick | C18: Christian Elizabeth | D18: =_xlfn.XLOOKUP(C18,P:P,R:R,0) -> 0 | E18: =_xlfn.XLOOKUP(C18,P:P,S:S,0) -> 0 | F18: =_xlfn.XLOOKUP(C18,P:P,T:T,0) -> 0 | P18: Adriana Alejandra Ayala Orellana | Q18: aaayala@theofficegurus.biz
B19: Nick | C19: Destiny Rich | D19: =_xlfn.XLOOKUP(C19,P:P,R:R,0) -> 6 | E19: =_xlfn.XLOOKUP(C19,P:P,S:S,0) -> 0.8 | F19: =_xlfn.XLOOKUP(C19,P:P,T:T,0) -> 1 | P19: Adriana Daniela Molina Tobares | Q19: adtobares@theofficegurus.biz | R19: 1 | S19: 0.77 | T19: 0
B20: Nick | C20: Dinesh Kandoth | D20: =_xlfn.XLOOKUP(C20,P:P,R:R,0) -> 6 | E20: =_xlfn.XLOOKUP(C20,P:P,S:S,0) -> 0.85 | F20: =_xlfn.XLOOKUP(C20,P:P,T:T,0) -> 1 | P20: Ahmed Nur | Q20: Ahmed.Nur@corp.spdatallc.com
B21: Nick | C21: Donna Plummer | D21: =_xlfn.XLOOKUP(C21,P:P,R:R,0) -> 6 | E21: =_xlfn.XLOOKUP(C21,P:P,S:S,0) -> 0.87 | F21: =_xlfn.XLOOKUP(C21,P:P,T:T,0) -> 1 | P21: Akeem Aman | Q21: Akeem.Aman@corp.spdatallc.com
B22: Nick | C22: Eric Brown | D22: =_xlfn.XLOOKUP(C22,P:P,R:R,0) -> 6 | E22: =_xlfn.XLOOKUP(C22,P:P,S:S,0) -> 0.82 | F22: =_xlfn.XLOOKUP(C22,P:P,T:T,0) -> 1 | P22: Akhil Karra | Q22: Akhil.Karra@corp.spdatallc.com | R22: 2 | S22: 0.81 | T22: 0
B23: Nick | C23: Heather Kester | D23: =_xlfn.XLOOKUP(C23,P:P,R:R,0) -> 6 | E23: =_xlfn.XLOOKUP(C23,P:P,S:S,0) -> 0.93 | F23: =_xlfn.XLOOKUP(C23,P:P,T:T,0) -> 1 | P23: Akib Lipu | Q23: Akib.Lipu@corp.spdatallc.com
B24: Nick | C24: Javier Ottenwalder | D24: =_xlfn.XLOOKUP(C24,P:P,R:R,0) -> 7 | E24: =_xlfn.XLOOKUP(C24,P:P,S:S,0) -> 0.95 | F24: =_xlfn.XLOOKUP(C24,P:P,T:T,0) -> 1 | P24: Alan Bladimir Funes Ventura | Q24: afunes@theofficegurus.biz
B25: Nick | C25: Kellee Silva | D25: =_xlfn.XLOOKUP(C25,P:P,R:R,0) -> 5 | E25: =_xlfn.XLOOKUP(C25,P:P,S:S,0) -> 0.96 | F25: =_xlfn.XLOOKUP(C25,P:P,T:T,0) -> 1 | P25: Alan Houston | Q25: Alan.Houston@domesticandgeneral.com
B26: Nick | C26: Marcia Fabry | D26: =_xlfn.XLOOKUP(C26,P:P,R:R,0) -> 5 | E26: =_xlfn.XLOOKUP(C26,P:P,S:S,0) -> 0.99 | F26: =_xlfn.XLOOKUP(C26,P:P,T:T,0) -> 1 | P26: Albany Covington-Owens | Q26: Albany.Owens@corp.spdatallc.com
B27: Nick | C27: Michael Moyer | D27: =_xlfn.XLOOKUP(C27,P:P,R:R,0) -> 5 | E27: =_xlfn.XLOOKUP(C27,P:P,S:S,0) -> 0.96 | F27: =_xlfn.XLOOKUP(C27,P:P,T:T,0) -> 1 | P27: Albert Hartinger | Q27: Albert.Hartinger@corp.spdatallc.com
B28: Nick | C28: Oyindamola Olajoye | D28: =_xlfn.XLOOKUP(C28,P:P,R:R,0) -> 5 | E28: =_xlfn.XLOOKUP(C28,P:P,S:S,0) -> 0.97 | F28: =_xlfn.XLOOKUP(C28,P:P,T:T,0) -> 1 | P28: Alberto Montoya | Q28: Alberto.Montoya@movate.com
B29: Nick | C29: Prottasha Prentice | D29: =_xlfn.XLOOKUP(C29,P:P,R:R,0) -> 5 | E29: =_xlfn.XLOOKUP(C29,P:P,S:S,0) -> 0.92 | F29: =_xlfn.XLOOKUP(C29,P:P,T:T,0) -> 1 | P29: Alberto Zeniff Montalvo Aguila | Q29: azmaguila@theofficegurus.biz
B30: Nick | C30: SHANIQUE REID | D30: =_xlfn.XLOOKUP(C30,P:P,R:R,0) -> 5 | E30: =_xlfn.XLOOKUP(C30,P:P,S:S,0) -> 0.85 | F30: =_xlfn.XLOOKUP(C30,P:P,T:T,0) -> 1 | P30: Aldrin D'Almeida | Q30: aldrin.d'almeida@domesticandgeneral.com
B31: Nick | C31: Tika Mayo | D31: =_xlfn.XLOOKUP(C31,P:P,R:R,0) -> 5 | E31: =_xlfn.XLOOKUP(C31,P:P,S:S,0) -> 0.88 | F31: =_xlfn.XLOOKUP(C31,P:P,T:T,0) -> 1 | P31: Alejandra Leticia Diaz Beltra | Q31: aldiaz@theofficegurus.biz
B32: Nick | C32: Tina Rogers | D32: =_xlfn.XLOOKUP(C32,P:P,R:R,0) -> 5 | E32: =_xlfn.XLOOKUP(C32,P:P,S:S,0) -> 0.79 | F32: =_xlfn.XLOOKUP(C32,P:P,T:T,0) -> 1 | P32: Alejandro Ernesto Cruz Barrientos | Q32: alecruz@theofficegurus.biz
B33: Nick | C33: Trevor Berry | D33: =_xlfn.XLOOKUP(C33,P:P,R:R,0) -> 5 | E33: =_xlfn.XLOOKUP(C33,P:P,S:S,0) -> 0.7 | F33: =_xlfn.XLOOKUP(C33,P:P,T:T,0) -> 1 | P33: Alessandro.Sedo | Q33: Alessandro.Sedo@movate.com
B34: Nick | C34: Uniqua Davis | D34: =_xlfn.XLOOKUP(C34,P:P,R:R,0) -> 6 | E34: =_xlfn.XLOOKUP(C34,P:P,S:S,0) -> 0.88 | F34: =_xlfn.XLOOKUP(C34,P:P,T:T,0) -> 1 | P34: Alex Clare | Q34: Alex.Clare@corp.spdatallc.com
B35: Nick | C35: Zycariah Fowler | D35: =_xlfn.XLOOKUP(C35,P:P,R:R,0) -> 0 | E35: =_xlfn.XLOOKUP(C35,P:P,S:S,0) -> 0 | F35: =_xlfn.XLOOKUP(C35,P:P,T:T,0) -> 0 | P35: Alexander Enrique Pinto Gomez | Q35: apinto@theofficegurus.biz
D36: =_xlfn.XLOOKUP(C36,P:P,R:R,0) -> 0 | E36: =_xlfn.XLOOKUP(C36,P:P,S:S,0) -> 0 | F36: =_xlfn.XLOOKUP(C36,P:P,T:T,0) -> 0 | P36: Alexander Figueroa | Q36: aafigueroa@theofficegurus.biz
D37: =_xlfn.XLOOKUP(C37,P:P,R:R,0) -> 0 | E37: =_xlfn.XLOOKUP(C37,P:P,S:S,0) -> 0 | F37: =_xlfn.XLOOKUP(C37,P:P,T:T,0) -> 0 | P37: Alexis Brown | Q37: Alexis.Brown@corp.spdatallc.com
D38: =_xlfn.XLOOKUP(C38,P:P,R:R,0) -> 0 | E38: =_xlfn.XLOOKUP(C38,P:P,S:S,0) -> 0 | F38: =_xlfn.XLOOKUP(C38,P:P,T:T,0) -> 0 | P38: Alexis Smith | Q38: Alexis.Smith@corp.spdatallc.com | R38: 2 | S38: 0.93 | T38: 0
D39: =_xlfn.XLOOKUP(C39,P:P,R:R,0) -> 0 | E39: =_xlfn.XLOOKUP(C39,P:P,S:S,0) -> 0 | F39: =_xlfn.XLOOKUP(C39,P:P,T:T,0) -> 0 | P39: Alicia Anderson | Q39: Alicia.Anderson@corp.spdatallc.com | R39: 2 | S39: 0.9 | T39: 0
D40: =_xlfn.XLOOKUP(C40,P:P,R:R,0) -> 0 | E40: =_xlfn.XLOOKUP(C40,P:P,S:S,0) -> 0 | F40: =_xlfn.XLOOKUP(C40,P:P,T:T,0) -> 0 | P40: Alicia Chase | Q40: Alicia.Chase@corp.spdatallc.com | R40: 2 | S40: 1 | T40: 0
D41: =_xlfn.XLOOKUP(C41,P:P,R:R,0) -> 0 | E41: =_xlfn.XLOOKUP(C41,P:P,S:S,0) -> 0 | F41: =_xlfn.XLOOKUP(C41,P:P,T:T,0) -> 0 | P41: Alicia Chavarria | Q41: Alicia.Chavarria@corp.spdatallc.com
B42: Total | D42: =SUBTOTAL(109,Table18[Evaluations]) -> 44 | E42: =SUBTOTAL(101,Table18[Average Score]) -> 0.58153846 | F42: =SUBTOTAL(101,Table18[Average Critical Score]) -> 0.60805861 | P42: Alicia Shields | Q42: Alicia.Shields@corp.spdatallc.com | R42: 2 | S42: 0.89 | T42: 0
P43: Aliesha Hoosain | Q43: Aliesha.Hoosain@corp.spdatallc.com
P44: Alirio Ruano | Q44: aeruano@theofficegurus.biz
P45: Alisha Williams | Q45: Alisha.Williams@corp.spdatallc.com
P46: Alissa Caskey | Q46: Alissa.Caskey@domesticandgeneral.com
P47: Alivia Haines | Q47: Alivia.Haines@corp.spdatallc.com
P48: Allan Giovanni Diaz Salamanca | Q48: agdias@theofficegurus.biz
P49: Allison Abigail Monterrosa Aguilar | Q49: aamaguilar@theofficegurus.biz | R49: 2 | S49: 0.48 | T49: 0
P50: Allison Sellers | Q50: Allison.Sellers@corp.spdatallc.com
P51: Almesha Shirley | Q51: Almesha.Shirley@corp.spdatallc.com
P52: Alonzia Perrin | Q52: Alonzia.Perrin@corp.spdatallc.com
P53: Alyse Vargas | Q53: Alyse.Vargas@corp.spdatallc.com
P54: Alyssa Torres | Q54: alyssa.torres@corp.spdatallc.com
P55: Amanda Ensz | Q55: Amanda.Ensz@corp.spdatallc.com
P56: Amanda Liriano | Q56: Amanda.Liriano@corp.spdatallc.com
P57: Amanda Mitchell | Q57: Amanda.Mitchell@corp.spdatallc.com
P58: Amanda Vega | Q58: Amanda.Vega@corp.spdatallc.com | R58: 2 | S58: 0.89 | T58: 0
P59: Amar Ramcharan | Q59: Amar.Ramcharan@corp.spdatallc.com
P60: Amarachi Nwodoh | Q60: Amarachi.Nwodoh@corp.spdatallc.com
P61: Amardeep Singh | Q61: Amardeep.Singh@corp.spdatallc.com | R61: 2 | S61: 0.77 | T61: 0
P62: Amit Bhamra | Q62: Amit.Bhamra@corp.spdatallc.com | R62: 2 | S62: 0.88 | T62: 0
P63: Amiyah Moye | Q63: Amiyah.Moye@corp.spdatallc.com
P64: Amresh Mungal | Q64: Amresh.Mungal@corp.spdatallc.com
P65: Amy Porter | Q65: Amy.Porter@corp.spdatallc.com | R65: 2 | S65: 0.94 | T65: 0
P66: Amy Smiley | Q66: amy.smiley@corp.spdatallc.com
P67: Amy Thomas | Q67: Amy.Thomas@corp.spdatallc.com
P68: Ana Patricia Flores Granados | Q68: apflores@theofficegurus.biz
P69: Ana Yancy Guadalupe Guerra Soto | Q69: aysoto@theofficegurus.biz
P70: Anastacia Hicks | Q70: anastacia.hicks@corp.spdatallc.com
P71: Anastasia Kalman | Q71: Anastasia.Kalman@corp.spdatallc.com
P72: Andre Bynoe | Q72: Andre.Bynoe@corp.spdatallc.com | R72: 2 | S72: 0.33 | T72: 0
P73: Andre Vladimir Romero Puente | Q73: avpuente@theofficegurus.biz | R73: 2 | S73: 0 | T73: 0
P74: Andrea Culbertson | Q74: Andrea.Culbertson@corp.spdatallc.com
P75: Andrea Elizabeth Benavides Velasquez | Q75: abenavides@theofficegurus.biz
P76: Andrea Guadalupe Franco Vasquez | Q76: agfvasquez@theofficegurus.biz | R76: 14 | S76: 0.83 | T76: 0
P77: Andrea Harris | Q77: Andrea.Harris@corp.spdatallc.com
P78: Andrea Manning | Q78: amanning2@contactusinc.com
P79: Andrea Sallee | Q79: asallee1@contactusinc.com
P80: Andres Barrantes | Q80: Andres.Barrantes@movate.com | R80: 1 | S80: 0.62 | T80: 0
P81: Andres Rodrigo Serrano Chinchilla | Q81: aserrano@theofficegurus.biz | R81: 6 | S81: 0.92 | T81: 0
P82: Andres Vindas | Q82: Andres.Vindas@movate.com
P83: Andrew Barratt | Q83: Andrew.Barratt@corp.spdatallc.com
P84: Andrew Bressi | Q84: abressi@contactusinc.com
P85: Andrew Henderson | Q85: andrew.henderson@domesticandgeneral.com
P86: Andrew Reid | Q86: Andrew.Reid@corp.spdatallc.com
P87: Andrey Marin | Q87: Andrey.Marin@movate.com | R87: 8 | S87: 0.77 | T87: 0
P88: Andy Vargas01 | Q88: Andy.Vargas01@movate.com
P89: Aneena Sheela Nath | Q89: AneenaSheela.Nath@corp.spdatallc.com
P90: Angel Ernesto Merlos Amaya | Q90: aemerlos@theofficegurus.biz
P91: Angel Scarbrough | Q91: Angel.Scarbrough@corp.spdatallc.com
P92: Angela Gonzales | Q92: Angela.Gonzales@corp.spdatallc.com
P93: Angelica Gonzalez | Q93: angelica.gonzalez@corp.spdatallc.com
P94: Angelica Martinez | Q94: Angelica.Martinez@corp.spdatallc.com
P95: Angella Dunn | Q95: Angella.Dunn@corp.spdatallc.com
P96: Angie Vega | Q96: Angie.Vega@movate.com | R96: 1 | S96: 0.79 | T96: 0
P97: Anil Somwaru | Q97: Anil.Somwaru@corp.spdatallc.com
P98: Ann Leblanc | Q98: Ann.Leblanc@corp.spdatallc.com
P99: Anna Herrera | Q99: Anna.Herrera@corp.spdatallc.com
P100: Anna Perez | Q100: Anna.perez@corp.spdatallc.com
...

Sheet ININ
P1: Interval Start | Q1: Interval End | R1: Interval Complete | S1: Filters | T1: Media Type | U1: Agent Id | V1: Agent Name | W1: Answered | X1: Handle | Y1: Avg Handle | Z1: Avg Talk | AA1: Avg Hold | AB1: Avg ACW | AC1: Held | AD1: Transferred
I2: Row Labels | J2: Sum of Handle | P2: 46068 | Q2: 46075.021 | R2: TRUE | S2: Wrap-up: ININ-WRAP-UP-TIMEOUT; Work Team: S&P Campaign - Team Danielle McMullan; Work Team: S&P Flex Trainer and SME Team; Work Team: S&P Outbound - Team Eddie Mendoza; Work Team: S&P Retention Agents - Team William Coad; Work Team: S&P Retention Service - Team Nicholas Boudreau; Work Team: S&P Service - Nesting 1; Work Team: S&P Service - Team John Burdett; Work Team: S&P Service - Team Reina Morales; Work Team: S&P Service - Team Stefano Lista; Work Team: S&P Tel Reg - Nesting ; Work Team: S&P Tel Reg - Nesting 2; Work Team: S&P Tel Reg - Team Alex Clare; Work Team: S&P Tel Reg - Team Brian Finnstrom; Work Team: S&P Tel Reg - Team Charnetta Hull; Work Team: S&P Tel Reg - Team David Densmore; Work Team: S&P Tel Reg - Team David Locke; Work Team: S&P Tel Reg - Team Jaime Collazo; Work Team: S&P Tel Reg - Team Michael Garrion; Work Team: S&P Tel Reg - Team Raul Tejada; Work Team: S&P Tel Reg - Team Terrence Toepler | T2: voice | U2: 9ea94676-2d91-4cc9-9b19-eefd38914c27 | V2: Aaliyah Kemp | X2: 2 | Y2: 1282292.5 | Z2: 1242292.5 | AB2: 40000
C3: Amy Smiley | D3: =_xlfn.XLOOKUP(C3,I:I,J:J,0) -> 0 | I3: Aaliyah Kemp | J3: 2 | P3: 46068 | Q3: 46075.021 | R3: TRUE | S3: Wrap-up: ININ-WRAP-UP-TIMEOUT; Work Team: S&P Campaign - Team Danielle McMullan; Work Team: S&P Flex Trainer and SME Team; Work Team: S&P Outbound - Team Eddie Mendoza; Work Team: S&P Retention Agents - Team William Coad; Work Team: S&P Retention Service - Team Nicholas Boudreau; Work Team: S&P Service - Nesting 1; Work Team: S&P Service - Team John Burdett; Work Team: S&P Service - Team Reina Morales; Work Team: S&P Service - Team Stefano Lista; Work Team: S&P Tel Reg - Nesting ; Work Team: S&P Tel Reg - Nesting 2; Work Team: S&P Tel Reg - Team Alex Clare; Work Team: S&P Tel Reg - Team Brian Finnstrom; Work Team: S&P Tel Reg - Team Charnetta Hull; Work Team: S&P Tel Reg - Team David Densmore; Work Team: S&P Tel Reg - Team David Locke; Work Team: S&P Tel Reg - Team Jaime Collazo; Work Team: S&P Tel Reg - Team Michael Garrion; Work Team: S&P Tel Reg - Team Raul Tejada; Work Team: S&P Tel Reg - Team Terrence Toepler | T3: voice | U3: 3d4142a0-3469-416b-9e5a-eb4a3403e480 | V3: Aana Taufiq
C4: Angelica Gonzalez | D4: =_xlfn.XLOOKUP(C4,I:I,J:J,0) -> 7 | I4: Aana Taufiq | P4: 46068 | Q4: 46075.021 | R4: TRUE | S4: Wrap-up: ININ-WRAP-UP-TIMEOUT; Work Team: S&P Campaign - Team Danielle McMullan; Work Team: S&P Flex Trainer and SME Team; Work Team: S&P Outbound - Team Eddie Mendoza; Work Team: S&P Retention Agents - Team William Coad; Work Team: S&P Retention Service - Team Nicholas Boudreau; Work Team: S&P Service - Nesting 1; Work Team: S&P Service - Team John Burdett; Work Team: S&P Service - Team Reina Morales; Work Team: S&P Service - Team Stefano Lista; Work Team: S&P Tel Reg - Nesting ; Work Team: S&P Tel Reg - Nesting 2; Work Team: S&P Tel Reg - Team Alex Clare; Work Team: S&P Tel Reg - Team Brian Finnstrom; Work Team: S&P Tel Reg - Team Charnetta Hull; Work Team: S&P Tel Reg - Team David Densmore; Work Team: S&P Tel Reg - Team David Locke; Work Team: S&P Tel Reg - Team Jaime Collazo; Work Team: S&P Tel Reg - Team Michael Garrion; Work Team: S&P Tel Reg - Team Raul Tejada; Work Team: S&P Tel Reg - Team Terrence Toepler | T4: voice | U4: ec30c194-38f5-46d9-b9af-b673ddfdbd13 | V4: Aaron Alfaro02
C5: Chanetta Gant | D5: =_xlfn.XLOOKUP(C5,I:I,J:J,0) -> 2 | I5: Aaron Alfaro02 | P5: 46068 | Q5: 46075.021 | R5: TRUE | S5: Wrap-up: ININ-WRAP-UP-TIMEOUT; Work Team: S&P Campaign - Team Danielle McMullan; Work Team: S&P Flex Trainer and SME Team; Work Team: S&P Outbound - Team Eddie Mendoza; Work Team: S&P Retention Agents - Team William Coad; Work Team: S&P Retention Service - Team Nicholas Boudreau; Work Team: S&P Service - Nesting 1; Work Team: S&P Service - Team John Burdett; Work Team: S&P Service - Team Reina Morales; Work Team: S&P Service - Team Stefano Lista; Work Team: S&P Tel Reg - Nesting ; Work Team: S&P Tel Reg - Nesting 2; Work Team: S&P Tel Reg - Team Alex Clare; Work Team: S&P Tel Reg - Team Brian Finnstrom; Work Team: S&P Tel Reg - Team Charnetta Hull; Work Team: S&P Tel Reg - Team David Densmore; Work Team: S&P Tel Reg - Team David Locke; Work Team: S&P Tel Reg - Team Jaime Collazo; Work Team: S&P Tel Reg - Team Michael Garrion; Work Team: S&P Tel Reg - Team Raul Tejada; Work Team: S&P Tel Reg - Team Terrence Toepler | T5: voice | U5: 89694374-14c1-4860-b887-f58a19b98826 | V5: Aaron Royal
C6: Chasady Parker | D6: =_xlfn.XLOOKUP(C6,I:I,J:J,0) -> 26 | I6: Aaron Royal | P6: 46068 | Q6: 46075.021 | R6: TRUE | S6: Wrap-up: ININ-WRAP-UP-TIMEOUT; Work Team: S&P Campaign - Team Danielle McMullan; Work Team: S&P Flex Trainer and SME Team; Work Team: S&P Outbound - Team Eddie Mendoza; Work Team: S&P Retention Agents - Team William Coad; Work Team: S&P Retention Service - Team Nicholas Boudreau; Work Team: S&P Service - Nesting 1; Work Team: S&P Service - Team John Burdett; Work Team: S&P Service - Team Reina Morales; Work Team: S&P Service - Team Stefano Lista; Work Team: S&P Tel Reg - Nesting ; Work Team: S&P Tel Reg - Nesting 2; Work Team: S&P Tel Reg - Team Alex Clare; Work Team: S&P Tel Reg - Team Brian Finnstrom; Work Team: S&P Tel Reg - Team Charnetta Hull; Work Team: S&P Tel Reg - Team David Densmore; Work Team: S&P Tel Reg - Team David Locke; Work Team: S&P Tel Reg - Team Jaime Collazo; Work Team: S&P Tel Reg - Team Michael Garrion; Work Team: S&P Tel Reg - Team Raul Tejada; Work Team: S&P Tel Reg - Team Terrence Toepler | T6: voice | U6: ee618fa5-023f-4d58-92be-d5af27491f2e | V6: Abdifitah Ahmed | X6: 3 | Y6: 1091701 | Z6: 1018402 | AA6: 99897 | AB6: 40000 | AC6: 1
C7: Christina Johnson | D7: =_xlfn.XLOOKUP(C7,I:I,J:J,0) -> 0 | I7: Abdifitah Ahmed | J7: 3 | P7: 46068 | Q7: 46075.021 | R7: TRUE | S7: Wrap-up: ININ-WRAP-UP-TIMEOUT; Work Team: S&P Campaign - Team Danielle McMullan; Work Team: S&P Flex Trainer and SME Team; Work Team: S&P Outbound - Team Eddie Mendoza; Work Team: S&P Retention Agents - Team William Coad; Work Team: S&P Retention Service - Team Nicholas Boudreau; Work Team: S&P Service - Nesting 1; Work Team: S&P Service - Team John Burdett; Work Team: S&P Service - Team Reina Morales; Work Team: S&P Service - Team Stefano Lista; Work Team: S&P Tel Reg - Nesting ; Work Team: S&P Tel Reg - Nesting 2; Work Team: S&P Tel Reg - Team Alex Clare; Work Team: S&P Tel Reg - Team Brian Finnstrom; Work Team: S&P Tel Reg - Team Charnetta Hull; Work Team: S&P Tel Reg - Team David Densmore; Work Team: S&P Tel Reg - Team David Locke; Work Team: S&P Tel Reg - Team Jaime Collazo; Work Team: S&P Tel Reg - Team Michael Garrion; Work Team: S&P Tel Reg - Team Raul Tejada; Work Team: S&P Tel Reg - Team Terrence Toepler | T7: voice | U7: 74fc609e-4284-4496-ba8b-67ceb642b02f | V7: Abhiuday Pundir | X7: 1 | Y7: 967440 | Z7: 927440 | AB7: 40000
C8: Douglas Barnes | D8: =_xlfn.XLOOKUP(C8,I:I,J:J,0) -> 3 | I8: Abhiuday Pundir | J8: 1 | P8: 46068 | Q8: 46075.021 | R8: TRUE | S8: Wrap-up: ININ-WRAP-UP-TIMEOUT; Work Team: S&P Campaign - Team Danielle McMullan; Work Team: S&P Flex Trainer and SME Team; Work Team: S&P Outbound - Team Eddie Mendoza; Work Team: S&P Retention Agents - Team William Coad; Work Team: S&P Retention Service - Team Nicholas Boudreau; Work Team: S&P Service - Nesting 1; Work Team: S&P Service - Team John Burdett; Work Team: S&P Service - Team Reina Morales; Work Team: S&P Service - Team Stefano Lista; Work Team: S&P Tel Reg - Nesting ; Work Team: S&P Tel Reg - Nesting 2; Work Team: S&P Tel Reg - Team Alex Clare; Work Team: S&P Tel Reg - Team Brian Finnstrom; Work Team: S&P Tel Reg - Team Charnetta Hull; Work Team: S&P Tel Reg - Team David Densmore; Work Team: S&P Tel Reg - Team David Locke; Work Team: S&P Tel Reg - Team Jaime Collazo; Work Team: S&P Tel Reg - Team Michael Garrion; Work Team: S&P Tel Reg - Team Raul Tejada; Work Team: S&P Tel Reg - Team Terrence Toepler | T8: voice | U8: 9bd45363-41ae-4078-ae56-fdd7062c4b5e | V8: Abigail Ruiz
C9: Khadijah Young | D9: =_xlfn.XLOOKUP(C9,I:I,J:J,0) -> 0 | I9: Abigail Ruiz | P9: 46068 | Q9: 46075.021 | R9: TRUE | S9: Wrap-up: ININ-WRAP-UP-TIMEOUT; Work Team: S&P Campaign - Team Danielle McMullan; Work Team: S&P Flex Trainer and SME Team; Work Team: S&P Outbound - Team Eddie Mendoza; Work Team: S&P Retention Agents - Team William Coad; Work Team: S&P Retention Service - Team Nicholas Boudreau; Work Team: S&P Service - Nesting 1; Work Team: S&P Service - Team John Burdett; Work Team: S&P Service - Team Reina Morales; Work Team: S&P Service - Team Stefano Lista; Work Team: S&P Tel Reg - Nesting ; Work Team: S&P Tel Reg - Nesting 2; Work Team: S&P Tel Reg - Team Alex Clare; Work Team: S&P Tel Reg - Team Brian Finnstrom; Work Team: S&P Tel Reg - Team Charnetta Hull; Work Team: S&P Tel Reg - Team David Densmore; Work Team: S&P Tel Reg - Team David Locke; Work Team: S&P Tel Reg - Team Jaime Collazo; Work Team: S&P Tel Reg - Team Michael Garrion; Work Team: S&P Tel Reg - Team Raul Tejada; Work Team: S&P Tel Reg - Team Terrence Toepler | T9: voice | U9: 74de28d6-b534-4a8e-ac7b-abbe441d82e1 | V9: Abinash Sritharan | X9: 2 | Y9: 1892056.5 | Z9: 1852056.5 | AB9: 40000
C10: Larry Moorehead | D10: =_xlfn.XLOOKUP(C10,I:I,J:J,0) -> 0 | I10: Abinash Sritharan | J10: 2 | P10: 46068 | Q10: 46075.021 | R10: TRUE | S10: Wrap-up: ININ-WRAP-UP-TIMEOUT; Work Team: S&P Campaign - Team Danielle McMullan; Work Team: S&P Flex Trainer and SME Team; Work Team: S&P Outbound - Team Eddie Mendoza; Work Team: S&P Retention Agents - Team William Coad; Work Team: S&P Retention Service - Team Nicholas Boudreau; Work Team: S&P Service - Nesting 1; Work Team: S&P Service - Team John Burdett; Work Team: S&P Service - Team Reina Morales; Work Team: S&P Service - Team Stefano Lista; Work Team: S&P Tel Reg - Nesting ; Work Team: S&P Tel Reg - Nesting 2; Work Team: S&P Tel Reg - Team Alex Clare; Work Team: S&P Tel Reg - Team Brian Finnstrom; Work Team: S&P Tel Reg - Team Charnetta Hull; Work Team: S&P Tel Reg - Team David Densmore; Work Team: S&P Tel Reg - Team David Locke; Work Team: S&P Tel Reg - Team Jaime Collazo; Work Team: S&P Tel Reg - Team Michael Garrion; Work Team: S&P Tel Reg - Team Raul Tejada; Work Team: S&P Tel Reg - Team Terrence Toepler | T10: voice | U10: 4300e4bd-5df1-484b-b3a2-72807dbc0928 | V10: Abraham.Martinez
C11: Margaret Reddy | D11: =_xlfn.XLOOKUP(C11,I:I,J:J,0) -> 0 | I11: Abraham.Martinez | P11: 46068 | Q11: 46075.021 | R11: TRUE | S11: Wrap-up: ININ-WRAP-UP-TIMEOUT; Work Team: S&P Campaign - Team Danielle McMullan; Work Team: S&P Flex Trainer and SME Team; Work Team: S&P Outbound - Team Eddie Mendoza; Work Team: S&P Retention Agents - Team William Coad; Work Team: S&P Retention Service - Team Nicholas Boudreau; Work Team: S&P Service - Nesting 1; Work Team: S&P Service - Team John Burdett; Work Team: S&P Service - Team Reina Morales; Work Team: S&P Service - Team Stefano Lista; Work Team: S&P Tel Reg - Nesting ; Work Team: S&P Tel Reg - Nesting 2; Work Team: S&P Tel Reg - Team Alex Clare; Work Team: S&P Tel Reg - Team Brian Finnstrom; Work Team: S&P Tel Reg - Team Charnetta Hull; Work Team: S&P Tel Reg - Team David Densmore; Work Team: S&P Tel Reg - Team David Locke; Work Team: S&P Tel Reg - Team Jaime Collazo; Work Team: S&P Tel Reg - Team Michael Garrion; Work Team: S&P Tel Reg - Team Raul Tejada; Work Team: S&P Tel Reg - Team Terrence Toepler | T11: voice | U11: 5af13963-6e81-4b9e-bc2f-cff5a110996b | V11: Adam Wilkes
C12: Matthew Livingstone | D12: =_xlfn.XLOOKUP(C12,I:I,J:J,0) -> 1 | I12: Adam Wilkes | P12: 46068 | Q12: 46075.021 | R12: TRUE | S12: Wrap-up: ININ-WRAP-UP-TIMEOUT; Work Team: S&P Campaign - Team Danielle McMullan; Work Team: S&P Flex Trainer and SME Team; Work Team: S&P Outbound - Team Eddie Mendoza; Work Team: S&P Retention Agents - Team William Coad; Work Team: S&P Retention Service - Team Nicholas Boudreau; Work Team: S&P Service - Nesting 1; Work Team: S&P Service - Team John Burdett; Work Team: S&P Service - Team Reina Morales; Work Team: S&P Service - Team Stefano Lista; Work Team: S&P Tel Reg - Nesting ; Work Team: S&P Tel Reg - Nesting 2; Work Team: S&P Tel Reg - Team Alex Clare; Work Team: S&P Tel Reg - Team Brian Finnstrom; Work Team: S&P Tel Reg - Team Charnetta Hull; Work Team: S&P Tel Reg - Team David Densmore; Work Team: S&P Tel Reg - Team David Locke; Work Team: S&P Tel Reg - Team Jaime Collazo; Work Team: S&P Tel Reg - Team Michael Garrion; Work Team: S&P Tel Reg - Team Raul Tejada; Work Team: S&P Tel Reg - Team Terrence Toepler | T12: voice | U12: 08c10b33-30a7-4986-8ed6-efffe260db83 | V12: Aditya Karnawat
C13: Mohamed Bayoumy | D13: =_xlfn.XLOOKUP(C13,I:I,J:J,0) -> 5 | I13: Aditya Karnawat | P13: 46068 | Q13: 46075.021 | R13: TRUE | S13: Wrap-up: ININ-WRAP-UP-TIMEOUT; Work Team: S&P Campaign - Team Danielle McMullan; Work Team: S&P Flex Trainer and SME Team; Work Team: S&P Outbound - Team Eddie Mendoza; Work Team: S&P Retention Agents - Team William Coad; Work Team: S&P Retention Service - Team Nicholas Boudreau; Work Team: S&P Service - Nesting 1; Work Team: S&P Service - Team John Burdett; Work Team: S&P Service - Team Reina Morales; Work Team: S&P Service - Team Stefano Lista; Work Team: S&P Tel Reg - Nesting ; Work Team: S&P Tel Reg - Nesting 2; Work Team: S&P Tel Reg - Team Alex Clare; Work Team: S&P Tel Reg - Team Brian Finnstrom; Work Team: S&P Tel Reg - Team Charnetta Hull; Work Team: S&P Tel Reg - Team David Densmore; Work Team: S&P Tel Reg - Team David Locke; Work Team: S&P Tel Reg - Team Jaime Collazo; Work Team: S&P Tel Reg - Team Michael Garrion; Work Team: S&P Tel Reg - Team Raul Tejada; Work Team: S&P Tel Reg - Team Terrence Toepler | T13: voice | U13: 745d5421-d7e5-404f-b96f-c0188fb35fef | V13: Adnan Malik | X13: 3 | Y13: 372832.67 | Z13: 282039.33 | AA13: 146955 | AB13: 40000 | AC13: 1
C14: Perry Young III | D14: =_xlfn.XLOOKUP(C14,I:I,J:J,0) -> 3 | I14: Adnan Malik | J14: 3 | P14: 46068 | Q14: 46075.021 | R14: TRUE | S14: Wrap-up: ININ-WRAP-UP-TIMEOUT; Work Team: S&P Campaign - Team Danielle McMullan; Work Team: S&P Flex Trainer and SME Team; Work Team: S&P Outbound - Team Eddie Mendoza; Work Team: S&P Retention Agents - Team William Coad; Work Team: S&P Retention Service - Team Nicholas Boudreau; Work Team: S&P Service - Nesting 1; Work Team: S&P Service - Team John Burdett; Work Team: S&P Service - Team Reina Morales; Work Team: S&P Service - Team Stefano Lista; Work Team: S&P Tel Reg - Nesting ; Work Team: S&P Tel Reg - Nesting 2; Work Team: S&P Tel Reg - Team Alex Clare; Work Team: S&P Tel Reg - Team Brian Finnstrom; Work Team: S&P Tel Reg - Team Charnetta Hull; Work Team: S&P Tel Reg - Team David Densmore; Work Team: S&P Tel Reg - Team David Locke; Work Team: S&P Tel Reg - Team Jaime Collazo; Work Team: S&P Tel Reg - Team Michael Garrion; Work Team: S&P Tel Reg - Team Raul Tejada; Work Team: S&P Tel Reg - Team Terrence Toepler | T14: voice | U14: a584ef3e-fed4-47ae-87db-899690f9434a | V14: Adonis Rosalle
C15: Regina Watson | D15: =_xlfn.XLOOKUP(C15,I:I,J:J,0) -> 5 | I15: Adonis Rosalle | P15: 46068 | Q15: 46075.021 | R15: TRUE | S15: Wrap-up: ININ-WRAP-UP-TIMEOUT; Work Team: S&P Campaign - Team Danielle McMullan; Work Team: S&P Flex Trainer and SME Team; Work Team: S&P Outbound - Team Eddie Mendoza; Work Team: S&P Retention Agents - Team William Coad; Work Team: S&P Retention Service - Team Nicholas Boudreau; Work Team: S&P Service - Nesting 1; Work Team: S&P Service - Team John Burdett; Work Team: S&P Service - Team Reina Morales; Work Team: S&P Service - Team Stefano Lista; Work Team: S&P Tel Reg - Nesting ; Work Team: S&P Tel Reg - Nesting 2; Work Team: S&P Tel Reg - Team Alex Clare; Work Team: S&P Tel Reg - Team Brian Finnstrom; Work Team: S&P Tel Reg - Team Charnetta Hull; Work Team: S&P Tel Reg - Team David Densmore; Work Team: S&P Tel Reg - Team David Locke; Work Team: S&P Tel Reg - Team Jaime Collazo; Work Team: S&P Tel Reg - Team Michael Garrion; Work Team: S&P Tel Reg - Team Raul Tejada; Work Team: S&P Tel Reg - Team Terrence Toepler | T15: voice | U15: 5cd9227a-47f1-40a5-867c-f0b59d01b4d7 | V15: Adrian Marin
C16: Carla Grant | D16: =_xlfn.XLOOKUP(C16,I:I,J:J,0) -> 21 | I16: Adrian Marin | P16: 46068 | Q16: 46075.021 | R16: TRUE | S16: Wrap-up: ININ-WRAP-UP-TIMEOUT; Work Team: S&P Campaign - Team Danielle McMullan; Work Team: S&P Flex Trainer and SME Team; Work Team: S&P Outbound - Team Eddie Mendoza; Work Team: S&P Retention Agents - Team William Coad; Work Team: S&P Retention Service - Team Nicholas Boudreau; Work Team: S&P Service - Nesting 1; Work Team: S&P Service - Team John Burdett; Work Team: S&P Service - Team Reina Morales; Work Team: S&P Service - Team Stefano Lista; Work Team: S&P Tel Reg - Nesting ; Work Team: S&P Tel Reg - Nesting 2; Work Team: S&P Tel Reg - Team Alex Clare; Work Team: S&P Tel Reg - Team Brian Finnstrom; Work Team: S&P Tel Reg - Team Charnetta Hull; Work Team: S&P Tel Reg - Team David Densmore; Work Team: S&P Tel Reg - Team David Locke; Work Team: S&P Tel Reg - Team Jaime Collazo; Work Team: S&P Tel Reg - Team Michael Garrion; Work Team: S&P Tel Reg - Team Raul Tejada; Work Team: S&P Tel Reg - Team Terrence Toepler | T16: voice | U16: 53eb2405-d5d2-46cb-8f43-2fa1efe404f3 | V16: Adrian Rapadas
C17: Cassiddy Jordan | D17: =_xlfn.XLOOKUP(C17,I:I,J:J,0) -> 2 | I17: Adrian Rapadas | P17: 46068 | Q17: 46075.021 | R17: TRUE | S17: Wrap-up: ININ-WRAP-UP-TIMEOUT; Work Team: S&P Campaign - Team Danielle McMullan; Work Team: S&P Flex Trainer and SME Team; Work Team: S&P Outbound - Team Eddie Mendoza; Work Team: S&P Retention Agents - Team William Coad; Work Team: S&P Retention Service - Team Nicholas Boudreau; Work Team: S&P Service - Nesting 1; Work Team: S&P Service - Team John Burdett; Work Team: S&P Service - Team Reina Morales; Work Team: S&P Service - Team Stefano Lista; Work Team: S&P Tel Reg - Nesting ; Work Team: S&P Tel Reg - Nesting 2; Work Team: S&P Tel Reg - Team Alex Clare; Work Team: S&P Tel Reg - Team Brian Finnstrom; Work Team: S&P Tel Reg - Team Charnetta Hull; Work Team: S&P Tel Reg - Team David Densmore; Work Team: S&P Tel Reg - Team David Locke; Work Team: S&P Tel Reg - Team Jaime Collazo; Work Team: S&P Tel Reg - Team Michael Garrion; Work Team: S&P Tel Reg - Team Raul Tejada; Work Team: S&P Tel Reg - Team Terrence Toepler | T17: voice | U17: 463ad4f9-1e92-4e8e-adf7-c88c16f8cc0f | V17: Adrian Underwood
C18: Christian Elizabeth | D18: =_xlfn.XLOOKUP(C18,I:I,J:J,0) -> 0 | I18: Adrian Underwood | P18: 46068 | Q18: 46075.021 | R18: TRUE | S18: Wrap-up: ININ-WRAP-UP-TIMEOUT; Work Team: S&P Campaign - Team Danielle McMullan; Work Team: S&P Flex Trainer and SME Team; Work Team: S&P Outbound - Team Eddie Mendoza; Work Team: S&P Retention Agents - Team William Coad; Work Team: S&P Retention Service - Team Nicholas Boudreau; Work Team: S&P Service - Nesting 1; Work Team: S&P Service - Team John Burdett; Work Team: S&P Service - Team Reina Morales; Work Team: S&P Service - Team Stefano Lista; Work Team: S&P Tel Reg - Nesting ; Work Team: S&P Tel Reg - Nesting 2; Work Team: S&P Tel Reg - Team Alex Clare; Work Team: S&P Tel Reg - Team Brian Finnstrom; Work Team: S&P Tel Reg - Team Charnetta Hull; Work Team: S&P Tel Reg - Team David Densmore; Work Team: S&P Tel Reg - Team David Locke; Work Team: S&P Tel Reg - Team Jaime Collazo; Work Team: S&P Tel Reg - Team Michael Garrion; Work Team: S&P Tel Reg - Team Raul Tejada; Work Team: S&P Tel Reg - Team Terrence Toepler | T18: voice | U18: 9231ba2d-f7c6-4c2d-ac20-68553371bcca | V18: Adriana Alejandra Ayala Orellana
C19: Destiny Rich | D19: =_xlfn.XLOOKUP(C19,I:I,J:J,0) -> 22 | I19: Adriana Alejandra Ayala Orellana | P19: 46068 | Q19: 46075.021 | R19: TRUE | S19: Wrap-up: ININ-WRAP-UP-TIMEOUT; Work Team: S&P Campaign - Team Danielle McMullan; Work Team: S&P Flex Trainer and SME Team; Work Team: S&P Outbound - Team Eddie Mendoza; Work Team: S&P Retention Agents - Team William Coad; Work Team: S&P Retention Service - Team Nicholas Boudreau; Work Team: S&P Service - Nesting 1; Work Team: S&P Service - Team John Burdett; Work Team: S&P Service - Team Reina Morales; Work Team: S&P Service - Team Stefano Lista; Work Team: S&P Tel Reg - Nesting ; Work Team: S&P Tel Reg - Nesting 2; Work Team: S&P Tel Reg - Team Alex Clare; Work Team: S&P Tel Reg - Team Brian Finnstrom; Work Team: S&P Tel Reg - Team Charnetta Hull; Work Team: S&P Tel Reg - Team David Densmore; Work Team: S&P Tel Reg - Team David Locke; Work Team: S&P Tel Reg - Team Jaime Collazo; Work Team: S&P Tel Reg - Team Michael Garrion; Work Team: S&P Tel Reg - Team Raul Tejada; Work Team: S&P Tel Reg - Team Terrence Toepler | T19: voice | U19: 93f8db7a-f512-4e9b-b85f-bd166d794d44 | V19: Adriana Daniela Molina Tobares
C20: Dinesh Kandoth | D20: =_xlfn.XLOOKUP(C20,I:I,J:J,0) -> 1 | I20: Adriana Daniela Molina Tobares | P20: 46068 | Q20: 46075.021 | R20: TRUE | S20: Wrap-up: ININ-WRAP-UP-TIMEOUT; Work Team: S&P Campaign - Team Danielle McMullan; Work Team: S&P Flex Trainer and SME Team; Work Team: S&P Outbound - Team Eddie Mendoza; Work Team: S&P Retention Agents - Team William Coad; Work Team: S&P Retention Service - Team Nicholas Boudreau; Work Team: S&P Service - Nesting 1; Work Team: S&P Service - Team John Burdett; Work Team: S&P Service - Team Reina Morales; Work Team: S&P Service - Team Stefano Lista; Work Team: S&P Tel Reg - Nesting ; Work Team: S&P Tel Reg - Nesting 2; Work Team: S&P Tel Reg - Team Alex Clare; Work Team: S&P Tel Reg - Team Brian Finnstrom; Work Team: S&P Tel Reg - Team Charnetta Hull; Work Team: S&P Tel Reg - Team David Densmore; Work Team: S&P Tel Reg - Team David Locke; Work Team: S&P Tel Reg - Team Jaime Collazo; Work Team: S&P Tel Reg - Team Michael Garrion; Work Team: S&P Tel Reg - Team Raul Tejada; Work Team: S&P Tel Reg - Team Terrence Toepler | T20: voice | U20: f602411e-342d-4b63-ad96-393eaaf8fe71 | V20: Ahmed Nur
C21: Donna Plummer | D21: =_xlfn.XLOOKUP(C21,I:I,J:J,0) -> 10 | I21: Ahmed Nur | P21: 46068 | Q21: 46075.021 | R21: TRUE | S21: Wrap-up: ININ-WRAP-UP-TIMEOUT; Work Team: S&P Campaign - Team Danielle McMullan; Work Team: S&P Flex Trainer and SME Team; Work Team: S&P Outbound - Team Eddie Mendoza; Work Team: S&P Retention Agents - Team William Coad; Work Team: S&P Retention Service - Team Nicholas Boudreau; Work Team: S&P Service - Nesting 1; Work Team: S&P Service - Team John Burdett; Work Team: S&P Service - Team Reina Morales; Work Team: S&P Service - Team Stefano Lista; Work Team: S&P Tel Reg - Nesting ; Work Team: S&P Tel Reg - Nesting 2; Work Team: S&P Tel Reg - Team Alex Clare; Work Team: S&P Tel Reg - Team Brian Finnstrom; Work Team: S&P Tel Reg - Team Charnetta Hull; Work Team: S&P Tel Reg - Team David Densmore; Work Team: S&P Tel Reg - Team David Locke; Work Team: S&P Tel Reg - Team Jaime Collazo; Work Team: S&P Tel Reg - Team Michael Garrion; Work Team: S&P Tel Reg - Team Raul Tejada; Work Team: S&P Tel Reg - Team Terrence Toepler | T21: voice | U21: 05e01ca3-b798-447a-9e05-663ac746cdb5 | V21: Akeem Aman
C22: Eric Brown | D22: =_xlfn.XLOOKUP(C22,I:I,J:J,0) -> 13 | I22: Akeem Aman | P22: 46068 | Q22: 46075.021 | R22: TRUE | S22: Wrap-up: ININ-WRAP-UP-TIMEOUT; Work Team: S&P Campaign - Team Danielle McMullan; Work Team: S&P Flex Trainer and SME Team; Work Team: S&P Outbound - Team Eddie Mendoza; Work Team: S&P Retention Agents - Team William Coad; Work Team: S&P Retention Service - Team Nicholas Boudreau; Work Team: S&P Service - Nesting 1; Work Team: S&P Service - Team John Burdett; Work Team: S&P Service - Team Reina Morales; Work Team: S&P Service - Team Stefano Lista; Work Team: S&P Tel Reg - Nesting ; Work Team: S&P Tel Reg - Nesting 2; Work Team: S&P Tel Reg - Team Alex Clare; Work Team: S&P Tel Reg - Team Brian Finnstrom; Work Team: S&P Tel Reg - Team Charnetta Hull; Work Team: S&P Tel Reg - Team David Densmore; Work Team: S&P Tel Reg - Team David Locke; Work Team: S&P Tel Reg - Team Jaime Collazo; Work Team: S&P Tel Reg - Team Michael Garrion; Work Team: S&P Tel Reg - Team Raul Tejada; Work Team: S&P Tel Reg - Team Terrence Toepler | T22: voice | U22: 27cc6d0a-1f8c-4d53-bb13-871b35ec1aa7 | V22: Akhil Karra | X22: 2 | Y22: 410940.5 | Z22: 370940.5 | AB22: 40000
C23: Heather Kester | D23: =_xlfn.XLOOKUP(C23,I:I,J:J,0) -> 21 | I23: Akhil Karra | J23: 2 | P23: 46068 | Q23: 46075.021 | R23: TRUE | S23: Wrap-up: ININ-WRAP-UP-TIMEOUT; Work Team: S&P Campaign - Team Danielle McMullan; Work Team: S&P Flex Trainer and SME Team; Work Team: S&P Outbound - Team Eddie Mendoza; Work Team: S&P Retention Agents - Team William Coad; Work Team: S&P Retention Service - Team Nicholas Boudreau; Work Team: S&P Service - Nesting 1; Work Team: S&P Service - Team John Burdett; Work Team: S&P Service - Team Reina Morales; Work Team: S&P Service - Team Stefano Lista; Work Team: S&P Tel Reg - Nesting ; Work Team: S&P Tel Reg - Nesting 2; Work Team: S&P Tel Reg - Team Alex Clare; Work Team: S&P Tel Reg - Team Brian Finnstrom; Work Team: S&P Tel Reg - Team Charnetta Hull; Work Team: S&P Tel Reg - Team David Densmore; Work Team: S&P Tel Reg - Team David Locke; Work Team: S&P Tel Reg - Team Jaime Collazo; Work Team: S&P Tel Reg - Team Michael Garrion; Work Team: S&P Tel Reg - Team Raul Tejada; Work Team: S&P Tel Reg - Team Terrence Toepler | T23: voice | U23: f304c468-a023-4d32-ab8c-7271adf9a391 | V23: Akib Lipu
C24: Javier Ottenwalder | D24: =_xlfn.XLOOKUP(C24,I:I,J:J,0) -> 9 | I24: Akib Lipu | P24: 46068 | Q24: 46075.021 | R24: TRUE | S24: Wrap-up: ININ-WRAP-UP-TIMEOUT; Work Team: S&P Campaign - Team Danielle McMullan; Work Team: S&P Flex Trainer and SME Team; Work Team: S&P Outbound - Team Eddie Mendoza; Work Team: S&P Retention Agents - Team William Coad; Work Team: S&P Retention Service - Team Nicholas Boudreau; Work Team: S&P Service - Nesting 1; Work Team: S&P Service - Team John Burdett; Work Team: S&P Service - Team Reina Morales; Work Team: S&P Service - Team Stefano Lista; Work Team: S&P Tel Reg - Nesting ; Work Team: S&P Tel Reg - Nesting 2; Work Team: S&P Tel Reg - Team Alex Clare; Work Team: S&P Tel Reg - Team Brian Finnstrom; Work Team: S&P Tel Reg - Team Charnetta Hull; Work Team: S&P Tel Reg - Team David Densmore; Work Team: S&P Tel Reg - Team David Locke; Work Team: S&P Tel Reg - Team Jaime Collazo; Work Team: S&P Tel Reg - Team Michael Garrion; Work Team: S&P Tel Reg - Team Raul Tejada; Work Team: S&P Tel Reg - Team Terrence Toepler | T24: voice | U24: dafaef3a-8e0d-471c-9c79-e060a7ab3022 | V24: Alan Bladimir Funes Ventura
C25: Kellee Silva | D25: =_xlfn.XLOOKUP(C25,I:I,J:J,0) -> 14 | I25: Alan Bladimir Funes Ventura | P25: 46068 | Q25: 46075.021 | R25: TRUE | S25: Wrap-up: ININ-WRAP-UP-TIMEOUT; Work Team: S&P Campaign - Team Danielle McMullan; Work Team: S&P Flex Trainer and SME Team; Work Team: S&P Outbound - Team Eddie Mendoza; Work Team: S&P Retention Agents - Team William Coad; Work Team: S&P Retention Service - Team Nicholas Boudreau; Work Team: S&P Service - Nesting 1; Work Team: S&P Service - Team John Burdett; Work Team: S&P Service - Team Reina Morales; Work Team: S&P Service - Team Stefano Lista; Work Team: S&P Tel Reg - Nesting ; Work Team: S&P Tel Reg - Nesting 2; Work Team: S&P Tel Reg - Team Alex Clare; Work Team: S&P Tel Reg - Team Brian Finnstrom; Work Team: S&P Tel Reg - Team Charnetta Hull; Work Team: S&P Tel Reg - Team David Densmore; Work Team: S&P Tel Reg - Team David Locke; Work Team: S&P Tel Reg - Team Jaime Collazo; Work Team: S&P Tel Reg - Team Michael Garrion; Work Team: S&P Tel Reg - Team Raul Tejada; Work Team: S&P Tel Reg - Team Terrence Toepler | T25: voice | U25: 362e8490-673f-4698-a9c5-3035faaca765 | V25: Alan Houston
C26: Marcia Fabry | D26: =_xlfn.XLOOKUP(C26,I:I,J:J,0) -> 10 | I26: Alan Houston | P26: 46068 | Q26: 46075.021 | R26: TRUE | S26: Wrap-up: ININ-WRAP-UP-TIMEOUT; Work Team: S&P Campaign - Team Danielle McMullan; Work Team: S&P Flex Trainer and SME Team; Work Team: S&P Outbound - Team Eddie Mendoza; Work Team: S&P Retention Agents - Team William Coad; Work Team: S&P Retention Service - Team Nicholas Boudreau; Work Team: S&P Service - Nesting 1; Work Team: S&P Service - Team John Burdett; Work Team: S&P Service - Team Reina Morales; Work Team: S&P Service - Team Stefano Lista; Work Team: S&P Tel Reg - Nesting ; Work Team: S&P Tel Reg - Nesting 2; Work Team: S&P Tel Reg - Team Alex Clare; Work Team: S&P Tel Reg - Team Brian Finnstrom; Work Team: S&P Tel Reg - Team Charnetta Hull; Work Team: S&P Tel Reg - Team David Densmore; Work Team: S&P Tel Reg - Team David Locke; Work Team: S&P Tel Reg - Team Jaime Collazo; Work Team: S&P Tel Reg - Team Michael Garrion; Work Team: S&P Tel Reg - Team Raul Tejada; Work Team: S&P Tel Reg - Team Terrence Toepler | T26: voice | U26: c0f67450-ff61-4dd6-8eec-0e6b2aa5502d | V26: Albany Covington-Owens
C27: Michael Moyer | D27: =_xlfn.XLOOKUP(C27,I:I,J:J,0) -> 25 | I27: Albany Covington-Owens | P27: 46068 | Q27: 46075.021 | R27: TRUE | S27: Wrap-up: ININ-WRAP-UP-TIMEOUT; Work Team: S&P Campaign - Team Danielle McMullan; Work Team: S&P Flex Trainer and SME Team; Work Team: S&P Outbound - Team Eddie Mendoza; Work Team: S&P Retention Agents - Team William Coad; Work Team: S&P Retention Service - Team Nicholas Boudreau; Work Team: S&P Service - Nesting 1; Work Team: S&P Service - Team John Burdett; Work Team: S&P Service - Team Reina Morales; Work Team: S&P Service - Team Stefano Lista; Work Team: S&P Tel Reg - Nesting ; Work Team: S&P Tel Reg - Nesting 2; Work Team: S&P Tel Reg - Team Alex Clare; Work Team: S&P Tel Reg - Team Brian Finnstrom; Work Team: S&P Tel Reg - Team Charnetta Hull; Work Team: S&P Tel Reg - Team David Densmore; Work Team: S&P Tel Reg - Team David Locke; Work Team: S&P Tel Reg - Team Jaime Collazo; Work Team: S&P Tel Reg - Team Michael Garrion; Work Team: S&P Tel Reg - Team Raul Tejada; Work Team: S&P Tel Reg - Team Terrence Toepler | T27: voice | U27: b141ab5d-43de-4f61-b229-3e55e5569501 | V27: Albert Hartinger
C28: Oyindamola Olajoye | D28: =_xlfn.XLOOKUP(C28,I:I,J:J,0) -> 0 | I28: Albert Hartinger | P28: 46068 | Q28: 46075.021 | R28: TRUE | S28: Wrap-up: ININ-WRAP-UP-TIMEOUT; Work Team: S&P Campaign - Team Danielle McMullan; Work Team: S&P Flex Trainer and SME Team; Work Team: S&P Outbound - Team Eddie Mendoza; Work Team: S&P Retention Agents - Team William Coad; Work Team: S&P Retention Service - Team Nicholas Boudreau; Work Team: S&P Service - Nesting 1; Work Team: S&P Service - Team John Burdett; Work Team: S&P Service - Team Reina Morales; Work Team: S&P Service - Team Stefano Lista; Work Team: S&P Tel Reg - Nesting ; Work Team: S&P Tel Reg - Nesting 2; Work Team: S&P Tel Reg - Team Alex Clare; Work Team: S&P Tel Reg - Team Brian Finnstrom; Work Team: S&P Tel Reg - Team Charnetta Hull; Work Team: S&P Tel Reg - Team David Densmore; Work Team: S&P Tel Reg - Team David Locke; Work Team: S&P Tel Reg - Team Jaime Collazo; Work Team: S&P Tel Reg - Team Michael Garrion; Work Team: S&P Tel Reg - Team Raul Tejada; Work Team: S&P Tel Reg - Team Terrence Toepler | T28: voice | U28: 2de27936-339a-437b-9aa2-b145a7cb5a4d | V28: Alberto Montoya
C29: Prottasha Prentice | D29: =_xlfn.XLOOKUP(C29,I:I,J:J,0) -> 13 | I29: Alberto Montoya | P29: 46068 | Q29: 46075.021 | R29: TRUE | S29: Wrap-up: ININ-WRAP-UP-TIMEOUT; Work Team: S&P Campaign - Team Danielle McMullan; Work Team: S&P Flex Trainer and SME Team; Work Team: S&P Outbound - Team Eddie Mendoza; Work Team: S&P Retention Agents - Team William Coad; Work Team: S&P Retention Service - Team Nicholas Boudreau; Work Team: S&P Service - Nesting 1; Work Team: S&P Service - Team John Burdett; Work Team: S&P Service - Team Reina Morales; Work Team: S&P Service - Team Stefano Lista; Work Team: S&P Tel Reg - Nesting ; Work Team: S&P Tel Reg - Nesting 2; Work Team: S&P Tel Reg - Team Alex Clare; Work Team: S&P Tel Reg - Team Brian Finnstrom; Work Team: S&P Tel Reg - Team Charnetta Hull; Work Team: S&P Tel Reg - Team David Densmore; Work Team: S&P Tel Reg - Team David Locke; Work Team: S&P Tel Reg - Team Jaime Collazo; Work Team: S&P Tel Reg - Team Michael Garrion; Work Team: S&P Tel Reg - Team Raul Tejada; Work Team: S&P Tel Reg - Team Terrence Toepler | T29: voice | U29: 6146d8cf-ce51-49c3-b46e-f3cc3aad31eb | V29: Alberto Zeniff Montalvo Aguila
C30: SHANIQUE REID | D30: =_xlfn.XLOOKUP(C30,I:I,J:J,0) -> 21 | I30: Alberto Zeniff Montalvo Aguila | P30: 46068 | Q30: 46075.021 | R30: TRUE | S30: Wrap-up: ININ-WRAP-UP-TIMEOUT; Work Team: S&P Campaign - Team Danielle McMullan; Work Team: S&P Flex Trainer and SME Team; Work Team: S&P Outbound - Team Eddie Mendoza; Work Team: S&P Retention Agents - Team William Coad; Work Team: S&P Retention Service - Team Nicholas Boudreau; Work Team: S&P Service - Nesting 1; Work Team: S&P Service - Team John Burdett; Work Team: S&P Service - Team Reina Morales; Work Team: S&P Service - Team Stefano Lista; Work Team: S&P Tel Reg - Nesting ; Work Team: S&P Tel Reg - Nesting 2; Work Team: S&P Tel Reg - Team Alex Clare; Work Team: S&P Tel Reg - Team Brian Finnstrom; Work Team: S&P Tel Reg - Team Charnetta Hull; Work Team: S&P Tel Reg - Team David Densmore; Work Team: S&P Tel Reg - Team David Locke; Work Team: S&P Tel Reg - Team Jaime Collazo; Work Team: S&P Tel Reg - Team Michael Garrion; Work Team: S&P Tel Reg - Team Raul Tejada; Work Team: S&P Tel Reg - Team Terrence Toepler | T30: voice | U30: 15122abc-b966-488d-af5d-312aa43a7cdc | V30: Aldrin D'Almeida
C31: Tika Mayo | D31: =_xlfn.XLOOKUP(C31,I:I,J:J,0) -> 26 | I31: Aldrin D'Almeida | P31: 46068 | Q31: 46075.021 | R31: TRUE | S31: Wrap-up: ININ-WRAP-UP-TIMEOUT; Work Team: S&P Campaign - Team Danielle McMullan; Work Team: S&P Flex Trainer and SME Team; Work Team: S&P Outbound - Team Eddie Mendoza; Work Team: S&P Retention Agents - Team William Coad; Work Team: S&P Retention Service - Team Nicholas Boudreau; Work Team: S&P Service - Nesting 1; Work Team: S&P Service - Team John Burdett; Work Team: S&P Service - Team Reina Morales; Work Team: S&P Service - Team Stefano Lista; Work Team: S&P Tel Reg - Nesting ; Work Team: S&P Tel Reg - Nesting 2; Work Team: S&P Tel Reg - Team Alex Clare; Work Team: S&P Tel Reg - Team Brian Finnstrom; Work Team: S&P Tel Reg - Team Charnetta Hull; Work Team: S&P Tel Reg - Team David Densmore; Work Team: S&P Tel Reg - Team David Locke; Work Team: S&P Tel Reg - Team Jaime Collazo; Work Team: S&P Tel Reg - Team Michael Garrion; Work Team: S&P Tel Reg - Team Raul Tejada; Work Team: S&P Tel Reg - Team Terrence Toepler | T31: voice | U31: 7e9bf2e2-2009-4bb3-a784-164ca04e7b1e | V31: Alejandra Leticia Diaz Beltra
C32: Tina Rogers | D32: =_xlfn.XLOOKUP(C32,I:I,J:J,0) -> 44 | I32: Alejandra Leticia Diaz Beltra | P32: 46068 | Q32: 46075.021 | R32: TRUE | S32: Wrap-up: ININ-WRAP-UP-TIMEOUT; Work Team: S&P Campaign - Team Danielle McMullan; Work Team: S&P Flex Trainer and SME Team; Work Team: S&P Outbound - Team Eddie Mendoza; Work Team: S&P Retention Agents - Team William Coad; Work Team: S&P Retention Service - Team Nicholas Boudreau; Work Team: S&P Service - Nesting 1; Work Team: S&P Service - Team John Burdett; Work Team: S&P Service - Team Reina Morales; Work Team: S&P Service - Team Stefano Lista; Work Team: S&P Tel Reg - Nesting ; Work Team: S&P Tel Reg - Nesting 2; Work Team: S&P Tel Reg - Team Alex Clare; Work Team: S&P Tel Reg - Team Brian Finnstrom; Work Team: S&P Tel Reg - Team Charnetta Hull; Work Team: S&P Tel Reg - Team David Densmore; Work Team: S&P Tel Reg - Team David Locke; Work Team: S&P Tel Reg - Team Jaime Collazo; Work Team: S&P Tel Reg - Team Michael Garrion; Work Team: S&P Tel Reg - Team Raul Tejada; Work Team: S&P Tel Reg - Team Terrence Toepler | T32: voice | U32: 05004194-0d4b-4207-ad6e-65393395b5f6 | V32: Alejandro Ernesto Cruz Barrientos
C33: Trevor Berry | D33: =_xlfn.XLOOKUP(C33,I:I,J:J,0) -> 57 | I33: Alejandro Ernesto Cruz Barrientos | P33: 46068 | Q33: 46075.021 | R33: TRUE | S33: Wrap-up: ININ-WRAP-UP-TIMEOUT; Work Team: S&P Campaign - Team Danielle McMullan; Work Team: S&P Flex Trainer and SME Team; Work Team: S&P Outbound - Team Eddie Mendoza; Work Team: S&P Retention Agents - Team William Coad; Work Team: S&P Retention Service - Team Nicholas Boudreau; Work Team: S&P Service - Nesting 1; Work Team: S&P Service - Team John Burdett; Work Team: S&P Service - Team Reina Morales; Work Team: S&P Service - Team Stefano Lista; Work Team: S&P Tel Reg - Nesting ; Work Team: S&P Tel Reg - Nesting 2; Work Team: S&P Tel Reg - Team Alex Clare; Work Team: S&P Tel Reg - Team Brian Finnstrom; Work Team: S&P Tel Reg - Team Charnetta Hull; Work Team: S&P Tel Reg - Team David Densmore; Work Team: S&P Tel Reg - Team David Locke; Work Team: S&P Tel Reg - Team Jaime Collazo; Work Team: S&P Tel Reg - Team Michael Garrion; Work Team: S&P Tel Reg - Team Raul Tejada; Work Team: S&P Tel Reg - Team Terrence Toepler | T33: voice | U33: 1803eb93-c06b-403a-b9fb-69f1423034b1 | V33: Alessandro.Sedo
C34: Uniqua Davis | D34: =_xlfn.XLOOKUP(C34,I:I,J:J,0) -> 8 | I34: Alessandro.Sedo | P34: 46068 | Q34: 46075.021 | R34: TRUE | S34: Wrap-up: ININ-WRAP-UP-TIMEOUT; Work Team: S&P Campaign - Team Danielle McMullan; Work Team: S&P Flex Trainer and SME Team; Work Team: S&P Outbound - Team Eddie Mendoza; Work Team: S&P Retention Agents - Team William Coad; Work Team: S&P Retention Service - Team Nicholas Boudreau; Work Team: S&P Service - Nesting 1; Work Team: S&P Service - Team John Burdett; Work Team: S&P Service - Team Reina Morales; Work Team: S&P Service - Team Stefano Lista; Work Team: S&P Tel Reg - Nesting ; Work Team: S&P Tel Reg - Nesting 2; Work Team: S&P Tel Reg - Team Alex Clare; Work Team: S&P Tel Reg - Team Brian Finnstrom; Work Team: S&P Tel Reg - Team Charnetta Hull; Work Team: S&P Tel Reg - Team David Densmore; Work Team: S&P Tel Reg - Team David Locke; Work Team: S&P Tel Reg - Team Jaime Collazo; Work Team: S&P Tel Reg - Team Michael Garrion; Work Team: S&P Tel Reg - Team Raul Tejada; Work Team: S&P Tel Reg - Team Terrence Toepler | T34: voice | U34: 98e3e470-24dd-4982-8c82-e27eb80e0f35 | V34: Alex Clare
C35: Zycariah Fowler | D35: =_xlfn.XLOOKUP(C35,I:I,J:J,0) -> 0 | I35: Alex Clare | P35: 46068 | Q35: 46075.021 | R35: TRUE | S35: Wrap-up: ININ-WRAP-UP-TIMEOUT; Work Team: S&P Campaign - Team Danielle McMullan; Work Team: S&P Flex Trainer and SME Team; Work Team: S&P Outbound - Team Eddie Mendoza; Work Team: S&P Retention Agents - Team William Coad; Work Team: S&P Retention Service - Team Nicholas Boudreau; Work Team: S&P Service - Nesting 1; Work Team: S&P Service - Team John Burdett; Work Team: S&P Service - Team Reina Morales; Work Team: S&P Service - Team Stefano Lista; Work Team: S&P Tel Reg - Nesting ; Work Team: S&P Tel Reg - Nesting 2; Work Team: S&P Tel Reg - Team Alex Clare; Work Team: S&P Tel Reg - Team Brian Finnstrom; Work Team: S&P Tel Reg - Team Charnetta Hull; Work Team: S&P Tel Reg - Team David Densmore; Work Team: S&P Tel Reg - Team David Locke; Work Team: S&P Tel Reg - Team Jaime Collazo; Work Team: S&P Tel Reg - Team Michael Garrion; Work Team: S&P Tel Reg - Team Raul Tejada; Work Team: S&P Tel Reg - Team Terrence Toepler | T35: voice | U35: 1a1a3ecd-ea40-45f9-b407-2cd5693e459e | V35: Alexander Enrique Pinto Gomez
I36: Alexander Enrique Pinto Gomez | P36: 46068 | Q36: 46075.021 | R36: TRUE | S36: Wrap-up: ININ-WRAP-UP-TIMEOUT; Work Team: S&P Campaign - Team Danielle McMullan; Work Team: S&P Flex Trainer and SME Team; Work Team: S&P Outbound - Team Eddie Mendoza; Work Team: S&P Retention Agents - Team William Coad; Work Team: S&P Retention Service - Team Nicholas Boudreau; Work Team: S&P Service - Nesting 1; Work Team: S&P Service - Team John Burdett; Work Team: S&P Service - Team Reina Morales; Work Team: S&P Service - Team Stefano Lista; Work Team: S&P Tel Reg - Nesting ; Work Team: S&P Tel Reg - Nesting 2; Work Team: S&P Tel Reg - Team Alex Clare; Work Team: S&P Tel Reg - Team Brian Finnstrom; Work Team: S&P Tel Reg - Team Charnetta Hull; Work Team: S&P Tel Reg - Team David Densmore; Work Team: S&P Tel Reg - Team David Locke; Work Team: S&P Tel Reg - Team Jaime Collazo; Work Team: S&P Tel Reg - Team Michael Garrion; Work Team: S&P Tel Reg - Team Raul Tejada; Work Team: S&P Tel Reg - Team Terrence Toepler | T36: voice | U36: 2bf69d46-2ee9-400c-92d9-644652fd68fd | V36: Alexander Figueroa
I37: Alexander Figueroa | P37: 46068 | Q37: 46075.021 | R37: TRUE | S37: Wrap-up: ININ-WRAP-UP-TIMEOUT; Work Team: S&P Campaign - Team Danielle McMullan; Work Team: S&P Flex Trainer and SME Team; Work Team: S&P Outbound - Team Eddie Mendoza; Work Team: S&P Retention Agents - Team William Coad; Work Team: S&P Retention Service - Team Nicholas Boudreau; Work Team: S&P Service - Nesting 1; Work Team: S&P Service - Team John Burdett; Work Team: S&P Service - Team Reina Morales; Work Team: S&P Service - Team Stefano Lista; Work Team: S&P Tel Reg - Nesting ; Work Team: S&P Tel Reg - Nesting 2; Work Team: S&P Tel Reg - Team Alex Clare; Work Team: S&P Tel Reg - Team Brian Finnstrom; Work Team: S&P Tel Reg - Team Charnetta Hull; Work Team: S&P Tel Reg - Team David Densmore; Work Team: S&P Tel Reg - Team David Locke; Work Team: S&P Tel Reg - Team Jaime Collazo; Work Team: S&P Tel Reg - Team Michael Garrion; Work Team: S&P Tel Reg - Team Raul Tejada; Work Team: S&P Tel Reg - Team Terrence Toepler | T37: voice | U37: b27d7bdc-c7ed-4a78-bd8e-5bb0000fd8f8 | V37: Alexis Brown | X37: 2 | Y37: 868326 | Z37: 840826 | AB37: 27500
I38: Alexis Brown | J38: 2 | P38: 46068 | Q38: 46075.021 | R38: TRUE | S38: Wrap-up: ININ-WRAP-UP-TIMEOUT; Work Team: S&P Campaign - Team Danielle McMullan; Work Team: S&P Flex Trainer and SME Team; Work Team: S&P Outbound - Team Eddie Mendoza; Work Team: S&P Retention Agents - Team William Coad; Work Team: S&P Retention Service - Team Nicholas Boudreau; Work Team: S&P Service - Nesting 1; Work Team: S&P Service - Team John Burdett; Work Team: S&P Service - Team Reina Morales; Work Team: S&P Service - Team Stefano Lista; Work Team: S&P Tel Reg - Nesting ; Work Team: S&P Tel Reg - Nesting 2; Work Team: S&P Tel Reg - Team Alex Clare; Work Team: S&P Tel Reg - Team Brian Finnstrom; Work Team: S&P Tel Reg - Team Charnetta Hull; Work Team: S&P Tel Reg - Team David Densmore; Work Team: S&P Tel Reg - Team David Locke; Work Team: S&P Tel Reg - Team Jaime Collazo; Work Team: S&P Tel Reg - Team Michael Garrion; Work Team: S&P Tel Reg - Team Raul Tejada; Work Team: S&P Tel Reg - Team Terrence Toepler | T38: voice | U38: 1fcb9ef1-8fd6-4b10-946b-53268e47aad0 | V38: Alexis Smith | X38: 8 | Y38: 697734.88 | Z38: 582613.5 | AA38: 200323.67 | AB38: 40000 | AC38: 3
I39: Alexis Smith | J39: 8 | P39: 46068 | Q39: 46075.021 | R39: TRUE | S39: Wrap-up: ININ-WRAP-UP-TIMEOUT; Work Team: S&P Campaign - Team Danielle McMullan; Work Team: S&P Flex Trainer and SME Team; Work Team: S&P Outbound - Team Eddie Mendoza; Work Team: S&P Retention Agents - Team William Coad; Work Team: S&P Retention Service - Team Nicholas Boudreau; Work Team: S&P Service - Nesting 1; Work Team: S&P Service - Team John Burdett; Work Team: S&P Service - Team Reina Morales; Work Team: S&P Service - Team Stefano Lista; Work Team: S&P Tel Reg - Nesting ; Work Team: S&P Tel Reg - Nesting 2; Work Team: S&P Tel Reg - Team Alex Clare; Work Team: S&P Tel Reg - Team Brian Finnstrom; Work Team: S&P Tel Reg - Team Charnetta Hull; Work Team: S&P Tel Reg - Team David Densmore; Work Team: S&P Tel Reg - Team David Locke; Work Team: S&P Tel Reg - Team Jaime Collazo; Work Team: S&P Tel Reg - Team Michael Garrion; Work Team: S&P Tel Reg - Team Raul Tejada; Work Team: S&P Tel Reg - Team Terrence Toepler | T39: voice | U39: eb64d3f9-a86a-4f8d-b406-231b1f39aa36 | V39: Alicia Anderson | X39: 2 | Y39: 488324 | Z39: 448324 | AB39: 40000
I40: Alicia Anderson | J40: 2 | P40: 46068 | Q40: 46075.021 | R40: TRUE | S40: Wrap-up: ININ-WRAP-UP-TIMEOUT; Work Team: S&P Campaign - Team Danielle McMullan; Work Team: S&P Flex Trainer and SME Team; Work Team: S&P Outbound - Team Eddie Mendoza; Work Team: S&P Retention Agents - Team William Coad; Work Team: S&P Retention Service - Team Nicholas Boudreau; Work Team: S&P Service - Nesting 1; Work Team: S&P Service - Team John Burdett; Work Team: S&P Service - Team Reina Morales; Work Team: S&P Service - Team Stefano Lista; Work Team: S&P Tel Reg - Nesting ; Work Team: S&P Tel Reg - Nesting 2; Work Team: S&P Tel Reg - Team Alex Clare; Work Team: S&P Tel Reg - Team Brian Finnstrom; Work Team: S&P Tel Reg - Team Charnetta Hull; Work Team: S&P Tel Reg - Team David Densmore; Work Team: S&P Tel Reg - Team David Locke; Work Team: S&P Tel Reg - Team Jaime Collazo; Work Team: S&P Tel Reg - Team Michael Garrion; Work Team: S&P Tel Reg - Team Raul Tejada; Work Team: S&P Tel Reg - Team Terrence Toepler | T40: voice | U40: 10f2b2cf-c623-4093-9303-c943117e2a96 | V40: Alicia Chase | X40: 2 | Y40: 237783.5 | Z40: 197783.5 | AB40: 40000
I41: Alicia Chase | J41: 2 | P41: 46068 | Q41: 46075.021 | R41: TRUE | S41: Wrap-up: ININ-WRAP-UP-TIMEOUT; Work Team: S&P Campaign - Team Danielle McMullan; Work Team: S&P Flex Trainer and SME Team; Work Team: S&P Outbound - Team Eddie Mendoza; Work Team: S&P Retention Agents - Team William Coad; Work Team: S&P Retention Service - Team Nicholas Boudreau; Work Team: S&P Service - Nesting 1; Work Team: S&P Service - Team John Burdett; Work Team: S&P Service - Team Reina Morales; Work Team: S&P Service - Team Stefano Lista; Work Team: S&P Tel Reg - Nesting ; Work Team: S&P Tel Reg - Nesting 2; Work Team: S&P Tel Reg - Team Alex Clare; Work Team: S&P Tel Reg - Team Brian Finnstrom; Work Team: S&P Tel Reg - Team Charnetta Hull; Work Team: S&P Tel Reg - Team David Densmore; Work Team: S&P Tel Reg - Team David Locke; Work Team: S&P Tel Reg - Team Jaime Collazo; Work Team: S&P Tel Reg - Team Michael Garrion; Work Team: S&P Tel Reg - Team Raul Tejada; Work Team: S&P Tel Reg - Team Terrence Toepler | T41: voice | U41: 1f6eb9d2-a74a-463f-bf92-ef55cc032cb5 | V41: Alicia Chavarria | X41: 4 | Y41: 775808 | Z41: 743308 | AB41: 32500
I42: Alicia Chavarria | J42: 4 | P42: 46068 | Q42: 46075.021 | R42: TRUE | S42: Wrap-up: ININ-WRAP-UP-TIMEOUT; Work Team: S&P Campaign - Team Danielle McMullan; Work Team: S&P Flex Trainer and SME Team; Work Team: S&P Outbound - Team Eddie Mendoza; Work Team: S&P Retention Agents - Team William Coad; Work Team: S&P Retention Service - Team Nicholas Boudreau; Work Team: S&P Service - Nesting 1; Work Team: S&P Service - Team John Burdett; Work Team: S&P Service - Team Reina Morales; Work Team: S&P Service - Team Stefano Lista; Work Team: S&P Tel Reg - Nesting ; Work Team: S&P Tel Reg - Nesting 2; Work Team: S&P Tel Reg - Team Alex Clare; Work Team: S&P Tel Reg - Team Brian Finnstrom; Work Team: S&P Tel Reg - Team Charnetta Hull; Work Team: S&P Tel Reg - Team David Densmore; Work Team: S&P Tel Reg - Team David Locke; Work Team: S&P Tel Reg - Team Jaime Collazo; Work Team: S&P Tel Reg - Team Michael Garrion; Work Team: S&P Tel Reg - Team Raul Tejada; Work Team: S&P Tel Reg - Team Terrence Toepler | T42: voice | U42: f0a61a34-273c-4af2-b2bb-382906332239 | V42: Alicia Shields
I43: Alicia Shields | P43: 46068 | Q43: 46075.021 | R43: TRUE | S43: Wrap-up: ININ-WRAP-UP-TIMEOUT; Work Team: S&P Campaign - Team Danielle McMullan; Work Team: S&P Flex Trainer and SME Team; Work Team: S&P Outbound - Team Eddie Mendoza; Work Team: S&P Retention Agents - Team William Coad; Work Team: S&P Retention Service - Team Nicholas Boudreau; Work Team: S&P Service - Nesting 1; Work Team: S&P Service - Team John Burdett; Work Team: S&P Service - Team Reina Morales; Work Team: S&P Service - Team Stefano Lista; Work Team: S&P Tel Reg - Nesting ; Work Team: S&P Tel Reg - Nesting 2; Work Team: S&P Tel Reg - Team Alex Clare; Work Team: S&P Tel Reg - Team Brian Finnstrom; Work Team: S&P Tel Reg - Team Charnetta Hull; Work Team: S&P Tel Reg - Team David Densmore; Work Team: S&P Tel Reg - Team David Locke; Work Team: S&P Tel Reg - Team Jaime Collazo; Work Team: S&P Tel Reg - Team Michael Garrion; Work Team: S&P Tel Reg - Team Raul Tejada; Work Team: S&P Tel Reg - Team Terrence Toepler | T43: voice | U43: f1482717-da4c-4a25-b68b-38562910ad0c | V43: Aliesha Hoosain
I44: Aliesha Hoosain | P44: 46068 | Q44: 46075.021 | R44: TRUE | S44: Wrap-up: ININ-WRAP-UP-TIMEOUT; Work Team: S&P Campaign - Team Danielle McMullan; Work Team: S&P Flex Trainer and SME Team; Work Team: S&P Outbound - Team Eddie Mendoza; Work Team: S&P Retention Agents - Team William Coad; Work Team: S&P Retention Service - Team Nicholas Boudreau; Work Team: S&P Service - Nesting 1; Work Team: S&P Service - Team John Burdett; Work Team: S&P Service - Team Reina Morales; Work Team: S&P Service - Team Stefano Lista; Work Team: S&P Tel Reg - Nesting ; Work Team: S&P Tel Reg - Nesting 2; Work Team: S&P Tel Reg - Team Alex Clare; Work Team: S&P Tel Reg - Team Brian Finnstrom; Work Team: S&P Tel Reg - Team Charnetta Hull; Work Team: S&P Tel Reg - Team David Densmore; Work Team: S&P Tel Reg - Team David Locke; Work Team: S&P Tel Reg - Team Jaime Collazo; Work Team: S&P Tel Reg - Team Michael Garrion; Work Team: S&P Tel Reg - Team Raul Tejada; Work Team: S&P Tel Reg - Team Terrence Toepler | T44: voice | U44: 97ccda5c-bc98-4a30-b21b-ba39f9934759 | V44: Alirio Ruano
I45: Alirio Ruano | P45: 46068 | Q45: 46075.021 | R45: TRUE | S45: Wrap-up: ININ-WRAP-UP-TIMEOUT; Work Team: S&P Campaign - Team Danielle McMullan; Work Team: S&P Flex Trainer and SME Team; Work Team: S&P Outbound - Team Eddie Mendoza; Work Team: S&P Retention Agents - Team William Coad; Work Team: S&P Retention Service - Team Nicholas Boudreau; Work Team: S&P Service - Nesting 1; Work Team: S&P Service - Team John Burdett; Work Team: S&P Service - Team Reina Morales; Work Team: S&P Service - Team Stefano Lista; Work Team: S&P Tel Reg - Nesting ; Work Team: S&P Tel Reg - Nesting 2; Work Team: S&P Tel Reg - Team Alex Clare; Work Team: S&P Tel Reg - Team Brian Finnstrom; Work Team: S&P Tel Reg - Team Charnetta Hull; Work Team: S&P Tel Reg - Team David Densmore; Work Team: S&P Tel Reg - Team David Locke; Work Team: S&P Tel Reg - Team Jaime Collazo; Work Team: S&P Tel Reg - Team Michael Garrion; Work Team: S&P Tel Reg - Team Raul Tejada; Work Team: S&P Tel Reg - Team Terrence Toepler | T45: voice | U45: 20d62313-1605-4040-82f2-db930bda73ff | V45: Alisha Williams
I46: Alisha Williams | P46: 46068 | Q46: 46075.021 | R46: TRUE | S46: Wrap-up: ININ-WRAP-UP-TIMEOUT; Work Team: S&P Campaign - Team Danielle McMullan; Work Team: S&P Flex Trainer and SME Team; Work Team: S&P Outbound - Team Eddie Mendoza; Work Team: S&P Retention Agents - Team William Coad; Work Team: S&P Retention Service - Team Nicholas Boudreau; Work Team: S&P Service - Nesting 1; Work Team: S&P Service - Team John Burdett; Work Team: S&P Service - Team Reina Morales; Work Team: S&P Service - Team Stefano Lista; Work Team: S&P Tel Reg - Nesting ; Work Team: S&P Tel Reg - Nesting 2; Work Team: S&P Tel Reg - Team Alex Clare; Work Team: S&P Tel Reg - Team Brian Finnstrom; Work Team: S&P Tel Reg - Team Charnetta Hull; Work Team: S&P Tel Reg - Team David Densmore; Work Team: S&P Tel Reg - Team David Locke; Work Team: S&P Tel Reg - Team Jaime Collazo; Work Team: S&P Tel Reg - Team Michael Garrion; Work Team: S&P Tel Reg - Team Raul Tejada; Work Team: S&P Tel Reg - Team Terrence Toepler | T46: voice | U46: 0263e81c-202c-4315-855b-b4875fa7a528 | V46: Alissa Caskey
I47: Alissa Caskey | P47: 46068 | Q47: 46075.021 | R47: TRUE | S47: Wrap-up: ININ-WRAP-UP-TIMEOUT; Work Team: S&P Campaign - Team Danielle McMullan; Work Team: S&P Flex Trainer and SME Team; Work Team: S&P Outbound - Team Eddie Mendoza; Work Team: S&P Retention Agents - Team William Coad; Work Team: S&P Retention Service - Team Nicholas Boudreau; Work Team: S&P Service - Nesting 1; Work Team: S&P Service - Team John Burdett; Work Team: S&P Service - Team Reina Morales; Work Team: S&P Service - Team Stefano Lista; Work Team: S&P Tel Reg - Nesting ; Work Team: S&P Tel Reg - Nesting 2; Work Team: S&P Tel Reg - Team Alex Clare; Work Team: S&P Tel Reg - Team Brian Finnstrom; Work Team: S&P Tel Reg - Team Charnetta Hull; Work Team: S&P Tel Reg - Team David Densmore; Work Team: S&P Tel Reg - Team David Locke; Work Team: S&P Tel Reg - Team Jaime Collazo; Work Team: S&P Tel Reg - Team Michael Garrion; Work Team: S&P Tel Reg - Team Raul Tejada; Work Team: S&P Tel Reg - Team Terrence Toepler | T47: voice | U47: cc9eec10-f44b-467f-8cba-352ef08b9702 | V47: Alivia Haines
I48: Alivia Haines | P48: 46068 | Q48: 46075.021 | R48: TRUE | S48: Wrap-up: ININ-WRAP-UP-TIMEOUT; Work Team: S&P Campaign - Team Danielle McMullan; Work Team: S&P Flex Trainer and SME Team; Work Team: S&P Outbound - Team Eddie Mendoza; Work Team: S&P Retention Agents - Team William Coad; Work Team: S&P Retention Service - Team Nicholas Boudreau; Work Team: S&P Service - Nesting 1; Work Team: S&P Service - Team John Burdett; Work Team: S&P Service - Team Reina Morales; Work Team: S&P Service - Team Stefano Lista; Work Team: S&P Tel Reg - Nesting ; Work Team: S&P Tel Reg - Nesting 2; Work Team: S&P Tel Reg - Team Alex Clare; Work Team: S&P Tel Reg - Team Brian Finnstrom; Work Team: S&P Tel Reg - Team Charnetta Hull; Work Team: S&P Tel Reg - Team David Densmore; Work Team: S&P Tel Reg - Team David Locke; Work Team: S&P Tel Reg - Team Jaime Collazo; Work Team: S&P Tel Reg - Team Michael Garrion; Work Team: S&P Tel Reg - Team Raul Tejada; Work Team: S&P Tel Reg - Team Terrence Toepler | T48: voice | U48: 2b60b87a-8b3e-435c-a1f0-378768a47013 | V48: Allan Giovanni Diaz Salamanca
I49: Allan Giovanni Diaz Salamanca | P49: 46068 | Q49: 46075.021 | R49: TRUE | S49: Wrap-up: ININ-WRAP-UP-TIMEOUT; Work Team: S&P Campaign - Team Danielle McMullan; Work Team: S&P Flex Trainer and SME Team; Work Team: S&P Outbound - Team Eddie Mendoza; Work Team: S&P Retention Agents - Team William Coad; Work Team: S&P Retention Service - Team Nicholas Boudreau; Work Team: S&P Service - Nesting 1; Work Team: S&P Service - Team John Burdett; Work Team: S&P Service - Team Reina Morales; Work Team: S&P Service - Team Stefano Lista; Work Team: S&P Tel Reg - Nesting ; Work Team: S&P Tel Reg - Nesting 2; Work Team: S&P Tel Reg - Team Alex Clare; Work Team: S&P Tel Reg - Team Brian Finnstrom; Work Team: S&P Tel Reg - Team Charnetta Hull; Work Team: S&P Tel Reg - Team David Densmore; Work Team: S&P Tel Reg - Team David Locke; Work Team: S&P Tel Reg - Team Jaime Collazo; Work Team: S&P Tel Reg - Team Michael Garrion; Work Team: S&P Tel Reg - Team Raul Tejada; Work Team: S&P Tel Reg - Team Terrence Toepler | T49: voice | U49: 4979738d-a037-4b03-a7e8-d1f258b4cc75 | V49: Allison Abigail Monterrosa Aguilar
I50: Allison Abigail Monterrosa Aguilar | P50: 46068 | Q50: 46075.021 | R50: TRUE | S50: Wrap-up: ININ-WRAP-UP-TIMEOUT; Work Team: S&P Campaign - Team Danielle McMullan; Work Team: S&P Flex Trainer and SME Team; Work Team: S&P Outbound - Team Eddie Mendoza; Work Team: S&P Retention Agents - Team William Coad; Work Team: S&P Retention Service - Team Nicholas Boudreau; Work Team: S&P Service - Nesting 1; Work Team: S&P Service - Team John Burdett; Work Team: S&P Service - Team Reina Morales; Work Team: S&P Service - Team Stefano Lista; Work Team: S&P Tel Reg - Nesting ; Work Team: S&P Tel Reg - Nesting 2; Work Team: S&P Tel Reg - Team Alex Clare; Work Team: S&P Tel Reg - Team Brian Finnstrom; Work Team: S&P Tel Reg - Team Charnetta Hull; Work Team: S&P Tel Reg - Team David Densmore; Work Team: S&P Tel Reg - Team David Locke; Work Team: S&P Tel Reg - Team Jaime Collazo; Work Team: S&P Tel Reg - Team Michael Garrion; Work Team: S&P Tel Reg - Team Raul Tejada; Work Team: S&P Tel Reg - Team Terrence Toepler | T50: voice | U50: b226f3f0-86d8-44a8-9fb9-b0a64d4ca8fc | V50: Allison Sellers
I51: Allison Sellers | P51: 46068 | Q51: 46075.021 | R51: TRUE | S51: Wrap-up: ININ-WRAP-UP-TIMEOUT; Work Team: S&P Campaign - Team Danielle McMullan; Work Team: S&P Flex Trainer and SME Team; Work Team: S&P Outbound - Team Eddie Mendoza; Work Team: S&P Retention Agents - Team William Coad; Work Team: S&P Retention Service - Team Nicholas Boudreau; Work Team: S&P Service - Nesting 1; Work Team: S&P Service - Team John Burdett; Work Team: S&P Service - Team Reina Morales; Work Team: S&P Service - Team Stefano Lista; Work Team: S&P Tel Reg - Nesting ; Work Team: S&P Tel Reg - Nesting 2; Work Team: S&P Tel Reg - Team Alex Clare; Work Team: S&P Tel Reg - Team Brian Finnstrom; Work Team: S&P Tel Reg - Team Charnetta Hull; Work Team: S&P Tel Reg - Team David Densmore; Work Team: S&P Tel Reg - Team David Locke; Work Team: S&P Tel Reg - Team Jaime Collazo; Work Team: S&P Tel Reg - Team Michael Garrion; Work Team: S&P Tel Reg - Team Raul Tejada; Work Team: S&P Tel Reg - Team Terrence Toepler | T51: voice | U51: f56cf6fa-8b46-4d1b-bb21-3c23d356cab7 | V51: Almesha Shirley
I52: Almesha Shirley | P52: 46068 | Q52: 46075.021 | R52: TRUE | S52: Wrap-up: ININ-WRAP-UP-TIMEOUT; Work Team: S&P Campaign - Team Danielle McMullan; Work Team: S&P Flex Trainer and SME Team; Work Team: S&P Outbound - Team Eddie Mendoza; Work Team: S&P Retention Agents - Team William Coad; Work Team: S&P Retention Service - Team Nicholas Boudreau; Work Team: S&P Service - Nesting 1; Work Team: S&P Service - Team John Burdett; Work Team: S&P Service - Team Reina Morales; Work Team: S&P Service - Team Stefano Lista; Work Team: S&P Tel Reg - Nesting ; Work Team: S&P Tel Reg - Nesting 2; Work Team: S&P Tel Reg - Team Alex Clare; Work Team: S&P Tel Reg - Team Brian Finnstrom; Work Team: S&P Tel Reg - Team Charnetta Hull; Work Team: S&P Tel Reg - Team David Densmore; Work Team: S&P Tel Reg - Team David Locke; Work Team: S&P Tel Reg - Team Jaime Collazo; Work Team: S&P Tel Reg - Team Michael Garrion; Work Team: S&P Tel Reg - Team Raul Tejada; Work Team: S&P Tel Reg - Team Terrence Toepler | T52: voice | U52: ce908e9d-0a61-41ea-bdd7-b90332ea3675 | V52: Alonzia Perrin
I53: Alonzia Perrin | P53: 46068 | Q53: 46075.021 | R53: TRUE | S53: Wrap-up: ININ-WRAP-UP-TIMEOUT; Work Team: S&P Campaign - Team Danielle McMullan; Work Team: S&P Flex Trainer and SME Team; Work Team: S&P Outbound - Team Eddie Mendoza; Work Team: S&P Retention Agents - Team William Coad; Work Team: S&P Retention Service - Team Nicholas Boudreau; Work Team: S&P Service - Nesting 1; Work Team: S&P Service - Team John Burdett; Work Team: S&P Service - Team Reina Morales; Work Team: S&P Service - Team Stefano Lista; Work Team: S&P Tel Reg - Nesting ; Work Team: S&P Tel Reg - Nesting 2; Work Team: S&P Tel Reg - Team Alex Clare; Work Team: S&P Tel Reg - Team Brian Finnstrom; Work Team: S&P Tel Reg - Team Charnetta Hull; Work Team: S&P Tel Reg - Team David Densmore; Work Team: S&P Tel Reg - Team David Locke; Work Team: S&P Tel Reg - Team Jaime Collazo; Work Team: S&P Tel Reg - Team Michael Garrion; Work Team: S&P Tel Reg - Team Raul Tejada; Work Team: S&P Tel Reg - Team Terrence Toepler | T53: voice | U53: 3405a0d4-af4e-44f9-9347-a6e8a5379251 | V53: Alyse Vargas
I54: Alyse Vargas | P54: 46068 | Q54: 46075.021 | R54: TRUE | S54: Wrap-up: ININ-WRAP-UP-TIMEOUT; Work Team: S&P Campaign - Team Danielle McMullan; Work Team: S&P Flex Trainer and SME Team; Work Team: S&P Outbound - Team Eddie Mendoza; Work Team: S&P Retention Agents - Team William Coad; Work Team: S&P Retention Service - Team Nicholas Boudreau; Work Team: S&P Service - Nesting 1; Work Team: S&P Service - Team John Burdett; Work Team: S&P Service - Team Reina Morales; Work Team: S&P Service - Team Stefano Lista; Work Team: S&P Tel Reg - Nesting ; Work Team: S&P Tel Reg - Nesting 2; Work Team: S&P Tel Reg - Team Alex Clare; Work Team: S&P Tel Reg - Team Brian Finnstrom; Work Team: S&P Tel Reg - Team Charnetta Hull; Work Team: S&P Tel Reg - Team David Densmore; Work Team: S&P Tel Reg - Team David Locke; Work Team: S&P Tel Reg - Team Jaime Collazo; Work Team: S&P Tel Reg - Team Michael Garrion; Work Team: S&P Tel Reg - Team Raul Tejada; Work Team: S&P Tel Reg - Team Terrence Toepler | T54: voice | U54: 284479fb-e88b-4039-96ca-8a75a49d218b | V54: Alyssa Torres
... I58: Amanda Mitchell | P58: 46068 | Q58: 46075.021 | R58: TRUE | S58: Wrap-up: ININ-WRAP-UP-TIMEOUT; Work Team: S&P Campaign - Team Danielle McMullan; Work Team: S&P Flex Trainer and SME Team; Work Team: S&P Outbound - Team Eddie Mendoza; Work Team: S&P Retention Agents - Team William Coad; Work Team: S&P Retention Service - Team Nicholas Boudreau; Work Team: S&P Service - Nesting 1; Work Team: S&P Service - Team John Burdett; Work Team: S&P Service - Team Reina Morales; Work Team: S&P Service - Team Stefano Lista; Work Team: S&P Tel Reg - Nesting ; Work Team: S&P Tel Reg - Nesting 2; Work Team: S&P Tel Reg - Team Alex Clare; Work Team: S&P Tel Reg - Team Brian Finnstrom; Work Team: S&P Tel Reg - Team Charnetta Hull; Work Team: S&P Tel Reg - Team David Densmore; Work Team: S&P Tel Reg - Team David Locke; Work Team: S&P Tel Reg - Team Jaime Collazo; Work Team: S&P Tel Reg - Team Michael Garrion; Work Team: S&P Tel Reg - Team Raul Tejada; Work Team: S&P Tel Reg - Team Terrence Toepler | T58: voice | U58: 868abbc3-5332-4e82-9e53-464688f78467 | V58: Amanda Vega
I59: Amanda Vega | P59: 46068 | Q59: 46075.021 | R59: TRUE | S59: Wrap-up: ININ-WRAP-UP-TIMEOUT; Work Team: S&P Campaign - Team Danielle McMullan; Work Team: S&P Flex Trainer and SME Team; Work Team: S&P Outbound - Team Eddie Mendoza; Work Team: S&P Retention Agents - Team William Coad; Work Team: S&P Retention Service - Team Nicholas Boudreau; Work Team: S&P Service - Nesting 1; Work Team: S&P Service - Team John Burdett; Work Team: S&P Service - Team Reina Morales; Work Team: S&P Service - Team Stefano Lista; Work Team: S&P Tel Reg - Nesting ; Work Team: S&P Tel Reg - Nesting 2; Work Team: S&P Tel Reg - Team Alex Clare; Work Team: S&P Tel Reg - Team Brian Finnstrom; Work Team: S&P Tel Reg - Team Charnetta Hull; Work Team: S&P Tel Reg - Team David Densmore; Work Team: S&P Tel Reg - Team David Locke; Work Team: S&P Tel Reg - Team Jaime Collazo; Work Team: S&P Tel Reg - Team Michael Garrion; Work Team: S&P Tel Reg - Team Raul Tejada; Work Team: S&P Tel Reg - Team Terrence Toepler | T59: voice | U59: bcd1fc80-b4b5-4086-9739-dcd3894459e4 | V59: Amar Ramcharan | X59: 1 | Y59: 248902 | Z59: 218902 | AB59: 30000
I60: Amar Ramcharan | J60: 1 | P60: 46068 | Q60: 46075.021 | R60: TRUE | S60: Wrap-up: ININ-WRAP-UP-TIMEOUT; Work Team: S&P Campaign - Team Danielle McMullan; Work Team: S&P Flex Trainer and SME Team; Work Team: S&P Outbound - Team Eddie Mendoza; Work Team: S&P Retention Agents - Team William Coad; Work Team: S&P Retention Service - Team Nicholas Boudreau; Work Team: S&P Service - Nesting 1; Work Team: S&P Service - Team John Burdett; Work Team: S&P Service - Team Reina Morales; Work Team: S&P Service - Team Stefano Lista; Work Team: S&P Tel Reg - Nesting ; Work Team: S&P Tel Reg - Nesting 2; Work Team: S&P Tel Reg - Team Alex Clare; Work Team: S&P Tel Reg - Team Brian Finnstrom; Work Team: S&P Tel Reg - Team Charnetta Hull; Work Team: S&P Tel Reg - Team David Densmore; Work Team: S&P Tel Reg - Team David Locke; Work Team: S&P Tel Reg - Team Jaime Collazo; Work Team: S&P Tel Reg - Team Michael Garrion; Work Team: S&P Tel Reg - Team Raul Tejada; Work Team: S&P Tel Reg - Team Terrence Toepler | T60: voice | U60: b3a9c0f9-267d-4256-90af-b1edb61a5f4e | V60: Amarachi Nwodoh
I61: Amarachi Nwodoh | P61: 46068 | Q61: 46075.021 | R61: TRUE | S61: Wrap-up: ININ-WRAP-UP-TIMEOUT; Work Team: S&P Campaign - Team Danielle McMullan; Work Team: S&P Flex Trainer and SME Team; Work Team: S&P Outbound - Team Eddie Mendoza; Work Team: S&P Retention Agents - Team William Coad; Work Team: S&P Retention Service - Team Nicholas Boudreau; Work Team: S&P Service - Nesting 1; Work Team: S&P Service - Team John Burdett; Work Team: S&P Service - Team Reina Morales; Work Team: S&P Service - Team Stefano Lista; Work Team: S&P Tel Reg - Nesting ; Work Team: S&P Tel Reg - Nesting 2; Work Team: S&P Tel Reg - Team Alex Clare; Work Team: S&P Tel Reg - Team Brian Finnstrom; Work Team: S&P Tel Reg - Team Charnetta Hull; Work Team: S&P Tel Reg - Team David Densmore; Work Team: S&P Tel Reg - Team David Locke; Work Team: S&P Tel Reg - Team Jaime Collazo; Work Team: S&P Tel Reg - Team Michael Garrion; Work Team: S&P Tel Reg - Team Raul Tejada; Work Team: S&P Tel Reg - Team Terrence Toepler | T61: voice | U61: 4cc640c8-2e38-4c9b-98ef-391e736f98d4 | V61: Amardeep Singh | X61: 1 | Y61: 707579 | Z61: 667579 | AB61: 40000
I62: Amardeep Singh | J62: 1 | P62: 46068 | Q62: 46075.021 | R62: TRUE | S62: Wrap-up: ININ-WRAP-UP-TIMEOUT; Work Team: S&P Campaign - Team Danielle McMullan; Work Team: S&P Flex Trainer and SME Team; Work Team: S&P Outbound - Team Eddie Mendoza; Work Team: S&P Retention Agents - Team William Coad; Work Team: S&P Retention Service - Team Nicholas Boudreau; Work Team: S&P Service - Nesting 1; Work Team: S&P Service - Team John Burdett; Work Team: S&P Service - Team Reina Morales; Work Team: S&P Service - Team Stefano Lista; Work Team: S&P Tel Reg - Nesting ; Work Team: S&P Tel Reg - Nesting 2; Work Team: S&P Tel Reg - Team Alex Clare; Work Team: S&P Tel Reg - Team Brian Finnstrom; Work Team: S&P Tel Reg - Team Charnetta Hull; Work Team: S&P Tel Reg - Team David Densmore; Work Team: S&P Tel Reg - Team David Locke; Work Team: S&P Tel Reg - Team Jaime Collazo; Work Team: S&P Tel Reg - Team Michael Garrion; Work Team: S&P Tel Reg - Team Raul Tejada; Work Team: S&P Tel Reg - Team Terrence Toepler | T62: voice | U62: d1798398-3898-4d31-b4d6-fba4dba0e286 | V62: Amit Bhamra | X62: 4 | Y62: 965508 | Z62: 908511.5 | AA62: 67986 | AB62: 40000 | AC62: 1
I63: Amit Bhamra | J63: 4 | P63: 46068 | Q63: 46075.021 | R63: TRUE | S63: Wrap-up: ININ-WRAP-UP-TIMEOUT; Work Team: S&P Campaign - Team Danielle McMullan; Work Team: S&P Flex Trainer and SME Team; Work Team: S&P Outbound - Team Eddie Mendoza; Work Team: S&P Retention Agents - Team William Coad; Work Team: S&P Retention Service - Team Nicholas Boudreau; Work Team: S&P Service - Nesting 1; Work Team: S&P Service - Team John Burdett; Work Team: S&P Service - Team Reina Morales; Work Team: S&P Service - Team Stefano Lista; Work Team: S&P Tel Reg - Nesting ; Work Team: S&P Tel Reg - Nesting 2; Work Team: S&P Tel Reg - Team Alex Clare; Work Team: S&P Tel Reg - Team Brian Finnstrom; Work Team: S&P Tel Reg - Team Charnetta Hull; Work Team: S&P Tel Reg - Team David Densmore; Work Team: S&P Tel Reg - Team David Locke; Work Team: S&P Tel Reg - Team Jaime Collazo; Work Team: S&P Tel Reg - Team Michael Garrion; Work Team: S&P Tel Reg - Team Raul Tejada; Work Team: S&P Tel Reg - Team Terrence Toepler | T63: voice | U63: ab6419c2-4c8d-4771-9621-d27f281fdd9d | V63: Amiyah Moye
I64: Amiyah Moye | P64: 46068 | Q64: 46075.021 | R64: TRUE | S64: Wrap-up: ININ-WRAP-UP-TIMEOUT; Work Team: S&P Campaign - Team Danielle McMullan; Work Team: S&P Flex Trainer and SME Team; Work Team: S&P Outbound - Team Eddie Mendoza; Work Team: S&P Retention Agents - Team William Coad; Work Team: S&P Retention Service - Team Nicholas Boudreau; Work Team: S&P Service - Nesting 1; Work Team: S&P Service - Team John Burdett; Work Team: S&P Service - Team Reina Morales; Work Team: S&P Service - Team Stefano Lista; Work Team: S&P Tel Reg - Nesting ; Work Team: S&P Tel Reg - Nesting 2; Work Team: S&P Tel Reg - Team Alex Clare; Work Team: S&P Tel Reg - Team Brian Finnstrom; Work Team: S&P Tel Reg - Team Charnetta Hull; Work Team: S&P Tel Reg - Team David Densmore; Work Team: S&P Tel Reg - Team David Locke; Work Team: S&P Tel Reg - Team Jaime Collazo; Work Team: S&P Tel Reg - Team Michael Garrion; Work Team: S&P Tel Reg - Team Raul Tejada; Work Team: S&P Tel Reg - Team Terrence Toepler | T64: voice | U64: b744fd85-e4a0-413f-ba2f-f6b0d53b5256 | V64: Amresh Mungal | X64: 1 | Y64: 771442 | Z64: 718544 | AB64: 25000
I65: Amresh Mungal | J65: 1 | P65: 46068 | Q65: 46075.021 | R65: TRUE | S65: Wrap-up: ININ-WRAP-UP-TIMEOUT; Work Team: S&P Campaign - Team Danielle McMullan; Work Team: S&P Flex Trainer and SME Team; Work Team: S&P Outbound - Team Eddie Mendoza; Work Team: S&P Retention Agents - Team William Coad; Work Team: S&P Retention Service - Team Nicholas Boudreau; Work Team: S&P Service - Nesting 1; Work Team: S&P Service - Team John Burdett; Work Team: S&P Service - Team Reina Morales; Work Team: S&P Service - Team Stefano Lista; Work Team: S&P Tel Reg - Nesting ; Work Team: S&P Tel Reg - Nesting 2; Work Team: S&P Tel Reg - Team Alex Clare; Work Team: S&P Tel Reg - Team Brian Finnstrom; Work Team: S&P Tel Reg - Team Charnetta Hull; Work Team: S&P Tel Reg - Team David Densmore; Work Team: S&P Tel Reg - Team David Locke; Work Team: S&P Tel Reg - Team Jaime Collazo; Work Team: S&P Tel Reg - Team Michael Garrion; Work Team: S&P Tel Reg - Team Raul Tejada; Work Team: S&P Tel Reg - Team Terrence Toepler | T65: voice | U65: 2906f83a-127a-41e2-98a7-500804ff9ccd | V65: Amy Porter | X65: 13 | Y65: 341057.77 | Z65: 300252 | AA65: 10475 | AB65: 40000 | AC65: 1
I66: Amy Porter | J66: 13 | P66: 46068 | Q66: 46075.021 | R66: TRUE | S66: Wrap-up: ININ-WRAP-UP-TIMEOUT; Work Team: S&P Campaign - Team Danielle McMullan; Work Team: S&P Flex Trainer and SME Team; Work Team: S&P Outbound - Team Eddie Mendoza; Work Team: S&P Retention Agents - Team William Coad; Work Team: S&P Retention Service - Team Nicholas Boudreau; Work Team: S&P Service - Nesting 1; Work Team: S&P Service - Team John Burdett; Work Team: S&P Service - Team Reina Morales; Work Team: S&P Service - Team Stefano Lista; Work Team: S&P Tel Reg - Nesting ; Work Team: S&P Tel Reg - Nesting 2; Work Team: S&P Tel Reg - Team Alex Clare; Work Team: S&P Tel Reg - Team Brian Finnstrom; Work Team: S&P Tel Reg - Team Charnetta Hull; Work Team: S&P Tel Reg - Team David Densmore; Work Team: S&P Tel Reg - Team David Locke; Work Team: S&P Tel Reg - Team Jaime Collazo; Work Team: S&P Tel Reg - Team Michael Garrion; Work Team: S&P Tel Reg - Team Raul Tejada; Work Team: S&P Tel Reg - Team Terrence Toepler | T66: voice | U66: c7c9a4f3-4fd7-4418-b4de-39d164df0902 | V66: Amy Smiley
I67: Amy Smiley | P67: 46068 | Q67: 46075.021 | R67: TRUE | S67: Wrap-up: ININ-WRAP-UP-TIMEOUT; Work Team: S&P Campaign - Team Danielle McMullan; Work Team: S&P Flex Trainer and SME Team; Work Team: S&P Outbound - Team Eddie Mendoza; Work Team: S&P Retention Agents - Team William Coad; Work Team: S&P Retention Service - Team Nicholas Boudreau; Work Team: S&P Service - Nesting 1; Work Team: S&P Service - Team John Burdett; Work Team: S&P Service - Team Reina Morales; Work Team: S&P Service - Team Stefano Lista; Work Team: S&P Tel Reg - Nesting ; Work Team: S&P Tel Reg - Nesting 2; Work Team: S&P Tel Reg - Team Alex Clare; Work Team: S&P Tel Reg - Team Brian Finnstrom; Work Team: S&P Tel Reg - Team Charnetta Hull; Work Team: S&P Tel Reg - Team David Densmore; Work Team: S&P Tel Reg - Team David Locke; Work Team: S&P Tel Reg - Team Jaime Collazo; Work Team: S&P Tel Reg - Team Michael Garrion; Work Team: S&P Tel Reg - Team Raul Tejada; Work Team: S&P Tel Reg - Team Terrence Toepler | T67: voice | U67: bd7f9b01-3dd5-44fb-8789-7f771c641af9 | V67: Amy Thomas
I68: Amy Thomas | P68: 46068 | Q68: 46075.021 | R68: TRUE | S68: Wrap-up: ININ-WRAP-UP-TIMEOUT; Work Team: S&P Campaign - Team Danielle McMullan; Work Team: S&P Flex Trainer and SME Team; Work Team: S&P Outbound - Team Eddie Mendoza; Work Team: S&P Retention Agents - Team William Coad; Work Team: S&P Retention Service - Team Nicholas Boudreau; Work Team: S&P Service - Nesting 1; Work Team: S&P Service - Team John Burdett; Work Team: S&P Service - Team Reina Morales; Work Team: S&P Service - Team Stefano Lista; Work Team: S&P Tel Reg - Nesting ; Work Team: S&P Tel Reg - Nesting 2; Work Team: S&P Tel Reg - Team Alex Clare; Work Team: S&P Tel Reg - Team Brian Finnstrom; Work Team: S&P Tel Reg - Team Charnetta Hull; Work Team: S&P Tel Reg - Team David Densmore; Work Team: S&P Tel Reg - Team David Locke; Work Team: S&P Tel Reg - Team Jaime Collazo; Work Team: S&P Tel Reg - Team Michael Garrion; Work Team: S&P Tel Reg - Team Raul Tejada; Work Team: S&P Tel Reg - Team Terrence Toepler | T68: voice | U68: 61c2830a-104a-4de2-bdb1-f0b8d06dc029 | V68: Ana Patricia Flores Granados
I69: Ana Patricia Flores Granados | P69: 46068 | Q69: 46075.021 | R69: TRUE | S69: Wrap-up: ININ-WRAP-UP-TIMEOUT; Work Team: S&P Campaign - Team Danielle McMullan; Work Team: S&P Flex Trainer and SME Team; Work Team: S&P Outbound - Team Eddie Mendoza; Work Team: S&P Retention Agents - Team William Coad; Work Team: S&P Retention Service - Team Nicholas Boudreau; Work Team: S&P Service - Nesting 1; Work Team: S&P Service - Team John Burdett; Work Team: S&P Service - Team Reina Morales; Work Team: S&P Service - Team Stefano Lista; Work Team: S&P Tel Reg - Nesting ; Work Team: S&P Tel Reg - Nesting 2; Work Team: S&P Tel Reg - Team Alex Clare; Work Team: S&P Tel Reg - Team Brian Finnstrom; Work Team: S&P Tel Reg - Team Charnetta Hull; Work Team: S&P Tel Reg - Team David Densmore; Work Team: S&P Tel Reg - Team David Locke; Work Team: S&P Tel Reg - Team Jaime Collazo; Work Team: S&P Tel Reg - Team Michael Garrion; Work Team: S&P Tel Reg - Team Raul Tejada; Work Team: S&P Tel Reg - Team Terrence Toepler | T69: voice | U69: ab72ab6b-2b49-4b7b-a2b4-14e4ca515ea7 | V69: Ana Yancy Guadalupe Guerra Soto
I70: Ana Yancy Guadalupe Guerra Soto | P70: 46068 | Q70: 46075.021 | R70: TRUE | S70: Wrap-up: ININ-WRAP-UP-TIMEOUT; Work Team: S&P Campaign - Team Danielle McMullan; Work Team: S&P Flex Trainer and SME Team; Work Team: S&P Outbound - Team Eddie Mendoza; Work Team: S&P Retention Agents - Team William Coad; Work Team: S&P Retention Service - Team Nicholas Boudreau; Work Team: S&P Service - Nesting 1; Work Team: S&P Service - Team John Burdett; Work Team: S&P Service - Team Reina Morales; Work Team: S&P Service - Team Stefano Lista; Work Team: S&P Tel Reg - Nesting ; Work Team: S&P Tel Reg - Nesting 2; Work Team: S&P Tel Reg - Team Alex Clare; Work Team: S&P Tel Reg - Team Brian Finnstrom; Work Team: S&P Tel Reg - Team Charnetta Hull; Work Team: S&P Tel Reg - Team David Densmore; Work Team: S&P Tel Reg - Team David Locke; Work Team: S&P Tel Reg - Team Jaime Collazo; Work Team: S&P Tel Reg - Team Michael Garrion; Work Team: S&P Tel Reg - Team Raul Tejada; Work Team: S&P Tel Reg - Team Terrence Toepler | T70: voice | U70: a41bc554-4f84-42aa-9ddf-5e2c05ff60dc | V70: Anastacia Hicks | X70: 4 | Y70: 701230 | Z70: 581230 | AB70: 120000
I71: Anastacia Hicks | J71: 4 | P71: 46068 | Q71: 46075.021 | R71: TRUE | S71: Wrap-up: ININ-WRAP-UP-TIMEOUT; Work Team: S&P Campaign - Team Danielle McMullan; Work Team: S&P Flex Trainer and SME Team; Work Team: S&P Outbound - Team Eddie Mendoza; Work Team: S&P Retention Agents - Team William Coad; Work Team: S&P Retention Service - Team Nicholas Boudreau; Work Team: S&P Service - Nesting 1; Work Team: S&P Service - Team John Burdett; Work Team: S&P Service - Team Reina Morales; Work Team: S&P Service - Team Stefano Lista; Work Team: S&P Tel Reg - Nesting ; Work Team: S&P Tel Reg - Nesting 2; Work Team: S&P Tel Reg - Team Alex Clare; Work Team: S&P Tel Reg - Team Brian Finnstrom; Work Team: S&P Tel Reg - Team Charnetta Hull; Work Team: S&P Tel Reg - Team David Densmore; Work Team: S&P Tel Reg - Team David Locke; Work Team: S&P Tel Reg - Team Jaime Collazo; Work Team: S&P Tel Reg - Team Michael Garrion; Work Team: S&P Tel Reg - Team Raul Tejada; Work Team: S&P Tel Reg - Team Terrence Toepler | T71: voice | U71: 83e0ad02-f36a-4dd3-9cbf-037e34c11522 | V71: Anastasia Kalman
I72: Anastasia Kalman | P72: 46068 | Q72: 46075.021 | R72: TRUE | S72: Wrap-up: ININ-WRAP-UP-TIMEOUT; Work Team: S&P Campaign - Team Danielle McMullan; Work Team: S&P Flex Trainer and SME Team; Work Team: S&P Outbound - Team Eddie Mendoza; Work Team: S&P Retention Agents - Team William Coad; Work Team: S&P Retention Service - Team Nicholas Boudreau; Work Team: S&P Service - Nesting 1; Work Team: S&P Service - Team John Burdett; Work Team: S&P Service - Team Reina Morales; Work Team: S&P Service - Team Stefano Lista; Work Team: S&P Tel Reg - Nesting ; Work Team: S&P Tel Reg - Nesting 2; Work Team: S&P Tel Reg - Team Alex Clare; Work Team: S&P Tel Reg - Team Brian Finnstrom; Work Team: S&P Tel Reg - Team Charnetta Hull; Work Team: S&P Tel Reg - Team David Densmore; Work Team: S&P Tel Reg - Team David Locke; Work Team: S&P Tel Reg - Team Jaime Collazo; Work Team: S&P Tel Reg - Team Michael Garrion; Work Team: S&P Tel Reg - Team Raul Tejada; Work Team: S&P Tel Reg - Team Terrence Toepler | T72: voice | U72: 23abe9c4-2c15-46b6-b8d3-aa6e7d1ae3c5 | V72: Andre Bynoe | X72: 2 | Y72: 768435.5 | Z72: 728435.5 | AB72: 40000
I73: Andre Bynoe | J73: 2 | P73: 46068 | Q73: 46075.021 | R73: TRUE | S73: Wrap-up: ININ-WRAP-UP-TIMEOUT; Work Team: S&P Campaign - Team Danielle McMullan; Work Team: S&P Flex Trainer and SME Team; Work Team: S&P Outbound - Team Eddie Mendoza; Work Team: S&P Retention Agents - Team William Coad; Work Team: S&P Retention Service - Team Nicholas Boudreau; Work Team: S&P Service - Nesting 1; Work Team: S&P Service - Team John Burdett; Work Team: S&P Service - Team Reina Morales; Work Team: S&P Service - Team Stefano Lista; Work Team: S&P Tel Reg - Nesting ; Work Team: S&P Tel Reg - Nesting 2; Work Team: S&P Tel Reg - Team Alex Clare; Work Team: S&P Tel Reg - Team Brian Finnstrom; Work Team: S&P Tel Reg - Team Charnetta Hull; Work Team: S&P Tel Reg - Team David Densmore; Work Team: S&P Tel Reg - Team David Locke; Work Team: S&P Tel Reg - Team Jaime Collazo; Work Team: S&P Tel Reg - Team Michael Garrion; Work Team: S&P Tel Reg - Team Raul Tejada; Work Team: S&P Tel Reg - Team Terrence Toepler | T73: voice | U73: 1981d2a8-8dad-4ad4-9ae4-3df3f03283bf | V73: Andre Vladimir Romero Puente
I74: Andre Vladimir Romero Puente | P74: 46068 | Q74: 46075.021 | R74: TRUE | S74: Wrap-up: ININ-WRAP-UP-TIMEOUT; Work Team: S&P Campaign - Team Danielle McMullan; Work Team: S&P Flex Trainer and SME Team; Work Team: S&P Outbound - Team Eddie Mendoza; Work Team: S&P Retention Agents - Team William Coad; Work Team: S&P Retention Service - Team Nicholas Boudreau; Work Team: S&P Service - Nesting 1; Work Team: S&P Service - Team John Burdett; Work Team: S&P Service - Team Reina Morales; Work Team: S&P Service - Team Stefano Lista; Work Team: S&P Tel Reg - Nesting ; Work Team: S&P Tel Reg - Nesting 2; Work Team: S&P Tel Reg - Team Alex Clare; Work Team: S&P Tel Reg - Team Brian Finnstrom; Work Team: S&P Tel Reg - Team Charnetta Hull; Work Team: S&P Tel Reg - Team David Densmore; Work Team: S&P Tel Reg - Team David Locke; Work Team: S&P Tel Reg - Team Jaime Collazo; Work Team: S&P Tel Reg - Team Michael Garrion; Work Team: S&P Tel Reg - Team Raul Tejada; Work Team: S&P Tel Reg - Team Terrence Toepler | T74: voice | U74: 8e0eda60-06ea-460b-9a2b-92c0b87acc7f | V74: Andrea Culbertson
I75: Andrea Culbertson | P75: 46068 | Q75: 46075.021 | R75: TRUE | S75: Wrap-up: ININ-WRAP-UP-TIMEOUT; Work Team: S&P Campaign - Team Danielle McMullan; Work Team: S&P Flex Trainer and SME Team; Work Team: S&P Outbound - Team Eddie Mendoza; Work Team: S&P Retention Agents - Team William Coad; Work Team: S&P Retention Service - Team Nicholas Boudreau; Work Team: S&P Service - Nesting 1; Work Team: S&P Service - Team John Burdett; Work Team: S&P Service - Team Reina Morales; Work Team: S&P Service - Team Stefano Lista; Work Team: S&P Tel Reg - Nesting ; Work Team: S&P Tel Reg - Nesting 2; Work Team: S&P Tel Reg - Team Alex Clare; Work Team: S&P Tel Reg - Team Brian Finnstrom; Work Team: S&P Tel Reg - Team Charnetta Hull; Work Team: S&P Tel Reg - Team David Densmore; Work Team: S&P Tel Reg - Team David Locke; Work Team: S&P Tel Reg - Team Jaime Collazo; Work Team: S&P Tel Reg - Team Michael Garrion; Work Team: S&P Tel Reg - Team Raul Tejada; Work Team: S&P Tel Reg - Team Terrence Toepler | T75: voice | U75: 2c633542-89b1-47d4-8660-c374ae3b6167 | V75: Andrea Elizabeth Benavides Velasquez
I76: Andrea Elizabeth Benavides Velasquez | P76: 46068 | Q76: 46075.021 | R76: TRUE | S76: Wrap-up: ININ-WRAP-UP-TIMEOUT; Work Team: S&P Campaign - Team Danielle McMullan; Work Team: S&P Flex Trainer and SME Team; Work Team: S&P Outbound - Team Eddie Mendoza; Work Team: S&P Retention Agents - Team William Coad; Work Team: S&P Retention Service - Team Nicholas Boudreau; Work Team: S&P Service - Nesting 1; Work Team: S&P Service - Team John Burdett; Work Team: S&P Service - Team Reina Morales; Work Team: S&P Service - Team Stefano Lista; Work Team: S&P Tel Reg - Nesting ; Work Team: S&P Tel Reg - Nesting 2; Work Team: S&P Tel Reg - Team Alex Clare; Work Team: S&P Tel Reg - Team Brian Finnstrom; Work Team: S&P Tel Reg - Team Charnetta Hull; Work Team: S&P Tel Reg - Team David Densmore; Work Team: S&P Tel Reg - Team David Locke; Work Team: S&P Tel Reg - Team Jaime Collazo; Work Team: S&P Tel Reg - Team Michael Garrion; Work Team: S&P Tel Reg - Team Raul Tejada; Work Team: S&P Tel Reg - Team Terrence Toepler | T76: voice | U76: 19feca7d-a3b5-42b3-833d-27faff4f989b | V76: Andrea Guadalupe Franco Vasquez
I77: Andrea Guadalupe Franco Vasquez | P77: 46068 | Q77: 46075.021 | R77: TRUE | S77: Wrap-up: ININ-WRAP-UP-TIMEOUT; Work Team: S&P Campaign - Team Danielle McMullan; Work Team: S&P Flex Trainer and SME Team; Work Team: S&P Outbound - Team Eddie Mendoza; Work Team: S&P Retention Agents - Team William Coad; Work Team: S&P Retention Service - Team Nicholas Boudreau; Work Team: S&P Service - Nesting 1; Work Team: S&P Service - Team John Burdett; Work Team: S&P Service - Team Reina Morales; Work Team: S&P Service - Team Stefano Lista; Work Team: S&P Tel Reg - Nesting ; Work Team: S&P Tel Reg - Nesting 2; Work Team: S&P Tel Reg - Team Alex Clare; Work Team: S&P Tel Reg - Team Brian Finnstrom; Work Team: S&P Tel Reg - Team Charnetta Hull; Work Team: S&P Tel Reg - Team David Densmore; Work Team: S&P Tel Reg - Team David Locke; Work Team: S&P Tel Reg - Team Jaime Collazo; Work Team: S&P Tel Reg - Team Michael Garrion; Work Team: S&P Tel Reg - Team Raul Tejada; Work Team: S&P Tel Reg - Team Terrence Toepler | T77: voice | U77: 97b32bb1-d91f-4ab2-a23b-46598fd1caf5 | V77: Andrea Harris
I78: Andrea Harris | P78: 46068 | Q78: 46075.021 | R78: TRUE | S78: Wrap-up: ININ-WRAP-UP-TIMEOUT; Work Team: S&P Campaign - Team Danielle McMullan; Work Team: S&P Flex Trainer and SME Team; Work Team: S&P Outbound - Team Eddie Mendoza; Work Team: S&P Retention Agents - Team William Coad; Work Team: S&P Retention Service - Team Nicholas Boudreau; Work Team: S&P Service - Nesting 1; Work Team: S&P Service - Team John Burdett; Work Team: S&P Service - Team Reina Morales; Work Team: S&P Service - Team Stefano Lista; Work Team: S&P Tel Reg - Nesting ; Work Team: S&P Tel Reg - Nesting 2; Work Team: S&P Tel Reg - Team Alex Clare; Work Team: S&P Tel Reg - Team Brian Finnstrom; Work Team: S&P Tel Reg - Team Charnetta Hull; Work Team: S&P Tel Reg - Team David Densmore; Work Team: S&P Tel Reg - Team David Locke; Work Team: S&P Tel Reg - Team Jaime Collazo; Work Team: S&P Tel Reg - Team Michael Garrion; Work Team: S&P Tel Reg - Team Raul Tejada; Work Team: S&P Tel Reg - Team Terrence Toepler | T78: voice | U78: 0494c073-62b1-4da8-b9a0-f1246bdd13ed | V78: Andrea Manning
I79: Andrea Manning | P79: 46068 | Q79: 46075.021 | R79: TRUE | S79: Wrap-up: ININ-WRAP-UP-TIMEOUT; Work Team: S&P Campaign - Team Danielle McMullan; Work Team: S&P Flex Trainer and SME Team; Work Team: S&P Outbound - Team Eddie Mendoza; Work Team: S&P Retention Agents - Team William Coad; Work Team: S&P Retention Service - Team Nicholas Boudreau; Work Team: S&P Service - Nesting 1; Work Team: S&P Service - Team John Burdett; Work Team: S&P Service - Team Reina Morales; Work Team: S&P Service - Team Stefano Lista; Work Team: S&P Tel Reg - Nesting ; Work Team: S&P Tel Reg - Nesting 2; Work Team: S&P Tel Reg - Team Alex Clare; Work Team: S&P Tel Reg - Team Brian Finnstrom; Work Team: S&P Tel Reg - Team Charnetta Hull; Work Team: S&P Tel Reg - Team David Densmore; Work Team: S&P Tel Reg - Team David Locke; Work Team: S&P Tel Reg - Team Jaime Collazo; Work Team: S&P Tel Reg - Team Michael Garrion; Work Team: S&P Tel Reg - Team Raul Tejada; Work Team: S&P Tel Reg - Team Terrence Toepler | T79: voice | U79: c246a45c-641e-489d-8f1f-bbebf0ba854b | V79: Andrea Sallee
I80: Andrea Sallee | P80: 46068 | Q80: 46075.021 | R80: TRUE | S80: Wrap-up: ININ-WRAP-UP-TIMEOUT; Work Team: S&P Campaign - Team Danielle McMullan; Work Team: S&P Flex Trainer and SME Team; Work Team: S&P Outbound - Team Eddie Mendoza; Work Team: S&P Retention Agents - Team William Coad; Work Team: S&P Retention Service - Team Nicholas Boudreau; Work Team: S&P Service - Nesting 1; Work Team: S&P Service - Team John Burdett; Work Team: S&P Service - Team Reina Morales; Work Team: S&P Service - Team Stefano Lista; Work Team: S&P Tel Reg - Nesting ; Work Team: S&P Tel Reg - Nesting 2; Work Team: S&P Tel Reg - Team Alex Clare; Work Team: S&P Tel Reg - Team Brian Finnstrom; Work Team: S&P Tel Reg - Team Charnetta Hull; Work Team: S&P Tel Reg - Team David Densmore; Work Team: S&P Tel Reg - Team David Locke; Work Team: S&P Tel Reg - Team Jaime Collazo; Work Team: S&P Tel Reg - Team Michael Garrion; Work Team: S&P Tel Reg - Team Raul Tejada; Work Team: S&P Tel Reg - Team Terrence Toepler | T80: voice | U80: 4f3f7be0-b3b0-4f10-af9a-5b9171b168c2 | V80: Andres Barrantes
I81: Andres Barrantes | P81: 46068 | Q81: 46075.021 | R81: TRUE | S81: Wrap-up: ININ-WRAP-UP-TIMEOUT; Work Team: S&P Campaign - Team Danielle McMullan; Work Team: S&P Flex Trainer and SME Team; Work Team: S&P Outbound - Team Eddie Mendoza; Work Team: S&P Retention Agents - Team William Coad; Work Team: S&P Retention Service - Team Nicholas Boudreau; Work Team: S&P Service - Nesting 1; Work Team: S&P Service - Team John Burdett; Work Team: S&P Service - Team Reina Morales; Work Team: S&P Service - Team Stefano Lista; Work Team: S&P Tel Reg - Nesting ; Work Team: S&P Tel Reg - Nesting 2; Work Team: S&P Tel Reg - Team Alex Clare; Work Team: S&P Tel Reg - Team Brian Finnstrom; Work Team: S&P Tel Reg - Team Charnetta Hull; Work Team: S&P Tel Reg - Team David Densmore; Work Team: S&P Tel Reg - Team David Locke; Work Team: S&P Tel Reg - Team Jaime Collazo; Work Team: S&P Tel Reg - Team Michael Garrion; Work Team: S&P Tel Reg - Team Raul Tejada; Work Team: S&P Tel Reg - Team Terrence Toepler | T81: voice | U81: 797a1314-01ea-4634-ba80-bf04f599bd27 | V81: Andres Rodrigo Serrano Chinchilla
I82: Andres Rodrigo Serrano Chinchilla | P82: 46068 | Q82: 46075.021 | R82: TRUE | S82: Wrap-up: ININ-WRAP-UP-TIMEOUT; Work Team: S&P Campaign - Team Danielle McMullan; Work Team: S&P Flex Trainer and SME Team; Work Team: S&P Outbound - Team Eddie Mendoza; Work Team: S&P Retention Agents - Team William Coad; Work Team: S&P Retention Service - Team Nicholas Boudreau; Work Team: S&P Service - Nesting 1; Work Team: S&P Service - Team John Burdett; Work Team: S&P Service - Team Reina Morales; Work Team: S&P Service - Team Stefano Lista; Work Team: S&P Tel Reg - Nesting ; Work Team: S&P Tel Reg - Nesting 2; Work Team: S&P Tel Reg - Team Alex Clare; Work Team: S&P Tel Reg - Team Brian Finnstrom; Work Team: S&P Tel Reg - Team Charnetta Hull; Work Team: S&P Tel Reg - Team David Densmore; Work Team: S&P Tel Reg - Team David Locke; Work Team: S&P Tel Reg - Team Jaime Collazo; Work Team: S&P Tel Reg - Team Michael Garrion; Work Team: S&P Tel Reg - Team Raul Tejada; Work Team: S&P Tel Reg - Team Terrence Toepler | T82: voice | U82: 116fec5f-bbd0-40d2-8a51-f7e292d6a1b4 | V82: Andres Vindas
I83: Andres Vindas | P83: 46068 | Q83: 46075.021 | R83: TRUE | S83: Wrap-up: ININ-WRAP-UP-TIMEOUT; Work Team: S&P Campaign - Team Danielle McMullan; Work Team: S&P Flex Trainer and SME Team; Work Team: S&P Outbound - Team Eddie Mendoza; Work Team: S&P Retention Agents - Team William Coad; Work Team: S&P Retention Service - Team Nicholas Boudreau; Work Team: S&P Service - Nesting 1; Work Team: S&P Service - Team John Burdett; Work Team: S&P Service - Team Reina Morales; Work Team: S&P Service - Team Stefano Lista; Work Team: S&P Tel Reg - Nesting ; Work Team: S&P Tel Reg - Nesting 2; Work Team: S&P Tel Reg - Team Alex Clare; Work Team: S&P Tel Reg - Team Brian Finnstrom; Work Team: S&P Tel Reg - Team Charnetta Hull; Work Team: S&P Tel Reg - Team David Densmore; Work Team: S&P Tel Reg - Team David Locke; Work Team: S&P Tel Reg - Team Jaime Collazo; Work Team: S&P Tel Reg - Team Michael Garrion; Work Team: S&P Tel Reg - Team Raul Tejada; Work Team: S&P Tel Reg - Team Terrence Toepler | T83: voice | U83: 1b79e8f7-9496-4075-9539-ef7a6a706390 | V83: Andrew Barratt
I84: Andrew Barratt | P84: 46068 | Q84: 46075.021 | R84: TRUE | S84: Wrap-up: ININ-WRAP-UP-TIMEOUT; Work Team: S&P Campaign - Team Danielle McMullan; Work Team: S&P Flex Trainer and SME Team; Work Team: S&P Outbound - Team Eddie Mendoza; Work Team: S&P Retention Agents - Team William Coad; Work Team: S&P Retention Service - Team Nicholas Boudreau; Work Team: S&P Service - Nesting 1; Work Team: S&P Service - Team John Burdett; Work Team: S&P Service - Team Reina Morales; Work Team: S&P Service - Team Stefano Lista; Work Team: S&P Tel Reg - Nesting ; Work Team: S&P Tel Reg - Nesting 2; Work Team: S&P Tel Reg - Team Alex Clare; Work Team: S&P Tel Reg - Team Brian Finnstrom; Work Team: S&P Tel Reg - Team Charnetta Hull; Work Team: S&P Tel Reg - Team David Densmore; Work Team: S&P Tel Reg - Team David Locke; Work Team: S&P Tel Reg - Team Jaime Collazo; Work Team: S&P Tel Reg - Team Michael Garrion; Work Team: S&P Tel Reg - Team Raul Tejada; Work Team: S&P Tel Reg - Team Terrence Toepler | T84: voice | U84: c95fb214-9cbe-4568-9e02-85725614fcc4 | V84: Andrew Bressi
I85: Andrew Bressi | P85: 46068 | Q85: 46075.021 | R85: TRUE | S85: Wrap-up: ININ-WRAP-UP-TIMEOUT; Work Team: S&P Campaign - Team Danielle McMullan; Work Team: S&P Flex Trainer and SME Team; Work Team: S&P Outbound - Team Eddie Mendoza; Work Team: S&P Retention Agents - Team William Coad; Work Team: S&P Retention Service - Team Nicholas Boudreau; Work Team: S&P Service - Nesting 1; Work Team: S&P Service - Team John Burdett; Work Team: S&P Service - Team Reina Morales; Work Team: S&P Service - Team Stefano Lista; Work Team: S&P Tel Reg - Nesting ; Work Team: S&P Tel Reg - Nesting 2; Work Team: S&P Tel Reg - Team Alex Clare; Work Team: S&P Tel Reg - Team Brian Finnstrom; Work Team: S&P Tel Reg - Team Charnetta Hull; Work Team: S&P Tel Reg - Team David Densmore; Work Team: S&P Tel Reg - Team David Locke; Work Team: S&P Tel Reg - Team Jaime Collazo; Work Team: S&P Tel Reg - Team Michael Garrion; Work Team: S&P Tel Reg - Team Raul Tejada; Work Team: S&P Tel Reg - Team Terrence Toepler | T85: voice | U85: ddd5c5c2-19ac-4ac7-b1b5-b91bfef96e2b | V85: Andrew Henderson
... I88: Andrey Marin | P88: 46068 | Q88: 46075.021 | R88: TRUE | S88: Wrap-up: ININ-WRAP-UP-TIMEOUT; Work Team: S&P Campaign - Team Danielle McMullan; Work Team: S&P Flex Trainer and SME Team; Work Team: S&P Outbound - Team Eddie Mendoza; Work Team: S&P Retention Agents - Team William Coad; Work Team: S&P Retention Service - Team Nicholas Boudreau; Work Team: S&P Service - Nesting 1; Work Team: S&P Service - Team John Burdett; Work Team: S&P Service - Team Reina Morales; Work Team: S&P Service - Team Stefano Lista; Work Team: S&P Tel Reg - Nesting ; Work Team: S&P Tel Reg - Nesting 2; Work Team: S&P Tel Reg - Team Alex Clare; Work Team: S&P Tel Reg - Team Brian Finnstrom; Work Team: S&P Tel Reg - Team Charnetta Hull; Work Team: S&P Tel Reg - Team David Densmore; Work Team: S&P Tel Reg - Team David Locke; Work Team: S&P Tel Reg - Team Jaime Collazo; Work Team: S&P Tel Reg - Team Michael Garrion; Work Team: S&P Tel Reg - Team Raul Tejada; Work Team: S&P Tel Reg - Team Terrence Toepler | T88: voice | U88: b3363c9e-22e3-4954-8fef-644ff9ad8f0a | V88: Andy Vargas01
I89: Andy Vargas01 | P89: 46068 | Q89: 46075.021 | R89: TRUE | S89: Wrap-up: ININ-WRAP-UP-TIMEOUT; Work Team: S&P Campaign - Team Danielle McMullan; Work Team: S&P Flex Trainer and SME Team; Work Team: S&P Outbound - Team Eddie Mendoza; Work Team: S&P Retention Agents - Team William Coad; Work Team: S&P Retention Service - Team Nicholas Boudreau; Work Team: S&P Service - Nesting 1; Work Team: S&P Service - Team John Burdett; Work Team: S&P Service - Team Reina Morales; Work Team: S&P Service - Team Stefano Lista; Work Team: S&P Tel Reg - Nesting ; Work Team: S&P Tel Reg - Nesting 2; Work Team: S&P Tel Reg - Team Alex Clare; Work Team: S&P Tel Reg - Team Brian Finnstrom; Work Team: S&P Tel Reg - Team Charnetta Hull; Work Team: S&P Tel Reg - Team David Densmore; Work Team: S&P Tel Reg - Team David Locke; Work Team: S&P Tel Reg - Team Jaime Collazo; Work Team: S&P Tel Reg - Team Michael Garrion; Work Team: S&P Tel Reg - Team Raul Tejada; Work Team: S&P Tel Reg - Team Terrence Toepler | T89: voice | U89: 0040f795-2771-4f1e-8b1f-b1981d6f17df | V89: Aneena Sheela Nath | X89: 2 | Y89: 1376249.5 | Z89: 1336249.5 | AB89: 40000
I90: Aneena Sheela Nath | J90: 2 | P90: 46068 | Q90: 46075.021 | R90: TRUE | S90: Wrap-up: ININ-WRAP-UP-TIMEOUT; Work Team: S&P Campaign - Team Danielle McMullan; Work Team: S&P Flex Trainer and SME Team; Work Team: S&P Outbound - Team Eddie Mendoza; Work Team: S&P Retention Agents - Team William Coad; Work Team: S&P Retention Service - Team Nicholas Boudreau; Work Team: S&P Service - Nesting 1; Work Team: S&P Service - Team John Burdett; Work Team: S&P Service - Team Reina Morales; Work Team: S&P Service - Team Stefano Lista; Work Team: S&P Tel Reg - Nesting ; Work Team: S&P Tel Reg - Nesting 2; Work Team: S&P Tel Reg - Team Alex Clare; Work Team: S&P Tel Reg - Team Brian Finnstrom; Work Team: S&P Tel Reg - Team Charnetta Hull; Work Team: S&P Tel Reg - Team David Densmore; Work Team: S&P Tel Reg - Team David Locke; Work Team: S&P Tel Reg - Team Jaime Collazo; Work Team: S&P Tel Reg - Team Michael Garrion; Work Team: S&P Tel Reg - Team Raul Tejada; Work Team: S&P Tel Reg - Team Terrence Toepler | T90: voice | U90: de56b1a2-c40e-49a2-9c2a-9669b071e706 | V90: Angel Ernesto Merlos Amaya
I91: Angel Ernesto Merlos Amaya | P91: 46068 | Q91: 46075.021 | R91: TRUE | S91: Wrap-up: ININ-WRAP-UP-TIMEOUT; Work Team: S&P Campaign - Team Danielle McMullan; Work Team: S&P Flex Trainer and SME Team; Work Team: S&P Outbound - Team Eddie Mendoza; Work Team: S&P Retention Agents - Team William Coad; Work Team: S&P Retention Service - Team Nicholas Boudreau; Work Team: S&P Service - Nesting 1; Work Team: S&P Service - Team John Burdett; Work Team: S&P Service - Team Reina Morales; Work Team: S&P Service - Team Stefano Lista; Work Team: S&P Tel Reg - Nesting ; Work Team: S&P Tel Reg - Nesting 2; Work Team: S&P Tel Reg - Team Alex Clare; Work Team: S&P Tel Reg - Team Brian Finnstrom; Work Team: S&P Tel Reg - Team Charnetta Hull; Work Team: S&P Tel Reg - Team David Densmore; Work Team: S&P Tel Reg - Team David Locke; Work Team: S&P Tel Reg - Team Jaime Collazo; Work Team: S&P Tel Reg - Team Michael Garrion; Work Team: S&P Tel Reg - Team Raul Tejada; Work Team: S&P Tel Reg - Team Terrence Toepler | T91: voice | U91: f0d88564-679f-4630-bff8-9227b9990d2e | V91: Angel Scarbrough
I92: Angel Scarbrough | P92: 46068 | Q92: 46075.021 | R92: TRUE | S92: Wrap-up: ININ-WRAP-UP-TIMEOUT; Work Team: S&P Campaign - Team Danielle McMullan; Work Team: S&P Flex Trainer and SME Team; Work Team: S&P Outbound - Team Eddie Mendoza; Work Team: S&P Retention Agents - Team William Coad; Work Team: S&P Retention Service - Team Nicholas Boudreau; Work Team: S&P Service - Nesting 1; Work Team: S&P Service - Team John Burdett; Work Team: S&P Service - Team Reina Morales; Work Team: S&P Service - Team Stefano Lista; Work Team: S&P Tel Reg - Nesting ; Work Team: S&P Tel Reg - Nesting 2; Work Team: S&P Tel Reg - Team Alex Clare; Work Team: S&P Tel Reg - Team Brian Finnstrom; Work Team: S&P Tel Reg - Team Charnetta Hull; Work Team: S&P Tel Reg - Team David Densmore; Work Team: S&P Tel Reg - Team David Locke; Work Team: S&P Tel Reg - Team Jaime Collazo; Work Team: S&P Tel Reg - Team Michael Garrion; Work Team: S&P Tel Reg - Team Raul Tejada; Work Team: S&P Tel Reg - Team Terrence Toepler | T92: voice | U92: ac362447-058d-4d77-9979-f86ec722636a | V92: Angela Gonzales
I93: Angela Gonzales | P93: 46068 | Q93: 46075.021 | R93: TRUE | S93: Wrap-up: ININ-WRAP-UP-TIMEOUT; Work Team: S&P Campaign - Team Danielle McMullan; Work Team: S&P Flex Trainer and SME Team; Work Team: S&P Outbound - Team Eddie Mendoza; Work Team: S&P Retention Agents - Team William Coad; Work Team: S&P Retention Service - Team Nicholas Boudreau; Work Team: S&P Service - Nesting 1; Work Team: S&P Service - Team John Burdett; Work Team: S&P Service - Team Reina Morales; Work Team: S&P Service - Team Stefano Lista; Work Team: S&P Tel Reg - Nesting ; Work Team: S&P Tel Reg - Nesting 2; Work Team: S&P Tel Reg - Team Alex Clare; Work Team: S&P Tel Reg - Team Brian Finnstrom; Work Team: S&P Tel Reg - Team Charnetta Hull; Work Team: S&P Tel Reg - Team David Densmore; Work Team: S&P Tel Reg - Team David Locke; Work Team: S&P Tel Reg - Team Jaime Collazo; Work Team: S&P Tel Reg - Team Michael Garrion; Work Team: S&P Tel Reg - Team Raul Tejada; Work Team: S&P Tel Reg - Team Terrence Toepler | T93: voice | U93: 69d7b430-076a-4183-8950-df1faf4cd4d2 | V93: Angelica Gonzalez | X93: 7 | Y93: 135575.43 | Z93: 81496.286 | AA93: 67851.333 | AB93: 25000 | AC93: 3
I94: Angelica Gonzalez | J94: 7 | P94: 46068 | Q94: 46075.021 | R94: TRUE | S94: Wrap-up: ININ-WRAP-UP-TIMEOUT; Work Team: S&P Campaign - Team Danielle McMullan; Work Team: S&P Flex Trainer and SME Team; Work Team: S&P Outbound - Team Eddie Mendoza; Work Team: S&P Retention Agents - Team William Coad; Work Team: S&P Retention Service - Team Nicholas Boudreau; Work Team: S&P Service - Nesting 1; Work Team: S&P Service - Team John Burdett; Work Team: S&P Service - Team Reina Morales; Work Team: S&P Service - Team Stefano Lista; Work Team: S&P Tel Reg - Nesting ; Work Team: S&P Tel Reg - Nesting 2; Work Team: S&P Tel Reg - Team Alex Clare; Work Team: S&P Tel Reg - Team Brian Finnstrom; Work Team: S&P Tel Reg - Team Charnetta Hull; Work Team: S&P Tel Reg - Team David Densmore; Work Team: S&P Tel Reg - Team David Locke; Work Team: S&P Tel Reg - Team Jaime Collazo; Work Team: S&P Tel Reg - Team Michael Garrion; Work Team: S&P Tel Reg - Team Raul Tejada; Work Team: S&P Tel Reg - Team Terrence Toepler | T94: voice | U94: 0014a8e1-ae07-4108-a8f2-75cded764c1b | V94: Angelica Martinez
I95: Angelica Martinez | P95: 46068 | Q95: 46075.021 | R95: TRUE | S95: Wrap-up: ININ-WRAP-UP-TIMEOUT; Work Team: S&P Campaign - Team Danielle McMullan; Work Team: S&P Flex Trainer and SME Team; Work Team: S&P Outbound - Team Eddie Mendoza; Work Team: S&P Retention Agents - Team William Coad; Work Team: S&P Retention Service - Team Nicholas Boudreau; Work Team: S&P Service - Nesting 1; Work Team: S&P Service - Team John Burdett; Work Team: S&P Service - Team Reina Morales; Work Team: S&P Service - Team Stefano Lista; Work Team: S&P Tel Reg - Nesting ; Work Team: S&P Tel Reg - Nesting 2; Work Team: S&P Tel Reg - Team Alex Clare; Work Team: S&P Tel Reg - Team Brian Finnstrom; Work Team: S&P Tel Reg - Team Charnetta Hull; Work Team: S&P Tel Reg - Team David Densmore; Work Team: S&P Tel Reg - Team David Locke; Work Team: S&P Tel Reg - Team Jaime Collazo; Work Team: S&P Tel Reg - Team Michael Garrion; Work Team: S&P Tel Reg - Team Raul Tejada; Work Team: S&P Tel Reg - Team Terrence Toepler | T95: voice | U95: 5c3d8e83-5056-4130-aa4c-606f62f43c80 | V95: Angella Dunn
I96: Angella Dunn | P96: 46068 | Q96: 46075.021 | R96: TRUE | S96: Wrap-up: ININ-WRAP-UP-TIMEOUT; Work Team: S&P Campaign - Team Danielle McMullan; Work Team: S&P Flex Trainer and SME Team; Work Team: S&P Outbound - Team Eddie Mendoza; Work Team: S&P Retention Agents - Team William Coad; Work Team: S&P Retention Service - Team Nicholas Boudreau; Work Team: S&P Service - Nesting 1; Work Team: S&P Service - Team John Burdett; Work Team: S&P Service - Team Reina Morales; Work Team: S&P Service - Team Stefano Lista; Work Team: S&P Tel Reg - Nesting ; Work Team: S&P Tel Reg - Nesting 2; Work Team: S&P Tel Reg - Team Alex Clare; Work Team: S&P Tel Reg - Team Brian Finnstrom; Work Team: S&P Tel Reg - Team Charnetta Hull; Work Team: S&P Tel Reg - Team David Densmore; Work Team: S&P Tel Reg - Team David Locke; Work Team: S&P Tel Reg - Team Jaime Collazo; Work Team: S&P Tel Reg - Team Michael Garrion; Work Team: S&P Tel Reg - Team Raul Tejada; Work Team: S&P Tel Reg - Team Terrence Toepler | T96: voice | U96: aae7ed1b-8921-4c31-8158-81a75d69761a | V96: Angie Vega
I97: Angie Vega | P97: 46068 | Q97: 46075.021 | R97: TRUE | S97: Wrap-up: ININ-WRAP-UP-TIMEOUT; Work Team: S&P Campaign - Team Danielle McMullan; Work Team: S&P Flex Trainer and SME Team; Work Team: S&P Outbound - Team Eddie Mendoza; Work Team: S&P Retention Agents - Team William Coad; Work Team: S&P Retention Service - Team Nicholas Boudreau; Work Team: S&P Service - Nesting 1; Work Team: S&P Service - Team John Burdett; Work Team: S&P Service - Team Reina Morales; Work Team: S&P Service - Team Stefano Lista; Work Team: S&P Tel Reg - Nesting ; Work Team: S&P Tel Reg - Nesting 2; Work Team: S&P Tel Reg - Team Alex Clare; Work Team: S&P Tel Reg - Team Brian Finnstrom; Work Team: S&P Tel Reg - Team Charnetta Hull; Work Team: S&P Tel Reg - Team David Densmore; Work Team: S&P Tel Reg - Team David Locke; Work Team: S&P Tel Reg - Team Jaime Collazo; Work Team: S&P Tel Reg - Team Michael Garrion; Work Team: S&P Tel Reg - Team Raul Tejada; Work Team: S&P Tel Reg - Team Terrence Toepler | T97: voice | U97: 494e928e-f769-4066-98bf-5327ec7bc032 | V97: Anil Somwaru
I98: Anil Somwaru | P98: 46068 | Q98: 46075.021 | R98: TRUE | S98: Wrap-up: ININ-WRAP-UP-TIMEOUT; Work Team: S&P Campaign - Team Danielle McMullan; Work Team: S&P Flex Trainer and SME Team; Work Team: S&P Outbound - Team Eddie Mendoza; Work Team: S&P Retention Agents - Team William Coad; Work Team: S&P Retention Service - Team Nicholas Boudreau; Work Team: S&P Service - Nesting 1; Work Team: S&P Service - Team John Burdett; Work Team: S&P Service - Team Reina Morales; Work Team: S&P Service - Team Stefano Lista; Work Team: S&P Tel Reg - Nesting ; Work Team: S&P Tel Reg - Nesting 2; Work Team: S&P Tel Reg - Team Alex Clare; Work Team: S&P Tel Reg - Team Brian Finnstrom; Work Team: S&P Tel Reg - Team Charnetta Hull; Work Team: S&P Tel Reg - Team David Densmore; Work Team: S&P Tel Reg - Team David Locke; Work Team: S&P Tel Reg - Team Jaime Collazo; Work Team: S&P Tel Reg - Team Michael Garrion; Work Team: S&P Tel Reg - Team Raul Tejada; Work Team: S&P Tel Reg - Team Terrence Toepler | T98: voice | U98: 5a23f31c-cd81-45e0-94df-4f581d3a2d6b | V98: Ann Leblanc
I99: Ann Leblanc | P99: 46068 | Q99: 46075.021 | R99: TRUE | S99: Wrap-up: ININ-WRAP-UP-TIMEOUT; Work Team: S&P Campaign - Team Danielle McMullan; Work Team: S&P Flex Trainer and SME Team; Work Team: S&P Outbound - Team Eddie Mendoza; Work Team: S&P Retention Agents - Team William Coad; Work Team: S&P Retention Service - Team Nicholas Boudreau; Work Team: S&P Service - Nesting 1; Work Team: S&P Service - Team John Burdett; Work Team: S&P Service - Team Reina Morales; Work Team: S&P Service - Team Stefano Lista; Work Team: S&P Tel Reg - Nesting ; Work Team: S&P Tel Reg - Nesting 2; Work Team: S&P Tel Reg - Team Alex Clare; Work Team: S&P Tel Reg - Team Brian Finnstrom; Work Team: S&P Tel Reg - Team Charnetta Hull; Work Team: S&P Tel Reg - Team David Densmore; Work Team: S&P Tel Reg - Team David Locke; Work Team: S&P Tel Reg - Team Jaime Collazo; Work Team: S&P Tel Reg - Team Michael Garrion; Work Team: S&P Tel Reg - Team Raul Tejada; Work Team: S&P Tel Reg - Team Terrence Toepler | T99: voice | U99: 3d568db0-309b-4677-8346-28f79b15c1fa | V99: Anna Herrera
I100: Anna Herrera | P100: 46068 | Q100: 46075.021 | R100: TRUE | S100: Wrap-up: ININ-WRAP-UP-TIMEOUT; Work Team: S&P Campaign - Team Danielle McMullan; Work Team: S&P Flex Trainer and SME Team; Work Team: S&P Outbound - Team Eddie Mendoza; Work Team: S&P Retention Agents - Team William Coad; Work Team: S&P Retention Service - Team Nicholas Boudreau; Work Team: S&P Service - Nesting 1; Work Team: S&P Service - Team John Burdett; Work Team: S&P Service - Team Reina Morales; Work Team: S&P Service - Team Stefano Lista; Work Team: S&P Tel Reg - Nesting ; Work Team: S&P Tel Reg - Nesting 2; Work Team: S&P Tel Reg - Team Alex Clare; Work Team: S&P Tel Reg - Team Brian Finnstrom; Work Team: S&P Tel Reg - Team Charnetta Hull; Work Team: S&P Tel Reg - Team David Densmore; Work Team: S&P Tel Reg - Team David Locke; Work Team: S&P Tel Reg - Team Jaime Collazo; Work Team: S&P Tel Reg - Team Michael Garrion; Work Team: S&P Tel Reg - Team Raul Tejada; Work Team: S&P Tel Reg - Team Terrence Toepler | T100: voice | U100: a9f82edc-45e1-4354-80af-f0fbe7f0320a | V100: Anna Perez
I101: Anna Perez | P101: 46068 | Q101: 46075.021 | R101: TRUE | S101: Wrap-up: ININ-WRAP-UP-TIMEOUT; Work Team: S&P Campaign - Team Danielle McMullan; Work Team: S&P Flex Trainer and SME Team; Work Team: S&P Outbound - Team Eddie Mendoza; Work Team: S&P Retention Agents - Team William Coad; Work Team: S&P Retention Service - Team Nicholas Boudreau; Work Team: S&P Service - Nesting 1; Work Team: S&P Service - Team John Burdett; Work Team: S&P Service - Team Reina Morales; Work Team: S&P Service - Team Stefano Lista; Work Team: S&P Tel Reg - Nesting ; Work Team: S&P Tel Reg - Nesting 2; Work Team: S&P Tel Reg - Team Alex Clare; Work Team: S&P Tel Reg - Team Brian Finnstrom; Work Team: S&P Tel Reg - Team Charnetta Hull; Work Team: S&P Tel Reg - Team David Densmore; Work Team: S&P Tel Reg - Team David Locke; Work Team: S&P Tel Reg - Team Jaime Collazo; Work Team: S&P Tel Reg - Team Michael Garrion; Work Team: S&P Tel Reg - Team Raul Tejada; Work Team: S&P Tel Reg - Team Terrence Toepler | T101: voice | U101: b46380de-e5c5-4ed5-a136-9028cd3d9fd3 | V101: Anna Shonubi
I102: Anna Shonubi | P102: 46068 | Q102: 46075.021 | R102: TRUE | S102: Wrap-up: ININ-WRAP-UP-TIMEOUT; Work Team: S&P Campaign - Team Danielle McMullan; Work Team: S&P Flex Trainer and SME Team; Work Team: S&P Outbound - Team Eddie Mendoza; Work Team: S&P Retention Agents - Team William Coad; Work Team: S&P Retention Service - Team Nicholas Boudreau; Work Team: S&P Service - Nesting 1; Work Team: S&P Service - Team John Burdett; Work Team: S&P Service - Team Reina Morales; Work Team: S&P Service - Team Stefano Lista; Work Team: S&P Tel Reg - Nesting ; Work Team: S&P Tel Reg - Nesting 2; Work Team: S&P Tel Reg - Team Alex Clare; Work Team: S&P Tel Reg - Team Brian Finnstrom; Work Team: S&P Tel Reg - Team Charnetta Hull; Work Team: S&P Tel Reg - Team David Densmore; Work Team: S&P Tel Reg - Team David Locke; Work Team: S&P Tel Reg - Team Jaime Collazo; Work Team: S&P Tel Reg - Team Michael Garrion; Work Team: S&P Tel Reg - Team Raul Tejada; Work Team: S&P Tel Reg - Team Terrence Toepler | T102: voice | U102: 658c7d6e-2df3-43e0-b9e1-f6e9d4d4c02f | V102: Anna Tolentino | X102: 4 | Y102: 639700.25 | Z102: 599700.25 | AB102: 40000 | AD102: 1
I103: Anna Tolentino | J103: 4 | P103: 46068 | Q103: 46075.021 | R103: TRUE | S103: Wrap-up: ININ-WRAP-UP-TIMEOUT; Work Team: S&P Campaign - Team Danielle McMullan; Work Team: S&P Flex Trainer and SME Team; Work Team: S&P Outbound - Team Eddie Mendoza; Work Team: S&P Retention Agents - Team William Coad; Work Team: S&P Retention Service - Team Nicholas Boudreau; Work Team: S&P Service - Nesting 1; Work Team: S&P Service - Team John Burdett; Work Team: S&P Service - Team Reina Morales; Work Team: S&P Service - Team Stefano Lista; Work Team: S&P Tel Reg - Nesting ; Work Team: S&P Tel Reg - Nesting 2; Work Team: S&P Tel Reg - Team Alex Clare; Work Team: S&P Tel Reg - Team Brian Finnstrom; Work Team: S&P Tel Reg - Team Charnetta Hull; Work Team: S&P Tel Reg - Team David Densmore; Work Team: S&P Tel Reg - Team David Locke; Work Team: S&P Tel Reg - Team Jaime Collazo; Work Team: S&P Tel Reg - Team Michael Garrion; Work Team: S&P Tel Reg - Team Raul Tejada; Work Team: S&P Tel Reg - Team Terrence Toepler | T103: voice | U103: e85e2dca-18d6-47d9-914a-7234c9e11a55 | V103: Annam Viswanath
I104: Annam Viswanath | P104: 46068 | Q104: 46075.021 | R104: TRUE | S104: Wrap-up: ININ-WRAP-UP-TIMEOUT; Work Team: S&P Campaign - Team Danielle McMullan; Work Team: S&P Flex Trainer and SME Team; Work Team: S&P Outbound - Team Eddie Mendoza; Work Team: S&P Retention Agents - Team William Coad; Work Team: S&P Retention Service - Team Nicholas Boudreau; Work Team: S&P Service - Nesting 1; Work Team: S&P Service - Team John Burdett; Work Team: S&P Service - Team Reina Morales; Work Team: S&P Service - Team Stefano Lista; Work Team: S&P Tel Reg - Nesting ; Work Team: S&P Tel Reg - Nesting 2; Work Team: S&P Tel Reg - Team Alex Clare; Work Team: S&P Tel Reg - Team Brian Finnstrom; Work Team: S&P Tel Reg - Team Charnetta Hull; Work Team: S&P Tel Reg - Team David Densmore; Work Team: S&P Tel Reg - Team David Locke; Work Team: S&P Tel Reg - Team Jaime Collazo; Work Team: S&P Tel Reg - Team Michael Garrion; Work Team: S&P Tel Reg - Team Raul Tejada; Work Team: S&P Tel Reg - Team Terrence Toepler | T104: voice | U104: fd60d5ad-287c-452f-a2ea-a985627b18e1 | V104: Annie Cuevas
I105: Annie Cuevas | P105: 46068 | Q105: 46075.021 | R105: TRUE | S105: Wrap-up: ININ-WRAP-UP-TIMEOUT; Work Team: S&P Campaign - Team Danielle McMullan; Work Team: S&P Flex Trainer and SME Team; Work Team: S&P Outbound - Team Eddie Mendoza; Work Team: S&P Retention Agents - Team William Coad; Work Team: S&P Retention Service - Team Nicholas Boudreau; Work Team: S&P Service - Nesting 1; Work Team: S&P Service - Team John Burdett; Work Team: S&P Service - Team Reina Morales; Work Team: S&P Service - Team Stefano Lista; Work Team: S&P Tel Reg - Nesting ; Work Team: S&P Tel Reg - Nesting 2; Work Team: S&P Tel Reg - Team Alex Clare; Work Team: S&P Tel Reg - Team Brian Finnstrom; Work Team: S&P Tel Reg - Team Charnetta Hull; Work Team: S&P Tel Reg - Team David Densmore; Work Team: S&P Tel Reg - Team David Locke; Work Team: S&P Tel Reg - Team Jaime Collazo; Work Team: S&P Tel Reg - Team Michael Garrion; Work Team: S&P Tel Reg - Team Raul Tejada; Work Team: S&P Tel Reg - Team Terrence Toepler | T105: voice | U105: 0c1ee5f2-c0d6-4242-b01e-34f426db9c9c | V105: Antasia Phillips
...

Sheet MTD
B1: TL | C1: NN | D1: Agents | E1: Cancels | F1: Saves | G1: Camp | H1: OOW | I1: IW | J1: All Sales | K1: Reg | L1: Ret Calls | M1: Serv calls | N1: All Calls | O1: Canc % | P1: Save % | Q1: oow % | R1: Serv % | S1: RPC | T1: Save Efficiency | U1: Status
B2: Will | D2: Amy Smiley | E2: =_xlfn.XLOOKUP(Table4[[#This Row],[Agents]],'MTD Raw'!L:L,'MTD Raw'!M:M,0) -> 26 | F2: =_xlfn.XLOOKUP(Table4[[#This Row],[Agents]],'MTD Raw'!I:I,'MTD Raw'!J:J,0)+E41 -> 49 | G2: =_xlfn.XLOOKUP(Table4[[#This Row],[Agents]],'MTD Raw'!A:A,'MTD Raw'!B:B,0) -> 0 | H2: =_xlfn.XLOOKUP(Table4[[#This Row],[Agents]],'MTD Raw'!A:A,'MTD Raw'!C:C,0) -> 3 | I2: =_xlfn.XLOOKUP(Table4[[#This Row],[Agents]],'MTD Raw'!A:A,'MTD Raw'!D:D,0) -> 0 | J2: =SUM(Table4[[#This Row],[Camp]:[IW]])+H41 -> 5 | K2: =_xlfn.XLOOKUP(Table4[[#This Row],[Agents]],'MTD Raw'!A:A,'MTD Raw'!E:E,0) -> 0 | L2: =_xlfn.XLOOKUP(Table4[[#This Row],[Agents]],'MTD Raw'!AB:AB,'MTD Raw'!AE:AE,0) -> 31 | M2: =_xlfn.XLOOKUP(Table4[[#This Row],[Agents]],'MTD Raw'!AU:AU,'MTD Raw'!AX:AX,0) -> 0 | N2: =SUM(Table4[[#This Row],[Ret Calls]:[Serv calls]]) -> 31 | O2: =IFERROR(Table4[[#This Row],[Cancels]]/Table4[[#This Row],[Ret Calls]],0) -> 0.83870968 | P2: =IFERROR(Table4[[#This Row],[Saves]]/Table4[[#This Row],[Ret Calls]],0) -> 1.5806452 | Q2: =IFERROR(Table4[[#This Row],[OOW]]/Table4[[#This Row],[All Calls]],0) -> 0.096774194 | R2: =IFERROR(Table4[[#This Row],[All Sales]]/Table4[[#This Row],[Serv calls]],0) -> 0 | S2: =IFERROR(Table4[[#This Row],[Reg]]/Table4[[#This Row],[Serv calls]],0) -> 0 | T2: =Table4[[#This Row],[Saves]]/Table4[[#This Row],[Cancels]] -> 1.8846154
B3: Will | D3: Mohamed Bayoumy | E3: =_xlfn.XLOOKUP(Table4[[#This Row],[Agents]],'MTD Raw'!L:L,'MTD Raw'!M:M,0) -> 117 | F3: =_xlfn.XLOOKUP(Table4[[#This Row],[Agents]],'MTD Raw'!I:I,'MTD Raw'!J:J,0)+E42 -> 135 | G3: =_xlfn.XLOOKUP(Table4[[#This Row],[Agents]],'MTD Raw'!A:A,'MTD Raw'!B:B,0) -> 0 | H3: =_xlfn.XLOOKUP(Table4[[#This Row],[Agents]],'MTD Raw'!A:A,'MTD Raw'!C:C,0) -> 5 | I3: =_xlfn.XLOOKUP(Table4[[#This Row],[Agents]],'MTD Raw'!A:A,'MTD Raw'!D:D,0) -> 0 | J3: =SUM(Table4[[#This Row],[Camp]:[IW]])+H42 -> 6 | K3: =_xlfn.XLOOKUP(Table4[[#This Row],[Agents]],'MTD Raw'!A:A,'MTD Raw'!E:E,0) -> 8 | L3: =_xlfn.XLOOKUP(Table4[[#This Row],[Agents]],'MTD Raw'!AB:AB,'MTD Raw'!AE:AE,0) -> 130 | M3: =_xlfn.XLOOKUP(Table4[[#This Row],[Agents]],'MTD Raw'!AU:AU,'MTD Raw'!AX:AX,0) -> 0 | N3: =SUM(Table4[[#This Row],[Ret Calls]:[Serv calls]]) -> 130 | O3: =IFERROR(Table4[[#This Row],[Cancels]]/Table4[[#This Row],[Ret Calls]],0) -> 0.9 | P3: =IFERROR(Table4[[#This Row],[Saves]]/Table4[[#This Row],[Ret Calls]],0) -> 1.0384615 | Q3: =IFERROR(Table4[[#This Row],[OOW]]/Table4[[#This Row],[All Calls]],0) -> 0.038461538 | R3: =IFERROR(Table4[[#This Row],[All Sales]]/Table4[[#This Row],[Serv calls]],0) -> 0 | S3: =IFERROR(Table4[[#This Row],[Reg]]/Table4[[#This Row],[Serv calls]],0) -> 0 | T3: =Table4[[#This Row],[Saves]]/Table4[[#This Row],[Cancels]] -> 1.1538462
B4: Will | D4: Angelica Gonzalez | E4: =_xlfn.XLOOKUP(Table4[[#This Row],[Agents]],'MTD Raw'!L:L,'MTD Raw'!M:M,0) -> 83 | F4: =_xlfn.XLOOKUP(Table4[[#This Row],[Agents]],'MTD Raw'!I:I,'MTD Raw'!J:J,0)+E43 -> 127 | G4: =_xlfn.XLOOKUP(Table4[[#This Row],[Agents]],'MTD Raw'!A:A,'MTD Raw'!B:B,0) -> 2 | H4: =_xlfn.XLOOKUP(Table4[[#This Row],[Agents]],'MTD Raw'!A:A,'MTD Raw'!C:C,0) -> 5 | I4: =_xlfn.XLOOKUP(Table4[[#This Row],[Agents]],'MTD Raw'!A:A,'MTD Raw'!D:D,0) -> 0 | J4: =SUM(Table4[[#This Row],[Camp]:[IW]])+H43 -> 7 | K4: =_xlfn.XLOOKUP(Table4[[#This Row],[Agents]],'MTD Raw'!A:A,'MTD Raw'!E:E,0) -> 4 | L4: =_xlfn.XLOOKUP(Table4[[#This Row],[Agents]],'MTD Raw'!AB:AB,'MTD Raw'!AE:AE,0) -> 121 | M4: =_xlfn.XLOOKUP(Table4[[#This Row],[Agents]],'MTD Raw'!AU:AU,'MTD Raw'!AX:AX,0) -> 0 | N4: =SUM(Table4[[#This Row],[Ret Calls]:[Serv calls]]) -> 121 | O4: =IFERROR(Table4[[#This Row],[Cancels]]/Table4[[#This Row],[Ret Calls]],0) -> 0.68595041 | P4: =IFERROR(Table4[[#This Row],[Saves]]/Table4[[#This Row],[Ret Calls]],0) -> 1.0495868 | Q4: =IFERROR(Table4[[#This Row],[OOW]]/Table4[[#This Row],[All Calls]],0) -> 0.041322314 | R4: =IFERROR(Table4[[#This Row],[All Sales]]/Table4[[#This Row],[Serv calls]],0) -> 0 | S4: =IFERROR(Table4[[#This Row],[Reg]]/Table4[[#This Row],[Serv calls]],0) -> 0 | T4: =Table4[[#This Row],[Saves]]/Table4[[#This Row],[Cancels]] -> 1.5301205
B5: Will | D5: Dinesh Kandoth | E5: =_xlfn.XLOOKUP(Table4[[#This Row],[Agents]],'MTD Raw'!L:L,'MTD Raw'!M:M,0) -> 92 | F5: =_xlfn.XLOOKUP(Table4[[#This Row],[Agents]],'MTD Raw'!I:I,'MTD Raw'!J:J,0)+E44 -> 50 | G5: =_xlfn.XLOOKUP(Table4[[#This Row],[Agents]],'MTD Raw'!A:A,'MTD Raw'!B:B,0) -> 1 | H5: =_xlfn.XLOOKUP(Table4[[#This Row],[Agents]],'MTD Raw'!A:A,'MTD Raw'!C:C,0) -> 10 | I5: =_xlfn.XLOOKUP(Table4[[#This Row],[Agents]],'MTD Raw'!A:A,'MTD Raw'!D:D,0) -> 0 | J5: =SUM(Table4[[#This Row],[Camp]:[IW]])+H44 -> 14 | K5: =_xlfn.XLOOKUP(Table4[[#This Row],[Agents]],'MTD Raw'!A:A,'MTD Raw'!E:E,0) -> 1 | L5: =_xlfn.XLOOKUP(Table4[[#This Row],[Agents]],'MTD Raw'!AB:AB,'MTD Raw'!AE:AE,0) -> 100 | M5: =_xlfn.XLOOKUP(Table4[[#This Row],[Agents]],'MTD Raw'!AU:AU,'MTD Raw'!AX:AX,0) -> 185 | N5: =SUM(Table4[[#This Row],[Ret Calls]:[Serv calls]]) -> 285 | O5: =IFERROR(Table4[[#This Row],[Cancels]]/Table4[[#This Row],[Ret Calls]],0) -> 0.92 | P5: =IFERROR(Table4[[#This Row],[Saves]]/Table4[[#This Row],[Ret Calls]],0) -> 0.5 | Q5: =IFERROR(Table4[[#This Row],[OOW]]/Table4[[#This Row],[All Calls]],0) -> 0.035087719 | R5: =IFERROR(Table4[[#This Row],[All Sales]]/Table4[[#This Row],[Serv calls]],0) -> 0.075675676 | S5: =IFERROR(Table4[[#This Row],[Reg]]/Table4[[#This Row],[Serv calls]],0) -> 0.0054054054 | T5: =Table4[[#This Row],[Saves]]/Table4[[#This Row],[Cancels]] -> 0.54347826
B6: Will | D6: Regina Watson | E6: =_xlfn.XLOOKUP(Table4[[#This Row],[Agents]],'MTD Raw'!L:L,'MTD Raw'!M:M,0) -> 64 | F6: =_xlfn.XLOOKUP(Table4[[#This Row],[Agents]],'MTD Raw'!I:I,'MTD Raw'!J:J,0)+E45 -> 118 | G6: =_xlfn.XLOOKUP(Table4[[#This Row],[Agents]],'MTD Raw'!A:A,'MTD Raw'!B:B,0) -> 0 | H6: =_xlfn.XLOOKUP(Table4[[#This Row],[Agents]],'MTD Raw'!A:A,'MTD Raw'!C:C,0) -> 7 | I6: =_xlfn.XLOOKUP(Table4[[#This Row],[Agents]],'MTD Raw'!A:A,'MTD Raw'!D:D,0) -> 0 | J6: =SUM(Table4[[#This Row],[Camp]:[IW]])+H45 -> 9 | K6: =_xlfn.XLOOKUP(Table4[[#This Row],[Agents]],'MTD Raw'!A:A,'MTD Raw'!E:E,0) -> 5 | L6: =_xlfn.XLOOKUP(Table4[[#This Row],[Agents]],'MTD Raw'!AB:AB,'MTD Raw'!AE:AE,0) -> 111 | M6: =_xlfn.XLOOKUP(Table4[[#This Row],[Agents]],'MTD Raw'!AU:AU,'MTD Raw'!AX:AX,0) -> 0 | N6: =SUM(Table4[[#This Row],[Ret Calls]:[Serv calls]]) -> 111 | O6: =IFERROR(Table4[[#This Row],[Cancels]]/Table4[[#This Row],[Ret Calls]],0) -> 0.57657658 | P6: =IFERROR(Table4[[#This Row],[Saves]]/Table4[[#This Row],[Ret Calls]],0) -> 1.0630631 | Q6: =IFERROR(Table4[[#This Row],[OOW]]/Table4[[#This Row],[All Calls]],0) -> 0.063063063 | R6: =IFERROR(Table4[[#This Row],[All Sales]]/Table4[[#This Row],[Serv calls]],0) -> 0 | S6: =IFERROR(Table4[[#This Row],[Reg]]/Table4[[#This Row],[Serv calls]],0) -> 0 | T6: =Table4[[#This Row],[Saves]]/Table4[[#This Row],[Cancels]] -> 1.84375
B7: Will | D7: Douglas Barnes | E7: =_xlfn.XLOOKUP(Table4[[#This Row],[Agents]],'MTD Raw'!L:L,'MTD Raw'!M:M,0) -> 97 | F7: =_xlfn.XLOOKUP(Table4[[#This Row],[Agents]],'MTD Raw'!I:I,'MTD Raw'!J:J,0)+E46 -> 65 | G7: =_xlfn.XLOOKUP(Table4[[#This Row],[Agents]],'MTD Raw'!A:A,'MTD Raw'!B:B,0) -> 0 | H7: =_xlfn.XLOOKUP(Table4[[#This Row],[Agents]],'MTD Raw'!A:A,'MTD Raw'!C:C,0) -> 3 | I7: =_xlfn.XLOOKUP(Table4[[#This Row],[Agents]],'MTD Raw'!A:A,'MTD Raw'!D:D,0) -> 0 | J7: =SUM(Table4[[#This Row],[Camp]:[IW]])+H46 -> 5 | K7: =_xlfn.XLOOKUP(Table4[[#This Row],[Agents]],'MTD Raw'!A:A,'MTD Raw'!E:E,0) -> 1 | L7: =_xlfn.XLOOKUP(Table4[[#This Row],[Agents]],'MTD Raw'!AB:AB,'MTD Raw'!AE:AE,0) -> 102 | M7: =_xlfn.XLOOKUP(Table4[[#This Row],[Agents]],'MTD Raw'!AU:AU,'MTD Raw'!AX:AX,0) -> 0 | N7: =SUM(Table4[[#This Row],[Ret Calls]:[Serv calls]]) -> 102 | O7: =IFERROR(Table4[[#This Row],[Cancels]]/Table4[[#This Row],[Ret Calls]],0) -> 0.95098039 | P7: =IFERROR(Table4[[#This Row],[Saves]]/Table4[[#This Row],[Ret Calls]],0) -> 0.6372549 | Q7: =IFERROR(Table4[[#This Row],[OOW]]/Table4[[#This Row],[All Calls]],0) -> 0.029411765 | R7: =IFERROR(Table4[[#This Row],[All Sales]]/Table4[[#This Row],[Serv calls]],0) -> 0 | S7: =IFERROR(Table4[[#This Row],[Reg]]/Table4[[#This Row],[Serv calls]],0) -> 0 | T7: =Table4[[#This Row],[Saves]]/Table4[[#This Row],[Cancels]] -> 0.67010309
B8: Will | D8: Margaret Reddy | E8: =_xlfn.XLOOKUP(Table4[[#This Row],[Agents]],'MTD Raw'!L:L,'MTD Raw'!M:M,0) -> 119 | F8: =_xlfn.XLOOKUP(Table4[[#This Row],[Agents]],'MTD Raw'!I:I,'MTD Raw'!J:J,0)+E47 -> 88 | G8: =_xlfn.XLOOKUP(Table4[[#This Row],[Agents]],'MTD Raw'!A:A,'MTD Raw'!B:B,0) -> 0 | H8: =_xlfn.XLOOKUP(Table4[[#This Row],[Agents]],'MTD Raw'!A:A,'MTD Raw'!C:C,0) -> 1 | I8: =_xlfn.XLOOKUP(Table4[[#This Row],[Agents]],'MTD Raw'!A:A,'MTD Raw'!D:D,0) -> 0 | J8: =SUM(Table4[[#This Row],[Camp]:[IW]])+H47 -> 1 | K8: =_xlfn.XLOOKUP(Table4[[#This Row],[Agents]],'MTD Raw'!A:A,'MTD Raw'!E:E,0) -> 6 | L8: =_xlfn.XLOOKUP(Table4[[#This Row],[Agents]],'MTD Raw'!AB:AB,'MTD Raw'!AE:AE,0) -> 171 | M8: =_xlfn.XLOOKUP(Table4[[#This Row],[Agents]],'MTD Raw'!AU:AU,'MTD Raw'!AX:AX,0) -> 0 | N8: =SUM(Table4[[#This Row],[Ret Calls]:[Serv calls]]) -> 171 | O8: =IFERROR(Table4[[#This Row],[Cancels]]/Table4[[#This Row],[Ret Calls]],0) -> 0.69590643 | P8: =IFERROR(Table4[[#This Row],[Saves]]/Table4[[#This Row],[Ret Calls]],0) -> 0.51461988 | Q8: =IFERROR(Table4[[#This Row],[OOW]]/Table4[[#This Row],[All Calls]],0) -> 0.0058479532 | R8: =IFERROR(Table4[[#This Row],[All Sales]]/Table4[[#This Row],[Serv calls]],0) -> 0 | S8: =IFERROR(Table4[[#This Row],[Reg]]/Table4[[#This Row],[Serv calls]],0) -> 0 | T8: =Table4[[#This Row],[Saves]]/Table4[[#This Row],[Cancels]] -> 0.7394958
B9: Will | D9: Larry Moorehead | E9: =_xlfn.XLOOKUP(Table4[[#This Row],[Agents]],'MTD Raw'!L:L,'MTD Raw'!M:M,0) -> 74 | F9: =_xlfn.XLOOKUP(Table4[[#This Row],[Agents]],'MTD Raw'!I:I,'MTD Raw'!J:J,0)+E48 -> 56 | G9: =_xlfn.XLOOKUP(Table4[[#This Row],[Agents]],'MTD Raw'!A:A,'MTD Raw'!B:B,0) -> 0 | H9: =_xlfn.XLOOKUP(Table4[[#This Row],[Agents]],'MTD Raw'!A:A,'MTD Raw'!C:C,0) -> 6 | I9: =_xlfn.XLOOKUP(Table4[[#This Row],[Agents]],'MTD Raw'!A:A,'MTD Raw'!D:D,0) -> 0 | J9: =SUM(Table4[[#This Row],[Camp]:[IW]])+H48 -> 9 | K9: =_xlfn.XLOOKUP(Table4[[#This Row],[Agents]],'MTD Raw'!A:A,'MTD Raw'!E:E,0) -> 2 | L9: =_xlfn.XLOOKUP(Table4[[#This Row],[Agents]],'MTD Raw'!AB:AB,'MTD Raw'!AE:AE,0) -> 147 | M9: =_xlfn.XLOOKUP(Table4[[#This Row],[Agents]],'MTD Raw'!AU:AU,'MTD Raw'!AX:AX,0) -> 0 | N9: =SUM(Table4[[#This Row],[Ret Calls]:[Serv calls]]) -> 147 | O9: =IFERROR(Table4[[#This Row],[Cancels]]/Table4[[#This Row],[Ret Calls]],0) -> 0.50340136 | P9: =IFERROR(Table4[[#This Row],[Saves]]/Table4[[#This Row],[Ret Calls]],0) -> 0.38095238 | Q9: =IFERROR(Table4[[#This Row],[OOW]]/Table4[[#This Row],[All Calls]],0) -> 0.040816327 | R9: =IFERROR(Table4[[#This Row],[All Sales]]/Table4[[#This Row],[Serv calls]],0) -> 0 | S9: =IFERROR(Table4[[#This Row],[Reg]]/Table4[[#This Row],[Serv calls]],0) -> 0 | T9: =Table4[[#This Row],[Saves]]/Table4[[#This Row],[Cancels]] -> 0.75675676
B10: Will | D10: Chanetta Gant | E10: =_xlfn.XLOOKUP(Table4[[#This Row],[Agents]],'MTD Raw'!L:L,'MTD Raw'!M:M,0) -> 70 | F10: =_xlfn.XLOOKUP(Table4[[#This Row],[Agents]],'MTD Raw'!I:I,'MTD Raw'!J:J,0)+E49 -> 81 | G10: =_xlfn.XLOOKUP(Table4[[#This Row],[Agents]],'MTD Raw'!A:A,'MTD Raw'!B:B,0) -> 0 | H10: =_xlfn.XLOOKUP(Table4[[#This Row],[Agents]],'MTD Raw'!A:A,'MTD Raw'!C:C,0) -> 3 | I10: =_xlfn.XLOOKUP(Table4[[#This Row],[Agents]],'MTD Raw'!A:A,'MTD Raw'!D:D,0) -> 0 | J10: =SUM(Table4[[#This Row],[Camp]:[IW]])+H49 -> 4 | K10: =_xlfn.XLOOKUP(Table4[[#This Row],[Agents]],'MTD Raw'!A:A,'MTD Raw'!E:E,0) -> 7 | L10: =_xlfn.XLOOKUP(Table4[[#This Row],[Agents]],'MTD Raw'!AB:AB,'MTD Raw'!AE:AE,0) -> 104 | M10: =_xlfn.XLOOKUP(Table4[[#This Row],[Agents]],'MTD Raw'!AU:AU,'MTD Raw'!AX:AX,0) -> 0 | N10: =SUM(Table4[[#This Row],[Ret Calls]:[Serv calls]]) -> 104 | O10: =IFERROR(Table4[[#This Row],[Cancels]]/Table4[[#This Row],[Ret Calls]],0) -> 0.67307692 | P10: =IFERROR(Table4[[#This Row],[Saves]]/Table4[[#This Row],[Ret Calls]],0) -> 0.77884615 | Q10: =IFERROR(Table4[[#This Row],[OOW]]/Table4[[#This Row],[All Calls]],0) -> 0.028846154 | R10: =IFERROR(Table4[[#This Row],[All Sales]]/Table4[[#This Row],[Serv calls]],0) -> 0 | S10: =IFERROR(Table4[[#This Row],[Reg]]/Table4[[#This Row],[Serv calls]],0) -> 0 | T10: =Table4[[#This Row],[Saves]]/Table4[[#This Row],[Cancels]] -> 1.1571429
B11: Will | D11: Khadijah Young | E11: =_xlfn.XLOOKUP(Table4[[#This Row],[Agents]],'MTD Raw'!L:L,'MTD Raw'!M:M,0) -> 85 | F11: =_xlfn.XLOOKUP(Table4[[#This Row],[Agents]],'MTD Raw'!I:I,'MTD Raw'!J:J,0)+E50 -> 72 | G11: =_xlfn.XLOOKUP(Table4[[#This Row],[Agents]],'MTD Raw'!A:A,'MTD Raw'!B:B,0) -> 0 | H11: =_xlfn.XLOOKUP(Table4[[#This Row],[Agents]],'MTD Raw'!A:A,'MTD Raw'!C:C,0) -> 2 | I11: =_xlfn.XLOOKUP(Table4[[#This Row],[Agents]],'MTD Raw'!A:A,'MTD Raw'!D:D,0) -> 1 | J11: =SUM(Table4[[#This Row],[Camp]:[IW]])+H50 -> 6 | K11: =_xlfn.XLOOKUP(Table4[[#This Row],[Agents]],'MTD Raw'!A:A,'MTD Raw'!E:E,0) -> 3 | L11: =_xlfn.XLOOKUP(Table4[[#This Row],[Agents]],'MTD Raw'!AB:AB,'MTD Raw'!AE:AE,0) -> 148 | M11: =_xlfn.XLOOKUP(Table4[[#This Row],[Agents]],'MTD Raw'!AU:AU,'MTD Raw'!AX:AX,0) -> 0 | N11: =SUM(Table4[[#This Row],[Ret Calls]:[Serv calls]]) -> 148 | O11: =IFERROR(Table4[[#This Row],[Cancels]]/Table4[[#This Row],[Ret Calls]],0) -> 0.57432432 | P11: =IFERROR(Table4[[#This Row],[Saves]]/Table4[[#This Row],[Ret Calls]],0) -> 0.48648649 | Q11: =IFERROR(Table4[[#This Row],[OOW]]/Table4[[#This Row],[All Calls]],0) -> 0.013513514 | R11: =IFERROR(Table4[[#This Row],[All Sales]]/Table4[[#This Row],[Serv calls]],0) -> 0 | S11: =IFERROR(Table4[[#This Row],[Reg]]/Table4[[#This Row],[Serv calls]],0) -> 0 | T11: =Table4[[#This Row],[Saves]]/Table4[[#This Row],[Cancels]] -> 0.84705882
B12: Will | D12: Chasady Parker | E12: =_xlfn.XLOOKUP(Table4[[#This Row],[Agents]],'MTD Raw'!L:L,'MTD Raw'!M:M,0) -> 5 | F12: =_xlfn.XLOOKUP(Table4[[#This Row],[Agents]],'MTD Raw'!I:I,'MTD Raw'!J:J,0)+E51 -> 10 | G12: =_xlfn.XLOOKUP(Table4[[#This Row],[Agents]],'MTD Raw'!A:A,'MTD Raw'!B:B,0) -> 0 | H12: =_xlfn.XLOOKUP(Table4[[#This Row],[Agents]],'MTD Raw'!A:A,'MTD Raw'!C:C,0) -> 0 | I12: =_xlfn.XLOOKUP(Table4[[#This Row],[Agents]],'MTD Raw'!A:A,'MTD Raw'!D:D,0) -> 1 | J12: =SUM(Table4[[#This Row],[Camp]:[IW]])+H51 -> 1 | K12: =_xlfn.XLOOKUP(Table4[[#This Row],[Agents]],'MTD Raw'!A:A,'MTD Raw'!E:E,0) -> 0 | L12: =_xlfn.XLOOKUP(Table4[[#This Row],[Agents]],'MTD Raw'!AB:AB,'MTD Raw'!AE:AE,0) -> 20 | M12: =_xlfn.XLOOKUP(Table4[[#This Row],[Agents]],'MTD Raw'!AU:AU,'MTD Raw'!AX:AX,0) -> 78 | N12: =SUM(Table4[[#This Row],[Ret Calls]:[Serv calls]]) -> 98 | O12: =IFERROR(Table4[[#This Row],[Cancels]]/Table4[[#This Row],[Ret Calls]],0) -> 0.25 | P12: =IFERROR(Table4[[#This Row],[Saves]]/Table4[[#This Row],[Ret Calls]],0) -> 0.5 | Q12: =IFERROR(Table4[[#This Row],[OOW]]/Table4[[#This Row],[All Calls]],0) -> 0 | R12: =IFERROR(Table4[[#This Row],[All Sales]]/Table4[[#This Row],[Serv calls]],0) -> 0.012820513 | S12: =IFERROR(Table4[[#This Row],[Reg]]/Table4[[#This Row],[Serv calls]],0) -> 0 | T12: =Table4[[#This Row],[Saves]]/Table4[[#This Row],[Cancels]] -> 2
B13: Will | C13: Perry Young III | D13: Perry Young | E13: =_xlfn.XLOOKUP(Table4[[#This Row],[Agents]],'MTD Raw'!L:L,'MTD Raw'!M:M,0) -> 100 | F13: =_xlfn.XLOOKUP(Table4[[#This Row],[Agents]],'MTD Raw'!I:I,'MTD Raw'!J:J,0)+E52 -> 93 | G13: =_xlfn.XLOOKUP(Table4[[#This Row],[Agents]],'MTD Raw'!A:A,'MTD Raw'!B:B,0) -> 0 | H13: =_xlfn.XLOOKUP(Table4[[#This Row],[Agents]],'MTD Raw'!A:A,'MTD Raw'!C:C,0) -> 2 | I13: =_xlfn.XLOOKUP(Table4[[#This Row],[Agents]],'MTD Raw'!A:A,'MTD Raw'!D:D,0) -> 0 | J13: =SUM(Table4[[#This Row],[Camp]:[IW]])+H52 -> 3 | K13: =_xlfn.XLOOKUP(Table4[[#This Row],[Agents]],'MTD Raw'!A:A,'MTD Raw'!E:E,0) -> 2 | L13: =_xlfn.XLOOKUP(Table4[[#This Row],[NN]],'MTD Raw'!AB:AB,'MTD Raw'!AE:AE,0) -> 195 | M13: =_xlfn.XLOOKUP(Table4[[#This Row],[NN]],'MTD Raw'!AU:AU,'MTD Raw'!AX:AX,0) -> 0 | N13: =SUM(Table4[[#This Row],[Ret Calls]:[Serv calls]]) -> 195 | O13: =IFERROR(Table4[[#This Row],[Cancels]]/Table4[[#This Row],[Ret Calls]],0) -> 0.51282051 | P13: =IFERROR(Table4[[#This Row],[Saves]]/Table4[[#This Row],[Ret Calls]],0) -> 0.47692308 | Q13: =IFERROR(Table4[[#This Row],[OOW]]/Table4[[#This Row],[All Calls]],0) -> 0.01025641 | R13: =IFERROR(Table4[[#This Row],[All Sales]]/Table4[[#This Row],[Serv calls]],0) -> 0 | S13: =IFERROR(Table4[[#This Row],[Reg]]/Table4[[#This Row],[Serv calls]],0) -> 0 | T13: =Table4[[#This Row],[Saves]]/Table4[[#This Row],[Cancels]] -> 0.93
B14: Will | D14: Matthew Livingstone | E14: =_xlfn.XLOOKUP(Table4[[#This Row],[Agents]],'MTD Raw'!L:L,'MTD Raw'!M:M,0) -> 125 | F14: =_xlfn.XLOOKUP(Table4[[#This Row],[Agents]],'MTD Raw'!I:I,'MTD Raw'!J:J,0)+E53 -> 105 | G14: =_xlfn.XLOOKUP(Table4[[#This Row],[Agents]],'MTD Raw'!A:A,'MTD Raw'!B:B,0) -> 0 | H14: =_xlfn.XLOOKUP(Table4[[#This Row],[Agents]],'MTD Raw'!A:A,'MTD Raw'!C:C,0) -> 0 | I14: =_xlfn.XLOOKUP(Table4[[#This Row],[Agents]],'MTD Raw'!A:A,'MTD Raw'!D:D,0) -> 0 | J14: =SUM(Table4[[#This Row],[Camp]:[IW]])+H53 -> 1 | K14: =_xlfn.XLOOKUP(Table4[[#This Row],[Agents]],'MTD Raw'!A:A,'MTD Raw'!E:E,0) -> 2 | L14: =_xlfn.XLOOKUP(Table4[[#This Row],[Agents]],'MTD Raw'!AB:AB,'MTD Raw'!AE:AE,0) -> 201 | M14: =_xlfn.XLOOKUP(Table4[[#This Row],[Agents]],'MTD Raw'!AU:AU,'MTD Raw'!AX:AX,0) -> 0 | N14: =SUM(Table4[[#This Row],[Ret Calls]:[Serv calls]]) -> 201 | O14: =IFERROR(Table4[[#This Row],[Cancels]]/Table4[[#This Row],[Ret Calls]],0) -> 0.62189055 | P14: =IFERROR(Table4[[#This Row],[Saves]]/Table4[[#This Row],[Ret Calls]],0) -> 0.52238806 | Q14: =IFERROR(Table4[[#This Row],[OOW]]/Table4[[#This Row],[All Calls]],0) -> 0 | R14: =IFERROR(Table4[[#This Row],[All Sales]]/Table4[[#This Row],[Serv calls]],0) -> 0 | S14: =IFERROR(Table4[[#This Row],[Reg]]/Table4[[#This Row],[Serv calls]],0) -> 0 | T14: =Table4[[#This Row],[Saves]]/Table4[[#This Row],[Cancels]] -> 0.84
B15: Will | D15: Vasilikija Dimitrievska | E15: =_xlfn.XLOOKUP(Table4[[#This Row],[Agents]],'MTD Raw'!L:L,'MTD Raw'!M:M,0) -> 0 | F15: =_xlfn.XLOOKUP(Table4[[#This Row],[Agents]],'MTD Raw'!I:I,'MTD Raw'!J:J,0)+E54 -> 0 | G15: =_xlfn.XLOOKUP(Table4[[#This Row],[Agents]],'MTD Raw'!A:A,'MTD Raw'!B:B,0) -> 0 | H15: =_xlfn.XLOOKUP(Table4[[#This Row],[Agents]],'MTD Raw'!A:A,'MTD Raw'!C:C,0) -> 0 | I15: =_xlfn.XLOOKUP(Table4[[#This Row],[Agents]],'MTD Raw'!A:A,'MTD Raw'!D:D,0) -> 0 | J15: =SUM(Table4[[#This Row],[Camp]:[IW]])+H54 -> 0 | K15: =_xlfn.XLOOKUP(Table4[[#This Row],[Agents]],'MTD Raw'!A:A,'MTD Raw'!E:E,0) -> 0 | L15: =_xlfn.XLOOKUP(Table4[[#This Row],[Agents]],'MTD Raw'!AB:AB,'MTD Raw'!AE:AE,0) -> 0 | M15: =_xlfn.XLOOKUP(Table4[[#This Row],[Agents]],'MTD Raw'!AU:AU,'MTD Raw'!AX:AX,0) -> 0 | N15: =SUM(Table4[[#This Row],[Ret Calls]:[Serv calls]]) -> 0 | O15: =IFERROR(Table4[[#This Row],[Cancels]]/Table4[[#This Row],[Ret Calls]],0) -> 0 | P15: =IFERROR(Table4[[#This Row],[Saves]]/Table4[[#This Row],[Ret Calls]],0) -> 0 | Q15: =IFERROR(Table4[[#This Row],[OOW]]/Table4[[#This Row],[All Calls]],0) -> 0 | R15: =IFERROR(Table4[[#This Row],[All Sales]]/Table4[[#This Row],[Serv calls]],0) -> 0 | S15: =IFERROR(Table4[[#This Row],[Reg]]/Table4[[#This Row],[Serv calls]],0) -> 0 | T15: =Table4[[#This Row],[Saves]]/Table4[[#This Row],[Cancels]] -> #DIV/0!
B16: Will | D16: John Allen | E16: =_xlfn.XLOOKUP(Table4[[#This Row],[Agents]],'MTD Raw'!L:L,'MTD Raw'!M:M,0) -> 3 | F16: =_xlfn.XLOOKUP(Table4[[#This Row],[Agents]],'MTD Raw'!I:I,'MTD Raw'!J:J,0)+E55 -> 0 | G16: =_xlfn.XLOOKUP(Table4[[#This Row],[Agents]],'MTD Raw'!A:A,'MTD Raw'!B:B,0) -> 1 | H16: =_xlfn.XLOOKUP(Table4[[#This Row],[Agents]],'MTD Raw'!A:A,'MTD Raw'!C:C,0) -> 1 | I16: =_xlfn.XLOOKUP(Table4[[#This Row],[Agents]],'MTD Raw'!A:A,'MTD Raw'!D:D,0) -> 1 | J16: =SUM(Table4[[#This Row],[Camp]:[IW]])+H55 -> 3 | K16: =_xlfn.XLOOKUP(Table4[[#This Row],[Agents]],'MTD Raw'!A:A,'MTD Raw'!E:E,0) -> 1 | L16: =_xlfn.XLOOKUP(Table4[[#This Row],[Agents]],'MTD Raw'!AB:AB,'MTD Raw'!AE:AE,0) -> 0 | M16: =_xlfn.XLOOKUP(Table4[[#This Row],[Agents]],'MTD Raw'!AU:AU,'MTD Raw'!AX:AX,0) -> 0 | N16: =SUM(Table4[[#This Row],[Ret Calls]:[Serv calls]]) -> 0 | O16: =IFERROR(Table4[[#This Row],[Cancels]]/Table4[[#This Row],[Ret Calls]],0) -> 0 | P16: =IFERROR(Table4[[#This Row],[Saves]]/Table4[[#This Row],[Ret Calls]],0) -> 0 | Q16: =IFERROR(Table4[[#This Row],[OOW]]/Table4[[#This Row],[All Calls]],0) -> 0 | R16: =IFERROR(Table4[[#This Row],[All Sales]]/Table4[[#This Row],[Serv calls]],0) -> 0 | S16: =IFERROR(Table4[[#This Row],[Reg]]/Table4[[#This Row],[Serv calls]],0) -> 0 | T16: =Table4[[#This Row],[Saves]]/Table4[[#This Row],[Cancels]] -> 0
B17: Will | D17: Bram Benderoff | E17: =_xlfn.XLOOKUP(Table4[[#This Row],[Agents]],'MTD Raw'!L:L,'MTD Raw'!M:M,0) -> 14 | F17: =_xlfn.XLOOKUP(Table4[[#This Row],[Agents]],'MTD Raw'!I:I,'MTD Raw'!J:J,0)+E56 -> 2 | G17: =_xlfn.XLOOKUP(Table4[[#This Row],[Agents]],'MTD Raw'!A:A,'MTD Raw'!B:B,0) -> 0 | H17: =_xlfn.XLOOKUP(Table4[[#This Row],[Agents]],'MTD Raw'!A:A,'MTD Raw'!C:C,0) -> 2 | I17: =_xlfn.XLOOKUP(Table4[[#This Row],[Agents]],'MTD Raw'!A:A,'MTD Raw'!D:D,0) -> 0 | J17: =SUM(Table4[[#This Row],[Camp]:[IW]])+H56 -> 2 | K17: =_xlfn.XLOOKUP(Table4[[#This Row],[Agents]],'MTD Raw'!A:A,'MTD Raw'!E:E,0) -> 1 | L17: =_xlfn.XLOOKUP(Table4[[#This Row],[Agents]],'MTD Raw'!AB:AB,'MTD Raw'!AE:AE,0) -> 0 | M17: =_xlfn.XLOOKUP(Table4[[#This Row],[Agents]],'MTD Raw'!AU:AU,'MTD Raw'!AX:AX,0) -> 255 | N17: =SUM(Table4[[#This Row],[Ret Calls]:[Serv calls]]) -> 255 | O17: =IFERROR(Table4[[#This Row],[Cancels]]/Table4[[#This Row],[Ret Calls]],0) -> 0 | P17: =IFERROR(Table4[[#This Row],[Saves]]/Table4[[#This Row],[Ret Calls]],0) -> 0 | Q17: =IFERROR(Table4[[#This Row],[OOW]]/Table4[[#This Row],[All Calls]],0) -> 0.0078431373 | R17: =IFERROR(Table4[[#This Row],[All Sales]]/Table4[[#This Row],[Serv calls]],0) -> 0.0078431373 | S17: =IFERROR(Table4[[#This Row],[Reg]]/Table4[[#This Row],[Serv calls]],0) -> 0.0039215686 | T17: =Table4[[#This Row],[Saves]]/Table4[[#This Row],[Cancels]] -> 0.14285714
B18: Will | D18: Justin Williams | E18: =_xlfn.XLOOKUP(Table4[[#This Row],[Agents]],'MTD Raw'!L:L,'MTD Raw'!M:M,0) -> 5 | F18: =_xlfn.XLOOKUP(Table4[[#This Row],[Agents]],'MTD Raw'!I:I,'MTD Raw'!J:J,0)+E57 -> 0 | G18: =_xlfn.XLOOKUP(Table4[[#This Row],[Agents]],'MTD Raw'!A:A,'MTD Raw'!B:B,0) -> 0 | H18: =_xlfn.XLOOKUP(Table4[[#This Row],[Agents]],'MTD Raw'!A:A,'MTD Raw'!C:C,0) -> 0 | I18: =_xlfn.XLOOKUP(Table4[[#This Row],[Agents]],'MTD Raw'!A:A,'MTD Raw'!D:D,0) -> 6 | J18: =SUM(Table4[[#This Row],[Camp]:[IW]])+H57 -> 6 | K18: =_xlfn.XLOOKUP(Table4[[#This Row],[Agents]],'MTD Raw'!A:A,'MTD Raw'!E:E,0) -> 1 | L18: =_xlfn.XLOOKUP(Table4[[#This Row],[Agents]],'MTD Raw'!AB:AB,'MTD Raw'!AE:AE,0) -> 0 | M18: =_xlfn.XLOOKUP(Table4[[#This Row],[Agents]],'MTD Raw'!AU:AU,'MTD Raw'!AX:AX,0) -> 187 | N18: =SUM(Table4[[#This Row],[Ret Calls]:[Serv calls]]) -> 187 | O18: =IFERROR(Table4[[#This Row],[Cancels]]/Table4[[#This Row],[Ret Calls]],0) -> 0 | P18: =IFERROR(Table4[[#This Row],[Saves]]/Table4[[#This Row],[Ret Calls]],0) -> 0 | Q18: =IFERROR(Table4[[#This Row],[OOW]]/Table4[[#This Row],[All Calls]],0) -> 0 | R18: =IFERROR(Table4[[#This Row],[All Sales]]/Table4[[#This Row],[Serv calls]],0) -> 0.032085561 | S18: =IFERROR(Table4[[#This Row],[Reg]]/Table4[[#This Row],[Serv calls]],0) -> 0.0053475936 | T18: =Table4[[#This Row],[Saves]]/Table4[[#This Row],[Cancels]] -> 0
B19: Nick | D19: Cassiddy Jordan | E19: =_xlfn.XLOOKUP(Table4[[#This Row],[Agents]],'MTD Raw'!L:L,'MTD Raw'!M:M,0) -> 88 | F19: =_xlfn.XLOOKUP(Table4[[#This Row],[Agents]],'MTD Raw'!I:I,'MTD Raw'!J:J,0) -> 60 | G19: =_xlfn.XLOOKUP(Table4[[#This Row],[Agents]],'MTD Raw'!A:A,'MTD Raw'!B:B,0) -> 1 | H19: =_xlfn.XLOOKUP(Table4[[#This Row],[Agents]],'MTD Raw'!A:A,'MTD Raw'!D:D,0) -> 0 | I19: =_xlfn.XLOOKUP(Table4[[#This Row],[Agents]],'MTD Raw'!A:A,'MTD Raw'!D:D,0) -> 0 | J19: =SUM(Table4[[#This Row],[Camp]:[IW]]) -> 1 | K19: =_xlfn.XLOOKUP(Table4[[#This Row],[Agents]],'MTD Raw'!A:A,'MTD Raw'!E:E,0) -> 4 | L19: =_xlfn.XLOOKUP(Table4[[#This Row],[Agents]],'MTD Raw'!AB:AB,'MTD Raw'!AE:AE,0) -> 147 | M19: =_xlfn.XLOOKUP(Table4[[#This Row],[Agents]],'MTD Raw'!AU:AU,'MTD Raw'!AX:AX,0) -> 0 | N19: =SUM(Table4[[#This Row],[Ret Calls]:[Serv calls]]) -> 147 | O19: =IFERROR(Table4[[#This Row],[Cancels]]/Table4[[#This Row],[Ret Calls]],0) -> 0.59863946 | P19: =IFERROR(Table4[[#This Row],[Saves]]/Table4[[#This Row],[Ret Calls]],0) -> 0.40816327 | Q19: =IFERROR(Table4[[#This Row],[OOW]]/Table4[[#This Row],[All Calls]],0) -> 0 | R19: =IFERROR(Table4[[#This Row],[All Sales]]/Table4[[#This Row],[Serv calls]],0) -> 0 | S19: =IFERROR(Table4[[#This Row],[Reg]]/Table4[[#This Row],[Serv calls]],0) -> 0 | T19: =Table4[[#This Row],[Saves]]/Table4[[#This Row],[Cancels]] -> 0.68181818
B20: Nick | D20: Destiny Rich | E20: =_xlfn.XLOOKUP(Table4[[#This Row],[Agents]],'MTD Raw'!L:L,'MTD Raw'!M:M,0) -> 53 | F20: =_xlfn.XLOOKUP(Table4[[#This Row],[Agents]],'MTD Raw'!I:I,'MTD Raw'!J:J,0) -> 11 | G20: =_xlfn.XLOOKUP(Table4[[#This Row],[Agents]],'MTD Raw'!A:A,'MTD Raw'!B:B,0) -> 0 | H20: =_xlfn.XLOOKUP(Table4[[#This Row],[Agents]],'MTD Raw'!A:A,'MTD Raw'!D:D,0) -> 0 | I20: =_xlfn.XLOOKUP(Table4[[#This Row],[Agents]],'MTD Raw'!A:A,'MTD Raw'!D:D,0) -> 0 | J20: =SUM(Table4[[#This Row],[Camp]:[IW]]) -> 0 | K20: =_xlfn.XLOOKUP(Table4[[#This Row],[Agents]],'MTD Raw'!A:A,'MTD Raw'!E:E,0) -> 0 | L20: =_xlfn.XLOOKUP(Table4[[#This Row],[Agents]],'MTD Raw'!AB:AB,'MTD Raw'!AE:AE,0) -> 79 | M20: =_xlfn.XLOOKUP(Table4[[#This Row],[Agents]],'MTD Raw'!AU:AU,'MTD Raw'!AX:AX,0) -> 0 | N20: =SUM(Table4[[#This Row],[Ret Calls]:[Serv calls]]) -> 79 | O20: =IFERROR(Table4[[#This Row],[Cancels]]/Table4[[#This Row],[Ret Calls]],0) -> 0.67088608 | P20: =IFERROR(Table4[[#This Row],[Saves]]/Table4[[#This Row],[Ret Calls]],0) -> 0.13924051 | Q20: =IFERROR(Table4[[#This Row],[OOW]]/Table4[[#This Row],[All Calls]],0) -> 0 | R20: =IFERROR(Table4[[#This Row],[All Sales]]/Table4[[#This Row],[Serv calls]],0) -> 0 | S20: =IFERROR(Table4[[#This Row],[Reg]]/Table4[[#This Row],[Serv calls]],0) -> 0 | T20: =Table4[[#This Row],[Saves]]/Table4[[#This Row],[Cancels]] -> 0.20754717
B21: Nick | D21: Donna Plummer | E21: =_xlfn.XLOOKUP(Table4[[#This Row],[Agents]],'MTD Raw'!L:L,'MTD Raw'!M:M,0) -> 62 | F21: =_xlfn.XLOOKUP(Table4[[#This Row],[Agents]],'MTD Raw'!I:I,'MTD Raw'!J:J,0) -> 11 | G21: =_xlfn.XLOOKUP(Table4[[#This Row],[Agents]],'MTD Raw'!A:A,'MTD Raw'!B:B,0) -> 0 | H21: =_xlfn.XLOOKUP(Table4[[#This Row],[Agents]],'MTD Raw'!A:A,'MTD Raw'!D:D,0) -> 0 | I21: =_xlfn.XLOOKUP(Table4[[#This Row],[Agents]],'MTD Raw'!A:A,'MTD Raw'!D:D,0) -> 0 | J21: =SUM(Table4[[#This Row],[Camp]:[IW]]) -> 0 | K21: =_xlfn.XLOOKUP(Table4[[#This Row],[Agents]],'MTD Raw'!A:A,'MTD Raw'!E:E,0) -> 0 | L21: =_xlfn.XLOOKUP(Table4[[#This Row],[Agents]],'MTD Raw'!AB:AB,'MTD Raw'!AE:AE,0) -> 78 | M21: =_xlfn.XLOOKUP(Table4[[#This Row],[Agents]],'MTD Raw'!AU:AU,'MTD Raw'!AX:AX,0) -> 0 | N21: =SUM(Table4[[#This Row],[Ret Calls]:[Serv calls]]) -> 78 | O21: =IFERROR(Table4[[#This Row],[Cancels]]/Table4[[#This Row],[Ret Calls]],0) -> 0.79487179 | P21: =IFERROR(Table4[[#This Row],[Saves]]/Table4[[#This Row],[Ret Calls]],0) -> 0.14102564 | Q21: =IFERROR(Table4[[#This Row],[OOW]]/Table4[[#This Row],[All Calls]],0) -> 0 | R21: =IFERROR(Table4[[#This Row],[All Sales]]/Table4[[#This Row],[Serv calls]],0) -> 0 | S21: =IFERROR(Table4[[#This Row],[Reg]]/Table4[[#This Row],[Serv calls]],0) -> 0 | T21: =Table4[[#This Row],[Saves]]/Table4[[#This Row],[Cancels]] -> 0.17741935
B22: Nick | D22: Elizabeth Christian | E22: =_xlfn.XLOOKUP(Table4[[#This Row],[Agents]],'MTD Raw'!L:L,'MTD Raw'!M:M,0) -> 0 | F22: =_xlfn.XLOOKUP(Table4[[#This Row],[Agents]],'MTD Raw'!I:I,'MTD Raw'!J:J,0) -> 0 | G22: =_xlfn.XLOOKUP(Table4[[#This Row],[Agents]],'MTD Raw'!A:A,'MTD Raw'!B:B,0) -> 0 | H22: =_xlfn.XLOOKUP(Table4[[#This Row],[Agents]],'MTD Raw'!A:A,'MTD Raw'!D:D,0) -> 0 | I22: =_xlfn.XLOOKUP(Table4[[#This Row],[Agents]],'MTD Raw'!A:A,'MTD Raw'!D:D,0) -> 0 | J22: =SUM(Table4[[#This Row],[Camp]:[IW]]) -> 0 | K22: =_xlfn.XLOOKUP(Table4[[#This Row],[Agents]],'MTD Raw'!A:A,'MTD Raw'!E:E,0) -> 0 | L22: =_xlfn.XLOOKUP(Table4[[#This Row],[Agents]],'MTD Raw'!AB:AB,'MTD Raw'!AE:AE,0) -> 0 | M22: =_xlfn.XLOOKUP(Table4[[#This Row],[Agents]],'MTD Raw'!AU:AU,'MTD Raw'!AX:AX,0) -> 0 | N22: =SUM(Table4[[#This Row],[Ret Calls]:[Serv calls]]) -> 0 | O22: =IFERROR(Table4[[#This Row],[Cancels]]/Table4[[#This Row],[Ret Calls]],0) -> 0 | P22: =IFERROR(Table4[[#This Row],[Saves]]/Table4[[#This Row],[Ret Calls]],0) -> 0 | Q22: =IFERROR(Table4[[#This Row],[OOW]]/Table4[[#This Row],[All Calls]],0) -> 0 | R22: =IFERROR(Table4[[#This Row],[All Sales]]/Table4[[#This Row],[Serv calls]],0) -> 0 | S22: =IFERROR(Table4[[#This Row],[Reg]]/Table4[[#This Row],[Serv calls]],0) -> 0 | T22: =Table4[[#This Row],[Saves]]/Table4[[#This Row],[Cancels]] -> #DIV/0!
B23: Nick | D23: Eric Brown | E23: =_xlfn.XLOOKUP(Table4[[#This Row],[Agents]],'MTD Raw'!L:L,'MTD Raw'!M:M,0) -> 17 | F23: =_xlfn.XLOOKUP(Table4[[#This Row],[Agents]],'MTD Raw'!I:I,'MTD Raw'!J:J,0) -> 64 | G23: =_xlfn.XLOOKUP(Table4[[#This Row],[Agents]],'MTD Raw'!A:A,'MTD Raw'!B:B,0) -> 0 | H23: =_xlfn.XLOOKUP(Table4[[#This Row],[Agents]],'MTD Raw'!A:A,'MTD Raw'!D:D,0) -> 0 | I23: =_xlfn.XLOOKUP(Table4[[#This Row],[Agents]],'MTD Raw'!A:A,'MTD Raw'!D:D,0) -> 0 | J23: =SUM(Table4[[#This Row],[Camp]:[IW]]) -> 0 | K23: =_xlfn.XLOOKUP(Table4[[#This Row],[Agents]],'MTD Raw'!A:A,'MTD Raw'!E:E,0) -> 2 | L23: =_xlfn.XLOOKUP(Table4[[#This Row],[Agents]],'MTD Raw'!AB:AB,'MTD Raw'!AE:AE,0) -> 14 | M23: =_xlfn.XLOOKUP(Table4[[#This Row],[Agents]],'MTD Raw'!AU:AU,'MTD Raw'!AX:AX,0) -> 0 | N23: =SUM(Table4[[#This Row],[Ret Calls]:[Serv calls]]) -> 14 | O23: =IFERROR(Table4[[#This Row],[Cancels]]/Table4[[#This Row],[Ret Calls]],0) -> 1.2142857 | P23: =IFERROR(Table4[[#This Row],[Saves]]/Table4[[#This Row],[Ret Calls]],0) -> 4.5714286 | Q23: =IFERROR(Table4[[#This Row],[OOW]]/Table4[[#This Row],[All Calls]],0) -> 0 | R23: =IFERROR(Table4[[#This Row],[All Sales]]/Table4[[#This Row],[Serv calls]],0) -> 0 | S23: =IFERROR(Table4[[#This Row],[Reg]]/Table4[[#This Row],[Serv calls]],0) -> 0 | T23: =Table4[[#This Row],[Saves]]/Table4[[#This Row],[Cancels]] -> 3.7647059
B24: Nick | D24: Heather Kester | E24: =_xlfn.XLOOKUP(Table4[[#This Row],[Agents]],'MTD Raw'!L:L,'MTD Raw'!M:M,0) -> 28 | F24: =_xlfn.XLOOKUP(Table4[[#This Row],[Agents]],'MTD Raw'!I:I,'MTD Raw'!J:J,0) -> 0 | G24: =_xlfn.XLOOKUP(Table4[[#This Row],[Agents]],'MTD Raw'!A:A,'MTD Raw'!B:B,0) -> 0 | H24: =_xlfn.XLOOKUP(Table4[[#This Row],[Agents]],'MTD Raw'!A:A,'MTD Raw'!D:D,0) -> 0 | I24: =_xlfn.XLOOKUP(Table4[[#This Row],[Agents]],'MTD Raw'!A:A,'MTD Raw'!D:D,0) -> 0 | J24: =SUM(Table4[[#This Row],[Camp]:[IW]]) -> 0 | K24: =_xlfn.XLOOKUP(Table4[[#This Row],[Agents]],'MTD Raw'!A:A,'MTD Raw'!E:E,0) -> 1 | L24: =_xlfn.XLOOKUP(Table4[[#This Row],[Agents]],'MTD Raw'!AB:AB,'MTD Raw'!AE:AE,0) -> 56 | M24: =_xlfn.XLOOKUP(Table4[[#This Row],[Agents]],'MTD Raw'!AU:AU,'MTD Raw'!AX:AX,0) -> 35 | N24: =SUM(Table4[[#This Row],[Ret Calls]:[Serv calls]]) -> 91 | O24: =IFERROR(Table4[[#This Row],[Cancels]]/Table4[[#This Row],[Ret Calls]],0) -> 0.5 | P24: =IFERROR(Table4[[#This Row],[Saves]]/Table4[[#This Row],[Ret Calls]],0) -> 0 | Q24: =IFERROR(Table4[[#This Row],[OOW]]/Table4[[#This Row],[All Calls]],0) -> 0 | R24: =IFERROR(Table4[[#This Row],[All Sales]]/Table4[[#This Row],[Serv calls]],0) -> 0 | S24: =IFERROR(Table4[[#This Row],[Reg]]/Table4[[#This Row],[Serv calls]],0) -> 0.028571429 | T24: =Table4[[#This Row],[Saves]]/Table4[[#This Row],[Cancels]] -> 0
B25: Nick | D25: Javier Ottenwalder | E25: =_xlfn.XLOOKUP(Table4[[#This Row],[Agents]],'MTD Raw'!L:L,'MTD Raw'!M:M,0) -> 32 | F25: =_xlfn.XLOOKUP(Table4[[#This Row],[Agents]],'MTD Raw'!I:I,'MTD Raw'!J:J,0) -> 17 | G25: =_xlfn.XLOOKUP(Table4[[#This Row],[Agents]],'MTD Raw'!A:A,'MTD Raw'!B:B,0) -> 3 | H25: =_xlfn.XLOOKUP(Table4[[#This Row],[Agents]],'MTD Raw'!A:A,'MTD Raw'!D:D,0) -> 0 | I25: =_xlfn.XLOOKUP(Table4[[#This Row],[Agents]],'MTD Raw'!A:A,'MTD Raw'!D:D,0) -> 0 | J25: =SUM(Table4[[#This Row],[Camp]:[IW]]) -> 3 | K25: =_xlfn.XLOOKUP(Table4[[#This Row],[Agents]],'MTD Raw'!A:A,'MTD Raw'!E:E,0) -> 6 | L25: =_xlfn.XLOOKUP(Table4[[#This Row],[Agents]],'MTD Raw'!AB:AB,'MTD Raw'!AE:AE,0) -> 30 | M25: =_xlfn.XLOOKUP(Table4[[#This Row],[Agents]],'MTD Raw'!AU:AU,'MTD Raw'!AX:AX,0) -> 0 | N25: =SUM(Table4[[#This Row],[Ret Calls]:[Serv calls]]) -> 30 | O25: =IFERROR(Table4[[#This Row],[Cancels]]/Table4[[#This Row],[Ret Calls]],0) -> 1.0666667 | P25: =IFERROR(Table4[[#This Row],[Saves]]/Table4[[#This Row],[Ret Calls]],0) -> 0.56666667 | Q25: =IFERROR(Table4[[#This Row],[OOW]]/Table4[[#This Row],[All Calls]],0) -> 0 | R25: =IFERROR(Table4[[#This Row],[All Sales]]/Table4[[#This Row],[Serv calls]],0) -> 0 | S25: =IFERROR(Table4[[#This Row],[Reg]]/Table4[[#This Row],[Serv calls]],0) -> 0 | T25: =Table4[[#This Row],[Saves]]/Table4[[#This Row],[Cancels]] -> 0.53125
B26: Nick | D26: Kellee Silva | E26: =_xlfn.XLOOKUP(Table4[[#This Row],[Agents]],'MTD Raw'!L:L,'MTD Raw'!M:M,0) -> 0 | F26: =_xlfn.XLOOKUP(Table4[[#This Row],[Agents]],'MTD Raw'!I:I,'MTD Raw'!J:J,0) -> 0 | G26: =_xlfn.XLOOKUP(Table4[[#This Row],[Agents]],'MTD Raw'!A:A,'MTD Raw'!B:B,0) -> 0 | H26: =_xlfn.XLOOKUP(Table4[[#This Row],[Agents]],'MTD Raw'!A:A,'MTD Raw'!D:D,0) -> 0 | I26: =_xlfn.XLOOKUP(Table4[[#This Row],[Agents]],'MTD Raw'!A:A,'MTD Raw'!D:D,0) -> 0 | J26: =SUM(Table4[[#This Row],[Camp]:[IW]]) -> 0 | K26: =_xlfn.XLOOKUP(Table4[[#This Row],[Agents]],'MTD Raw'!A:A,'MTD Raw'!E:E,0) -> 1 | L26: =_xlfn.XLOOKUP(Table4[[#This Row],[Agents]],'MTD Raw'!AB:AB,'MTD Raw'!AE:AE,0) -> 9 | M26: =_xlfn.XLOOKUP(Table4[[#This Row],[Agents]],'MTD Raw'!AU:AU,'MTD Raw'!AX:AX,0) -> 0 | N26: =SUM(Table4[[#This Row],[Ret Calls]:[Serv calls]]) -> 9 | O26: =IFERROR(Table4[[#This Row],[Cancels]]/Table4[[#This Row],[Ret Calls]],0) -> 0 | P26: =IFERROR(Table4[[#This Row],[Saves]]/Table4[[#This Row],[Ret Calls]],0) -> 0 | Q26: =IFERROR(Table4[[#This Row],[OOW]]/Table4[[#This Row],[All Calls]],0) -> 0 | R26: =IFERROR(Table4[[#This Row],[All Sales]]/Table4[[#This Row],[Serv calls]],0) -> 0 | S26: =IFERROR(Table4[[#This Row],[Reg]]/Table4[[#This Row],[Serv calls]],0) -> 0 | T26: =Table4[[#This Row],[Saves]]/Table4[[#This Row],[Cancels]] -> #DIV/0!
B27: Nick | D27: Marcia Fabry | E27: =_xlfn.XLOOKUP(Table4[[#This Row],[Agents]],'MTD Raw'!L:L,'MTD Raw'!M:M,0) -> 33 | F27: =_xlfn.XLOOKUP(Table4[[#This Row],[Agents]],'MTD Raw'!I:I,'MTD Raw'!J:J,0) -> 11 | G27: =_xlfn.XLOOKUP(Table4[[#This Row],[Agents]],'MTD Raw'!A:A,'MTD Raw'!B:B,0) -> 1 | H27: =_xlfn.XLOOKUP(Table4[[#This Row],[Agents]],'MTD Raw'!A:A,'MTD Raw'!D:D,0) -> 0 | I27: =_xlfn.XLOOKUP(Table4[[#This Row],[Agents]],'MTD Raw'!A:A,'MTD Raw'!D:D,0) -> 0 | J27: =SUM(Table4[[#This Row],[Camp]:[IW]]) -> 1 | K27: =_xlfn.XLOOKUP(Table4[[#This Row],[Agents]],'MTD Raw'!A:A,'MTD Raw'!E:E,0) -> 2 | L27: =_xlfn.XLOOKUP(Table4[[#This Row],[Agents]],'MTD Raw'!AB:AB,'MTD Raw'!AE:AE,0) -> 39 | M27: =_xlfn.XLOOKUP(Table4[[#This Row],[Agents]],'MTD Raw'!AU:AU,'MTD Raw'!AX:AX,0) -> 87 | N27: =SUM(Table4[[#This Row],[Ret Calls]:[Serv calls]]) -> 126 | O27: =IFERROR(Table4[[#This Row],[Cancels]]/Table4[[#This Row],[Ret Calls]],0) -> 0.84615385 | P27: =IFERROR(Table4[[#This Row],[Saves]]/Table4[[#This Row],[Ret Calls]],0) -> 0.28205128 | Q27: =IFERROR(Table4[[#This Row],[OOW]]/Table4[[#This Row],[All Calls]],0) -> 0 | R27: =IFERROR(Table4[[#This Row],[All Sales]]/Table4[[#This Row],[Serv calls]],0) -> 0.011494253 | S27: =IFERROR(Table4[[#This Row],[Reg]]/Table4[[#This Row],[Serv calls]],0) -> 0.022988506 | T27: =Table4[[#This Row],[Saves]]/Table4[[#This Row],[Cancels]] -> 0.33333333
B28: Nick | D28: Michael Moyer | E28: =_xlfn.XLOOKUP(Table4[[#This Row],[Agents]],'MTD Raw'!L:L,'MTD Raw'!M:M,0) -> 103 | F28: =_xlfn.XLOOKUP(Table4[[#This Row],[Agents]],'MTD Raw'!I:I,'MTD Raw'!J:J,0) -> 16 | G28: =_xlfn.XLOOKUP(Table4[[#This Row],[Agents]],'MTD Raw'!A:A,'MTD Raw'!B:B,0) -> 0 | H28: =_xlfn.XLOOKUP(Table4[[#This Row],[Agents]],'MTD Raw'!A:A,'MTD Raw'!D:D,0) -> 0 | I28: =_xlfn.XLOOKUP(Table4[[#This Row],[Agents]],'MTD Raw'!A:A,'MTD Raw'!D:D,0) -> 0 | J28: =SUM(Table4[[#This Row],[Camp]:[IW]]) -> 0 | K28: =_xlfn.XLOOKUP(Table4[[#This Row],[Agents]],'MTD Raw'!A:A,'MTD Raw'!E:E,0) -> 0 | L28: =_xlfn.XLOOKUP(Table4[[#This Row],[Agents]],'MTD Raw'!AB:AB,'MTD Raw'!AE:AE,0) -> 116 | M28: =_xlfn.XLOOKUP(Table4[[#This Row],[Agents]],'MTD Raw'!AU:AU,'MTD Raw'!AX:AX,0) -> 0 | N28: =SUM(Table4[[#This Row],[Ret Calls]:[Serv calls]]) -> 116 | O28: =IFERROR(Table4[[#This Row],[Cancels]]/Table4[[#This Row],[Ret Calls]],0) -> 0.88793103 | P28: =IFERROR(Table4[[#This Row],[Saves]]/Table4[[#This Row],[Ret Calls]],0) -> 0.13793103 | Q28: =IFERROR(Table4[[#This Row],[OOW]]/Table4[[#This Row],[All Calls]],0) -> 0 | R28: =IFERROR(Table4[[#This Row],[All Sales]]/Table4[[#This Row],[Serv calls]],0) -> 0 | S28: =IFERROR(Table4[[#This Row],[Reg]]/Table4[[#This Row],[Serv calls]],0) -> 0 | T28: =Table4[[#This Row],[Saves]]/Table4[[#This Row],[Cancels]] -> 0.15533981
B29: Nick | D29: Prottasha Prentice | E29: =_xlfn.XLOOKUP(Table4[[#This Row],[Agents]],'MTD Raw'!L:L,'MTD Raw'!M:M,0) -> 169 | F29: =_xlfn.XLOOKUP(Table4[[#This Row],[Agents]],'MTD Raw'!I:I,'MTD Raw'!J:J,0) -> 64 | G29: =_xlfn.XLOOKUP(Table4[[#This Row],[Agents]],'MTD Raw'!A:A,'MTD Raw'!B:B,0) -> 0 | H29: =_xlfn.XLOOKUP(Table4[[#This Row],[Agents]],'MTD Raw'!A:A,'MTD Raw'!D:D,0) -> 0 | I29: =_xlfn.XLOOKUP(Table4[[#This Row],[Agents]],'MTD Raw'!A:A,'MTD Raw'!D:D,0) -> 0 | J29: =SUM(Table4[[#This Row],[Camp]:[IW]]) -> 0 | K29: =_xlfn.XLOOKUP(Table4[[#This Row],[Agents]],'MTD Raw'!A:A,'MTD Raw'!E:E,0) -> 1 | L29: =_xlfn.XLOOKUP(Table4[[#This Row],[Agents]],'MTD Raw'!AB:AB,'MTD Raw'!AE:AE,0) -> 246 | M29: =_xlfn.XLOOKUP(Table4[[#This Row],[Agents]],'MTD Raw'!AU:AU,'MTD Raw'!AX:AX,0) -> 0 | N29: =SUM(Table4[[#This Row],[Ret Calls]:[Serv calls]]) -> 246 | O29: =IFERROR(Table4[[#This Row],[Cancels]]/Table4[[#This Row],[Ret Calls]],0) -> 0.68699187 | P29: =IFERROR(Table4[[#This Row],[Saves]]/Table4[[#This Row],[Ret Calls]],0) -> 0.2601626 | Q29: =IFERROR(Table4[[#This Row],[OOW]]/Table4[[#This Row],[All Calls]],0) -> 0 | R29: =IFERROR(Table4[[#This Row],[All Sales]]/Table4[[#This Row],[Serv calls]],0) -> 0 | S29: =IFERROR(Table4[[#This Row],[Reg]]/Table4[[#This Row],[Serv calls]],0) -> 0 | T29: =Table4[[#This Row],[Saves]]/Table4[[#This Row],[Cancels]] -> 0.37869822
B30: Nick | D30: SHANIQUE REID | E30: =_xlfn.XLOOKUP(Table4[[#This Row],[Agents]],'MTD Raw'!L:L,'MTD Raw'!M:M,0) -> 19 | F30: =_xlfn.XLOOKUP(Table4[[#This Row],[Agents]],'MTD Raw'!I:I,'MTD Raw'!J:J,0) -> 13 | G30: =_xlfn.XLOOKUP(Table4[[#This Row],[Agents]],'MTD Raw'!A:A,'MTD Raw'!B:B,0) -> 0 | H30: =_xlfn.XLOOKUP(Table4[[#This Row],[Agents]],'MTD Raw'!A:A,'MTD Raw'!D:D,0) -> 0 | I30: =_xlfn.XLOOKUP(Table4[[#This Row],[Agents]],'MTD Raw'!A:A,'MTD Raw'!D:D,0) -> 0 | J30: =SUM(Table4[[#This Row],[Camp]:[IW]]) -> 0 | K30: =_xlfn.XLOOKUP(Table4[[#This Row],[Agents]],'MTD Raw'!A:A,'MTD Raw'!E:E,0) -> 0 | L30: =_xlfn.XLOOKUP(Table4[[#This Row],[Agents]],'MTD Raw'!AB:AB,'MTD Raw'!AE:AE,0) -> 35 | M30: =_xlfn.XLOOKUP(Table4[[#This Row],[Agents]],'MTD Raw'!AU:AU,'MTD Raw'!AX:AX,0) -> 0 | N30: =SUM(Table4[[#This Row],[Ret Calls]:[Serv calls]]) -> 35 | O30: =IFERROR(Table4[[#This Row],[Cancels]]/Table4[[#This Row],[Ret Calls]],0) -> 0.54285714 | P30: =IFERROR(Table4[[#This Row],[Saves]]/Table4[[#This Row],[Ret Calls]],0) -> 0.37142857 | Q30: =IFERROR(Table4[[#This Row],[OOW]]/Table4[[#This Row],[All Calls]],0) -> 0 | R30: =IFERROR(Table4[[#This Row],[All Sales]]/Table4[[#This Row],[Serv calls]],0) -> 0 | S30: =IFERROR(Table4[[#This Row],[Reg]]/Table4[[#This Row],[Serv calls]],0) -> 0 | T30: =Table4[[#This Row],[Saves]]/Table4[[#This Row],[Cancels]] -> 0.68421053
... B35: Nick | D35: Uniqua Davis | E35: =_xlfn.XLOOKUP(Table4[[#This Row],[Agents]],'MTD Raw'!L:L,'MTD Raw'!M:M,0) -> 64 | F35: =_xlfn.XLOOKUP(Table4[[#This Row],[Agents]],'MTD Raw'!I:I,'MTD Raw'!J:J,0) -> 23 | G35: =_xlfn.XLOOKUP(Table4[[#This Row],[Agents]],'MTD Raw'!A:A,'MTD Raw'!B:B,0) -> 0 | H35: =_xlfn.XLOOKUP(Table4[[#This Row],[Agents]],'MTD Raw'!A:A,'MTD Raw'!D:D,0) -> 1 | I35: =_xlfn.XLOOKUP(Table4[[#This Row],[Agents]],'MTD Raw'!A:A,'MTD Raw'!D:D,0) -> 1 | J35: =SUM(Table4[[#This Row],[Camp]:[IW]]) -> 2 | K35: =_xlfn.XLOOKUP(Table4[[#This Row],[Agents]],'MTD Raw'!A:A,'MTD Raw'!E:E,0) -> 9 | L35: =_xlfn.XLOOKUP(Table4[[#This Row],[Agents]],'MTD Raw'!AB:AB,'MTD Raw'!AE:AE,0) -> 84 | M35: =_xlfn.XLOOKUP(Table4[[#This Row],[Agents]],'MTD Raw'!AU:AU,'MTD Raw'!AX:AX,0) -> 0 | N35: =SUM(Table4[[#This Row],[Ret Calls]:[Serv calls]]) -> 84 | O35: =IFERROR(Table4[[#This Row],[Cancels]]/Table4[[#This Row],[Ret Calls]],0) -> 0.76190476 | P35: =IFERROR(Table4[[#This Row],[Saves]]/Table4[[#This Row],[Ret Calls]],0) -> 0.27380952 | Q35: =IFERROR(Table4[[#This Row],[OOW]]/Table4[[#This Row],[All Calls]],0) -> 0.011904762 | R35: =IFERROR(Table4[[#This Row],[All Sales]]/Table4[[#This Row],[Serv calls]],0) -> 0 | S35: =IFERROR(Table4[[#This Row],[Reg]]/Table4[[#This Row],[Serv calls]],0) -> 0 | T35: =Table4[[#This Row],[Saves]]/Table4[[#This Row],[Cancels]] -> 0.359375
B36: Total | E36: =SUBTOTAL(109,Table4[Cancels]) -> 1079 | F36: =SUBTOTAL(109,Table4[Saves]) -> 1051 | G36: =SUBTOTAL(109,Table4[Camp]) -> 4 | H36: =SUBTOTAL(109,Table4[OOW]) -> 50 | I36: =SUBTOTAL(109,Table4[IW]) -> 9 | J36: =SUBTOTAL(109,Table4[All Sales]) -> 82 | K36: =SUBTOTAL(109,Table4[Reg]) -> 44 | L36: =SUBTOTAL(109,Table4[Ret Calls]) -> 1581 | M36: =SUBTOTAL(109,Table4[Serv calls]) -> 705 | N36: =SUBTOTAL(109,Table4[All Calls]) -> 2286 | O36: =Table4[[#Totals],[Cancels]]/Table4[[#Totals],[Ret Calls]] -> 0.68247944 | P36: =Table4[[#Totals],[Saves]]/Table4[[#Totals],[Ret Calls]] -> 0.66476913 | Q36: =Table4[[#Totals],[OOW]]/Table4[[#Totals],[All Calls]] -> 0.021872266 | R36: =Table4[[#Totals],[All Sales]]/Table4[[#Totals],[Serv calls]] -> 0.11631206 | S36: =Table4[[#Totals],[Reg]]/Table4[[#Totals],[Serv calls]] -> 0.062411348 | T36: =Table4[[#Totals],[Saves]]/Table4[[#Totals],[Cancels]] -> 0.97405005 | U36: =SUBTOTAL(103,Table4[Status]) -> 0
F38: WIB Saves
E39: Tracked | F39: 148
D40: WIB Saves Tracked | G40: WIB Sales
D41: Angelica Gonzalez | E41: =_xlfn.XLOOKUP(D41,Sheet2!Z:Z,Sheet2!AA:AA,0) -> 0 | G41: Angelica Gonzalez | H41: {=_xlfn.XLOOKUP(G41,WIB!K:K,WIB!P:P+WIB!Q:Q+WIB!R:R,0)} -> 2
D42: Khadijah Young | E42: =_xlfn.XLOOKUP(D42,Sheet2!Z:Z,Sheet2!AA:AA,0) -> 9 | G42: Khadijah Young | H42: {=_xlfn.XLOOKUP(G42,WIB!K:K,WIB!P:P+WIB!Q:Q+WIB!R:R,0)} -> 1
D43: Regina Watson | E43: =_xlfn.XLOOKUP(D43,Sheet2!Z:Z,Sheet2!AA:AA,0) -> 8 | G43: Regina Watson | H43: {=_xlfn.XLOOKUP(G43,WIB!K:K,WIB!P:P+WIB!Q:Q+WIB!R:R,0)} -> 0
D44: Douglas Barnes | E44: =_xlfn.XLOOKUP(D44,Sheet2!Z:Z,Sheet2!AA:AA,0) -> 0 | G44: Douglas Barnes | H44: {=_xlfn.XLOOKUP(G44,WIB!K:K,WIB!P:P+WIB!Q:Q+WIB!R:R,0)} -> 3
D45: Perry Young | E45: =_xlfn.XLOOKUP(D45,Sheet2!Z:Z,Sheet2!AA:AA,0) -> 38 | G45: Perry Young | H45: {=_xlfn.XLOOKUP(G45,WIB!K:K,WIB!P:P+WIB!Q:Q+WIB!R:R,0)} -> 2
D46: Mohamed Bayoumy | E46: =_xlfn.XLOOKUP(D46,Sheet2!Z:Z,Sheet2!AA:AA,0) -> 34 | G46: Mohamed Bayoumy | H46: {=_xlfn.XLOOKUP(G46,WIB!K:K,WIB!P:P+WIB!Q:Q+WIB!R:R,0)} -> 2
D47: Larry Moorehead | E47: =_xlfn.XLOOKUP(D47,Sheet2!Z:Z,Sheet2!AA:AA,0) -> 11 | G47: Larry Moorehead | H47: {=_xlfn.XLOOKUP(G47,WIB!K:K,WIB!P:P+WIB!Q:Q+WIB!R:R,0)} -> 0
D48: Amy Smiley | E48: =_xlfn.XLOOKUP(D48,Sheet2!Z:Z,Sheet2!AA:AA,0) -> 6 | G48: Amy Smiley | H48: {=_xlfn.XLOOKUP(G48,WIB!K:K,WIB!P:P+WIB!Q:Q+WIB!R:R,0)} -> 3
D49: Chanetta Gant | E49: =_xlfn.XLOOKUP(D49,Sheet2!Z:Z,Sheet2!AA:AA,0) -> 35 | G49: Chanetta Gant | H49: {=_xlfn.XLOOKUP(G49,WIB!K:K,WIB!P:P+WIB!Q:Q+WIB!R:R,0)} -> 1
D50: Chasady Parker | E50: =_xlfn.XLOOKUP(D50,Sheet2!Z:Z,Sheet2!AA:AA,0) -> 2 | G50: Chasady Parker | H50: {=_xlfn.XLOOKUP(G50,WIB!K:K,WIB!P:P+WIB!Q:Q+WIB!R:R,0)} -> 3
D51: Dinesh Kandoth | E51: =_xlfn.XLOOKUP(D51,Sheet2!Z:Z,Sheet2!AA:AA,0) -> 0 | G51: Dinesh Kandoth | H51: {=_xlfn.XLOOKUP(G51,WIB!K:K,WIB!P:P+WIB!Q:Q+WIB!R:R,0)} -> 0
D52: Margaret Reddy | E52: =_xlfn.XLOOKUP(D52,Sheet2!Z:Z,Sheet2!AA:AA,0) -> 21 | G52: Margaret Reddy | H52: {=_xlfn.XLOOKUP(G52,WIB!K:K,WIB!P:P+WIB!Q:Q+WIB!R:R,0)} -> 1
... D57: Justin Williams | E57: =_xlfn.XLOOKUP(D57,Sheet2!Z:Z,Sheet2!AA:AA,0) -> 0 | G57: Justin Williams | H57: {=_xlfn.XLOOKUP(G57,WIB!K:K,WIB!P:P+WIB!Q:Q+WIB!R:R,0)} -> 0

Sheet Week

Sheet Daily
B1: TL | C1: NN | D1: Agents | E1: Cancels | F1: Saves | G1: Camp | H1: OOW | I1: IW | J1: All Sales | K1: Reg | L1: Ret Calls | M1: Serv calls | N1: All Calls | O1: Canc % | P1: Save % | Q1: oow % | R1: Serv % | S1: RPC | T1: Save Efficiency | U1: Status
B2: Will | D2: Regina Watson | E2: =_xlfn.XLOOKUP(D2,'Daily Raw'!K:K,'Daily Raw'!L:L,0) -> 2 | F2: =_xlfn.XLOOKUP(D2,'Daily Raw'!H:H,'Daily Raw'!I:I,0) -> 6 | G2: =_xlfn.XLOOKUP(D2,'Daily Raw'!A:A,'Daily Raw'!B:B,0) -> 0 | H2: =_xlfn.XLOOKUP(D2,'Daily Raw'!A:A,'Daily Raw'!C:C,0) -> 3 | I2: =_xlfn.XLOOKUP(D2,'Daily Raw'!A:A,'Daily Raw'!D:D,0) -> 0 | J2: =SUM(G2:I2) -> 3 | K2: =_xlfn.XLOOKUP(D2,'Daily Raw'!A:A,'Daily Raw'!E:E,0) -> 0 | L2: =_xlfn.XLOOKUP(D2,'Daily Raw'!AC:AC,'Daily Raw'!AF:AF,0) -> 3 | M2: =_xlfn.XLOOKUP(D2,'Daily Raw'!AV:AV,'Daily Raw'!AY:AY,0) -> 10 | N2: =SUM(L2:M2) -> 13 | O2: =IFERROR(E2/L2,0) -> 0.66666667 | P2: =IFERROR(F2/L2,0) -> 2 | Q2: =IFERROR(H2/N2,0) -> 0.23076923 | R2: =IFERROR(J2/M2,"❎") -> 0.3 | S2: =IFERROR(K2/M2,0) -> 0 | T2: =IFERROR(Table3[[#This Row],[Saves]]/Table3[[#This Row],[Cancels]],0) -> 3
B3: Will | D3: Mohamed Bayoumy | E3: =_xlfn.XLOOKUP(D3,'Daily Raw'!K:K,'Daily Raw'!L:L,0) -> 5 | F3: =_xlfn.XLOOKUP(D3,'Daily Raw'!H:H,'Daily Raw'!I:I,0) -> 22 | G3: =_xlfn.XLOOKUP(D3,'Daily Raw'!A:A,'Daily Raw'!B:B,0) -> 0 | H3: =_xlfn.XLOOKUP(D3,'Daily Raw'!A:A,'Daily Raw'!C:C,0) -> 0 | I3: =_xlfn.XLOOKUP(D3,'Daily Raw'!A:A,'Daily Raw'!D:D,0) -> 0 | J3: =SUM(G3:I3) -> 0 | K3: =_xlfn.XLOOKUP(D3,'Daily Raw'!A:A,'Daily Raw'!E:E,0) -> 2 | L3: =_xlfn.XLOOKUP(D3,'Daily Raw'!AC:AC,'Daily Raw'!AF:AF,0) -> 14 | M3: =_xlfn.XLOOKUP(D3,'Daily Raw'!AV:AV,'Daily Raw'!AY:AY,0) -> 18 | N3: =SUM(L3:M3) -> 32 | O3: =IFERROR(E3/L3,0) -> 0.35714286 | P3: =IFERROR(F3/L3,0) -> 1.5714286 | Q3: =IFERROR(H3/N3,0) -> 0 | R3: =IFERROR(J3/M3,"❎") -> 0 | S3: =IFERROR(K3/M3,0) -> 0.11111111 | T3: =IFERROR(Table3[[#This Row],[Saves]]/Table3[[#This Row],[Cancels]],0) -> 4.4
B4: Will | D4: Margaret Reddy | E4: =_xlfn.XLOOKUP(D4,'Daily Raw'!K:K,'Daily Raw'!L:L,0) -> 11 | F4: =_xlfn.XLOOKUP(D4,'Daily Raw'!H:H,'Daily Raw'!I:I,0) -> 10 | G4: =_xlfn.XLOOKUP(D4,'Daily Raw'!A:A,'Daily Raw'!B:B,0) -> 0 | H4: =_xlfn.XLOOKUP(D4,'Daily Raw'!A:A,'Daily Raw'!C:C,0) -> 0 | I4: =_xlfn.XLOOKUP(D4,'Daily Raw'!A:A,'Daily Raw'!D:D,0) -> 0 | J4: =SUM(G4:I4) -> 0 | K4: =_xlfn.XLOOKUP(D4,'Daily Raw'!A:A,'Daily Raw'!E:E,0) -> 0 | L4: =_xlfn.XLOOKUP(D4,'Daily Raw'!AC:AC,'Daily Raw'!AF:AF,0) -> 11 | M4: =_xlfn.XLOOKUP(D4,'Daily Raw'!AV:AV,'Daily Raw'!AY:AY,0) -> 0 | N4: =SUM(L4:M4) -> 11 | O4: =IFERROR(E4/L4,0) -> 1 | P4: =IFERROR(F4/L4,0) -> 0.90909091 | Q4: =IFERROR(H4/N4,0) -> 0 | R4: =IFERROR(J4/M4,"❎") -> ❎ | S4: =IFERROR(K4/M4,0) -> 0 | T4: =IFERROR(Table3[[#This Row],[Saves]]/Table3[[#This Row],[Cancels]],0) -> 0.90909091
B5: Will | D5: Angelica Gonzalez | E5: =_xlfn.XLOOKUP(D5,'Daily Raw'!K:K,'Daily Raw'!L:L,0) -> 25 | F5: =_xlfn.XLOOKUP(D5,'Daily Raw'!H:H,'Daily Raw'!I:I,0) -> 18 | G5: =_xlfn.XLOOKUP(D5,'Daily Raw'!A:A,'Daily Raw'!B:B,0) -> 0 | H5: =_xlfn.XLOOKUP(D5,'Daily Raw'!A:A,'Daily Raw'!C:C,0) -> 0 | I5: =_xlfn.XLOOKUP(D5,'Daily Raw'!A:A,'Daily Raw'!D:D,0) -> 0 | J5: =SUM(G5:I5) -> 0 | K5: =_xlfn.XLOOKUP(D5,'Daily Raw'!A:A,'Daily Raw'!E:E,0) -> 2 | L5: =_xlfn.XLOOKUP(D5,'Daily Raw'!AC:AC,'Daily Raw'!AF:AF,0) -> 26 | M5: =_xlfn.XLOOKUP(D5,'Daily Raw'!AV:AV,'Daily Raw'!AY:AY,0) -> 0 | N5: =SUM(L5:M5) -> 26 | O5: =IFERROR(E5/L5,0) -> 0.96153846 | P5: =IFERROR(F5/L5,0) -> 0.69230769 | Q5: =IFERROR(H5/N5,0) -> 0 | R5: =IFERROR(J5/M5,"❎") -> ❎ | S5: =IFERROR(K5/M5,0) -> 0 | T5: =IFERROR(Table3[[#This Row],[Saves]]/Table3[[#This Row],[Cancels]],0) -> 0.72
B6: Will | D6: Khadijah Young | E6: =_xlfn.XLOOKUP(D6,'Daily Raw'!K:K,'Daily Raw'!L:L,0) -> 13 | F6: =_xlfn.XLOOKUP(D6,'Daily Raw'!H:H,'Daily Raw'!I:I,0) -> 13 | G6: =_xlfn.XLOOKUP(D6,'Daily Raw'!A:A,'Daily Raw'!B:B,0) -> 0 | H6: =_xlfn.XLOOKUP(D6,'Daily Raw'!A:A,'Daily Raw'!C:C,0) -> 0 | I6: =_xlfn.XLOOKUP(D6,'Daily Raw'!A:A,'Daily Raw'!D:D,0) -> 0 | J6: =SUM(G6:I6) -> 0 | K6: =_xlfn.XLOOKUP(D6,'Daily Raw'!A:A,'Daily Raw'!E:E,0) -> 0 | L6: =_xlfn.XLOOKUP(D6,'Daily Raw'!AC:AC,'Daily Raw'!AF:AF,0) -> 20 | M6: =_xlfn.XLOOKUP(D6,'Daily Raw'!AV:AV,'Daily Raw'!AY:AY,0) -> 0 | N6: =SUM(L6:M6) -> 20 | O6: =IFERROR(E6/L6,0) -> 0.65 | P6: =IFERROR(F6/L6,0) -> 0.65 | Q6: =IFERROR(H6/N6,0) -> 0 | R6: =IFERROR(J6/M6,"❎") -> ❎ | S6: =IFERROR(K6/M6,0) -> 0 | T6: =IFERROR(Table3[[#This Row],[Saves]]/Table3[[#This Row],[Cancels]],0) -> 1
B7: Will | D7: Matthew Livingstone | E7: =_xlfn.XLOOKUP(D7,'Daily Raw'!K:K,'Daily Raw'!L:L,0) -> 18 | F7: =_xlfn.XLOOKUP(D7,'Daily Raw'!H:H,'Daily Raw'!I:I,0) -> 12 | G7: =_xlfn.XLOOKUP(D7,'Daily Raw'!A:A,'Daily Raw'!B:B,0) -> 0 | H7: =_xlfn.XLOOKUP(D7,'Daily Raw'!A:A,'Daily Raw'!C:C,0) -> 0 | I7: =_xlfn.XLOOKUP(D7,'Daily Raw'!A:A,'Daily Raw'!D:D,0) -> 0 | J7: =SUM(G7:I7) -> 0 | K7: =_xlfn.XLOOKUP(D7,'Daily Raw'!A:A,'Daily Raw'!E:E,0) -> 2 | L7: =_xlfn.XLOOKUP(D7,'Daily Raw'!AC:AC,'Daily Raw'!AF:AF,0) -> 26 | M7: =_xlfn.XLOOKUP(D7,'Daily Raw'!AV:AV,'Daily Raw'!AY:AY,0) -> 0 | N7: =SUM(L7:M7) -> 26 | O7: =IFERROR(E7/L7,0) -> 0.69230769 | P7: =IFERROR(F7/L7,0) -> 0.46153846 | Q7: =IFERROR(H7/N7,0) -> 0 | R7: =IFERROR(J7/M7,"❎") -> ❎ | S7: =IFERROR(K7/M7,0) -> 0 | T7: =IFERROR(Table3[[#This Row],[Saves]]/Table3[[#This Row],[Cancels]],0) -> 0.66666667
B8: Will | D8: Douglas Barnes | E8: =_xlfn.XLOOKUP(D8,'Daily Raw'!K:K,'Daily Raw'!L:L,0) -> 10 | F8: =_xlfn.XLOOKUP(D8,'Daily Raw'!H:H,'Daily Raw'!I:I,0) -> 7 | G8: =_xlfn.XLOOKUP(D8,'Daily Raw'!A:A,'Daily Raw'!B:B,0) -> 0 | H8: =_xlfn.XLOOKUP(D8,'Daily Raw'!A:A,'Daily Raw'!C:C,0) -> 0 | I8: =_xlfn.XLOOKUP(D8,'Daily Raw'!A:A,'Daily Raw'!D:D,0) -> 0 | J8: =SUM(G8:I8) -> 0 | K8: =_xlfn.XLOOKUP(D8,'Daily Raw'!A:A,'Daily Raw'!E:E,0) -> 0 | L8: =_xlfn.XLOOKUP(D8,'Daily Raw'!AC:AC,'Daily Raw'!AF:AF,0) -> 19 | M8: =_xlfn.XLOOKUP(D8,'Daily Raw'!AV:AV,'Daily Raw'!AY:AY,0) -> 0 | N8: =SUM(L8:M8) -> 19 | O8: =IFERROR(E8/L8,0) -> 0.52631579 | P8: =IFERROR(F8/L8,0) -> 0.36842105 | Q8: =IFERROR(H8/N8,0) -> 0 | R8: =IFERROR(J8/M8,"❎") -> ❎ | S8: =IFERROR(K8/M8,0) -> 0 | T8: =IFERROR(Table3[[#This Row],[Saves]]/Table3[[#This Row],[Cancels]],0) -> 0.7
B9: Will | D9: Amy Smiley | E9: =_xlfn.XLOOKUP(D9,'Daily Raw'!K:K,'Daily Raw'!L:L,0) -> 2 | F9: =_xlfn.XLOOKUP(D9,'Daily Raw'!H:H,'Daily Raw'!I:I,0) -> 1 | G9: =_xlfn.XLOOKUP(D9,'Daily Raw'!A:A,'Daily Raw'!B:B,0) -> 0 | H9: =_xlfn.XLOOKUP(D9,'Daily Raw'!A:A,'Daily Raw'!C:C,0) -> 0 | I9: =_xlfn.XLOOKUP(D9,'Daily Raw'!A:A,'Daily Raw'!D:D,0) -> 0 | J9: =SUM(G9:I9) -> 0 | K9: =_xlfn.XLOOKUP(D9,'Daily Raw'!A:A,'Daily Raw'!E:E,0) -> 0 | L9: =_xlfn.XLOOKUP(D9,'Daily Raw'!AC:AC,'Daily Raw'!AF:AF,0) -> 3 | M9: =_xlfn.XLOOKUP(D9,'Daily Raw'!AV:AV,'Daily Raw'!AY:AY,0) -> 19 | N9: =SUM(L9:M9) -> 22 | O9: =IFERROR(E9/L9,0) -> 0.66666667 | P9: =IFERROR(F9/L9,0) -> 0.33333333 | Q9: =IFERROR(H9/N9,0) -> 0 | R9: =IFERROR(J9/M9,"❎") -> 0 | S9: =IFERROR(K9/M9,0) -> 0 | T9: =IFERROR(Table3[[#This Row],[Saves]]/Table3[[#This Row],[Cancels]],0) -> 0.5
B10: Will | D10: Chanetta Gant | E10: =_xlfn.XLOOKUP(D10,'Daily Raw'!K:K,'Daily Raw'!L:L,0) -> 1 | F10: =_xlfn.XLOOKUP(D10,'Daily Raw'!H:H,'Daily Raw'!I:I,0) -> 3 | G10: =_xlfn.XLOOKUP(D10,'Daily Raw'!A:A,'Daily Raw'!B:B,0) -> 0 | H10: =_xlfn.XLOOKUP(D10,'Daily Raw'!A:A,'Daily Raw'!C:C,0) -> 0 | I10: =_xlfn.XLOOKUP(D10,'Daily Raw'!A:A,'Daily Raw'!D:D,0) -> 0 | J10: =SUM(G10:I10) -> 0 | K10: =_xlfn.XLOOKUP(D10,'Daily Raw'!A:A,'Daily Raw'!E:E,0) -> 1 | L10: =_xlfn.XLOOKUP(D10,'Daily Raw'!AC:AC,'Daily Raw'!AF:AF,0) -> 10 | M10: =_xlfn.XLOOKUP(D10,'Daily Raw'!AV:AV,'Daily Raw'!AY:AY,0) -> 10 | N10: =SUM(L10:M10) -> 20 | O10: =IFERROR(E10/L10,0) -> 0.1 | P10: =IFERROR(F10/L10,0) -> 0.3 | Q10: =IFERROR(H10/N10,0) -> 0 | R10: =IFERROR(J10/M10,"❎") -> 0 | S10: =IFERROR(K10/M10,0) -> 0.1 | T10: =IFERROR(Table3[[#This Row],[Saves]]/Table3[[#This Row],[Cancels]],0) -> 3
