Workbook

Sheet DashBoard
E1: MTD by Tie Assoc | J1: Cases Open | U1: Cases Closed
A2: Word Days | B2: 23 | E2: Tie Associate | F2: Cases Owned | G2: Case Closed | H2: Sales | J2: Count of Account Name | K2: Column Labels | T2: Count of Status | U2: Column Labels
A3: Days Worked | B3: 17 | E3: Alyssa Torres | F3: =COUNTIF('Open SF cases MTD'!A:A,DashBoard!E3) -> 2 | G3: =_xlfn.XLOOKUP(E3,'Closed SF Cases MTD'!K:K,'Closed SF Cases MTD'!Z:Z,0) -> 2 | H3: =_xlfn.XLOOKUP(E3,BI!C:C,BI!M:M,0) -> 0 | J3: Row Labels | K3: In Process | L3: In Progress | M3: In Review | N3: New | O3: New Complaint | P3: On Hold | Q3: (blank) | R3: Grand Total | T3: Row Labels | U3: Account Support | V3: Billing | W3: Cancel Plan | X3: Email Third Party Escalations | Y3: Out of Network Repair | Z3: Parts | AA3: Plan Support | AB3: Repair Authorization | AC3: Replacement | AD3: Retention | AE3: Service Request | AF3: SR Mapping Research | AG3: Web/Portal Support | AH3: (blank) | AI3: Grand Total
A4: Cases closed P/d | B4: 8 | E4: Christina J Harris | F4: =COUNTIF('Open SF cases MTD'!A:A,DashBoard!E4) -> 22 | G4: =_xlfn.XLOOKUP(E4,'Closed SF Cases MTD'!K:K,'Closed SF Cases MTD'!Z:Z,0) -> 250 | H4: =_xlfn.XLOOKUP(E4,BI!C:C,BI!M:M,0) -> 0 | J4: Admin Tasks | N4: 26 | R4: 26 | T4: Admin Tasks | AA4: 1 | AH4: 1715 | AI4: 1716
E5: Clarene Stapleton | F5: =COUNTIF('Open SF cases MTD'!A:A,DashBoard!E5) -> 40 | G5: =_xlfn.XLOOKUP(E5,'Closed SF Cases MTD'!K:K,'Closed SF Cases MTD'!Z:Z,0) -> 865 | H5: =_xlfn.XLOOKUP(E5,BI!C:C,BI!M:M,0) -> 10 | J5: Alissa Caskey | N5: 36 | P5: 6 | R5: 42 | T5: Alissa Caskey | U5: 3 | V5: 41 | W5: 27 | Y5: 2 | AA5: 17 | AB5: 3 | AD5: 2 | AE5: 1 | AG5: 2 | AI5: 98
E6: Demetra Rainey | F6: =COUNTIF('Open SF cases MTD'!A:A,DashBoard!E6) -> 16 | G6: =_xlfn.XLOOKUP(E6,'Closed SF Cases MTD'!K:K,'Closed SF Cases MTD'!Z:Z,0) -> 77 | H6: =_xlfn.XLOOKUP(E6,BI!C:C,BI!M:M,0) -> 2 | J6: Alyssa Torres | L6: 1 | N6: 1 | R6: 2 | T6: Alyssa Torres | V6: 1 | AA6: 1 | AI6: 2
E7: Dessie Temple | F7: =COUNTIF('Open SF cases MTD'!A:A,DashBoard!E7) -> 35 | G7: =_xlfn.XLOOKUP(E7,'Closed SF Cases MTD'!K:K,'Closed SF Cases MTD'!Z:Z,0) -> 317 | H7: =_xlfn.XLOOKUP(E7,BI!C:C,BI!M:M,0) -> 4 | J7: Andrew Henderson | K7: 31 | N7: 2 | R7: 33 | T7: Asante Msosa | Y7: 24 | Z7: 7 | AA7: 4 | AB7: 2 | AC7: 5 | AE7: 59 | AH7: 21 | AI7: 122
E8: Joshua Ball | F8: =COUNTIF('Open SF cases MTD'!A:A,DashBoard!E8) -> 5 | G8: =_xlfn.XLOOKUP(E8,'Closed SF Cases MTD'!K:K,'Closed SF Cases MTD'!Z:Z,0) -> 13 | H8: =_xlfn.XLOOKUP(E8,BI!C:C,BI!M:M,0) -> 16 | J8: Asante Msosa | K8: 5 | N8: 17 | P8: 5 | R8: 27 | T8: Barb Phillips | V8: 3 | W8: 2 | Y8: 2 | Z8: 10 | AA8: 3 | AC8: 6 | AE8: 29 | AF8: 1 | AH8: 3 | AI8: 59
E9: Margaret Reddy | F9: =COUNTIF('Open SF cases MTD'!A:A,DashBoard!E9) -> 20 | G9: =_xlfn.XLOOKUP(E9,'Closed SF Cases MTD'!K:K,'Closed SF Cases MTD'!Z:Z,0) -> 32 | H9: =_xlfn.XLOOKUP(E9,BI!C:C,BI!M:M,0) -> 3 | J9: Barb Phillips | K9: 10 | N9: 1 | O9: 3 | P9: 1 | R9: 15 | T9: Brooke Elizabeth Stafford | AH9: 1 | AI9: 1
E10: Michael McSharry | F10: =COUNTIF('Open SF cases MTD'!A:A,DashBoard!E10) -> 8 | G10: =_xlfn.XLOOKUP(E10,'Closed SF Cases MTD'!K:K,'Closed SF Cases MTD'!Z:Z,0) -> 7 | H10: =_xlfn.XLOOKUP(E10,BI!C:C,BI!M:M,0) -> 14 | J10: Bavani Corrie | K10: 185 | N10: 2 | R10: 187 | T10: Christina J Harris | U10: 6 | V10: 31 | W10: 47 | Z10: 18 | AA10: 14 | AC10: 1 | AE10: 126 | AF10: 2 | AG10: 1 | AH10: 4 | AI10: 250
E11: Nancy Cleveland | F11: =COUNTIF('Open SF cases MTD'!A:A,DashBoard!E11) -> 14 | G11: =_xlfn.XLOOKUP(E11,'Closed SF Cases MTD'!K:K,'Closed SF Cases MTD'!Z:Z,0) -> 93 | H11: =_xlfn.XLOOKUP(E11,BI!C:C,BI!M:M,0) -> 12 | J11: Brooke Elizabeth Stafford | T11: Clarene Stapleton | U11: 27 | V11: 2 | W11: 533 | Z11: 9 | AA11: 90 | AB11: 1 | AC11: 137 | AE11: 29 | AG11: 29 | AH11: 8 | AI11: 865
E12: Perry Young | F12: =COUNTIF('Open SF cases MTD'!A:A,DashBoard!E12) -> 13 | G12: =_xlfn.XLOOKUP(E12,'Closed SF Cases MTD'!K:K,'Closed SF Cases MTD'!Z:Z,0) -> 10 | H12: =_xlfn.XLOOKUP(E12,BI!C:C,BI!M:M,0) -> 14 | J12: Christina J Harris | K12: 6 | L12: 6 | N12: 10 | R12: 22 | T12: Colleen Nash | U12: 1 | V12: 3 | AA12: 1 | AC12: 1 | AH12: 14 | AI12: 20
J13: Clarene Stapleton | L13: 38 | N13: 2 | R13: 40 | T13: Corey Krause | U13: 6 | V13: 109 | W13: 35 | Z13: 2 | AA13: 29 | AB13: 1 | AC13: 3 | AE13: 4 | AG13: 9 | AH13: 4 | AI13: 202
J14: Colleen Nash | K14: 1 | L14: 3 | N14: 2 | R14: 6 | T14: Cyn H | Z14: 1 | AI14: 1
E15: Case Type | J15: Corey Krause | K15: 9 | N15: 24 | R15: 33 | T15: Data Protection | AH15: 3 | AI15: 3
J16: Cyn H | N16: 1 | R16: 1 | T16: Debra Anis | V16: 2 | W16: 1 | Y16: 16 | Z16: 4 | AA16: 2 | AB16: 6 | AC16: 4 | AE16: 28 | AH16: 23 | AI16: 86
J17: Debra Anis | K17: 24 | N17: 1 | P17: 12 | R17: 37 | T17: Demetra Rainey | V17: 1 | W17: 11 | Y17: 3 | Z17: 15 | AA17: 3 | AB17: 2 | AC17: 1 | AE17: 36 | AG17: 1 | AH17: 4 | AI17: 77
E18: Open | F18: 1 | J18: Demetra Rainey | K18: 4 | L18: 11 | N18: 1 | R18: 16 | T18: Dessie Temple | U18: 6 | V18: 20 | W18: 173 | Y18: 5 | Z18: 10 | AA18: 26 | AC18: 13 | AE18: 12 | AG18: 9 | AH18: 43 | AI18: 317
E19: Case Owner | F19: Standard Priority Cases | J19: Dessie Temple | K19: 9 | L19: 2 | N19: 15 | R19: 26 | T19: Diana C | V19: 3 | W19: 9 | Y19: 33 | Z19: 28 | AA19: 3 | AB19: 4 | AC19: 2 | AE19: 22 | AH19: 23 | AI19: 127
J20: Diana C | K20: 30 | L20: 3 | N20: 35 | O20: 1 | P20: 8 | R20: 77 | T20: Dianna Resendez | AB20: 2 | AC20: 99 | AH20: 12 | AI20: 113
E21: Row Labels | F21: Count of Status | G21: % of Open | J21: Dianna Resendez | K21: 30 | L21: 171 | R21: 201 | T21: Gia Stinson | U21: 3 | V21: 38 | W21: 35 | AA21: 21 | AB21: 6 | AC21: 2 | AD21: 3 | AG21: 3 | AI21: 111
E22: Account Support | F22: 2 | G22: 0.0044843049 | J22: Gia Stinson | K22: 30 | L22: 2 | N22: 19 | R22: 51 | T22: High Priority Cases | V22: 1 | AI22: 1
E23: Billing | F23: 37 | G23: 0.082959641 | J23: Joshua Ball | K23: 4 | L23: 1 | R23: 5 | T23: Joshua Ball | V23: 3 | W23: 2 | AA23: 1 | AE23: 3 | AH23: 4 | AI23: 13
E24: Cancel Plan | F24: 24 | G24: 0.053811659 | J24: Kamry Williams | T24: Kimberly Teasley | U24: 1 | V24: 2 | W24: 2 | Z24: 13 | AA24: 12 | AB24: 2 | AC24: 14 | AE24: 55 | AH24: 1 | AI24: 102
E25: Out of Network Repair | F25: 37 | G25: 0.082959641 | J25: Kimberly Teasley | K25: 10 | L25: 1 | N25: 40 | P25: 1 | R25: 52 | T25: Magdalena Leon | W25: 1 | Z25: 3 | AC25: 1 | AE25: 1 | AH25: 10 | AI25: 16
E26: Parts | F26: 59 | G26: 0.132287 | J26: Magdalena Leon | K26: 4 | R26: 4 | T26: Margaret Reddy | Z26: 9 | AC26: 1 | AE26: 22 | AI26: 32
E27: Plan Support | F27: 15 | G27: 0.033632287 | J27: Margaret Reddy | K27: 5 | L27: 6 | N27: 4 | P27: 5 | R27: 20 | T27: Melissa Orosco | AC27: 222 | AE27: 1 | AH27: 4 | AI27: 227
E28: Repair Authorization | F28: 1 | G28: 0.0022421525 | J28: Melissa Orosco | K28: 43 | L28: 100 | N28: 7 | R28: 150 | T28: Michael McSharry | V28: 1 | W28: 2 | AA28: 1 | AF28: 1 | AH28: 2 | AI28: 7
E29: Replacement | F29: 12 | G29: 0.02690583 | J29: Michael McSharry | L29: 6 | R29: 6 | T29: Nancy Cleveland | U29: 1 | V29: 7 | W29: 6 | Y29: 4 | Z29: 9 | AA29: 28 | AB29: 1 | AC29: 9 | AD29: 3 | AE29: 19 | AH29: 6 | AI29: 93
E30: Retention | F30: 2 | G30: 0.0044843049 | J30: Nancy Cleveland | L30: 10 | N30: 1 | R30: 11 | T30: Nicole Erickson | U30: 2 | V30: 41 | W30: 1 | Z30: 4 | AA30: 2 | AB30: 5 | AE30: 2 | AH30: 8 | AI30: 65
E31: Service Request | F31: 164 | G31: 0.367713 | J31: New Complaints | N31: 4 | R31: 4 | T31: Paaton Howard | V31: 1 | W31: 1 | Y31: 30 | Z31: 9 | AB31: 1 | AC31: 3 | AE31: 75 | AF31: 3 | AG31: 2 | AH31: 22 | AI31: 147
E32: SR Mapping Research | F32: 15 | G32: 0.033632287 | J32: Nicole Erickson | K32: 16 | L32: 4 | N32: 4 | P32: 2 | R32: 26 | T32: Perry Young | Z32: 3 | AE32: 7 | AI32: 10
E33: Web/Portal Support | F33: 5 | G33: 0.011210762 | J33: Paaton Howard | K33: 4 | N33: 2 | R33: 6 | T33: Return Mail Followup | AA33: 87 | AI33: 87
E34: (blank) | F34: 73 | G34: 0.16367713 | J34: Perry Young | L34: 13 | R34: 13 | T34: Rosa Scott-Duren | W34: 1 | Y34: 17 | Z34: 5 | AB34: 4 | AC34: 16 | AE34: 35 | AH34: 16 | AI34: 94
E35: Grand Total | F35: 446 | G35: 1 | J35: Product Replacements | N35: 39 | R35: 39 | T35: Shelby Bickford | V35: 1 | W35: 2 | AA35: 6 | AB35: 1 | AG35: 2 | AH35: 2 | AI35: 14
J36: Quinn Graham | T36: Standard Priority Cases | U36: 200 | V36: 131 | W36: 16 | X36: 2 | Y36: 6 | Z36: 11 | AA36: 22 | AB36: 130 | AC36: 77 | AE36: 102 | AF36: 342 | AG36: 6 | AH36: 321 | AI36: 1366
J37: Rosa Scott-Duren | K37: 28 | N37: 2 | P37: 13 | R37: 43 | T37: Steven Yanis | V37: 1 | AE37: 1 | AH37: 2 | AI37: 4
J38: Service Watch | K38: 1 | N38: 1 | R38: 2 | T38: Tomekia (Ms. T) H. | U38: 1 | W38: 1 | Y38: 2 | AA38: 1 | AC38: 5 | AE38: 9 | AH38: 17 | AI38: 36
J39: Shanna Richards | T39: Vickie Phillips-Wall | U39: 1 | V39: 1 | W39: 3 | Y39: 3 | Z39: 9 | AA39: 2 | AB39: 1 | AC39: 7 | AE39: 13 | AG39: 8 | AH39: 72 | AI39: 120
J40: Shelby Bickford | T40: Web Cancel Requests | W40: 1 | AI40: 1
J41: Standard Priority Cases | K41: 5 | N41: 343 | R41: 348 | T41: Yvanca Jackson | V41: 1 | W41: 1 | Y41: 18 | Z41: 99 | AA41: 8 | AB41: 1 | AE41: 15 | AH41: 68 | AI41: 211
J42: Steven Yanis | L42: 1 | N42: 2 | R42: 3 | T42: (blank)
J43: Tomekia (Ms. T) H. | K43: 7 | L43: 1 | M43: 1 | N43: 9 | P43: 3 | R43: 21 | T43: Grand Total | U43: 258 | V43: 445 | W43: 913 | X43: 2 | Y43: 165 | Z43: 278 | AA43: 385 | AB43: 173 | AC43: 629 | AD43: 8 | AE43: 706 | AF43: 349 | AG43: 72 | AH43: 2433 | AI43: 6816
J44: Vickie Phillips-Wall | K44: 17 | L44: 3 | N44: 1 | P44: 1 | R44: 22
J45: Web Cancel Requests | N45: 6 | R45: 6
J46: Yvanca Jackson | K46: 22 | L46: 2 | N46: 29 | P46: 7 | R46: 60
J47: (blank)
J48: Grand Total | K48: 540 | L48: 385 | M48: 1 | N48: 689 | O48: 4 | P48: 64 | R48: 1683

Sheet Sheet3
B3: {=_xlfn.LET( _xlpm.TargetAssociates, {"Alyssa Torres";"Christina J Harris";"Clarene Stapleton";"Demetra Rainey";"Dessie Temple";"Joshua Bell";"Margaret Reddy";"Michael McSharry";"Nancy Cleveland";"Perry Young"}, _xlpm.Owners, 'Closed SF Cases MTD'!A2:A10000, _xlpm.Status, 'Closed SF Cases MTD'!D2:D10000, _xlpm.Dates, 'Closed SF Cases MTD'!H2:H10000, _xlpm.Filtered, _xlfn._xlws.FILTER(_xlpm.Owners, (_xlpm.Status="Closed") * (INT(_xlpm.Dates)=TODAY()) * ISNUMBER(MATCH(_xlpm.Owners, _xlpm.TargetAssociates, 0))), _xlpm.CountTable, _xlfn.UNIQUE(_xlpm.Filtered), _xlpm.Counts, _xlfn.MAP(_xlpm.CountTable, _xlfn.LAMBDA(_xlpm.a, COUNTIF(_xlpm.Filtered, _xlpm.a))), _xlpm.Sorted, _xlfn._xlws.SORT(_xlfn.HSTACK(_xlpm.CountTable, _xlpm.Counts), 2, -1), _xlfn.TAKE(_xlpm.Sorted, 10) )} -> #VALUE! | F3: {=_xlfn.LET( _xlpm.TargetAssociates, {"Alyssa Torres";"Christina J Harris";"Clarene Stapleton";"Demetra Rainey";"Dessie Temple";"Joshua Bell";"Margaret Reddy";"Michael McSharry";"Nancy Cleveland";"Perry Young"}, _xlpm.Owners, 'Closed SF Cases MTD'!A2:A10000, _xlpm.Status, 'Closed SF Cases MTD'!D2:D10000, _xlpm.Filtered, _xlfn._xlws.FILTER(_xlpm.Owners, (_xlpm.Status="Closed") * ISNUMBER(MATCH(_xlpm.Owners, _xlpm.TargetAssociates, 0))), _xlpm.CountTable, _xlfn.UNIQUE(_xlpm.Filtered), _xlpm.Counts, _xlfn.MAP(_xlpm.CountTable, _xlfn.LAMBDA(_xlpm.a, COUNTIF(_xlpm.Filtered, _xlpm.a))), _xlpm.Sorted, _xlfn._xlws.SORT(_xlfn.HSTACK(_xlpm.CountTable, _xlpm.Counts), 2, -1), _xlfn.TAKE(_xlpm.Sorted, 10) )} -> #VALUE!

Sheet Sheet1
A1: case# | B1: cx ph# | C1: case type | D1: case Desc | E1: Next Steps
A2: 12345 | B2: 12345678 | C2: Billing | D2: whatever | E2: Test

Sheet lists and dropdowns
A1: Account Support
A2: Billing
A3: Cancel Plan
A4: Out of Network Repair
A5: Parts
A6: Plan Support
A7: Repair Authorization
A8: Replacement
A9: Retention
A10: Service Request
A11: SR Mapping Research
A12: Web/Portal Support

Sheet Open SF cases MTD
A1: Case Owner | B1: Subject | C1: Account Name | D1: Opened Date | E1: Person Account: Home Phone | F1: Case Number | G1: Status | I1: Count of Account Name | J1: Column Labels
A2: Tomekia (Ms. T) H. | B2: Parts- Follow up with TPD and Cx on 12-11-25 (Barb) | C2: Elizabeth Sturm | D2: 45967 | E2: 7657164178 | F2: 271846 | G2: New | I2: Row Labels | J2: In Process | K2: In Progress | L2: In Review | M2: New | N2: New Complaint | O2: On Hold | P2: (blank) | Q2: Grand Total
A3: Steven Yanis | B3: [CEO Complaint] Refrigerator Repair TPD & CX follow-up | C3: Jamie Jackson | D3: 46178 | E3: 8186218043 | F3: 388285 | G3: New | I3: Admin Tasks | M3: 26 | Q3: 26
A4: Tomekia (Ms. T) H. | B4: CX will take legal action if he doesn't gets any updates from D&G | C4: Jason Angone | D4: 46181 | E4: 6306392351 | F4: 388577 | G4: New | I4: Alissa Caskey | M4: 36 | O4: 6 | Q4: 42
A5: Tomekia (Ms. T) H. | B5: Service Request-SR research-f/u needed on next steps after last repair on washer | C5: Carl Williams | D5: 46203 | F5: 394222 | G5: New | I5: Alyssa Torres | K5: 1 | M5: 1 | Q5: 2
A6: Tomekia (Ms. T) H. | B6: Service Request-SR research-cx threating with lawyer | C6: Karen Kennedy | D6: 46213 | F6: 396771 | G6: New | I6: Andrew Henderson | J6: 31 | M6: 2 | Q6: 33
A7: Tomekia (Ms. T) H. | B7: Service Request-SR research Complaint | C7: Dianne Apter-Mckay | D7: 46216 | F7: 397013 | G7: New | I7: Asante Msosa | J7: 5 | M7: 17 | O7: 5 | Q7: 27
A8: New Complaints | B8: Service Request-Find service tech-Cx claims fraud after pay and claim was offered. Going to Lawyer | C8: Elizabeth Benet | D8: 46223 | E8: 3344883417 | F8: 398688 | G8: New | I8: Barb Phillips | J8: 10 | M8: 1 | N8: 3 | O8: 1 | Q8: 15
A9: New Complaints | B9: Billing-Billing Inquiry-Account holder is deceased. Estate is closed. Removed cx from contact list | C9: Richard Morris | D9: 46223 | E9: 3369609420 | F9: 398983 | G9: New | I9: Bavani Corrie | J9: 185 | M9: 2 | Q9: 187
A10: Tomekia (Ms. T) H. | B10: Service Request-BBB Complaint 25060787 Refrigerator Repair | C10: William Sampson | D10: 46224 | F10: 399215 | G10: New | I10: Brooke Elizabeth Stafford
A11: New Complaints | B11: Service Request-SR research-Washer Open SR 2 Months Needs Followup | C11: Roger Atkinson | D11: 46225 | F11: 399439 | G11: New | I11: Christina J Harris | J11: 6 | K11: 6 | M11: 10 | Q11: 22
A12: New Complaints | B12: Parts-Parts on Order-cx called to say parts on order since 3 weeks as against 2 weeks tech said Cx requested that A supervisor Call back | C12: Melanie Skinner | D12: 46225 | E12: 8043669116 | F12: 399554 | G12: New | I12: Clarene Stapleton | K12: 38 | M12: 2 | Q12: 40
A13: Cyn H | B13: Replacement for Refrigerator, Top Mount | C13: BOBBIE HUNTER | D13: 45391 | E13: 9845690552 | F13: 47952 | G13: New | I13: Colleen Nash | J13: 1 | K13: 3 | M13: 2 | Q13: 6
A14: Andrew Henderson | B14: Plans did not properly bundle for payment causing collection failures. | C14: Maritza Velasquez | D14: 45443 | E14: 8324880183 | F14: 63460 | G14: New | I14: Corey Krause | J14: 9 | M14: 24 | Q14: 33
A15: Andrew Henderson | B15: Plans did not properly bundle for payment causing collection failures. | C15: Kathy Kritzer | D15: 45443 | F15: 61298 | G15: New | I15: Cyn H | M15: 1 | Q15: 1
A16: Bavani Corrie | B16: Cancel Plan-Failed Payments on plan-Duplicate plans have been cancelled. | C16: Taylor Alvarez | D16: 45917 | E16: 9037676577 | F16: 242073 | G16: New | I16: Debra Anis | J16: 24 | M16: 1 | O16: 12 | Q16: 37
A17: Bavani Corrie | B17: Cancel Plan-Other-Duplicate plan has been cancelled. | C17: Sonia Prestemon | D17: 45966 | F17: 270972 | G17: New | I17: Demetra Rainey | J17: 4 | K17: 11 | M17: 1 | Q17: 16
A18: Alissa Caskey | B18: Pending cx SOT | C18: Ralph Jones | D18: 45999 | F18: 290155 | G18: New | I18: Dessie Temple | J18: 9 | K18: 2 | M18: 15 | Q18: 26
A19: Gia Stinson | B19: Replacement-Other-cx had 3 sr same issue unit not fixed | C19: Sandra Wash | D19: 46017 | E19: 2108432178 | F19: 299600 | G19: New | I19: Diana C | J19: 30 | K19: 3 | M19: 35 | N19: 1 | O19: 8 | Q19: 77
A20: Melissa Orosco | B20: Replacement scheduled to arrive 5/14, wp, wp form | C20: Ajah Peace | D20: 46104 | F20: 345964 | G20: New | I20: Dianna Resendez | J20: 30 | K20: 171 | Q20: 201
A21: Brooke Elizabeth Stafford | B21: Allie Egerer from Domestic & General (Hub 6413964) has invited you to HubSpot | D21: 46132 | F21: 375213 | G21: New | I21: Gia Stinson | J21: 30 | K21: 2 | M21: 19 | Q21: 51
A22: Brooke Elizabeth Stafford | B22: HubSpot Account | D22: 46132 | F22: 375358 | G22: New | I22: Joshua Ball | J22: 4 | K22: 1 | Q22: 5
A23: Alissa Caskey | B23: Pending finance task | C23: Mervic Gil | D23: 46135 | E23: 3057986504 | F23: 376772 | G23: New | I23: Kamry Williams
A24: Diana C | B24: SOT | | C24: Linda Lewis | D24: 46139 | E24: 5178125216 | F24: 377643 | G24: New | I24: Kimberly Teasley | J24: 10 | K24: 1 | M24: 40 | O24: 1 | Q24: 52
A25: Steven Yanis | B25: CLAIM DISPUTE /Start date /10/10/2025 | C25: Vallia Huff | D25: 46146 | F25: 380410 | G25: New | I25: Magdalena Leon | J25: 4 | Q25: 4
A26: Alyssa Torres | B26: Replacement-Subsequent repair BER-Possible BER/ Tech just left, and washer is worse than before | C26: Clara Vanessa Valles Flores | D26: 46153 | E26: 9414656612 | F26: 382220 | G26: New | I26: Margaret Reddy | J26: 5 | K26: 6 | M26: 4 | O26: 5 | Q26: 20
A27: Christina J Harris | B27: Fridge: Confirmed BER -- 2nd email sent | C27: Craig Benendetti | D27: 46161 | F27: 384252 | G27: New | I27: Melissa Orosco | J27: 43 | K27: 100 | M27: 7 | Q27: 150
A28: Alissa Caskey | B28: Pending TPD response | D28: 46164 | F28: 384897 | G28: New | I28: Michael McSharry | K28: 6 | Q28: 6
A29: Demetra Rainey | B29: Service Request-SR research-Potential BER follow up 7.28 | C29: BILLY AALAND-PARRISH | D29: 46168 | E29: 9707788357 | F29: 385574 | G29: New | I29: Nancy Cleveland | K29: 10 | M29: 1 | Q29: 11
A30: Diana C | B30: Fw: Invoice | D30: 46170 | F30: 386137 | G30: New | I30: New Complaints | M30: 4 | Q30: 4
A31: Nicole Erickson | B31: Billing-Billing Inquiry-WP Refund for ACT- Cx provided # to WP. Closing case. | C31: Victor Preciado | D31: 46178 | F31: 388122 | G31: New | I31: Nicole Erickson | J31: 16 | K31: 4 | M31: 4 | O31: 2 | Q31: 26
A32: Diana C | B32: **SPANISH** | fu 07.20 FOLLOW UP | C32: Erika Trevino | D32: 46181 | F32: 388742 | G32: New | I32: Paaton Howard | J32: 4 | M32: 2 | Q32: 6
A33: Melissa Orosco | B33: Replacement scheduled to arrive 7/21, Lowes | C33: Joseph Dutcheshen | D33: 46182 | F33: 389073 | G33: New | I33: Perry Young | K33: 13 | Q33: 13
A34: Melissa Orosco | B34: Re: When repair isn?t possible, replacement is our promise. | C34: Joseph Dutcheshen | D34: 46184 | F34: 389570 | G34: New | I34: Product Replacements | M34: 39 | Q34: 39
A35: Margaret Reddy | B35: Parts-Parts on Order-Parts ordered 4 weeks ago. Ghosted by SP | C35: Diann Dixon | D35: 46185 | F35: 389951 | G35: New | I35: Quinn Graham
A36: Alissa Caskey | B36: Pending TPD response | C36: Emily Kemnitz | D36: 46185 | F36: 389979 | G36: New | I36: Rosa Scott-Duren | J36: 28 | M36: 2 | O36: 13 | Q36: 43
A37: Alissa Caskey | B37: Need to cancel plan got WIB error | D37: 46187 | F37: 390181 | G37: New | I37: Service Watch | J37: 1 | M37: 1 | Q37: 2
A38: Quinn Graham | B38: Re: << Ref:1002857 >> D&G Plan Cancellation Options | D38: 46189 | F38: 390889 | G38: New | I38: Shanna Richards
A39: Quinn Graham | B39: Case # 1006192 Plan # DG0102851040 | D39: 46189 | F39: 390899 | G39: New | I39: Shelby Bickford
A40: Alissa Caskey | B40: Pending TPD response | C40: Teresa Dargan | D40: 46190 | F40: 391061 | G40: New | I40: Standard Priority Cases | J40: 5 | M40: 343 | Q40: 348
A41: Tomekia (Ms. T) H. | B41: BBB Complaint # 25069490 Refrigerator Repair SR follow-up | C41: Heather lyons | D41: 46192 | F41: 391608 | G41: New | I41: Steven Yanis | K41: 1 | M41: 2 | Q41: 3
A42: Gia Stinson | B42: Cancel Plan-Open SR on Plan-Cx wants to cancel the plan | C42: Leila Rainey | D42: 46192 | F42: 391760 | G42: New | I42: Tomekia (Ms. T) H. | J42: 7 | K42: 1 | L42: 1 | M42: 9 | O42: 3 | Q42: 21
A43: Yvanca Jackson | B43: Refrigerator Shelf replacement | C43: Christine Coles | D43: 46195 | F43: 392095 | G43: New | I43: Vickie Phillips-Wall | J43: 17 | K43: 3 | M43: 1 | O43: 1 | Q43: 22
A44: Nicole Erickson | B44: Seeking refund -- cx paying on someone els's plan | C44: JENNIFER SMITH | D44: 46195 | E44: 8048157735 | F44: 392092 | G44: New | I44: Web Cancel Requests | M44: 6 | Q44: 6
A45: Yvanca Jackson | B45: Replacement door shelf | C45: Jada Thompson | D45: 46196 | F45: 392479 | G45: New | I45: Yvanca Jackson | J45: 22 | K45: 2 | M45: 29 | O45: 7 | Q45: 60
A46: Diana C | B46: Billing-Refund requested-cx states she canceIIed in may | C46: Aaliyah Price | D46: 46198 | F46: 393114 | G46: New | I46: (blank)
A47: Asante Msosa | B47: Repair Authorization-Other-WIB DG0102274988- Sears Autho REFRIGERATOR LISTED AS LG | C47: Stephanie Lambright | D47: 46198 | F47: 393145 | G47: New | I47: Grand Total | J47: 540 | K47: 385 | L47: 1 | M47: 689 | N47: 4 | O47: 64 | Q47: 1683
A48: Diana C | B48: REFUND | DG0001314772 | D48: 46200 | F48: 393451 | G48: New
A49: Alissa Caskey | B49: Pending admin task | C49: Tiffany PARKER | D49: 46202 | E49: 2533106884 | F49: 393676 | G49: New
A50: Yvanca Jackson | B50: Case # 00386826 | C50: Pauline Houck | D50: 46202 | F50: 393685 | G50: New
A51: Margaret Reddy | B51: Service Request-SR research-SP told cx they need updated model and serial information. | C51: Qaisar Shaikh | D51: 46202 | F51: 393695 | G51: New
A52: Yvanca Jackson | B52: CM needs a new drawer *middle one* out of the three | C52: Ascencion Granados | D52: 46202 | F52: 393770 | G52: New
A53: Clarene Stapleton | B53: Replacement for plan DG0001696302 | C53: Frances Vaughn | D53: 46202 | F53: 393848 | G53: New
A54: Asante Msosa | B54: rack on door second from bottom cx does not have oem number | C54: Mattie Martin | D54: 46203 | E54: 5132422538 | F54: 394016 | G54: New
A55: Yvanca Jackson | B55: Parts-Accessory replacement-cracked drawers on front panel | C55: Marie Robinson | D55: 46203 | F55: 394142 | G55: New
A56: Quinn Graham | B56: washer repair case #1006936 | D56: 46203 | F56: 394160 | G56: New
A57: Margaret Reddy | B57: Service Request-Reschedule request-Tech No call and No Show (twice)/ Customer needs to reschedule/ Experience the same issues/ Possible BER | C57: Miriam Garcia | D57: 46203 | F57: 394237 | G57: New
A58: Asante Msosa | B58: Fwd: Whirlpool refrigerator/freezer model number model #WRT541SZDM, cereal VSE2634989 5 inch crack in freezer liner. | C58: JOSEPH TIGUE | D58: 46203 | F58: 394207 | G58: New
A59: Alissa Caskey | B59: Billing-Refund requested-Cx is requesting refund for the last three months | C59: sharon bailey | D59: 46203 | F59: 394193 | G59: New
A60: Standard Priority Cases | B60: replacement draw | C60: Tisha Robinson | D60: 46203 | F60: 394221 | G60: New
A61: Melissa Orosco | B61: Replacement scheduled to arrive 7/28, wp | C61: Faigie Compton | D61: 46204 | E61: 2162910509 | F61: 394340 | G61: New
A62: Yvanca Jackson | B62: Parts-Accessory replacement-Drawer Replacement | C62: Ronald Telsare | D62: 46204 | F62: 394318 | G62: New
A63: Yvanca Jackson | B63: TWO FRONT GRATES ARE CRACKED | C63: Jim Catlin | D63: 46204 | F63: 394386 | G63: New
A64: Rosa Scott-Duren | B64: Parts-Parts on Order-SP came with the wrong parts but hasn't come back with new parts | C64: Marcie Kephart | D64: 46204 | E64: 3608934882 | F64: 394382 | G64: New
A65: Christina J Harris | B65: Service Request-SR needs to be canceled-CX needs new SR - Old SR from 06/03 still open in SB | C65: John Burnett | D65: 46204 | F65: 394455 | G65: New
A66: Melissa Orosco | B66: Replacement scheduled to arrive 7/24, wp, 8-12 | C66: Paul DeCiutiis | D66: 46204 | F66: 394479 | G66: New
A67: Yvanca Jackson | B67: Replacement knobs | C67: Imamu Johnson | D67: 46205 | F67: 394635 | G67: New
A68: Tomekia (Ms. T) H. | B68: WIB case #1010386- CX follow-up 7/22/26 | D68: 46205 | F68: 394624 | G68: New
A69: Shanna Richards | B69: Re: << Ref:1003661 >> Refrigerator Repair Update ? Outstanding Balance | D69: 46205 | F69: 394651 | G69: New
A70: Yvanca Jackson | B70: DOOR SHELF PANEL BROKEN | C70: Andreda Mosley | D70: 46205 | E70: 2513910966 | F70: 394714 | G70: New
A71: Nancy Cleveland | B71: Parts-Parts research-cx cant get a hold of SP to get update about parts | C71: Kimberly Rosner | D71: 46205 | E71: 6364475561 | F71: 394674 | G71: New
A72: Asante Msosa | B72: Service Request-SR research-Tech NCNS - Second Scheduled Attempt | C72: Franceccea Wasso | D72: 46205 | F72: 394706 | G72: New
A73: Melissa Orosco | B73: Replacement scheduled to arrive 7/18, Lowes, return | C73: Laurie Contor Duval | D73: 46205 | E73: 5592229234 | F73: 394709 | G73: New
A74: Diana C | B74: Service Request-RMS rejected order-Error 2012: No coverage could be found. | C74: Frank Torres | D74: 46205 | F74: 394805 | G74: New
A75: Rosa Scott-Duren | B75: Service Request-Reschedule request-cx has sear sr no call no show | C75: Alex Manzo | D75: 46205 | E75: 6464210353 | F75: 394813 | G75: New
A76: Yvanca Jackson | B76: Parts-Accessory replacement-The support ring under the glass turntable has to be replaced | C76: Irene Marquez | D76: 46205 | F76: 394818 | G76: New
A77: Yvanca Jackson | B77: Parts-Accessory replacement-Top shelf of fridge is cracked and needs replacement | C77: Nader Daoud | D77: 46205 | F77: 394823 | G77: New
A78: Standard Priority Cases | B78: Parts-Parts research-Refrigerator's door shelf is broken | C78: Ebony Moore | D78: 46206 | E78: 9295565723 | F78: 394928 | G78: New
A79: Diana C | B79: Out of Network Repair-Other-cx requ out of network repair- dg techs can not work on his range. | C79: Pratik Patel | D79: 46206 | F79: 394937 | G79: New
A80: Yvanca Jackson | B80: Cx has multiple cracked drawers and needs replacement (x4) | C80: Annette Lassalle | D80: 46206 | F80: 394941 | G80: New
A81: Yvanca Jackson | B81: Dg0104295176 | D81: 46206 | F81: 394962 | G81: New
A82: Paaton Howard | B82: Policy #DG0000896868 | C82: MARTIN CHOREN | D82: 46207 | E82: 4145738866 | F82: 395009 | G82: New
A83: Diana C | D83: 46207 | F83: 395055 | G83: New
A84: Colleen Nash | B84: On hold | C84: Linda Michler | D84: 46207 | E84: 4124801731 | F84: 395060 | G84: New
A85: Diana C | B85: Fw: Mr. Appliance Receipt | D85: 46209 | F85: 395155 | G85: New
A86: Shelby Bickford | B86: (WIB) No longer need Plan number: DG0106760382 | D86: 46209 | F86: 395154 | G86: New
A87: Kimberly Teasley | B87: Service Request-SR research-Cx has had over 4 SRs, 2 SPs still not freezing | C87: Harvest Anderson | D87: 46209 | F87: 395177 | G87: New
A88: Kimberly Teasley | B88: Service Request-Find service tech-Washer - Pay and claim | C88: nancy winkleman | D88: 46209 | F88: 395185 | G88: New
A89: Melissa Orosco | B89: Receipt 7/14, Wp form | C89: Despina Panagos | D89: 46209 | E89: 7272240453 | F89: 395268 | G89: New
A90: Kimberly Teasley | B90: Service Request-Reschedule request-oven and sears | C90: Sharon Pogue | D90: 46209 | F90: 395289 | G90: New
A91: Shelby Bickford | B91: (WIB) Account | D91: 46209 | F91: 395304 | G91: New
A92: Debra Anis | B92: Service Request-Other-complaint about tech | C92: Novella Owens | D92: 46209 | F92: 395253 | G92: New
A93: Christina J Harris | B93: Service Request-New SR needed-Washer - need new SR | C93: FREDERICH LEAMON | D93: 46209 | E93: 5593498136 | F93: 395273 | G93: New
A94: Kimberly Teasley | B94: Parts-Other-parts | C94: Kodi Callan | D94: 46209 | F94: 395347 | G94: New
A95: Gia Stinson | B95: Billing-Other-Customer needs a refund for two plans | C95: Pat Evans | D95: 46209 | F95: 395373 | G95: New
A96: Kimberly Teasley | B96: parts replacement | C96: Maliha Ahmad | D96: 46209 | F96: 395414 | G96: New
A97: Shelby Bickford | B97: (WIB) Dana Kerby | D97: 46209 | F97: 395410 | G97: New
A98: Alissa Caskey | B98: Billing-Other-refund for last month | C98: Harry Lumerman | D98: 46209 | F98: 395453 | G98: New
A99: Yvanca Jackson | B99: stove top grates black finish coming off and broke | C99: THOMAS MENTLICK | D99: 46209 | E99: 818-585-4648 | F99: 395463 | G99: New
A100: Kimberly Teasley | B100: Ice bucket broke | C100: Kenneth Mendoza | D100: 46210 | E100: 4076473135 | F100: 395513 | G100: New
...

Sheet Closed SF Cases MTD
A1: Case Owner | B1: Subject | C1: Account Name | D1: Status | E1: Person Account: Home Phone | F1: Case Number | G1: Case Last Modified By | H1: Date/Time Closed | I1: Type | K1: Count of Status | L1: Column Labels
A2: Standard Priority Cases | B2: Warranty payment | D2: Closed | F2: 394021 | G2: Colleen Nash | H2: 7/1/2026, 3:13 AM | K2: Row Labels | L2: Account Support | M2: Billing | N2: Cancel Plan | O2: Email Third Party Escalations | P2: Out of Network Repair | Q2: Parts | R2: Plan Support | S2: Repair Authorization | T2: Replacement | U2: Retention | V2: Service Request | W2: SR Mapping Research | X2: Web/Portal Support | Y2: (blank) | Z2: Grand Total
A3: Standard Priority Cases | B3: Case#00392432 | D3: Closed | F3: 394071 | G3: Colleen Nash | H3: 7/1/2026, 3:13 AM | K3: Admin Tasks | R3: 1 | Y3: 1715 | Z3: 1716
A4: Standard Priority Cases | D4: Closed | F4: 394079 | G4: Colleen Nash | H4: 7/1/2026, 3:17 AM | K4: Alissa Caskey | L4: 3 | M4: 41 | N4: 27 | P4: 2 | R4: 17 | S4: 3 | U4: 2 | V4: 1 | X4: 2 | Z4: 98
A5: Standard Priority Cases | B5: Re: Case # 00393738 | D5: Closed | F5: 394238 | G5: Colleen Nash | H5: 7/1/2026, 3:20 AM | K5: Alyssa Torres | M5: 1 | R5: 1 | Z5: 2
A6: Standard Priority Cases | B6: Re:Gillian Corbie - cancellation | D6: Closed | F6: 394091 | G6: Colleen Nash | H6: 7/1/2026, 3:20 AM | K6: Asante Msosa | P6: 24 | Q6: 7 | R6: 4 | S6: 2 | T6: 5 | V6: 59 | Y6: 21 | Z6: 122
A7: Standard Priority Cases | B7: Providing information | D7: Closed | F7: 394273 | G7: Colleen Nash | H7: 7/1/2026, 3:21 AM | K7: Barb Phillips | M7: 3 | N7: 2 | P7: 2 | Q7: 10 | R7: 3 | T7: 6 | V7: 29 | W7: 1 | Y7: 3 | Z7: 59
A8: Standard Priority Cases | B8: FW: Cancellation Confirmation ? D&G Appliance Protection Plan | D8: Closed | F8: 394132 | G8: Colleen Nash | H8: 7/1/2026, 3:22 AM | K8: Brooke Elizabeth Stafford | Y8: 1 | Z8: 1
A9: Standard Priority Cases | B9: Question about my billing | D9: Closed | F9: 394186 | G9: Colleen Nash | H9: 7/1/2026, 3:27 AM | K9: Christina J Harris | L9: 6 | M9: 31 | N9: 47 | Q9: 18 | R9: 14 | T9: 1 | V9: 126 | W9: 2 | X9: 1 | Y9: 4 | Z9: 250
A10: Standard Priority Cases | B10: Update payment details | D10: Closed | F10: 394245 | G10: Colleen Nash | H10: 7/1/2026, 3:31 AM | K10: Clarene Stapleton | L10: 27 | M10: 2 | N10: 533 | Q10: 9 | R10: 90 | S10: 1 | T10: 137 | V10: 29 | X10: 29 | Y10: 8 | Z10: 865
A11: Standard Priority Cases | B11: You have new held messages | D11: Closed | F11: 394276 | G11: Colleen Nash | H11: 7/1/2026, 3:32 AM | K11: Colleen Nash | L11: 1 | M11: 3 | R11: 1 | T11: 1 | Y11: 14 | Z11: 20
A12: Dessie Temple | B12: Attention Ms T & Ms Vickie | D12: Closed | F12: 394209 | G12: Dessie Temple | H12: 7/1/2026, 5:02 AM | K12: Corey Krause | L12: 6 | M12: 109 | N12: 35 | Q12: 2 | R12: 29 | S12: 1 | T12: 3 | V12: 4 | X12: 9 | Y12: 4 | Z12: 202
A13: Colleen Nash | B13: Cancel policy?s | D13: Closed | F13: 393300 | G13: Colleen Nash | H13: 7/1/2026, 5:32 AM | K13: Cyn H | Q13: 1 | Z13: 1
A14: Colleen Nash | B14: Close accounts | D14: Closed | F14: 393330 | G14: Colleen Nash | H14: 7/1/2026, 5:33 AM | K14: Data Protection | Y14: 3 | Z14: 3
A15: Diana C | B15: RELAY TO CASE#00312519 | D15: Closed | F15: 394180 | G15: Diana C | H15: 7/1/2026, 5:42 AM | K15: Debra Anis | M15: 2 | N15: 1 | P15: 16 | Q15: 4 | R15: 2 | S15: 6 | T15: 4 | V15: 28 | Y15: 23 | Z15: 86
A16: Vickie Phillips-Wall | B16: Service- Service is scheduled for 7/3 w/Sears | C16: Melissa Hartman | D16: Closed | F16: 391473 | G16: Vickie Phillips-Wall | H16: 7/1/2026, 6:10 AM | K16: Demetra Rainey | M16: 1 | N16: 11 | P16: 3 | Q16: 15 | R16: 3 | S16: 2 | T16: 1 | V16: 36 | X16: 1 | Y16: 4 | Z16: 77
A17: Magdalena Leon | B17: Plan cancelled on WIB case 1007689 | D17: Closed | F17: 394216 | G17: Magdalena Leon | H17: 7/1/2026, 6:18 AM | K17: Dessie Temple | L17: 6 | M17: 20 | N17: 173 | P17: 5 | Q17: 10 | R17: 26 | T17: 13 | V17: 12 | X17: 9 | Y17: 43 | Z17: 317
A18: Vickie Phillips-Wall | B18: WIB Case #1009160- Plan and SR cancelled | D18: Closed | F18: 391415 | G18: Vickie Phillips-Wall | H18: 7/1/2026, 6:25 AM | K18: Diana C | M18: 3 | N18: 9 | P18: 33 | Q18: 28 | R18: 3 | S18: 4 | T18: 2 | V18: 22 | Y18: 23 | Z18: 127
A19: Vickie Phillips-Wall | B19: Case # 1008056 | D19: Closed | F19: 391560 | G19: Vickie Phillips-Wall | H19: 7/1/2026, 6:43 AM | K19: Dianna Resendez | S19: 2 | T19: 99 | Y19: 12 | Z19: 113
A20: Vickie Phillips-Wall | B20: lack of good service | D20: Closed | F20: 391574 | G20: Vickie Phillips-Wall | H20: 7/1/2026, 6:50 AM | K20: Gia Stinson | L20: 3 | M20: 38 | N20: 35 | R20: 21 | S20: 6 | T20: 2 | U20: 3 | X20: 3 | Z20: 111
A21: Dessie Temple | B21: Hello | D21: Closed | F21: 393606 | G21: Dessie Temple | H21: 7/1/2026, 6:53 AM | K21: High Priority Cases | M21: 1 | Z21: 1
A22: Vickie Phillips-Wall | B22: Change Email Address | D22: Closed | F22: 391846 | G22: Vickie Phillips-Wall | H22: 7/1/2026, 6:59 AM | K22: Joshua Ball | M22: 3 | N22: 2 | R22: 1 | V22: 3 | Y22: 4 | Z22: 13
A23: Vickie Phillips-Wall | B23: Cancellation of policies | D23: Closed | F23: 391742 | G23: Vickie Phillips-Wall | H23: 7/1/2026, 7:01 AM | K23: Kimberly Teasley | L23: 1 | M23: 2 | N23: 2 | Q23: 13 | R23: 12 | S23: 2 | T23: 14 | V23: 55 | Y23: 1 | Z23: 102
A24: Diana C | B24: REPLACEMENT case 00392843 | REFUND SOT case#00392550 | D24: Closed | F24: 394272 | G24: Diana C | H24: 7/1/2026, 7:06 AM | K24: Magdalena Leon | N24: 1 | Q24: 3 | T24: 1 | V24: 1 | Y24: 10 | Z24: 16
A25: Vickie Phillips-Wall | B25: Service- Per TPD/SP the service was completed on 6/23 WIB Case#1009161 | D25: Closed | F25: 391897 | G25: Vickie Phillips-Wall | H25: 7/1/2026, 7:17 AM | K25: Margaret Reddy | Q25: 9 | T25: 1 | V25: 22 | Z25: 32
A26: Vickie Phillips-Wall | B26: Plan Number 62W0000613 | D26: Closed | F26: 392097 | G26: Vickie Phillips-Wall | H26: 7/1/2026, 8:02 AM | K26: Melissa Orosco | T26: 222 | V26: 1 | Y26: 4 | Z26: 227
A27: Vickie Phillips-Wall | B27: WIB Case#1007598-Out of Network Reimbursement | D27: Closed | F27: 392132 | G27: Vickie Phillips-Wall | H27: 7/1/2026, 8:21 AM | K27: Michael McSharry | M27: 1 | N27: 2 | R27: 1 | W27: 1 | Y27: 2 | Z27: 7
A28: Vickie Phillips-Wall | B28: Service- Unit was not deemed unrepairable need to be rescheduled-CASE #1006242 | D28: Closed | F28: 392339 | G28: Vickie Phillips-Wall | H28: 7/1/2026, 8:56 AM | K28: Nancy Cleveland | L28: 1 | M28: 7 | N28: 6 | P28: 4 | Q28: 9 | R28: 28 | S28: 1 | T28: 9 | U28: 3 | V28: 19 | Y28: 6 | Z28: 93
A29: Paaton Howard | B29: Fw: Quote from Farr's Hardware - 06/17/2026 | C29: Kerry Cavanagh | D29: Closed | F29: 392550 | G29: Paaton Howard | H29: 7/1/2026, 9:01 AM | K29: Nicole Erickson | L29: 2 | M29: 41 | N29: 1 | Q29: 4 | R29: 2 | S29: 5 | V29: 2 | Y29: 8 | Z29: 65
A30: Vickie Phillips-Wall | B30: Fw: PLAN NUMBER J2Z0094851 | D30: Closed | F30: 392396 | G30: Vickie Phillips-Wall | H30: 7/1/2026, 9:14 AM | K30: Paaton Howard | M30: 1 | N30: 1 | P30: 30 | Q30: 9 | S30: 1 | T30: 3 | V30: 75 | W30: 3 | X30: 2 | Y30: 22 | Z30: 147
A31: Standard Priority Cases | B31: Verified Review Support | D31: Closed | F31: 394341 | G31: Colleen Nash | H31: 7/1/2026, 9:41 AM | K31: Perry Young | Q31: 3 | V31: 7 | Z31: 10
A32: Standard Priority Cases | B32: You have new held messages | D32: Closed | F32: 394362 | G32: Colleen Nash | H32: 7/1/2026, 9:42 AM | K32: Return Mail Followup | R32: 87 | Z32: 87
A33: Standard Priority Cases | B33: Stolen money | D33: Closed | F33: 394331 | G33: Colleen Nash | H33: 7/1/2026, 9:43 AM | K33: Rosa Scott-Duren | N33: 1 | P33: 17 | Q33: 5 | S33: 4 | T33: 16 | V33: 35 | Y33: 16 | Z33: 94
A34: Standard Priority Cases | B34: Your message couldn't be delivered | D34: Closed | F34: 394334 | G34: Colleen Nash | H34: 7/1/2026, 9:44 AM | K34: Shelby Bickford | M34: 1 | N34: 2 | R34: 6 | S34: 1 | X34: 2 | Y34: 2 | Z34: 14
A35: Standard Priority Cases | D35: Closed | F35: 394280 | G35: Colleen Nash | H35: 7/1/2026, 9:47 AM | K35: Standard Priority Cases | L35: 200 | M35: 131 | N35: 16 | O35: 2 | P35: 6 | Q35: 11 | R35: 22 | S35: 130 | T35: 77 | V35: 102 | W35: 342 | X35: 6 | Y35: 321 | Z35: 1366
A36: Standard Priority Cases | B36: Refrigerador whirpool | D36: Closed | F36: 394381 | G36: Colleen Nash | H36: 7/1/2026, 9:48 AM | K36: Steven Yanis | M36: 1 | V36: 1 | Y36: 2 | Z36: 4
A37: Standard Priority Cases | B37: DG0001772861 | D37: Closed | F37: 394351 | G37: Colleen Nash | H37: 7/1/2026, 9:50 AM | K37: Tomekia (Ms. T) H. | L37: 1 | N37: 1 | P37: 2 | R37: 1 | T37: 5 | V37: 9 | Y37: 17 | Z37: 36
A38: Standard Priority Cases | B38: Payment | D38: Closed | F38: 394377 | G38: Colleen Nash | H38: 7/1/2026, 9:51 AM | K38: Vickie Phillips-Wall | L38: 1 | M38: 1 | N38: 3 | P38: 3 | Q38: 9 | R38: 2 | S38: 1 | T38: 7 | V38: 13 | X38: 8 | Y38: 72 | Z38: 120
A39: Asante Msosa | B39: Dishwasher is not working again | D39: Closed | F39: 392664 | G39: Asante Msosa | H39: 7/1/2026, 10:42 AM | K39: Web Cancel Requests | N39: 1 | Z39: 1
A40: Asante Msosa | B40: addressed on case 00394414 | D40: Closed | F40: 392665 | G40: Asante Msosa | H40: 7/1/2026, 10:44 AM | K40: Yvanca Jackson | M40: 1 | N40: 1 | P40: 18 | Q40: 99 | R40: 8 | S40: 1 | V40: 15 | Y40: 68 | Z40: 211
A41: Vickie Phillips-Wall | B41: Service-WIB Case #1009169 service is scheduled for 7/2 | D41: Closed | F41: 392691 | G41: Vickie Phillips-Wall | H41: 7/1/2026, 11:25 AM | K41: (blank)
A42: Dessie Temple | B42: Cancelation | C42: Samantha Arman | D42: Closed | F42: 393950 | G42: Dessie Temple | H42: 7/1/2026, 11:39 AM | K42: Grand Total | L42: 258 | M42: 445 | N42: 913 | O42: 2 | P42: 165 | Q42: 278 | R42: 385 | S42: 173 | T42: 629 | U42: 8 | V42: 706 | W42: 349 | X42: 72 | Y42: 2433 | Z42: 6816
A43: Yvanca Jackson | B43: I have appointments for tomorrow Wednesday June 17 URGENT URGENT - DG0105891412 | D43: Closed | F43: 390934 | G43: Yvanca Jackson | H43: 7/1/2026, 12:02 PM
A44: Vickie Phillips-Wall | C44: Maria Rodriguez | D44: Closed | E44: 9152401072 | F44: 394438 | G44: Vickie Phillips-Wall | H44: 7/1/2026, 12:05 PM
A45: Yvanca Jackson | B45: Need to cancel service on 6/15 for Stephen DiLeo - FR0105496066 WIB | D45: Closed | F45: 390229 | G45: Yvanca Jackson | H45: 7/1/2026, 12:13 PM
A46: Vickie Phillips-Wall | B46: WIB-Case #1009172 | D46: Closed | F46: 394424 | G46: Vickie Phillips-Wall | H46: 7/1/2026, 12:15 PM
A47: Dessie Temple | B47: Attention Ms T & Ms Vickie | D47: Closed | F47: 394210 | G47: Dessie Temple | H47: 7/1/2026, 12:17 PM
A48: Magdalena Leon | B48: Plan to stay active | D48: Closed | F48: 394437 | G48: Magdalena Leon | H48: 7/1/2026, 12:25 PM
A49: Asante Msosa | B49: Dishwasher is not working again | D49: Closed | F49: 392666 | G49: Asante Msosa | H49: 7/1/2026, 12:36 PM
A50: Yvanca Jackson | B50: 1007878 | D50: Closed | F50: 391273 | G50: Yvanca Jackson | H50: 7/1/2026, 12:37 PM
A51: Shelby Bickford | B51: Trouble signing in - collected missing payments on WIB plan | D51: Closed | F51: 394451 | G51: Shelby Bickford | H51: 7/1/2026, 12:45 PM
A52: Yvanca Jackson | B52: Incorrect Appliance Recorded on Policy ? Request for Investigation and Refund | D52: Closed | F52: 391344 | G52: Yvanca Jackson | H52: 7/1/2026, 12:45 PM
A53: Yvanca Jackson | D53: Closed | F53: 391396 | G53: Yvanca Jackson | H53: 7/1/2026, 12:47 PM
A54: Yvanca Jackson | D54: Closed | F54: 391434 | G54: Yvanca Jackson | H54: 7/1/2026, 12:52 PM
A55: Yvanca Jackson | B55: Warning notice remedial work required | D55: Closed | F55: 391777 | G55: Yvanca Jackson | H55: 7/1/2026, 12:56 PM
A56: Yvanca Jackson | B56: Repair initiation, 19June2026 | D56: Closed | F56: 392409 | G56: Yvanca Jackson | H56: 7/1/2026, 1:22 PM
A57: Diana C | D57: Closed | F57: 394463 | G57: Diana C | H57: 7/1/2026, 1:24 PM
A58: Diana C | B58: María | D58: Closed | F58: 394450 | G58: Diana C | H58: 7/1/2026, 1:26 PM
A59: Vickie Phillips-Wall | B59: Washer Repair-WIB Cae#1008544 Service is scheduled for 7/9 | D59: Closed | F59: 392444 | G59: Vickie Phillips-Wall | H59: 7/1/2026, 1:27 PM
A60: Vickie Phillips-Wall | B60: WIB Case#1007650-Claim 1007650 | D60: Closed | F60: 392272 | G60: Vickie Phillips-Wall | H60: 7/1/2026, 1:31 PM
A61: Nicole Erickson | B61: Re: << Ref:1003610 >> Plan Cancellation- 1005351- Plan cancelled with no refund due to Chargeback. Closing case. | D61: Closed | F61: 394243 | G61: Nicole Erickson | H61: 7/1/2026, 1:42 PM
A62: Paaton Howard | B62: KitchenAid Beverage Unit Failure WIB Case #1006254 | D62: Closed | F62: 392404 | G62: Paaton Howard | H62: 7/1/2026, 1:45 PM
A63: Vickie Phillips-Wall | B63: Service- Still IW referred to WP | C63: Maria Ramos | D63: Closed | E63: 6023347861 | F63: 394195 | G63: Vickie Phillips-Wall | H63: 7/1/2026, 1:47 PM
A64: Yvanca Jackson | B64: Complaint Regarding Delay in Freezer Repair | D64: Closed | F64: 392447 | G64: Yvanca Jackson | H64: 7/1/2026, 1:48 PM
A65: Vickie Phillips-Wall | B65: Re: << Ref:1003462 >> Case#1007160 Update on Parts & Service | D65: Closed | F65: 394083 | G65: Vickie Phillips-Wall | H65: 7/1/2026, 1:50 PM
A66: Diana C | B66: Account DG0001014115 | NAME CORRECTION | D66: Closed | F66: 394394 | G66: Diana C | H66: 7/1/2026, 2:36 PM
A67: Standard Priority Cases | B67: change payment method | D67: Closed | F67: 394430 | G67: Colleen Nash | H67: 7/2/2026, 3:06 AM
A68: Standard Priority Cases | B68: You have new held messages | D68: Closed | F68: 394447 | G68: Colleen Nash | H68: 7/2/2026, 3:09 AM
A69: Standard Priority Cases | B69: Billing | D69: Closed | F69: 394477 | G69: Colleen Nash | H69: 7/2/2026, 3:10 AM
A70: Standard Priority Cases | B70: You have new held messages | D70: Closed | F70: 394555 | G70: Colleen Nash | H70: 7/2/2026, 3:16 AM
A71: Standard Priority Cases | D71: Closed | F71: 394565 | G71: Colleen Nash | H71: 7/2/2026, 3:44 AM
A72: Melissa Orosco | B72: Whirlpool® 33-inch Wide Top Freezer Refrigerator with Total | C72: GARY GATES | D72: Closed | F72: 394464 | G72: Melissa Orosco | H72: 7/2/2026, 4:14 AM
A73: Melissa Orosco | B73: Replacement | C73: GARY GATES | D73: Closed | F73: 394468 | G73: Melissa Orosco | H73: 7/2/2026, 4:14 AM
A74: Debra Anis | B74: Appliance problem - Cx emailed on 6/27 - unable to find acct.. No response from cx. No further action req | D74: Closed | F74: 391240 | G74: Debra Anis | H74: 7/2/2026, 5:21 AM
A75: Yvanca Jackson | B75: Re: Cancelled Direct Debit to DOMESTIC & GENERAL on account ending 2343 | D75: Closed | F75: 394582 | G75: Yvanca Jackson | H75: 7/2/2026, 5:25 AM
A76: Yvanca Jackson | D76: Closed | F76: 394572 | G76: Yvanca Jackson | H76: 7/2/2026, 5:31 AM
A77: Yvanca Jackson | B77: Cancelation of Policy for Indesit fridge | D77: Closed | F77: 394571 | G77: Yvanca Jackson | H77: 7/2/2026, 5:33 AM
A78: Yvanca Jackson | B78: Complaint against Equinox Co Service | D78: Closed | F78: 394568 | G78: Yvanca Jackson | H78: 7/2/2026, 5:36 AM
A79: Yvanca Jackson | B79: Complaint against Equinox Co Service | D79: Closed | F79: 394558 | G79: Yvanca Jackson | H79: 7/2/2026, 5:37 AM
A80: Yvanca Jackson | D80: Closed | F80: 394489 | G80: Yvanca Jackson | H80: 7/2/2026, 6:04 AM
A81: Standard Priority Cases | B81: Request received | D81: Closed | F81: 394611 | G81: Colleen Nash | H81: 7/2/2026, 6:05 AM
A82: Standard Priority Cases | B82: [Request received] | D82: Closed | F82: 394608 | G82: Colleen Nash | H82: 7/2/2026, 6:06 AM
A83: Standard Priority Cases | B83: Re: Your Reputation Could Be Costing You Customers | D83: Closed | F83: 394612 | G83: Colleen Nash | H83: 7/2/2026, 6:06 AM
A84: Standard Priority Cases | B84: [Request received] | D84: Closed | F84: 394610 | G84: Colleen Nash | H84: 7/2/2026, 6:06 AM
A85: Dessie Temple | B85: Questions about charges follow up 7/2/26 | C85: Jan Justice | D85: Closed | F85: 393692 | G85: Dessie Temple | H85: 7/2/2026, 6:38 AM
A86: Yvanca Jackson | B86: Cancelled Service Plans | D86: Closed | F86: 394277 | G86: Yvanca Jackson | H86: 7/2/2026, 7:00 AM
A87: Dianna Resendez | B87: Case number 23426377 | C87: Julie Weigle | D87: Closed | E87: 7174132558 | F87: 392879 | G87: Melissa Orosco | H87: 7/2/2026, 7:04 AM
A88: Melissa Orosco | B88: Fwd: Invoice Email | C88: CHERYL ROSALES | D88: Closed | E88: 7608470183 | F88: 393031 | G88: Melissa Orosco | H88: 7/2/2026, 7:07 AM
A89: Rosa Scott-Duren | B89: Breach of T&C (Roach Infestation) | C89: Geovenel Julien | D89: Closed | E89: 9543956964 | F89: 390399 | G89: Rosa Scott-Duren | H89: 7/2/2026, 7:29 AM
A90: Nicole Erickson | B90: Case Number 1007857- Refer to WIB case, Closing case. | D90: Closed | F90: 394454 | G90: Nicole Erickson | H90: 7/2/2026, 7:40 AM
A91: Clarene Stapleton | B91: Call cx on 7/1 10:00 am | C91: German Hernandez | D91: Closed | E91: 2392504420 | F91: 393506 | G91: Clarene Stapleton | H91: 7/2/2026, 8:19 AM
A92: Debra Anis | B92: Dryer rack offer. Cx emailed. no further action req | C92: TRACY TRIMBLE | D92: Closed | F92: 383560 | G92: Debra Anis | H92: 7/2/2026, 9:19 AM
A93: Rosa Scott-Duren | B93: Cancel policy BMQ0019391 | D93: Closed | F93: 394114 | G93: Rosa Scott-Duren | H93: 7/2/2026, 9:28 AM
A94: Brooke Elizabeth Stafford | B94: Appliance Repair Teodor /// vendor | D94: Closed | F94: 394460 | G94: Brooke Stafford | H94: 7/2/2026, 9:36 AM
A95: Standard Priority Cases | B95: RFID Card Update | D95: Closed | F95: 394628 | G95: Colleen Nash | H95: 7/2/2026, 9:50 AM
A96: Standard Priority Cases | B96: Your message couldn't be delivered | D96: Closed | F96: 394648 | G96: Colleen Nash | H96: 7/2/2026, 9:51 AM
A97: Standard Priority Cases | B97: bp pulse Migration | D97: Closed | F97: 394557 | G97: Colleen Nash | H97: 7/2/2026, 9:51 AM
A98: Standard Priority Cases | B98: You have new held messages | D98: Closed | F98: 394580 | G98: Colleen Nash | H98: 7/2/2026, 9:51 AM
A99: Standard Priority Cases | B99: [Request received] | D99: Closed | F99: 394609 | G99: Colleen Nash | H99: 7/2/2026, 9:53 AM
A100: Standard Priority Cases | B100: ITC Vegas 2026 | D100: Closed | F100: 394601 | G100: Colleen Nash | H100: 7/2/2026, 9:53 AM
...

Sheet Case Type
A1: Case Owner | B1: Subject | C1: Account Name | D1: Status | E1: Type | F1: Open | I1: Open | J1: 1
A2: Steven Yanis | B2: Formal Complaint ? Unresolved Claim and Unacceptable Customer Service: Catalina Camps | C2: Catalina Camps | D2: In Progress | F2: 1 | I2: Case Owner | J2: Standard Priority Cases
A3: Andrew Henderson | B3: Urgent: New payment method needed on account. | D3: In Process | F3: 1
A4: Andrew Henderson | B4: Urgent: New payment method needed on account. | D4: In Process | F4: 1 | I4: Row Labels | J4: Count of Status | K4: % of Open
A5: Andrew Henderson | B5: Urgent: New payment method needed on account. | D5: In Process | F5: 1 | I5: Account Support | J5: 2 | K5: 0.0044843049
A6: Andrew Henderson | B6: Urgent: New payment method needed on account. | D6: In Process | F6: 1 | I6: Billing | J6: 37 | K6: 0.082959641
A7: Andrew Henderson | B7: Urgent: New payment method needed on account. | D7: In Process | F7: 1 | I7: Cancel Plan | J7: 24 | K7: 0.053811659
A8: Andrew Henderson | B8: Urgent: New payment method needed on account. | D8: In Process | F8: 1 | I8: Out of Network Repair | J8: 37 | K8: 0.082959641
A9: Andrew Henderson | B9: Urgent: New payment method needed on account. | D9: In Process | F9: 1 | I9: Parts | J9: 59 | K9: 0.132287
A10: Andrew Henderson | B10: Urgent: New payment method needed on account. | D10: In Process | F10: 1 | I10: Plan Support | J10: 15 | K10: 0.033632287
A11: Andrew Henderson | B11: Urgent: New payment method needed on account. | D11: In Process | F11: 1 | I11: Repair Authorization | J11: 1 | K11: 0.0022421525
A12: Andrew Henderson | B12: Urgent: New payment method needed on account. | D12: In Process | F12: 1 | I12: Replacement | J12: 12 | K12: 0.02690583
A13: Andrew Henderson | B13: Urgent: New payment method needed on account. | D13: In Process | F13: 1 | I13: Retention | J13: 2 | K13: 0.0044843049
A14: Andrew Henderson | B14: Urgent: New payment method needed on account. | D14: In Process | F14: 1 | I14: Service Request | J14: 164 | K14: 0.367713
A15: Andrew Henderson | B15: Urgent: New payment method needed on account. | D15: In Process | F15: 1 | I15: SR Mapping Research | J15: 15 | K15: 0.033632287
A16: Andrew Henderson | B16: Urgent: New payment method needed on account. | D16: In Process | F16: 1 | I16: Web/Portal Support | J16: 5 | K16: 0.011210762
... A18: Andrew Henderson | B18: Urgent: New payment method needed on account. | D18: In Process | F18: 1 | I18: Grand Total | J18: 446 | K18: 1
A19: Andrew Henderson | B19: Urgent: New payment method needed on account. | D19: In Process | F19: 1
A20: Andrew Henderson | B20: Urgent: New payment method needed on account. | D20: In Process | F20: 1
A21: Andrew Henderson | B21: Urgent: New payment method needed on account. | D21: In Process | F21: 1
A22: Andrew Henderson | B22: Urgent: New payment method needed on account. | D22: In Process | F22: 1
A23: Andrew Henderson | B23: Urgent: New payment method needed on account. | D23: In Process | F23: 1
A24: Andrew Henderson | B24: Urgent: New payment method needed on account. | D24: In Process | F24: 1
A25: Andrew Henderson | B25: Urgent: New payment method needed on account. | D25: In Process | F25: 1
A26: Andrew Henderson | B26: Urgent: New payment method needed on account. | D26: In Process | F26: 1
A27: Andrew Henderson | B27: Urgent: New payment method needed on account. | D27: In Process | F27: 1
A28: Andrew Henderson | B28: Urgent: New payment method needed on account. | D28: In Process | F28: 1
A29: Andrew Henderson | B29: Urgent: New payment method needed on account. | D29: In Process | F29: 1
A30: Andrew Henderson | B30: Urgent: New payment method needed on account. | D30: In Process | F30: 1
... A116: Brooke Elizabeth Stafford | B116: Allie is still waiting for you to join their team at your company | D116: In Process | F116: 1
A117: Nicole Erickson | B117: SR Needed-WIB Plan Ref- SOT details sent to Cx, pending estimate. Follow up 6/11 | C117: Randall Barnes | D117: In Process | F117: 1
A118: Nicole Erickson | B118: Fwd: Central Kansas Appliance Repair- Pending call to TPD 7/22 | C118: Laura Pratt | D118: In Process | F118: 1
A119: Debra Anis | B119: Maytag Washer Issues. cx had service - job completed 6/16 - cx upset as he says panel was all scratched up by 1st servicer. Wants the panel replaced. | C119: JORGE LLODRA | D119: In Process | F119: 1
A120: Diana C | B120: Fw: Invoice | D120: New | F120: 1
A121: Melissa Orosco | B121: Re: When repair isn?t possible, replacement is our promise. | C121: Joseph Dutcheshen | D121: New | F121: 1
A122: Melissa Orosco | B122: Waiting for approval 7/6, 2nd attempt | C122: Haileigh Daniel | D122: In Progress | F122: 1
A123: Vickie Phillips-Wall | B123: Re: << Ref:1002713 >> WIB Case#1005124 Update on Parts | D123: In Process | F123: 1
A124: Tomekia (Ms. T) H. | B124: BBB Complaint # 25069490 Refrigerator Repair SR follow-up | C124: Heather lyons | D124: New | F124: 1
A125: Nicole Erickson | B125: Fwd: Whirlpool Purchase Confirmation- Plan in lapsed, Pending call to Cx 7/8 | C125: Robynn Smith | D125: In Process | F125: 1
A126: Cyn H | B126: Extended Warranty Account Issue follow up 6/29/25 | D126: In Process | F126: 1
A127: Debra Anis | B127: Formal Complaint ? Immediate Resolution Requested | D127: In Process | F127: 1
A128: Quinn Graham | B128: washer repair case #1006936 | D128: New | F128: 1
A129: Asante Msosa | B129: Fwd: Whirlpool refrigerator/freezer model number model #WRT541SZDM, cereal VSE2634989 5 inch crack in freezer liner. | C129: JOSEPH TIGUE | D129: New | F129: 1
A130: Vickie Phillips-Wall | B130: Asap please | C130: Tammie Turner | D130: In Process | F130: 1
A131: Vickie Phillips-Wall | B131: Case # 1009129 | D131: In Process | F131: 1
A132: Tomekia (Ms. T) H. | B132: WIB case #1010386- CX follow-up 7/22/26 | D132: New | F132: 1
A133: Shanna Richards | B133: Re: << Ref:1003661 >> Refrigerator Repair Update ? Outstanding Balance | D133: New | F133: 1
A134: Diana C | D134: New | F134: 1
A135: Diana C | B135: Fw: Mr. Appliance Receipt | D135: New | F135: 1
A136: Yvanca Jackson | B136: Case Number 1009563 - W11749295 OOS 7/15 | D136: In Process | F136: 1
A137: Vickie Phillips-Wall | B137: Out of Network Repair-WIB case :1009401/00393070 URGENT WIB | C137: Julie Orosco | D137: New | F137: 1
A138: Yvanca Jackson | B138: D&G authorizes you to get a technician of your choice - WIB 1009316 | D138: In Process | F138: 1
A139: Colleen Nash | B139: 2026-182461 (Provost) AG | D139: In Process | F139: 1
A140: Asante Msosa | B140: Case#00305621 | D140: New | F140: 1
A141: Kimberly Teasley | B141: Cracks In Control Panel | D141: In Process | F141: 1
A142: Kimberly Teasley | B142: Appointment scheduling issue | D142: In Process | F142: 1
A143: Diana C | B143: Whirlpool washer fixed. | C143: Denice Pratesi | D143: New | F143: 1
A144: Dianna Resendez | B144: Office call & labor | D144: In Progress | F144: 1
A145: Asante Msosa | B145: Shelf in door | D145: New | F145: 1
A146: Kimberly Teasley | B146: Whirlpool washer issue | D146: In Process | F146: 1
A147: Standard Priority Cases | B147: Re: Chelsea, welcome to your Whirlpool Fixed Price Repair | D147: New | F147: 1
A148: Vickie Phillips-Wall | B148: Dryer appt | C148: Jennifer Martin | D148: In Process | F148: 1
A149: Tomekia (Ms. T) H. | B149: Receipt diagnostic | D149: New | F149: 1
A150: Standard Priority Cases | B150: Case 1010257 | D150: New | F150: 1
A151: Diana C | B151: FW: Estimate from Western Appliance Repair | C151: Linda Fisher | D151: New | F151: 1
A152: Asante Msosa | B152: Freezer drawers | D152: New | F152: 1
A153: Yvanca Jackson | B153: Case#1010294 | D153: In Process | F153: 1
A154: Standard Priority Cases | B154: HELP Case number 1008761. I need a call asap #3 email | D154: New | F154: 1
A155: Standard Priority Cases | B155: Case number 1008761 Urgent Call us Asap. Email number#2 today. | D155: New | F155: 1
A156: Standard Priority Cases | B156: Service job ID - SWPV74F2985B-1 | D156: New | F156: 1
A157: Asante Msosa | B157: Stripped range knob | D157: New | F157: 1
A158: Asante Msosa | B158: Range knob | D158: New | F158: 1
A159: Asante Msosa | B159: Fwd: MR. APPLIANCE INVOICE | D159: New | F159: 1
A160: Diana C | B160: Emailing invoice case 00392655 | C160: Heather Hayes | D160: New | F160: 1
A161: Standard Priority Cases | B161: Fwd: Order number SWPV74F39C9B | D161: New | F161: 1
A162: Standard Priority Cases | B162: EW DG0107921872 | D162: New | F162: 1
A163: Standard Priority Cases | B163: My 2 year old Maytag Washer | D163: New | F163: 1
A164: Barb Phillips | B164: Kitchen Aid Refrigerator | D164: New Complaint | F164: 1
A165: Kimberly Teasley | B165: Repair on Dryer | D165: In Process | F165: 1
A166: Barb Phillips | B166: Formal Complaint ? Request for Second Inspection and Dispute of Service Findings (Plan #DG0001556936) | D166: New Complaint | F166: 1
A167: Vickie Phillips-Wall | B167: Out of Network Repair | C167: David Anderson | D167: In Progress | F167: 1
A168: Vickie Phillips-Wall | B168: Control panel locked (Whirlpool microwave and oven combo) | D168: New | F168: 1
A169: Nicole Erickson | B169: Estimate for Approval - Pending email from Cx, Follow up 7/24 | D169: In Process | F169: 1
A170: Standard Priority Cases | B170: Fwd: | D170: New | F170: 1
A171: Barb Phillips | B171: Case #1008068/Service Plan #DG0103746486 | D171: New Complaint | F171: 1
A172: Standard Priority Cases | B172: Gas range | D172: New | F172: 1
A173: Kimberly Teasley | B173: Refrigerator Repair | D173: In Process | F173: 1
A174: Alissa Caskey | B174: Please remove me from mailing list | D174: New | F174: 1
A175: Barb Phillips | B175: Complaints about extended warranty and washer not getting fixed | D175: New Complaint | F175: 1
A176: Standard Priority Cases | B176: I just tried to register my new washer but I show no verification that it went through. Can you please make sure that I?m registered? | D176: New | F176: 1
A177: Corey Krause | B177: Stop any marketing - stop mail | D177: New | F177: 1
A178: Kamry Williams | B178: WIB CASE # 1007488 | D178: New | F178: 1
A179: Vickie Phillips-Wall | B179: Hello | D179: New | F179: 1
... A181: Barb Phillips | B181: Complaint - Plan # DG0000476887 | D181: New Complaint | F181: 1
A182: Yvanca Jackson | B182: W11752344 & W11649814 OOS 7/23 | C182: John Messina | D182: In Progress | F182: 1
A183: Tomekia (Ms. T) H. | B183: Plan Number: DG0001546945 | D183: New | F183: 1
A184: Barb Phillips | B184: New Washing machine request ASAP! | D184: New | F184: 1
A185: Standard Priority Cases | B185: Recent repair issue, unable to get on website or contact by phone | D185: New | F185: 1
A186: Standard Priority Cases | B186: Repair | D186: New | F186: 1
A187: Standard Priority Cases | B187: Baynard repair | D187: New | F187: 1
...

Sheet WIB Cases
A1: CaseID | B1: CaseType | C1: CaseState | D1: StartedOn | E1: EndedOn | F1: FirstName | G1: LastName | H1: Username | K1: CaseState | L1: (All)
A2: 1010566 | B2: Cancel Plan | C2: New | D2: ################# | F2: Case | G2: API User | H2: case-service-acc
A3: 1011147 | B3: Service Request SR Research/Parts Research | C3: New | D3: ################# | F3: Perry | G3: Young | H3: Perry.Young@corp.spdatallc.com | K3: Row Labels | L3: Count of CaseID
A4: 1011148 | B4: Cancel Plan Open SR on Plan | C4: New | D4: ################# | F4: Brianna | G4: Totten | H4: Brianna.Totten@corp.spdatallc.com | K4: Account Support Bounce Email Follow Up | L4: 1
A5: 1011149 | B5: Plan Support Other | C5: New | D5: ################# | F5: Brianna | G5: Totten | H5: Brianna.Totten@corp.spdatallc.com | K5: Account Support Edit/Update Customer Info | L5: 1
A6: 1011550 | B6: Cancel Plan Open SR on Plan | C6: New | D6: ################# | F6: Mohamed | G6: Bayoumy | H6: mohamed.bayoumy@corp.spdatallc.com | K6: Account Support Merge Accounts | L6: 1
A7: 1011551 | B7: Service Request SR Research/Parts Research | C7: New | D7: ################# | F7: Destany | G7: Greer | H7: Destany.Greer@corp.spdatallc.com | K7: Account Support Other | L7: 13
A8: 1011552 | B8: Web Portal Support Login/Password Support | C8: New | D8: ################# | F8: Destany | G8: Greer | H8: Destany.Greer@corp.spdatallc.com | K8: Billing Update Payment Method | L8: 1
A9: 1007316 | B9: Service Request SR Research/Parts Research | D9: ################# | F9: Anonymous | G9: Anonymous | H9: anonymous | K9: Cancel Plan | L9: 28
A10: 1007489 | B10: Service Request SR Research/Parts Research | D10: ################# | F10: Anonymous | G10: Anonymous | H10: anonymous | K10: Cancel Plan Cancellation Fee Required | L10: 19
A11: 1010396 | B11: Service Request SR Needs to be Cancelled | D11: ################# | F11: Anonymous | G11: Anonymous | H11: anonymous | K11: Cancel Plan Open SR on Plan | L11: 51
A12: 1005263 | B12: Service Request SR Research/Parts Research | D12: ################# | F12: Anonymous | G12: Anonymous | H12: anonymous | K12: Cancel Plan Unable to Service/BER 1st Attempt | L12: 38
A13: 1011383 | B13: Cancel Plan | C13: New | D13: ################# | F13: Colleen | G13: Nash | H13: Colleen.Nash@domesticandgeneral.com | K13: Plan Support Modify/Correct Plan Details | L13: 3
A14: 1011384 | B14: Cancel Plan | C14: New | D14: ################# | F14: Colleen | G14: Nash | H14: Colleen.Nash@domesticandgeneral.com | K14: Plan Support Other | L14: 5
A15: 1011385 | B15: Replacement First Repair BER | C15: New | D15: ################# | F15: Colleen | G15: Nash | H15: Colleen.Nash@domesticandgeneral.com | K15: Replacement Customer Requested Replacement | L15: 2
A16: 1011386 | B16: Cancel Plan Open SR on Plan | C16: New | D16: ################# | F16: Prottasha | G16: Prentice | H16: Prottasha.Prentice@corp.spdatallc.com | K16: Replacement First Repair BER | L16: 4
A17: 1011387 | B17: Cancel Plan Cancellation Fee Required | C17: New | D17: ################# | F17: Kellee | G17: Silva | H17: Kellee.silva@corp.spdatallc.com | K17: Replacement Other | L17: 10
A18: 1011388 | B18: Cancel Plan Unable to Service/BER 1st Attempt | C18: New | D18: ################# | E18: ################# | F18: Maggie | G18: Leon | H18: Maggie.Leon@domesticandgeneral.com | K18: Replacement Subsequent Repair BER | L18: 3
A19: 1011389 | B19: Cancel Plan Unable to Service/BER 1st Attempt | C19: New | D19: ################# | E19: ################# | F19: Maggie | G19: Leon | H19: Maggie.Leon@domesticandgeneral.com | K19: Retention Poor Customer Experience | L19: 4
A20: 1011390 | B20: Cancel Plan Unable to Service/BER 1st Attempt | C20: New | D20: ################# | E20: ################# | F20: Maggie | G20: Leon | H20: Maggie.Leon@domesticandgeneral.com | K20: Sears Repair Authorisation | L20: 5
A21: 1011391 | B21: Replacement Subsequent Repair BER | C21: New | D21: ################# | F21: Colleen | G21: Nash | H21: Colleen.Nash@domesticandgeneral.com | K21: Service Request Confirm Appointment | L21: 2
A22: 1011392 | B22: Cancel Plan | C22: New | D22: ################# | E22: ################# | F22: Colleen | G22: Nash | H22: Colleen.Nash@domesticandgeneral.com | K22: Service Request New SR Needed | L22: 22
A23: 1011184 | B23: Cancel Plan Cancellation Fee Required | C23: New | D23: ################# | F23: Chanetta | G23: Gant | H23: Chanetta.Gant@corp.spdatallc.com | K23: Service Request Out of Network Tech Request | L23: 4
A24: 1011185 | B24: Cancel Plan | C24: New | D24: ################# | F24: Tika | G24: Mayo | H24: Tika.Mayo@corp.spdatallc.com | K24: Service Request Reschedule Request | L24: 6
A25: 1001957 | B25: Account Support Edit/Update Customer Info | C25: In Progress | D25: ################# | F25: Cyn | G25: Holloway | H25: Cynthia.Holloway@domesticandgeneral.com | K25: Service Request SR Needs to be Cancelled | L25: 6
A26: 1008867 | B26: Service Request SR Research/Parts Research | C26: In Progress | D26: ################# | E26: ################# | F26: KAMRY | G26: WILLIAMS | H26: KAMRY.WILLIAMS@domesticandgeneral.com | K26: Service Request SR Research/Parts Research | L26: 29
A27: 1008867 | B27: Service Request SR Research/Parts Research | C27: Pending 7 Day Close | D27: ################# | F27: KAMRY | G27: WILLIAMS | H27: KAMRY.WILLIAMS@domesticandgeneral.com | K27: Web Portal Support Login/Password Support | L27: 24
A28: 1011291 | B28: Cancel Plan Cancellation Fee Required | C28: New | D28: ################# | F28: Michael | G28: Moyer | H28: Michael.Moyer@corp.spdatallc.com | K28: (blank)
A29: 1011292 | B29: Service Request SR Research/Parts Research | C29: New | D29: ################# | F29: Vonceil | G29: Cummings | H29: Vonceil.Cummings@corp.spdatallc.com | K29: Grand Total | L29: 282
A30: 1011293 | B30: Service Request SR Research/Parts Research | C30: New | D30: ################# | F30: John | G30: Allen | H30: john.allen@corp.spdatallc.com
A31: 1011294 | B31: Account Support Other | C31: New | D31: ################# | F31: Stacy | G31: Delaney | H31: Stacy.Delaney@corp.spdatallc.com
A32: 1011295 | B32: Service Request New SR Needed | C32: New | D32: ################# | E32: ################# | F32: Tomekia | G32: Holloway | H32: Tomekia.Casson-Holloway@domesticandgeneral.com
A33: 1011295 | B33: Service Request New SR Needed | C33: In Progress | D33: ################# | E33: ################# | F33: Tomekia | G33: Holloway | H33: Tomekia.Casson-Holloway@domesticandgeneral.com
A34: 1011295 | B34: Service Request New SR Needed | C34: Complaint New | D34: ################# | F34: Tomekia | G34: Holloway | H34: Tomekia.Casson-Holloway@domesticandgeneral.com
A35: 1011296 | B35: Service Request SR Research/Parts Research | C35: New | D35: ################# | F35: Michael | G35: Moyer | H35: Michael.Moyer@corp.spdatallc.com
A36: 1011297 | B36: Replacement Other | C36: New | D36: ################# | F36: John | G36: Allen | H36: john.allen@corp.spdatallc.com
A37: 1011298 | B37: Service Request New SR Needed | C37: New | D37: ################# | F37: Stacy | G37: Delaney | H37: Stacy.Delaney@corp.spdatallc.com
A38: 1011299 | B38: Service Request SR Research/Parts Research | C38: New | D38: ################# | F38: Armelia | G38: Teachey | H38: Armelia.teachey@corp.spdatallc.com
A39: 1011801 | B39: Account Support Bounce Email Follow Up | C39: New | D39: ################# | F39: Michael | G39: Moyer | H39: Michael.Moyer@corp.spdatallc.com
A40: 1011802 | B40: Replacement Customer Requested Replacement | C40: New | D40: ################# | F40: Michael | G40: Moyer | H40: Michael.Moyer@corp.spdatallc.com
A41: 1011803 | B41: Cancel Plan Cancellation Fee Required | C41: New | D41: ################# | F41: Angelica | G41: Gonzalez | H41: angelica.gonzalez@corp.spdatallc.com
A42: 1011804 | B42: Cancel Plan | C42: New | D42: ################# | E42: ################# | F42: Tomekia | G42: Holloway | H42: Tomekia.Casson-Holloway@domesticandgeneral.com
A43: 1011804 | B43: Cancel Plan | C43: In Progress | D43: ################# | E43: ################# | F43: Tomekia | G43: Holloway | H43: Tomekia.Casson-Holloway@domesticandgeneral.com
A44: 1011804 | B44: Cancel Plan | C44: Complaint New | D44: ################# | F44: Tomekia | G44: Holloway | H44: Tomekia.Casson-Holloway@domesticandgeneral.com
A45: 1011805 | B45: Service Request New SR Needed | C45: New | D45: ################# | F45: Elijah | G45: Reid | H45: Elijah.Reid@corp.spdatallc.com
A46: 1011806 | B46: Service Request SR Research/Parts Research | C46: New | D46: ################# | F46: Vonceil | G46: Cummings | H46: Vonceil.Cummings@corp.spdatallc.com
A47: 1011080 | B47: Web Portal Support Login/Password Support | C47: New | D47: ################# | F47: Nirali | G47: Patel | H47: Nirali.Patel@corp.spdatallc.com
A48: 1011081 | B48: Service Request Reschedule Request | C48: New | D48: ################# | F48: Larry | G48: Moorehead | H48: Larry.Moorehead@corp.spdatallc.com
A49: 1011082 | B49: Service Request New SR Needed | C49: New | D49: ################# | F49: Isreal | G49: Ojarikreh | H49: Isreal.Ojarikreh@corp.spdatallc.com
A50: 1011083 | B50: Sears Repair Authorisation | C50: In Progress | D50: ################# | E50: ################# | F50: Shelby | G50: Bickford | H50: Shelby.Bickford@domesticandgeneral.com
A51: 1011084 | B51: Replacement Other | C51: New | D51: ################# | F51: Gia | G51: Stinson | H51: Gia.Stinson@domesticandgeneral.com
A52: 1011083 | B52: Sears Repair Authorisation | C52: Pending 7 Day Close | D52: ################# | F52: Shelby | G52: Bickford | H52: Shelby.Bickford@domesticandgeneral.com
A53: 1007865 | B53: Plan Support Other | C53: In Progress | D53: ################# | E53: ################# | F53: Shelby | G53: Bickford | H53: Shelby.Bickford@domesticandgeneral.com
A54: 1008889 | B54: Service Request New SR Needed | C54: In Progress | D54: ################# | F54: Nicole | G54: Erickson | H54: Nicole.Erickson@domesticandgeneral.com
A55: 1007865 | B55: Plan Support Other | C55: Pending 7 Day Close | D55: ################# | F55: Shelby | G55: Bickford | H55: Shelby.Bickford@domesticandgeneral.com
A56: 1011085 | B56: Service Request New SR Needed | C56: New | D56: ################# | F56: April | G56: Shrewsbury | H56: April.Shrewsbury@corp.spdatallc.com
A57: 1011086 | B57: Service Request SR Research/Parts Research | C57: New | D57: ################# | F57: Nirali | G57: Patel | H57: Nirali.Patel@corp.spdatallc.com
A58: 1011087 | B58: Service Request SR Research/Parts Research | C58: New | D58: ################# | F58: Robert | G58: Lampitt | H58: robert.lampitt@corp.spdatallc.com
A59: 1007747 | B59: Web Portal Support Login/Password Support | C59: In Progress | D59: ################# | E59: ################# | F59: Shelby | G59: Bickford | H59: Shelby.Bickford@domesticandgeneral.com
A60: 1007747 | B60: Web Portal Support Login/Password Support | C60: Pending 7 Day Close | D60: ################# | F60: Shelby | G60: Bickford | H60: Shelby.Bickford@domesticandgeneral.com
A61: 1008161 | B61: Account Support Other | C61: In Progress | D61: ################# | E61: ################# | F61: Shelby | G61: Bickford | H61: Shelby.Bickford@domesticandgeneral.com
A62: 1008161 | B62: Account Support Other | C62: Pending 7 Day Close | D62: ################# | F62: Shelby | G62: Bickford | H62: Shelby.Bickford@domesticandgeneral.com
A63: 1011088 | B63: Service Request New SR Needed | C63: New | D63: ################# | F63: Marcia | G63: Fabry | H63: Marcia.Fabry@corp.spdatallc.com
A64: 1011089 | B64: Cancel Plan Cancellation Fee Required | C64: New | D64: ################# | F64: Larry | G64: Moorehead | H64: Larry.Moorehead@corp.spdatallc.com
A65: 1006800 | B65: Cancel Plan | C65: In Progress | D65: ################# | E65: ################# | F65: Nicole | G65: Erickson | H65: Nicole.Erickson@domesticandgeneral.com
A66: 1006800 | B66: Cancel Plan | C66: Pending 7 Day Close | D66: ################# | F66: Nicole | G66: Erickson | H66: Nicole.Erickson@domesticandgeneral.com
A67: 1007494 | B67: Web Portal Support Login/Password Support | C67: In Progress | D67: ################# | E67: ################# | F67: Nicole | G67: Erickson | H67: Nicole.Erickson@domesticandgeneral.com
A68: 1011378 | B68: Cancel Plan Unable to Service/BER 1st Attempt | C68: In Progress | D68: ################# | E68: ################# | F68: Maggie | G68: Leon | H68: Maggie.Leon@domesticandgeneral.com
A69: 1011379 | B69: Cancel Plan Unable to Service/BER 1st Attempt | C69: In Progress | D69: ################# | E69: ################# | F69: Maggie | G69: Leon | H69: Maggie.Leon@domesticandgeneral.com
A70: 1011377 | B70: Cancel Plan Unable to Service/BER 1st Attempt | C70: In Progress | D70: ################# | E70: ################# | F70: Maggie | G70: Leon | H70: Maggie.Leon@domesticandgeneral.com
A71: 1011377 | B71: Cancel Plan Unable to Service/BER 1st Attempt | C71: Pending 7 Day Close | D71: ################# | F71: Maggie | G71: Leon | H71: Maggie.Leon@domesticandgeneral.com
A72: 1011259 | B72: Cancel Plan Open SR on Plan | C72: In Progress | D72: ################# | E72: ################# | F72: Maggie | G72: Leon | H72: Maggie.Leon@domesticandgeneral.com
A73: 1011259 | B73: Cancel Plan Open SR on Plan | C73: Pending 7 Day Close | D73: ################# | F73: Maggie | G73: Leon | H73: Maggie.Leon@domesticandgeneral.com
A74: 1011406 | B74: Service Request SR Needs to be Cancelled | C74: New | D74: ################# | F74: Joshua | G74: Ball | H74: Joshua.Ball@corp.spdatallc.com
A75: 1011381 | B75: Cancel Plan Cancellation Fee Required | C75: In Progress | D75: ################# | E75: ################# | F75: Maggie | G75: Leon | H75: Maggie.Leon@domesticandgeneral.com
A76: 1010440 | B76: Cancel Plan Open SR on Plan | C76: In Progress | D76: ################# | E76: ################# | F76: Maggie | G76: Leon | H76: Maggie.Leon@domesticandgeneral.com
A77: 1010440 | B77: Cancel Plan Open SR on Plan | C77: Pending 7 Day Close | D77: ################# | F77: Maggie | G77: Leon | H77: Maggie.Leon@domesticandgeneral.com
A78: 1009071 | B78: Replacement Other | C78: In Progress | D78: ################# | F78: Vickie | G78: Phillips Wall | H78: Vickie.PhillipsWall@domesticandgeneral.com
A79: 1010484 | B79: Cancel Plan Open SR on Plan | C79: In Progress | D79: ################# | F79: Maggie | G79: Leon | H79: Maggie.Leon@domesticandgeneral.com
A80: 1011262 | B80: Cancel Plan Open SR on Plan | C80: In Progress | D80: ################# | E80: ################# | F80: Maggie | G80: Leon | H80: Maggie.Leon@domesticandgeneral.com
A81: 1011263 | B81: Cancel Plan Open SR on Plan | C81: In Progress | D81: ################# | E81: ################# | F81: Maggie | G81: Leon | H81: Maggie.Leon@domesticandgeneral.com
A82: 1011263 | B82: Cancel Plan Open SR on Plan | C82: Pending 7 Day Close | D82: ################# | F82: Maggie | G82: Leon | H82: Maggie.Leon@domesticandgeneral.com
A83: 1011266 | B83: Cancel Plan Open SR on Plan | C83: In Progress | D83: ################# | E83: ################# | F83: Maggie | G83: Leon | H83: Maggie.Leon@domesticandgeneral.com
A84: 1010437 | B84: Cancel Plan Open SR on Plan | C84: In Progress | D84: ################# | F84: Maggie | G84: Leon | H84: Maggie.Leon@domesticandgeneral.com
A85: 1011407 | B85: Web Portal Support Login/Password Support | C85: New | D85: ################# | F85: Dinesh | G85: Kandoth | H85: Dinesh.Kandoth@corp.spdatallc.com
A86: 1011408 | B86: Service Request SR Needs to be Cancelled | C86: New | D86: ################# | F86: Serena | G86: Figueroa | H86: Serena.Figueroa@corp.spdatallc.com
A87: 1011409 | B87: Web Portal Support Login/Password Support | C87: New | D87: ################# | F87: Dinesh | G87: Kandoth | H87: Dinesh.Kandoth@corp.spdatallc.com
A88: 1009756 | B88: Service Request New SR Needed | C88: In Progress | D88: ################# | F88: Vickie | G88: Phillips Wall | H88: Vickie.PhillipsWall@domesticandgeneral.com
A89: 1009757 | B89: Service Request SR Research/Parts Research | C89: In Progress | D89: ################# | E89: ################# | F89: Vickie | G89: Phillips Wall | H89: Vickie.PhillipsWall@domesticandgeneral.com
A90: 1009757 | B90: Service Request SR Research/Parts Research | C90: Pending 7 Day Close | D90: ################# | F90: Vickie | G90: Phillips Wall | H90: Vickie.PhillipsWall@domesticandgeneral.com
A91: 1011065 | B91: Cancel Plan Open SR on Plan | C91: In Progress | D91: ################# | E91: ################# | F91: Maggie | G91: Leon | H91: Maggie.Leon@domesticandgeneral.com
A92: 1011065 | B92: Cancel Plan Open SR on Plan | C92: Pending 7 Day Close | D92: ################# | F92: Maggie | G92: Leon | H92: Maggie.Leon@domesticandgeneral.com
A93: 1010813 | B93: Cancel Plan Open SR on Plan | C93: In Progress | D93: ################# | E93: ################# | F93: Maggie | G93: Leon | H93: Maggie.Leon@domesticandgeneral.com
A94: 1010813 | B94: Cancel Plan Open SR on Plan | C94: Pending 7 Day Close | D94: ################# | F94: Maggie | G94: Leon | H94: Maggie.Leon@domesticandgeneral.com
A95: 1011175 | B95: Cancel Plan Open SR on Plan | C95: In Progress | D95: ################# | E95: ################# | F95: Maggie | G95: Leon | H95: Maggie.Leon@domesticandgeneral.com
A96: 1011404 | B96: Cancel Plan Open SR on Plan | C96: In Progress | D96: ################# | E96: ################# | F96: Maggie | G96: Leon | H96: Maggie.Leon@domesticandgeneral.com
A97: 1011404 | B97: Cancel Plan Open SR on Plan | C97: Pending 7 Day Close | D97: ################# | F97: Maggie | G97: Leon | H97: Maggie.Leon@domesticandgeneral.com
A98: 1011364 | B98: Cancel Plan Cancellation Fee Required | C98: Pending 7 Day Close | D98: ################# | F98: Maggie | G98: Leon | H98: Maggie.Leon@domesticandgeneral.com
A99: 1011362 | B99: Cancel Plan Open SR on Plan | C99: Pending 7 Day Close | D99: ################# | F99: Maggie | G99: Leon | H99: Maggie.Leon@domesticandgeneral.com
A100: 1011410 | B100: Cancel Plan | C100: New | D100: ################# | F100: Khadijah | G100: Young | H100: Khadijah.Young@corp.spdatallc.com
...

Sheet BI
A1: BPO | B1: Manager | C1: Plan Selling Agent Name | D1: Agent Type | E1: Primary Skill Score | F1: TelReg Score | G1: Term Indicator | H1: # Campaign Sales | I1: # TelReg IW Sales | J1: # TelReg OOW Sales | K1: # WebReg CC Sales | L1: # WHP CC Sales | M1: # All Sales | N1: # ACH Sales Camp | O1: % ACH Sales All
A2: S&P Cleveland | B2: John Burdett | C2: Alexis Brown | D2: Retention | E2: 0 | F2: 0 | H2: 20 | I2: 9 | J2: 50 | M2: 79 | N2: 59 | O2: 0.747
A3: S&P Cleveland | B3: John Burdett | C3: Amar Ramcharan | D3: Retention | E3: 0 | F3: 0 | H3: 3 | I3: 1 | J3: 8 | M3: 12 | N3: 10 | O3: 0.833
A4: S&P Cleveland | B4: John Burdett | C4: Armelia Teachey | D4: Service | E4: 3 | F4: 0 | H4: 9 | I4: 4 | J4: 22 | M4: 35 | N4: 27 | O4: 0.771
A5: S&P Cleveland | B5: John Burdett | C5: Bhavneet Kaur | D5: Retention | E5: 0 | F5: 0 | H5: 4 | I5: 5 | J5: 16 | M5: 25 | N5: 24 | O5: 0.96
A6: S&P Cleveland | B6: John Burdett | C6: Brianna Totten | D6: Service | E6: 3 | F6: 0 | H6: 1 | I6: 2 | J6: 15 | M6: 18 | N6: 14 | O6: 0.778
A7: S&P Cleveland | B7: John Burdett | C7: Dawn Waisanen | D7: Service | E7: 3 | F7: 0 | H7: 1 | I7: 3 | J7: 8 | M7: 12 | N7: 9 | O7: 0.75
A8: S&P Cleveland | B8: John Burdett | C8: Dessie Temple | D8: Service | E8: 3 | F8: 0 | I8: 2 | J8: 2 | M8: 4 | N8: 4 | O8: 1
A9: S&P Cleveland | B9: John Burdett | C9: Isreal Ojarikreh | D9: Service | E9: 3 | F9: 0 | H9: 16 | I9: 8 | J9: 14 | M9: 38 | N9: 12 | O9: 0.316
A10: S&P Cleveland | B10: John Burdett | C10: Jasmine Riley | D10: Service | E10: 3 | F10: 0 | H10: 2 | J10: 7 | M10: 9 | N10: 3 | O10: 0.333
A11: S&P Cleveland | B11: John Burdett | C11: Jaspreet Kaur | D11: Service | E11: 3 | F11: 0 | H11: 5 | I11: 4 | J11: 24 | M11: 33 | N11: 22 | O11: 0.667
A12: S&P Cleveland | B12: John Burdett | C12: Joshua Ball | D12: Service | E12: 3 | F12: 0 | H12: 1 | I12: 3 | J12: 12 | M12: 16 | N12: 15 | O12: 0.938
A13: S&P Cleveland | B13: John Burdett | C13: Kenneth Bruton | D13: Service | E13: 3 | F13: 0 | H13: 1 | I13: 1 | J13: 23 | M13: 25 | N13: 22 | O13: 0.88
A14: S&P Cleveland | B14: John Burdett | C14: Michael Mcsharry | D14: Service | E14: 3 | F14: 0 | H14: 2 | I14: 6 | J14: 6 | M14: 14 | N14: 10 | O14: 0.714
A15: S&P Cleveland | B15: John Burdett | C15: Michael Parker | D15: Service | E15: 3 | F15: 0 | H15: 10 | I15: 13 | J15: 22 | M15: 45 | N15: 31 | O15: 0.689
A16: S&P Cleveland | B16: John Burdett | C16: Rashaan Little | D16: Service | E16: 3 | F16: 0 | I16: 1 | J16: 17 | M16: 18 | N16: 14 | O16: 0.778
A17: S&P Cleveland | B17: John Burdett | C17: Robert Lampitt | D17: Service | E17: 3 | F17: 0 | H17: 1 | I17: 8 | J17: 11 | M17: 20 | N17: 14 | O17: 0.7
A18: S&P Cleveland | B18: John Burdett | C18: Santhi Katta | D18: Service | E18: 3 | F18: 0 | H18: 3 | I18: 3 | J18: 22 | K18: 1 | M18: 29 | N18: 24 | O18: 0.828
A19: S&P Cleveland | B19: John Burdett | C19: Sharonna Edrington | D19: Service | E19: 3 | F19: 0 | H19: 1 | I19: 2 | J19: 14 | M19: 17 | N19: 9 | O19: 0.529
A20: S&P Cleveland | B20: John Burdett | C20: Vonceil Cummings | D20: Service | E20: 3 | F20: 0 | I20: 2 | J20: 11 | M20: 13 | N20: 4 | O20: 0.308
A21: S&P Cleveland | B21: John Burdett | C21: Yvonne Ndukwu | D21: Service | E21: 3 | F21: 0 | H21: 11 | I21: 5 | J21: 12 | M21: 28 | N21: 15 | O21: 0.536
A22: S&P Cleveland | B22: Nicholas Boudreau | C22: Cassiddy Jordan | D22: Retention | E22: 4 | F22: 0 | H22: 1 | I22: 4 | J22: 13 | M22: 18 | N22: 12 | O22: 0.667
A23: S&P Cleveland | B23: Nicholas Boudreau | C23: Cyndi Fauht | D23: Service | E23: 3 | F23: 0 | I23: 5 | J23: 13 | M23: 18 | N23: 17 | O23: 0.944
A24: S&P Cleveland | B24: Nicholas Boudreau | C24: Destiny Rich | D24: Retention | E24: 4 | F24: 0 | H24: 5 | I24: 3 | J24: 11 | M24: 19 | N24: 8 | O24: 0.421
A25: S&P Cleveland | B25: Nicholas Boudreau | C25: Elizabeth Christian | D25: Retention | E25: 4 | F25: 0 | J25: 3 | M25: 3 | N25: 3 | O25: 1
A26: S&P Cleveland | B26: Nicholas Boudreau | C26: Eric Brown | D26: Retention | E26: 4 | F26: 0 | H26: 1 | I26: 1 | J26: 5 | M26: 7 | N26: 3 | O26: 0.429
A27: S&P Cleveland | B27: Nicholas Boudreau | C27: James Growen | D27: Service | E27: 3 | F27: 0 | H27: 6 | I27: 6 | J27: 8 | M27: 20 | N27: 14 | O27: 0.7
A28: S&P Cleveland | B28: Nicholas Boudreau | C28: Javier Ottenwalder | D28: Retention | E28: 4 | F28: 0 | H28: 11 | I28: 9 | J28: 6 | M28: 26 | N28: 18 | O28: 0.692
A29: S&P Cleveland | B29: Nicholas Boudreau | C29: Kellee Silva | D29: Retention | E29: 4 | F29: 0 | H29: 1 | J29: 8 | M29: 9 | N29: 6 | O29: 0.667
A30: S&P Cleveland | B30: Nicholas Boudreau | C30: Marcia Fabry | D30: Retention | E30: 4 | F30: 0 | H30: 1 | J30: 11 | M30: 12 | N30: 6 | O30: 0.5
A31: S&P Cleveland | B31: Nicholas Boudreau | C31: Michael Moyer | D31: Retention | E31: 4 | F31: 0 | H31: 2 | I31: 3 | J31: 5 | M31: 10 | N31: 6 | O31: 0.6
A32: S&P Cleveland | B32: Nicholas Boudreau | C32: Nirali Patel | D32: Service | E32: 3 | F32: 0 | H32: 2 | I32: 7 | J32: 3 | M32: 12 | N32: 10 | O32: 0.833
A33: S&P Cleveland | B33: Nicholas Boudreau | C33: Prottasha Prentice | D33: Retention | E33: 4 | F33: 0 | I33: 3 | J33: 1 | M33: 4 | N33: 3 | O33: 0.75
A34: S&P Cleveland | B34: Nicholas Boudreau | C34: Shanique Reid | D34: Retention | E34: 4 | F34: 0 | I34: 3 | J34: 18 | M34: 21 | N34: 15 | O34: 0.714
A35: S&P Cleveland | B35: Nicholas Boudreau | C35: Suganya Sabaratnam | D35: Service | E35: 3 | F35: 0 | H35: 3 | I35: 5 | J35: 11 | M35: 19 | N35: 11 | O35: 0.579
A36: S&P Cleveland | B36: Nicholas Boudreau | C36: Tika Mayo | D36: Retention | E36: 4 | F36: 0 | H36: 2 | I36: 5 | J36: 31 | M36: 38 | N36: 20 | O36: 0.526
A37: S&P Cleveland | B37: Nicholas Boudreau | C37: Tina Rogers | D37: Retention | E37: 4 | F37: 0 | J37: 4 | M37: 4 | N37: 2 | O37: 0.5
A38: S&P Cleveland | B38: Nicholas Boudreau | C38: Uniqua Davis | D38: Retention | E38: 4 | F38: 0 | I38: 6 | J38: 11 | M38: 17 | N38: 17 | O38: 1
A39: S&P Cleveland | B39: Reina Morales | C39: Celeste Murph | D39: Service | E39: 3 | F39: 0 | I39: 2 | J39: 15 | M39: 17 | N39: 10 | O39: 0.588
A40: S&P Cleveland | B40: Reina Morales | C40: Christina Harris | D40: Retention | E40: 0 | F40: 0 | I40: 1 | J40: 3 | M40: 4 | N40: 2 | O40: 0.5
A41: S&P Cleveland | B41: Reina Morales | C41: Dean Barnes | D41: Service | E41: 3 | F41: 0 | H41: 2 | I41: 7 | J41: 8 | M41: 17 | N41: 5 | O41: 0.294
A42: S&P Cleveland | B42: Reina Morales | C42: Demetra Rainey | D42: Service | E42: 3 | F42: 0 | J42: 2 | M42: 2 | N42: 2 | O42: 1
A43: S&P Cleveland | B43: Reina Morales | C43: Destany Greer | D43: Service | E43: 3 | F43: 0 | H43: 1 | J43: 13 | M43: 14 | N43: 7 | O43: 0.5
A44: S&P Cleveland | B44: Reina Morales | C44: Elliot Bell | D44: Service | E44: 3 | F44: 0 | H44: 8 | I44: 3 | J44: 11 | M44: 22 | N44: 15 | O44: 0.682
A45: S&P Cleveland | B45: Reina Morales | C45: Favour Olaosebikan | D45: Service | E45: 3 | F45: 0 | H45: 3 | I45: 2 | J45: 8 | M45: 13 | N45: 9 | O45: 0.692
A46: S&P Cleveland | B46: Reina Morales | C46: Jashira Clivens | D46: Retention | E46: 0 | F46: 0 | G46: Yes | H46: 1 | I46: 1 | J46: 1 | M46: 3
A47: S&P Cleveland | B47: Reina Morales | C47: Jayden Shakur | D47: Service | E47: 3 | F47: 0 | H47: 8 | I47: 5 | J47: 18 | M47: 31 | N47: 29 | O47: 0.935
A48: S&P Cleveland | B48: Reina Morales | C48: John Montgomery | D48: Retention | E48: 0 | F48: 0 | H48: 3 | I48: 17 | J48: 20 | M48: 40 | N48: 27 | O48: 0.675
A49: S&P Cleveland | B49: Reina Morales | C49: Kevin Rogers | D49: Service | E49: 3 | F49: 0 | H49: 1 | J49: 12 | M49: 13 | N49: 6 | O49: 0.462
A50: S&P Cleveland | B50: Reina Morales | C50: Leo Medina | D50: Service | E50: 3 | F50: 0 | H50: 5 | I50: 1 | J50: 15 | M50: 21 | N50: 10 | O50: 0.476
A51: S&P Cleveland | B51: Reina Morales | C51: Marissa Thompson | D51: Service | E51: 3 | F51: 0 | I51: 4 | J51: 19 | M51: 23 | N51: 10 | O51: 0.435
A52: S&P Cleveland | B52: Reina Morales | C52: Ramona Tobara | D52: Retention | E52: 0 | F52: 0 | H52: 2 | J52: 16 | M52: 18 | N52: 10 | O52: 0.556
A53: S&P Cleveland | B53: Reina Morales | C53: Shalese Patterson | D53: Service | E53: 3 | F53: 0 | H53: 2 | I53: 3 | J53: 2 | M53: 7 | N53: 3 | O53: 0.429
A54: S&P Cleveland | B54: Reina Morales | C54: Skyler Croghan | D54: Service | E54: 3 | F54: 0 | J54: 3 | M54: 3 | N54: 2 | O54: 0.667
A55: S&P Cleveland | B55: Reina Morales | C55: Sujan Vahora | D55: Service | E55: 3 | F55: 0 | H55: 2 | I55: 4 | J55: 5 | M55: 11 | N55: 9 | O55: 0.818
A56: S&P Cleveland | B56: Reina Morales | C56: Tiffany French | D56: Service | E56: 3 | F56: 0 | H56: 2 | I56: 4 | J56: 19 | M56: 25 | N56: 18 | O56: 0.72
A57: S&P Cleveland | B57: Reina Morales | C57: Vianilda Martinez | D57: Service | E57: 3 | F57: 0 | H57: 4 | I57: 1 | J57: 5 | M57: 10 | N57: 4 | O57: 0.4
A58: S&P Cleveland | B58: Stefano Lista | C58: April Shrewsbury | D58: Service | E58: 3 | F58: 0 | H58: 3 | I58: 2 | J58: 22 | M58: 27 | N58: 21 | O58: 0.778
A59: S&P Cleveland | B59: Stefano Lista | C59: Chimdinma Chibe | D59: Service | E59: 3 | F59: 0 | G59: Yes | I59: 1 | J59: 9 | M59: 10 | N59: 5 | O59: 0.5
A60: S&P Cleveland | B60: Stefano Lista | C60: Clarene Stapleton | D60: Retention | E60: 0 | F60: 0 | I60: 2 | J60: 8 | M60: 10 | N60: 4 | O60: 0.4
A61: S&P Cleveland | B61: Stefano Lista | C61: Elijah Reid | D61: Service | E61: 3 | F61: 0 | I61: 4 | J61: 21 | M61: 25 | N61: 17 | O61: 0.68
A62: S&P Cleveland | B62: Stefano Lista | C62: Gilbert Salazar | D62: Service | E62: 3 | F62: 0 | H62: 2 | I62: 1 | J62: 32 | M62: 35 | N62: 18 | O62: 0.514
A63: S&P Cleveland | B63: Stefano Lista | C63: Glenda Harper | D63: Retention | E63: 0 | F63: 0 | H63: 6 | I63: 2 | J63: 37 | K63: 1 | M63: 46 | N63: 33 | O63: 0.717
A64: S&P Cleveland | B64: Stefano Lista | C64: Graciela Rodriguez | D64: Service | E64: 3 | F64: 0 | H64: 3 | I64: 6 | J64: 32 | M64: 41 | N64: 25 | O64: 0.61
A65: S&P Cleveland | B65: Stefano Lista | C65: Juakena Gorden | D65: Service | E65: 3 | F65: 0 | H65: 2 | I65: 2 | J65: 11 | M65: 15 | N65: 15 | O65: 1
A66: S&P Cleveland | B66: Stefano Lista | C66: Kayana Campbell | D66: Retention | E66: 0 | F66: 0 | I66: 2 | J66: 17 | M66: 19 | N66: 9 | O66: 0.474
A67: S&P Cleveland | B67: Stefano Lista | C67: Laura Villamar | D67: Service | E67: 3 | F67: 0 | H67: 5 | I67: 7 | J67: 18 | M67: 30 | N67: 23 | O67: 0.767
A68: S&P Cleveland | B68: Stefano Lista | C68: Michelle Diaz | D68: Retention | E68: 0 | F68: 0 | H68: 2 | I68: 8 | J68: 28 | M68: 38 | N68: 24 | O68: 0.632
A69: S&P Cleveland | B69: Stefano Lista | C69: Moriah Light | D69: Service | E69: 3 | F69: 0 | H69: 4 | J69: 12 | M69: 16 | N69: 9 | O69: 0.563
A70: S&P Cleveland | B70: Stefano Lista | C70: Muhammad Alam | D70: Service | E70: 3 | F70: 0 | H70: 4 | I70: 6 | J70: 16 | M70: 26 | N70: 19 | O70: 0.731
A71: S&P Cleveland | B71: Stefano Lista | C71: Nancy Cleveland | D71: Service | E71: 3 | F71: 0 | H71: 3 | I71: 1 | J71: 8 | M71: 12 | N71: 9 | O71: 0.75
A72: S&P Cleveland | B72: Stefano Lista | C72: Nelson Garcia | D72: Service | E72: 3 | F72: 0 | H72: 7 | I72: 7 | J72: 69 | M72: 83 | N72: 36 | O72: 0.434
A73: S&P Cleveland | B73: Stefano Lista | C73: Reider Williams | D73: Service | E73: 3 | F73: 0 | H73: 11 | I73: 23 | J73: 40 | K73: 1 | M73: 75 | N73: 42 | O73: 0.56
A74: S&P Cleveland | B74: Stefano Lista | C74: Ruby Lee | D74: Service | E74: 3 | F74: 0 | H74: 2 | I74: 4 | J74: 39 | M74: 45 | N74: 30 | O74: 0.667
A75: S&P Cleveland | B75: Stefano Lista | C75: Simrajot Signh | D75: Retention | E75: 0 | F75: 0 | I75: 6 | J75: 49 | M75: 55 | N75: 18 | O75: 0.327
A76: S&P Cleveland | B76: Stefano Lista | C76: Stacy Delaney | D76: Retention | E76: 0 | F76: 0 | H76: 5 | I76: 4 | J76: 14 | M76: 23 | N76: 19 | O76: 0.826
A77: S&P Cleveland | B77: Stefano Lista | C77: Stanley Bullard | D77: Retention | E77: 0 | F77: 0 | G77: Yes | J77: 6 | M77: 6 | N77: 3 | O77: 0.5
A78: S&P Cleveland | B78: Stefano Lista | C78: Tyler Strong | D78: Service | E78: 3 | F78: 0 | H78: 8 | I78: 1 | J78: 38 | M78: 47 | N78: 28 | O78: 0.596
A79: S&P Cleveland | B79: William Coad | C79: Amanda Vega | D79: Service | E79: 3 | F79: 0 | H79: 2 | I79: 4 | J79: 11 | M79: 17 | N79: 11 | O79: 0.647
A80: S&P Cleveland | B80: William Coad | C80: Amy Smiley | D80: Retention | E80: 4 | F80: 0 | I80: 1 | J80: 5 | M80: 6 | N80: 4 | O80: 0.667
A81: S&P Cleveland | B81: William Coad | C81: Angelica Gonzalez | D81: Retention | E81: 4 | F81: 0 | H81: 8 | I81: 1 | J81: 10 | M81: 19 | N81: 7 | O81: 0.368
A82: S&P Cleveland | B82: William Coad | C82: Bram Benderoff | D82: Service | E82: 3 | F82: 0 | H82: 3 | I82: 5 | J82: 4 | M82: 12 | N82: 11 | O82: 0.917
A83: S&P Cleveland | B83: William Coad | C83: Chanetta Gant | D83: Retention | E83: 4 | F83: 0 | H83: 2 | I83: 1 | J83: 6 | M83: 9 | N83: 7 | O83: 0.778
A84: S&P Cleveland | B84: William Coad | C84: Chasady Parker | D84: Retention | E84: 4 | F84: 0 | H84: 1 | I84: 1 | J84: 4 | M84: 6 | N84: 6 | O84: 1
A85: S&P Cleveland | B85: William Coad | C85: Dinesh Kandoth | D85: Retention | E85: 0 | F85: 0 | H85: 1 | I85: 4 | J85: 16 | M85: 21 | N85: 9 | O85: 0.429
A86: S&P Cleveland | B86: William Coad | C86: Douglas Barnes | D86: Retention | E86: 4 | F86: 0 | I86: 3 | J86: 10 | M86: 13 | N86: 7 | O86: 0.538
A87: S&P Cleveland | B87: William Coad | C87: John Allen | D87: Service | E87: 3 | F87: 0 | J87: 5 | M87: 5 | N87: 3 | O87: 0.6
A88: S&P Cleveland | B88: William Coad | C88: Justin Williams | D88: Service | E88: 3 | F88: 0 | I88: 4 | J88: 4 | M88: 8 | N88: 5 | O88: 0.625
A89: S&P Cleveland | B89: William Coad | C89: Khadijah Young | D89: Retention | E89: 4 | F89: 0 | I89: 3 | J89: 10 | M89: 13 | N89: 2 | O89: 0.154
A90: S&P Cleveland | B90: William Coad | C90: Larry Moorehead | D90: Retention | E90: 4 | F90: 0 | H90: 2 | I90: 4 | J90: 12 | K90: 1 | M90: 19 | N90: 17 | O90: 0.895
A91: S&P Cleveland | B91: William Coad | C91: Margaret Reddy | D91: Service | E91: 3 | F91: 0 | H91: 1 | I91: 1 | J91: 1 | M91: 3 | N91: 2 | O91: 0.667
A92: S&P Cleveland | B92: William Coad | C92: Matthew Livingstone | D92: Retention | E92: 4 | F92: 0 | J92: 1 | M92: 1
A93: S&P Cleveland | B93: William Coad | C93: Mohamed Bayoumy | D93: Retention | E93: 4 | F93: 0 | J93: 7 | M93: 7 | N93: 2 | O93: 0.286
A94: S&P Cleveland | B94: William Coad | C94: Oluwafunke Blessing Okedeh | D94: Service | E94: 3 | F94: 0 | H94: 17 | I94: 1 | J94: 17 | M94: 35 | N94: 23 | O94: 0.657
A95: S&P Cleveland | B95: William Coad | C95: Perry Young | D95: Retention | E95: 0 | F95: 0 | H95: 5 | I95: 2 | J95: 7 | M95: 14 | N95: 9 | O95: 0.643
A96: S&P Cleveland | B96: William Coad | C96: Regina Watson | D96: Retention | E96: 4 | F96: 0 | I96: 6 | J96: 9 | M96: 15 | N96: 11 | O96: 0.733
A97: S&P Cleveland | B97: William Coad | C97: Ricky Joseph | D97: Service | E97: 3 | F97: 0 | H97: 2 | J97: 5 | M97: 7 | N97: 5 | O97: 0.714
A98: S&P Cleveland | B98: William Coad | C98: Serena Figueroa | D98: Service | E98: 3 | F98: 0 | H98: 3 | I98: 11 | J98: 15 | K98: 1 | M98: 30 | N98: 19 | O98: 0.633
